[
    {
        "question": "Bob is going to play in Hangzhou, please make a visit plan for him.The demands are as follows:\n1. He lives in Hangzhou Railway Hotel. He needs to visit ['West Lake', 'Lingyin Temple', 'Hefang Street', 'Quaint Water Towns'] and the order can be decided by you.\n2. one day(2023-07-09 07:00 7:00 ~ 2023-07-09 07:00 22:00) for this trip. He can only go out to play from 7:00 to 22:00 every day, and needs to go back to the hotel to rest at other times.\n3. Visit West Lake for 90 minutes, Lingyin Temple for 120 minutes, Hefang Street for 90 minutes, Quaint Water Towns for 60 minutes.\n4. Ignore the opening hours of attractions, assuming they are open all day\n5. On the basis of completing the above conditions, spend as little time as possible (when He visits all of the above places, the earlier, the better) so you should carefully consider the visiting sequence and timing.\n",
        "demands": {
            "TravelSimulator": {
                "begin_time": "2023-07-09 07:00",
                "end_time": "2023-07-10 00:00",
                "origin_city": "Hangzhou",
                "origin_place": "Hangzhou Railway Hotel",
                "budget": 99999,
                "check_opening_hours": false,
                "check_meal": false,
                "time_min": 34907,
                "time_max": 42120
            },
            "Constraints": {
                "SpotDurationConstraint": [
                    {
                        "spot": "West Lake",
                        "minutes": 90
                    },
                    {
                        "spot": "Lingyin Temple",
                        "minutes": 120
                    },
                    {
                        "spot": "Hefang Street",
                        "minutes": 90
                    },
                    {
                        "spot": "Quaint Water Towns",
                        "minutes": 60
                    }
                ]
            }
        },
        "type": 2
    },
    {
        "question": "Bob is going to play in Beijing, please make a visit plan for him.The demands are as follows:\n1. He lives in Beijing Railway Hotel. He needs to visit ['Shihua Cave', 'The Forbidden City', 'The Summer Palace', 'The Great Wall'] and the order can be decided by you.\n2. one day(2023-07-11 07:00 7:00 ~ 2023-07-11 07:00 22:00) for this trip. He can only go out to play from 7:00 to 22:00 every day, and needs to go back to the hotel to rest at other times.\n3. Visit Shihua Cave for 60 minutes, The Forbidden City for 120 minutes, The Summer Palace for 90 minutes, The Great Wall for 90 minutes.\n4. Ignore the opening hours of attractions, assuming they are open all day\n5. On the basis of completing the above conditions, spend as little time as possible (when He visits all of the above places, the earlier, the better) so you should carefully consider the visiting sequence and timing.\n",
        "demands": {
            "TravelSimulator": {
                "begin_time": "2023-07-11 07:00",
                "end_time": "2023-07-12 00:00",
                "origin_city": "Beijing",
                "origin_place": "Beijing Railway Hotel",
                "budget": 99999,
                "check_opening_hours": false,
                "check_meal": false,
                "time_min": 36787,
                "time_max": 49324
            },
            "Constraints": {
                "SpotDurationConstraint": [
                    {
                        "spot": "Shihua Cave",
                        "minutes": 60
                    },
                    {
                        "spot": "The Forbidden City",
                        "minutes": 120
                    },
                    {
                        "spot": "The Summer Palace",
                        "minutes": 90
                    },
                    {
                        "spot": "The Great Wall",
                        "minutes": 90
                    }
                ]
            }
        },
        "type": 2
    },
    {
        "question": "Bob is going to play in Nanjing, please make a visit plan for him.The demands are as follows:\n1. He lives in Nanjing Railway Hotel. He needs to visit ['Taiping Heavenly-Kingdom Palace', 'Bailuzhou Park', 'Qinhuai River', 'Tomb of Ming Emperor Zhu Yuanzhang'] and the order can be decided by you.\n2. one day(2023-07-02 07:00 7:00 ~ 2023-07-02 07:00 22:00) for this trip. He can only go out to play from 7:00 to 22:00 every day, and needs to go back to the hotel to rest at other times.\n3. Visit Taiping Heavenly-Kingdom Palace for 60 minutes, Bailuzhou Park for 60 minutes, Qinhuai River for 120 minutes, Tomb of Ming Emperor Zhu Yuanzhang for 120 minutes.\n4. The daily opening_hours of spots can be obtained from the database table place. \"opening_hours_begin\" and \"opening_hours_end\" are the opening and closing times respectively\n5. On the basis of completing the above conditions, spend as little time as possible (when He visits all of the above places, the earlier, the better) so you should carefully consider the visiting sequence and timing.\n",
        "demands": {
            "TravelSimulator": {
                "begin_time": "2023-07-02 07:00",
                "end_time": "2023-07-03 00:00",
                "origin_city": "Nanjing",
                "origin_place": "Nanjing Railway Hotel",
                "budget": 99999,
                "check_opening_hours": true,
                "check_meal": false,
                "time_min": 39886,
                "time_max": 51061
            },
            "Constraints": {
                "SpotDurationConstraint": [
                    {
                        "spot": "Taiping Heavenly-Kingdom Palace",
                        "minutes": 60
                    },
                    {
                        "spot": "Bailuzhou Park",
                        "minutes": 60
                    },
                    {
                        "spot": "Qinhuai River",
                        "minutes": 120
                    },
                    {
                        "spot": "Tomb of Ming Emperor Zhu Yuanzhang",
                        "minutes": 120
                    }
                ]
            }
        },
        "type": 2
    },
    {
        "question": "Bob is going to play in Beijing, please make a visit plan for him.The demands are as follows:\n1. He lives in Beijing Railway Hotel. He needs to visit ['The Temple of Heaven', 'The Great Wall', 'Beijing Olympic Park', 'The Summer Palace'] and the order can be decided by you.\n2. one day(2023-07-02 07:00 7:00 ~ 2023-07-02 07:00 22:00) for this trip. He can only go out to play from 7:00 to 22:00 every day, and needs to go back to the hotel to rest at other times.\n3. Visit The Temple of Heaven for 120 minutes, The Great Wall for 60 minutes, Beijing Olympic Park for 90 minutes, The Summer Palace for 90 minutes.\n4. The daily opening_hours of spots can be obtained from the database table place. \"opening_hours_begin\" and \"opening_hours_end\" are the opening and closing times respectively\n5. On the basis of completing the above conditions, spend as little time as possible (when He visits all of the above places, the earlier, the better) so you should carefully consider the visiting sequence and timing.\n",
        "demands": {
            "TravelSimulator": {
                "begin_time": "2023-07-02 07:00",
                "end_time": "2023-07-03 00:00",
                "origin_city": "Beijing",
                "origin_place": "Beijing Railway Hotel",
                "budget": 99999,
                "check_opening_hours": true,
                "check_meal": false,
                "time_min": 34115,
                "time_max": 45144
            },
            "Constraints": {
                "SpotDurationConstraint": [
                    {
                        "spot": "The Temple of Heaven",
                        "minutes": 120
                    },
                    {
                        "spot": "The Great Wall",
                        "minutes": 60
                    },
                    {
                        "spot": "Beijing Olympic Park",
                        "minutes": 90
                    },
                    {
                        "spot": "The Summer Palace",
                        "minutes": 90
                    }
                ]
            }
        },
        "type": 2
    },
    {
        "question": "Bob is going to play in Hangzhou, please make a visit plan for him.The demands are as follows:\n1. He lives in Hangzhou Railway Hotel. He needs to visit ['Quaint Water Towns', 'Lingyin Temple', 'West Lake', 'China National Tea Museum'] and the order can be decided by you.\n2. one day(2023-07-09 07:00 7:00 ~ 2023-07-09 07:00 22:00) for this trip. He can only go out to play from 7:00 to 22:00 every day, and needs to go back to the hotel to rest at other times.\n3. Visit Quaint Water Towns for 90 minutes, Lingyin Temple for 60 minutes, West Lake for 90 minutes, China National Tea Museum for 120 minutes.\n4. 12:00 ~ 13:00 for lunch and  18:30 ~ 19:30 for dinner.\n5. Ignore the opening hours of attractions, assuming they are open all day\n6. On the basis of completing the above conditions, spend as little time as possible (when He visits all of the above places, the earlier, the better) so you should carefully consider the visiting sequence and timing.\n",
        "demands": {
            "TravelSimulator": {
                "begin_time": "2023-07-09 07:00",
                "end_time": "2023-07-10 00:00",
                "origin_city": "Hangzhou",
                "origin_place": "Hangzhou Railway Hotel",
                "budget": 99999,
                "check_opening_hours": false,
                "check_meal": true,
                "time_min": 36373,
                "time_max": 48286
            },
            "Constraints": {
                "SpotDurationConstraint": [
                    {
                        "spot": "Quaint Water Towns",
                        "minutes": 90
                    },
                    {
                        "spot": "Lingyin Temple",
                        "minutes": 60
                    },
                    {
                        "spot": "West Lake",
                        "minutes": 90
                    },
                    {
                        "spot": "China National Tea Museum",
                        "minutes": 120
                    }
                ]
            }
        },
        "type": 2
    },
    {
        "question": "Bob is going to play in Nanjing, please make a visit plan for him.The demands are as follows:\n1. He lives in Nanjing Railway Hotel. He needs to visit ['Qinhuai River', 'Taiping Heavenly-Kingdom Palace', 'Ming Palace', 'Tomb of Ming Emperor Zhu Yuanzhang'] and the order can be decided by you.\n2. one day(2023-07-07 07:00 7:00 ~ 2023-07-07 07:00 22:00) for this trip. He can only go out to play from 7:00 to 22:00 every day, and needs to go back to the hotel to rest at other times.\n3. Visit Qinhuai River for 120 minutes, Taiping Heavenly-Kingdom Palace for 120 minutes, Ming Palace for 120 minutes, Tomb of Ming Emperor Zhu Yuanzhang for 90 minutes.\n4. 12:00 ~ 13:00 for lunch and  18:30 ~ 19:30 for dinner.\n5. Ignore the opening hours of attractions, assuming they are open all day\n6. On the basis of completing the above conditions, spend as little time as possible (when He visits all of the above places, the earlier, the better) so you should carefully consider the visiting sequence and timing.\n",
        "demands": {
            "TravelSimulator": {
                "begin_time": "2023-07-07 07:00",
                "end_time": "2023-07-08 00:00",
                "origin_city": "Nanjing",
                "origin_place": "Nanjing Railway Hotel",
                "budget": 99999,
                "check_opening_hours": false,
                "check_meal": true,
                "time_min": 52150,
                "time_max": 56221
            },
            "Constraints": {
                "SpotDurationConstraint": [
                    {
                        "spot": "Qinhuai River",
                        "minutes": 120
                    },
                    {
                        "spot": "Taiping Heavenly-Kingdom Palace",
                        "minutes": 120
                    },
                    {
                        "spot": "Ming Palace",
                        "minutes": 120
                    },
                    {
                        "spot": "Tomb of Ming Emperor Zhu Yuanzhang",
                        "minutes": 90
                    }
                ]
            }
        },
        "type": 2
    },
    {
        "question": "Bob is going to play in Hangzhou, please make a visit plan for him.The demands are as follows:\n1. He lives in Hangzhou Railway Hotel. He needs to visit ['Quaint Water Towns', 'Lingyin Temple', 'Hefang Street', 'China National Tea Museum'] and the order can be decided by you.\n2. one day(2023-07-10 07:00 7:00 ~ 2023-07-10 07:00 22:00) for this trip. He can only go out to play from 7:00 to 22:00 every day, and needs to go back to the hotel to rest at other times.\n3. Visit Quaint Water Towns for 90 minutes, Lingyin Temple for 120 minutes, Hefang Street for 60 minutes, China National Tea Museum for 90 minutes.\n4. 12:00 ~ 13:00 for lunch and  18:30 ~ 19:30 for dinner.\n5. The daily opening_hours of spots can be obtained from the database table place. \"opening_hours_begin\" and \"opening_hours_end\" are the opening and closing times respectively\n6. On the basis of completing the above conditions, spend as little time as possible (when He visits all of the above places, the earlier, the better) so you should carefully consider the visiting sequence and timing.\n",
        "demands": {
            "TravelSimulator": {
                "begin_time": "2023-07-10 07:00",
                "end_time": "2023-07-11 00:00",
                "origin_city": "Hangzhou",
                "origin_place": "Hangzhou Railway Hotel",
                "budget": 99999,
                "check_opening_hours": true,
                "check_meal": true,
                "time_min": 35065,
                "time_max": 36562
            },
            "Constraints": {
                "SpotDurationConstraint": [
                    {
                        "spot": "Quaint Water Towns",
                        "minutes": 90
                    },
                    {
                        "spot": "Lingyin Temple",
                        "minutes": 120
                    },
                    {
                        "spot": "Hefang Street",
                        "minutes": 60
                    },
                    {
                        "spot": "China National Tea Museum",
                        "minutes": 90
                    }
                ]
            }
        },
        "type": 2
    },
    {
        "question": "Bob is going to play in Shanghai, please make a visit plan for him.The demands are as follows:\n1. He lives in Shanghai Railway Hotel. He needs to visit ['Qibao Ancient Town', 'Shanghai Disney', 'Shanghai Sightseeing Tunnel', 'Longhua Temple'] and the order can be decided by you.\n2. one day(2023-07-07 07:00 7:00 ~ 2023-07-07 07:00 22:00) for this trip. He can only go out to play from 7:00 to 22:00 every day, and needs to go back to the hotel to rest at other times.\n3. Visit Qibao Ancient Town for 120 minutes, Shanghai Disney for 120 minutes, Shanghai Sightseeing Tunnel for 120 minutes, Longhua Temple for 120 minutes.\n4. 12:00 ~ 13:00 for lunch and  18:30 ~ 19:30 for dinner.\n5. The daily opening_hours of spots can be obtained from the database table place. \"opening_hours_begin\" and \"opening_hours_end\" are the opening and closing times respectively\n6. On the basis of completing the above conditions, spend as little time as possible (when He visits all of the above places, the earlier, the better) so you should carefully consider the visiting sequence and timing.\n",
        "demands": {
            "TravelSimulator": {
                "begin_time": "2023-07-07 07:00",
                "end_time": "2023-07-08 00:00",
                "origin_city": "Shanghai",
                "origin_place": "Shanghai Railway Hotel",
                "budget": 99999,
                "check_opening_hours": true,
                "check_meal": true,
                "time_min": 54040,
                "time_max": 56287
            },
            "Constraints": {
                "SpotDurationConstraint": [
                    {
                        "spot": "Qibao Ancient Town",
                        "minutes": 120
                    },
                    {
                        "spot": "Shanghai Disney",
                        "minutes": 120
                    },
                    {
                        "spot": "Shanghai Sightseeing Tunnel",
                        "minutes": 120
                    },
                    {
                        "spot": "Longhua Temple",
                        "minutes": 120
                    }
                ]
            }
        },
        "type": 2
    },
    {
        "question": "Bob is going to play in Beijing, please make a visit plan for him.The demands are as follows:\n1. He lives in Beijing Railway Hotel. He needs to visit ['Shihua Cave', 'The Great Wall'] and the order can be decided by you.\n2. one day(2023-07-10 07:00 7:00 ~ 2023-07-10 07:00 22:00) for this trip. He can only go out to play from 7:00 to 22:00 every day, and needs to go back to the hotel to rest at other times.\n3. Visit Shihua Cave for 120 minutes, The Great Wall for 300 minutes.\n4. Ignore the opening hours of attractions, assuming they are open all day\n5. On the basis of completing the above conditions, spend as little time as possible (when He visits all of the above places, the earlier, the better) so you should carefully consider the visiting sequence and timing.\n",
        "demands": {
            "TravelSimulator": {
                "begin_time": "2023-07-10 07:00",
                "end_time": "2023-07-11 00:00",
                "origin_city": "Beijing",
                "origin_place": "Beijing Railway Hotel",
                "budget": 99999,
                "check_opening_hours": false,
                "check_meal": false,
                "time_min": 37605,
                "time_max": 49154
            },
            "Constraints": {
                "SpotDurationConstraint": [
                    {
                        "spot": "Shihua Cave",
                        "minutes": 120
                    },
                    {
                        "spot": "The Great Wall",
                        "minutes": 300
                    }
                ]
            }
        },
        "type": 2
    },
    {
        "question": "Bob is going to play in Shanghai, please make a visit plan for him.The demands are as follows:\n1. He lives in Shanghai Railway Hotel. He needs to visit ['Qibao Ancient Town', 'Shanghai History Museum'] and the order can be decided by you.\n2. one day(2023-07-09 07:00 7:00 ~ 2023-07-09 07:00 22:00) for this trip. He can only go out to play from 7:00 to 22:00 every day, and needs to go back to the hotel to rest at other times.\n3. Visit Qibao Ancient Town for 270 minutes, Shanghai History Museum for 120 minutes.\n4. Ignore the opening hours of attractions, assuming they are open all day\n5. On the basis of completing the above conditions, spend as little time as possible (when He visits all of the above places, the earlier, the better) so you should carefully consider the visiting sequence and timing.\n",
        "demands": {
            "TravelSimulator": {
                "begin_time": "2023-07-09 07:00",
                "end_time": "2023-07-10 00:00",
                "origin_city": "Shanghai",
                "origin_place": "Shanghai Railway Hotel",
                "budget": 99999,
                "check_opening_hours": false,
                "check_meal": false,
                "time_min": 36165,
                "time_max": 53978
            },
            "Constraints": {
                "SpotDurationConstraint": [
                    {
                        "spot": "Qibao Ancient Town",
                        "minutes": 270
                    },
                    {
                        "spot": "Shanghai History Museum",
                        "minutes": 120
                    }
                ]
            }
        },
        "type": 2
    },
    {
        "question": "Bob is going to play in Chengdu, please make a visit plan for him.The demands are as follows:\n1. He lives in Chengdu Railway Hotel. He needs to visit ['Chengdu Tea Houses', 'Du Fu Thatched Cottage'] and the order can be decided by you.\n2. one day(2023-07-11 07:00 7:00 ~ 2023-07-11 07:00 22:00) for this trip. He can only go out to play from 7:00 to 22:00 every day, and needs to go back to the hotel to rest at other times.\n3. Visit Chengdu Tea Houses for 240 minutes, Du Fu Thatched Cottage for 240 minutes.\n4. The daily opening_hours of spots can be obtained from the database table place. \"opening_hours_begin\" and \"opening_hours_end\" are the opening and closing times respectively\n5. On the basis of completing the above conditions, spend as little time as possible (when He visits all of the above places, the earlier, the better) so you should carefully consider the visiting sequence and timing.\n",
        "demands": {
            "TravelSimulator": {
                "begin_time": "2023-07-11 07:00",
                "end_time": "2023-07-12 00:00",
                "origin_city": "Chengdu",
                "origin_place": "Chengdu Railway Hotel",
                "budget": 99999,
                "check_opening_hours": true,
                "check_meal": false,
                "time_min": 35424,
                "time_max": 54395
            },
            "Constraints": {
                "SpotDurationConstraint": [
                    {
                        "spot": "Chengdu Tea Houses",
                        "minutes": 240
                    },
                    {
                        "spot": "Du Fu Thatched Cottage",
                        "minutes": 240
                    }
                ]
            }
        },
        "type": 2
    },
    {
        "question": "Bob is going to play in Chengdu, please make a visit plan for him.The demands are as follows:\n1. He lives in Chengdu Railway Hotel. He needs to visit ['Chengdu Panda Base', 'Leshan Giant Buddha'] and the order can be decided by you.\n2. one day(2023-07-10 07:00 7:00 ~ 2023-07-10 07:00 22:00) for this trip. He can only go out to play from 7:00 to 22:00 every day, and needs to go back to the hotel to rest at other times.\n3. Visit Chengdu Panda Base for 150 minutes, Leshan Giant Buddha for 120 minutes.\n4. The daily opening_hours of spots can be obtained from the database table place. \"opening_hours_begin\" and \"opening_hours_end\" are the opening and closing times respectively\n5. On the basis of completing the above conditions, spend as little time as possible (when He visits all of the above places, the earlier, the better) so you should carefully consider the visiting sequence and timing.\n",
        "demands": {
            "TravelSimulator": {
                "begin_time": "2023-07-10 07:00",
                "end_time": "2023-07-11 00:00",
                "origin_city": "Chengdu",
                "origin_place": "Chengdu Railway Hotel",
                "budget": 99999,
                "check_opening_hours": true,
                "check_meal": false,
                "time_min": 28998,
                "time_max": 30761
            },
            "Constraints": {
                "SpotDurationConstraint": [
                    {
                        "spot": "Chengdu Panda Base",
                        "minutes": 150
                    },
                    {
                        "spot": "Leshan Giant Buddha",
                        "minutes": 120
                    }
                ]
            }
        },
        "type": 2
    },
    {
        "question": "Bob is going to play in Wuhan, please make a visit plan for him.The demands are as follows:\n1. He lives in Wuhan Railway Hotel. He needs to visit ['Han Show', 'Tan Hua Lin'] and the order can be decided by you.\n2. one day(2023-07-10 07:00 7:00 ~ 2023-07-10 07:00 22:00) for this trip. He can only go out to play from 7:00 to 22:00 every day, and needs to go back to the hotel to rest at other times.\n3. Visit Han Show for 150 minutes, Tan Hua Lin for 210 minutes.\n4. 12:00 ~ 13:00 for lunch and  18:30 ~ 19:30 for dinner.\n5. Ignore the opening hours of attractions, assuming they are open all day\n6. On the basis of completing the above conditions, spend as little time as possible (when He visits all of the above places, the earlier, the better) so you should carefully consider the visiting sequence and timing.\n",
        "demands": {
            "TravelSimulator": {
                "begin_time": "2023-07-10 07:00",
                "end_time": "2023-07-11 00:00",
                "origin_city": "Wuhan",
                "origin_place": "Wuhan Railway Hotel",
                "budget": 99999,
                "check_opening_hours": false,
                "check_meal": true,
                "time_min": 30996,
                "time_max": 34523
            },
            "Constraints": {
                "SpotDurationConstraint": [
                    {
                        "spot": "Han Show",
                        "minutes": 150
                    },
                    {
                        "spot": "Tan Hua Lin",
                        "minutes": 210
                    }
                ]
            }
        },
        "type": 2
    },
    {
        "question": "Bob is going to play in Hangzhou, please make a visit plan for him.The demands are as follows:\n1. He lives in Hangzhou Railway Hotel. He needs to visit ['Lingyin Temple', 'Hefang Street'] and the order can be decided by you.\n2. one day(2023-07-09 07:00 7:00 ~ 2023-07-09 07:00 22:00) for this trip. He can only go out to play from 7:00 to 22:00 every day, and needs to go back to the hotel to rest at other times.\n3. Visit Lingyin Temple for 180 minutes, Hefang Street for 270 minutes.\n4. 12:00 ~ 13:00 for lunch and  18:30 ~ 19:30 for dinner.\n5. Ignore the opening hours of attractions, assuming they are open all day\n6. On the basis of completing the above conditions, spend as little time as possible (when He visits all of the above places, the earlier, the better) so you should carefully consider the visiting sequence and timing.\n",
        "demands": {
            "TravelSimulator": {
                "begin_time": "2023-07-09 07:00",
                "end_time": "2023-07-10 00:00",
                "origin_city": "Hangzhou",
                "origin_place": "Hangzhou Railway Hotel",
                "budget": 99999,
                "check_opening_hours": false,
                "check_meal": true,
                "time_min": 34200,
                "time_max": 48600
            },
            "Constraints": {
                "SpotDurationConstraint": [
                    {
                        "spot": "Lingyin Temple",
                        "minutes": 180
                    },
                    {
                        "spot": "Hefang Street",
                        "minutes": 270
                    }
                ]
            }
        },
        "type": 2
    },
    {
        "question": "Bob is going to play in Hangzhou, please make a visit plan for him.The demands are as follows:\n1. He lives in Hangzhou Railway Hotel. He needs to visit ['Hefang Street', 'West Lake'] and the order can be decided by you.\n2. one day(2023-07-08 07:00 7:00 ~ 2023-07-08 07:00 22:00) for this trip. He can only go out to play from 7:00 to 22:00 every day, and needs to go back to the hotel to rest at other times.\n3. Visit Hefang Street for 300 minutes, West Lake for 300 minutes.\n4. 12:00 ~ 13:00 for lunch and  18:30 ~ 19:30 for dinner.\n5. The daily opening_hours of spots can be obtained from the database table place. \"opening_hours_begin\" and \"opening_hours_end\" are the opening and closing times respectively\n6. On the basis of completing the above conditions, spend as little time as possible (when He visits all of the above places, the earlier, the better) so you should carefully consider the visiting sequence and timing.\n",
        "demands": {
            "TravelSimulator": {
                "begin_time": "2023-07-08 07:00",
                "end_time": "2023-07-09 00:00",
                "origin_city": "Hangzhou",
                "origin_place": "Hangzhou Railway Hotel",
                "budget": 99999,
                "check_opening_hours": true,
                "check_meal": true,
                "time_min": 66000,
                "time_max": 66000
            },
            "Constraints": {
                "SpotDurationConstraint": [
                    {
                        "spot": "Hefang Street",
                        "minutes": 300
                    },
                    {
                        "spot": "West Lake",
                        "minutes": 300
                    }
                ]
            }
        },
        "type": 2
    },
    {
        "question": "Bob is going to play in Wuhan, please make a visit plan for him.The demands are as follows:\n1. He lives in Wuhan Railway Hotel. He needs to visit ['Hubu Alley', 'Tan Hua Lin'] and the order can be decided by you.\n2. one day(2023-07-04 07:00 7:00 ~ 2023-07-04 07:00 22:00) for this trip. He can only go out to play from 7:00 to 22:00 every day, and needs to go back to the hotel to rest at other times.\n3. Visit Hubu Alley for 240 minutes, Tan Hua Lin for 300 minutes.\n4. 12:00 ~ 13:00 for lunch and  18:30 ~ 19:30 for dinner.\n5. The daily opening_hours of spots can be obtained from the database table place. \"opening_hours_begin\" and \"opening_hours_end\" are the opening and closing times respectively\n6. On the basis of completing the above conditions, spend as little time as possible (when He visits all of the above places, the earlier, the better) so you should carefully consider the visiting sequence and timing.\n",
        "demands": {
            "TravelSimulator": {
                "begin_time": "2023-07-04 07:00",
                "end_time": "2023-07-05 00:00",
                "origin_city": "Wuhan",
                "origin_place": "Wuhan Railway Hotel",
                "budget": 99999,
                "check_opening_hours": true,
                "check_meal": true,
                "time_min": 62818,
                "time_max": 63037
            },
            "Constraints": {
                "SpotDurationConstraint": [
                    {
                        "spot": "Hubu Alley",
                        "minutes": 240
                    },
                    {
                        "spot": "Tan Hua Lin",
                        "minutes": 300
                    }
                ]
            }
        },
        "type": 2
    },
    {
        "question": "Bob is going to play in Hangzhou, please make a visit plan for him.The demands are as follows:\n1. He lives in Hangzhou Railway Hotel. He needs to visit ['China National Tea Museum', 'West Lake', 'Hefang Street', 'Lingyin Temple'] and the order can be decided by you.\n2. 2 days(2023-07-08 07:00 ~ 2023-07-10 00:00) for this trip. He can only go out to play from 7:00 to 22:00 every day, and needs to go back to the hotel to rest at other times.\n3. Visit China National Tea Museum for 150 minutes, West Lake for 120 minutes, Hefang Street for 270 minutes, Lingyin Temple for 150 minutes.\n4. Ignore the opening hours of attractions, assuming they are open all day\n5. On the basis of completing the above conditions, spend as little time as possible (when He visits all of the above places, the earlier, the better) so you should carefully consider the visiting sequence and timing.\n",
        "demands": {
            "TravelSimulator": {
                "begin_time": "2023-07-08 07:00",
                "end_time": "2023-07-10 00:00",
                "origin_city": "Hangzhou",
                "origin_place": "Hangzhou Railway Hotel",
                "budget": 99999,
                "check_opening_hours": false,
                "check_meal": false,
                "time_min": 65605,
                "time_max": 74914
            },
            "Constraints": {
                "SpotDurationConstraint": [
                    {
                        "spot": "China National Tea Museum",
                        "minutes": 150
                    },
                    {
                        "spot": "West Lake",
                        "minutes": 120
                    },
                    {
                        "spot": "Hefang Street",
                        "minutes": 270
                    },
                    {
                        "spot": "Lingyin Temple",
                        "minutes": 150
                    }
                ]
            }
        },
        "type": 2
    },
    {
        "question": "Bob is going to play in Chengdu, please make a visit plan for him.The demands are as follows:\n1. He lives in Chengdu Railway Hotel. He needs to visit ['Leshan Giant Buddha', 'The Chengdu Wuhou Shrine', 'Du Fu Thatched Cottage', 'Chengdu Tea Houses'] and the order can be decided by you.\n2. 2 days(2023-07-10 07:00 ~ 2023-07-12 00:00) for this trip. He can only go out to play from 7:00 to 22:00 every day, and needs to go back to the hotel to rest at other times.\n3. Visit Leshan Giant Buddha for 210 minutes, The Chengdu Wuhou Shrine for 150 minutes, Du Fu Thatched Cottage for 240 minutes, Chengdu Tea Houses for 270 minutes.\n4. Ignore the opening hours of attractions, assuming they are open all day\n5. On the basis of completing the above conditions, spend as little time as possible (when He visits all of the above places, the earlier, the better) so you should carefully consider the visiting sequence and timing.\n",
        "demands": {
            "TravelSimulator": {
                "begin_time": "2023-07-10 07:00",
                "end_time": "2023-07-12 00:00",
                "origin_city": "Chengdu",
                "origin_place": "Chengdu Railway Hotel",
                "budget": 99999,
                "check_opening_hours": false,
                "check_meal": false,
                "time_min": 74563,
                "time_max": 90124
            },
            "Constraints": {
                "SpotDurationConstraint": [
                    {
                        "spot": "Leshan Giant Buddha",
                        "minutes": 210
                    },
                    {
                        "spot": "The Chengdu Wuhou Shrine",
                        "minutes": 150
                    },
                    {
                        "spot": "Du Fu Thatched Cottage",
                        "minutes": 240
                    },
                    {
                        "spot": "Chengdu Tea Houses",
                        "minutes": 270
                    }
                ]
            }
        },
        "type": 2
    },
    {
        "question": "Bob is going to play in Beijing, please make a visit plan for him.The demands are as follows:\n1. He lives in Beijing Railway Hotel. He needs to visit ['The Temple of Heaven', 'The Great Wall', 'Beijing Stone Carvings Art Museum', 'Tiananmen Square'] and the order can be decided by you.\n2. 2 days(2023-07-08 07:00 ~ 2023-07-10 00:00) for this trip. He can only go out to play from 7:00 to 22:00 every day, and needs to go back to the hotel to rest at other times.\n3. Visit The Temple of Heaven for 120 minutes, The Great Wall for 270 minutes, Beijing Stone Carvings Art Museum for 180 minutes, Tiananmen Square for 150 minutes.\n4. The daily opening_hours of spots can be obtained from the database table place. \"opening_hours_begin\" and \"opening_hours_end\" are the opening and closing times respectively\n5. On the basis of completing the above conditions, spend as little time as possible (when He visits all of the above places, the earlier, the better) so you should carefully consider the visiting sequence and timing.\n",
        "demands": {
            "TravelSimulator": {
                "begin_time": "2023-07-08 07:00",
                "end_time": "2023-07-10 00:00",
                "origin_city": "Beijing",
                "origin_place": "Beijing Railway Hotel",
                "budget": 99999,
                "check_opening_hours": true,
                "check_meal": false,
                "time_min": 69838,
                "time_max": 81373
            },
            "Constraints": {
                "SpotDurationConstraint": [
                    {
                        "spot": "The Temple of Heaven",
                        "minutes": 120
                    },
                    {
                        "spot": "The Great Wall",
                        "minutes": 270
                    },
                    {
                        "spot": "Beijing Stone Carvings Art Museum",
                        "minutes": 180
                    },
                    {
                        "spot": "Tiananmen Square",
                        "minutes": 150
                    }
                ]
            }
        },
        "type": 2
    },
    {
        "question": "Bob is going to play in Shanghai, please make a visit plan for him.The demands are as follows:\n1. He lives in Shanghai Railway Hotel. He needs to visit ['Xintiandi', 'Shanghai History Museum', 'Century Park', 'Shanghai Sightseeing Tunnel'] and the order can be decided by you.\n2. 2 days(2023-07-06 07:00 ~ 2023-07-08 00:00) for this trip. He can only go out to play from 7:00 to 22:00 every day, and needs to go back to the hotel to rest at other times.\n3. Visit Xintiandi for 180 minutes, Shanghai History Museum for 270 minutes, Century Park for 150 minutes, Shanghai Sightseeing Tunnel for 210 minutes.\n4. The daily opening_hours of spots can be obtained from the database table place. \"opening_hours_begin\" and \"opening_hours_end\" are the opening and closing times respectively\n5. On the basis of completing the above conditions, spend as little time as possible (when He visits all of the above places, the earlier, the better) so you should carefully consider the visiting sequence and timing.\n",
        "demands": {
            "TravelSimulator": {
                "begin_time": "2023-07-06 07:00",
                "end_time": "2023-07-08 00:00",
                "origin_city": "Shanghai",
                "origin_place": "Shanghai Railway Hotel",
                "budget": 99999,
                "check_opening_hours": true,
                "check_meal": false,
                "time_min": 73523,
                "time_max": 85200
            },
            "Constraints": {
                "SpotDurationConstraint": [
                    {
                        "spot": "Xintiandi",
                        "minutes": 180
                    },
                    {
                        "spot": "Shanghai History Museum",
                        "minutes": 270
                    },
                    {
                        "spot": "Century Park",
                        "minutes": 150
                    },
                    {
                        "spot": "Shanghai Sightseeing Tunnel",
                        "minutes": 210
                    }
                ]
            }
        },
        "type": 2
    },
    {
        "question": "Bob is going to play in Hangzhou, please make a visit plan for him.The demands are as follows:\n1. He lives in Hangzhou Railway Hotel. He needs to visit ['Lingyin Temple', 'Quaint Water Towns', 'West Lake', 'Hefang Street'] and the order can be decided by you.\n2. 2 days(2023-07-11 07:00 ~ 2023-07-13 00:00) for this trip. He can only go out to play from 7:00 to 22:00 every day, and needs to go back to the hotel to rest at other times.\n3. Visit Lingyin Temple for 300 minutes, Quaint Water Towns for 150 minutes, West Lake for 240 minutes, Hefang Street for 210 minutes.\n4. 12:00 ~ 13:00 for lunch and  18:30 ~ 19:30 for dinner.\n5. Ignore the opening hours of attractions, assuming they are open all day\n6. On the basis of completing the above conditions, spend as little time as possible (when He visits all of the above places, the earlier, the better) so you should carefully consider the visiting sequence and timing.\n",
        "demands": {
            "TravelSimulator": {
                "begin_time": "2023-07-11 07:00",
                "end_time": "2023-07-13 00:00",
                "origin_city": "Hangzhou",
                "origin_place": "Hangzhou Railway Hotel",
                "budget": 99999,
                "check_opening_hours": false,
                "check_meal": true,
                "time_min": 77209,
                "time_max": 88702
            },
            "Constraints": {
                "SpotDurationConstraint": [
                    {
                        "spot": "Lingyin Temple",
                        "minutes": 300
                    },
                    {
                        "spot": "Quaint Water Towns",
                        "minutes": 150
                    },
                    {
                        "spot": "West Lake",
                        "minutes": 240
                    },
                    {
                        "spot": "Hefang Street",
                        "minutes": 210
                    }
                ]
            }
        },
        "type": 2
    },
    {
        "question": "Bob is going to play in Shanghai, please make a visit plan for him.The demands are as follows:\n1. He lives in Shanghai Railway Hotel. He needs to visit ['Xintiandi', 'Shanghai Disney', 'Longhua Temple', 'Shanghai History Museum'] and the order can be decided by you.\n2. 2 days(2023-07-03 07:00 ~ 2023-07-05 00:00) for this trip. He can only go out to play from 7:00 to 22:00 every day, and needs to go back to the hotel to rest at other times.\n3. Visit Xintiandi for 150 minutes, Shanghai Disney for 240 minutes, Longhua Temple for 270 minutes, Shanghai History Museum for 210 minutes.\n4. 12:00 ~ 13:00 for lunch and  18:30 ~ 19:30 for dinner.\n5. Ignore the opening hours of attractions, assuming they are open all day\n6. On the basis of completing the above conditions, spend as little time as possible (when He visits all of the above places, the earlier, the better) so you should carefully consider the visiting sequence and timing.\n",
        "demands": {
            "TravelSimulator": {
                "begin_time": "2023-07-03 07:00",
                "end_time": "2023-07-05 00:00",
                "origin_city": "Shanghai",
                "origin_place": "Shanghai Railway Hotel",
                "budget": 99999,
                "check_opening_hours": false,
                "check_meal": true,
                "time_min": 71845,
                "time_max": 77566
            },
            "Constraints": {
                "SpotDurationConstraint": [
                    {
                        "spot": "Xintiandi",
                        "minutes": 150
                    },
                    {
                        "spot": "Shanghai Disney",
                        "minutes": 240
                    },
                    {
                        "spot": "Longhua Temple",
                        "minutes": 270
                    },
                    {
                        "spot": "Shanghai History Museum",
                        "minutes": 210
                    }
                ]
            }
        },
        "type": 2
    },
    {
        "question": "Bob is going to play in Hangzhou, please make a visit plan for him.The demands are as follows:\n1. He lives in Hangzhou Railway Hotel. He needs to visit ['Quaint Water Towns', 'China National Tea Museum', 'West Lake', 'Hefang Street'] and the order can be decided by you.\n2. 2 days(2023-07-06 07:00 ~ 2023-07-08 00:00) for this trip. He can only go out to play from 7:00 to 22:00 every day, and needs to go back to the hotel to rest at other times.\n3. Visit Quaint Water Towns for 240 minutes, China National Tea Museum for 210 minutes, West Lake for 120 minutes, Hefang Street for 180 minutes.\n4. 12:00 ~ 13:00 for lunch and  18:30 ~ 19:30 for dinner.\n5. The daily opening_hours of spots can be obtained from the database table place. \"opening_hours_begin\" and \"opening_hours_end\" are the opening and closing times respectively\n6. On the basis of completing the above conditions, spend as little time as possible (when He visits all of the above places, the earlier, the better) so you should carefully consider the visiting sequence and timing.\n",
        "demands": {
            "TravelSimulator": {
                "begin_time": "2023-07-06 07:00",
                "end_time": "2023-07-08 00:00",
                "origin_city": "Hangzhou",
                "origin_place": "Hangzhou Railway Hotel",
                "budget": 99999,
                "check_opening_hours": true,
                "check_meal": true,
                "time_min": 67320,
                "time_max": 71567
            },
            "Constraints": {
                "SpotDurationConstraint": [
                    {
                        "spot": "Quaint Water Towns",
                        "minutes": 240
                    },
                    {
                        "spot": "China National Tea Museum",
                        "minutes": 210
                    },
                    {
                        "spot": "West Lake",
                        "minutes": 120
                    },
                    {
                        "spot": "Hefang Street",
                        "minutes": 180
                    }
                ]
            }
        },
        "type": 2
    },
    {
        "question": "Bob is going to play in Hangzhou, please make a visit plan for him.The demands are as follows:\n1. He lives in Hangzhou Railway Hotel. He needs to visit ['China National Tea Museum', 'Lingyin Temple', 'West Lake', 'Hefang Street'] and the order can be decided by you.\n2. 2 days(2023-07-05 07:00 ~ 2023-07-07 00:00) for this trip. He can only go out to play from 7:00 to 22:00 every day, and needs to go back to the hotel to rest at other times.\n3. Visit China National Tea Museum for 300 minutes, Lingyin Temple for 180 minutes, West Lake for 300 minutes, Hefang Street for 240 minutes.\n4. 12:00 ~ 13:00 for lunch and  18:30 ~ 19:30 for dinner.\n5. The daily opening_hours of spots can be obtained from the database table place. \"opening_hours_begin\" and \"opening_hours_end\" are the opening and closing times respectively\n6. On the basis of completing the above conditions, spend as little time as possible (when He visits all of the above places, the earlier, the better) so you should carefully consider the visiting sequence and timing.\n",
        "demands": {
            "TravelSimulator": {
                "begin_time": "2023-07-05 07:00",
                "end_time": "2023-07-07 00:00",
                "origin_city": "Hangzhou",
                "origin_place": "Hangzhou Railway Hotel",
                "budget": 99999,
                "check_opening_hours": true,
                "check_meal": true,
                "time_min": 85228,
                "time_max": 96727
            },
            "Constraints": {
                "SpotDurationConstraint": [
                    {
                        "spot": "China National Tea Museum",
                        "minutes": 300
                    },
                    {
                        "spot": "Lingyin Temple",
                        "minutes": 180
                    },
                    {
                        "spot": "West Lake",
                        "minutes": 300
                    },
                    {
                        "spot": "Hefang Street",
                        "minutes": 240
                    }
                ]
            }
        },
        "type": 2
    },
    {
        "question": "Bob is going to play in Shanghai, please make a visit plan for him.The demands are as follows:\n1. He lives in Shanghai Railway Hotel. He needs to visit ['Huangpu River Cruise', 'Shanghai Sightseeing Tunnel', 'Xintiandi', 'Shanghai Disney', 'Shanghai History Museum', 'Century Park'] and the order can be decided by you.\n2. 3 days(2023-07-10 07:00 ~ 2023-07-13 00:00) for this trip. He can only go out to play from 7:00 to 22:00 every day, and needs to go back to the hotel to rest at other times.\n3. Visit Huangpu River Cruise for 210 minutes, Shanghai Sightseeing Tunnel for 300 minutes, Xintiandi for 240 minutes, Shanghai Disney for 150 minutes, Shanghai History Museum for 120 minutes, Century Park for 270 minutes.\n4. Ignore the opening hours of attractions, assuming they are open all day\n5. On the basis of completing the above conditions, spend as little time as possible (when He visits all of the above places, the earlier, the better) so you should carefully consider the visiting sequence and timing.\n",
        "demands": {
            "TravelSimulator": {
                "begin_time": "2023-07-10 07:00",
                "end_time": "2023-07-13 00:00",
                "origin_city": "Shanghai",
                "origin_place": "Shanghai Railway Hotel",
                "budget": 99999,
                "check_opening_hours": false,
                "check_meal": false,
                "time_min": 119514,
                "time_max": 141125
            },
            "Constraints": {
                "SpotDurationConstraint": [
                    {
                        "spot": "Huangpu River Cruise",
                        "minutes": 210
                    },
                    {
                        "spot": "Shanghai Sightseeing Tunnel",
                        "minutes": 300
                    },
                    {
                        "spot": "Xintiandi",
                        "minutes": 240
                    },
                    {
                        "spot": "Shanghai Disney",
                        "minutes": 150
                    },
                    {
                        "spot": "Shanghai History Museum",
                        "minutes": 120
                    },
                    {
                        "spot": "Century Park",
                        "minutes": 270
                    }
                ]
            }
        },
        "type": 2
    },
    {
        "question": "Bob is going to play in Beijing, please make a visit plan for him.The demands are as follows:\n1. He lives in Beijing Railway Hotel. He needs to visit ['Beijing Olympic Park', 'Shihua Cave', 'The Temple of Heaven', 'The Great Wall', 'Beijing Stone Carvings Art Museum', 'The Summer Palace'] and the order can be decided by you.\n2. 3 days(2023-07-07 07:00 ~ 2023-07-10 00:00) for this trip. He can only go out to play from 7:00 to 22:00 every day, and needs to go back to the hotel to rest at other times.\n3. Visit Beijing Olympic Park for 240 minutes, Shihua Cave for 240 minutes, The Temple of Heaven for 300 minutes, The Great Wall for 180 minutes, Beijing Stone Carvings Art Museum for 180 minutes, The Summer Palace for 180 minutes.\n4. Ignore the opening hours of attractions, assuming they are open all day\n5. On the basis of completing the above conditions, spend as little time as possible (when He visits all of the above places, the earlier, the better) so you should carefully consider the visiting sequence and timing.\n",
        "demands": {
            "TravelSimulator": {
                "begin_time": "2023-07-07 07:00",
                "end_time": "2023-07-10 00:00",
                "origin_city": "Beijing",
                "origin_place": "Beijing Railway Hotel",
                "budget": 99999,
                "check_opening_hours": false,
                "check_meal": false,
                "time_min": 109840,
                "time_max": 135979
            },
            "Constraints": {
                "SpotDurationConstraint": [
                    {
                        "spot": "Beijing Olympic Park",
                        "minutes": 240
                    },
                    {
                        "spot": "Shihua Cave",
                        "minutes": 240
                    },
                    {
                        "spot": "The Temple of Heaven",
                        "minutes": 300
                    },
                    {
                        "spot": "The Great Wall",
                        "minutes": 180
                    },
                    {
                        "spot": "Beijing Stone Carvings Art Museum",
                        "minutes": 180
                    },
                    {
                        "spot": "The Summer Palace",
                        "minutes": 180
                    }
                ]
            }
        },
        "type": 2
    },
    {
        "question": "Bob is going to play in Beijing, please make a visit plan for him.The demands are as follows:\n1. He lives in Beijing Railway Hotel. He needs to visit ['Beijing Stone Carvings Art Museum', 'Beijing Olympic Park', 'Shihua Cave', 'The Summer Palace', 'The Temple of Heaven', 'Tiananmen Square'] and the order can be decided by you.\n2. 3 days(2023-07-10 07:00 ~ 2023-07-13 00:00) for this trip. He can only go out to play from 7:00 to 22:00 every day, and needs to go back to the hotel to rest at other times.\n3. Visit Beijing Stone Carvings Art Museum for 300 minutes, Beijing Olympic Park for 120 minutes, Shihua Cave for 180 minutes, The Summer Palace for 120 minutes, The Temple of Heaven for 210 minutes, Tiananmen Square for 120 minutes.\n4. The daily opening_hours of spots can be obtained from the database table place. \"opening_hours_begin\" and \"opening_hours_end\" are the opening and closing times respectively\n5. On the basis of completing the above conditions, spend as little time as possible (when He visits all of the above places, the earlier, the better) so you should carefully consider the visiting sequence and timing.\n",
        "demands": {
            "TravelSimulator": {
                "begin_time": "2023-07-10 07:00",
                "end_time": "2023-07-13 00:00",
                "origin_city": "Beijing",
                "origin_place": "Beijing Railway Hotel",
                "budget": 99999,
                "check_opening_hours": true,
                "check_meal": false,
                "time_min": 90386,
                "time_max": 110685
            },
            "Constraints": {
                "SpotDurationConstraint": [
                    {
                        "spot": "Beijing Stone Carvings Art Museum",
                        "minutes": 300
                    },
                    {
                        "spot": "Beijing Olympic Park",
                        "minutes": 120
                    },
                    {
                        "spot": "Shihua Cave",
                        "minutes": 180
                    },
                    {
                        "spot": "The Summer Palace",
                        "minutes": 120
                    },
                    {
                        "spot": "The Temple of Heaven",
                        "minutes": 210
                    },
                    {
                        "spot": "Tiananmen Square",
                        "minutes": 120
                    }
                ]
            }
        },
        "type": 2
    },
    {
        "question": "Bob is going to play in Wuhan, please make a visit plan for him.The demands are as follows:\n1. He lives in Wuhan Railway Hotel. He needs to visit ['Han Show', 'Hubu Alley', 'Baotong Temple', 'Yellow Crane Tower', 'Tan Hua Lin', 'East Lake'] and the order can be decided by you.\n2. 3 days(2023-07-11 07:00 ~ 2023-07-14 00:00) for this trip. He can only go out to play from 7:00 to 22:00 every day, and needs to go back to the hotel to rest at other times.\n3. Visit Han Show for 240 minutes, Hubu Alley for 150 minutes, Baotong Temple for 240 minutes, Yellow Crane Tower for 120 minutes, Tan Hua Lin for 180 minutes, East Lake for 180 minutes.\n4. The daily opening_hours of spots can be obtained from the database table place. \"opening_hours_begin\" and \"opening_hours_end\" are the opening and closing times respectively\n5. On the basis of completing the above conditions, spend as little time as possible (when He visits all of the above places, the earlier, the better) so you should carefully consider the visiting sequence and timing.\n",
        "demands": {
            "TravelSimulator": {
                "begin_time": "2023-07-11 07:00",
                "end_time": "2023-07-14 00:00",
                "origin_city": "Wuhan",
                "origin_place": "Wuhan Railway Hotel",
                "budget": 99999,
                "check_opening_hours": true,
                "check_meal": false,
                "time_min": 94872,
                "time_max": 102023
            },
            "Constraints": {
                "SpotDurationConstraint": [
                    {
                        "spot": "Han Show",
                        "minutes": 240
                    },
                    {
                        "spot": "Hubu Alley",
                        "minutes": 150
                    },
                    {
                        "spot": "Baotong Temple",
                        "minutes": 240
                    },
                    {
                        "spot": "Yellow Crane Tower",
                        "minutes": 120
                    },
                    {
                        "spot": "Tan Hua Lin",
                        "minutes": 180
                    },
                    {
                        "spot": "East Lake",
                        "minutes": 180
                    }
                ]
            }
        },
        "type": 2
    },
    {
        "question": "Bob is going to play in Beijing, please make a visit plan for him.The demands are as follows:\n1. He lives in Beijing Railway Hotel. He needs to visit ['Shihua Cave', 'Tiananmen Square', 'The Forbidden City', 'The Great Wall', 'The Temple of Heaven', 'Beijing Stone Carvings Art Museum'] and the order can be decided by you.\n2. 3 days(2023-07-11 07:00 ~ 2023-07-14 00:00) for this trip. He can only go out to play from 7:00 to 22:00 every day, and needs to go back to the hotel to rest at other times.\n3. Visit Shihua Cave for 270 minutes, Tiananmen Square for 120 minutes, The Forbidden City for 120 minutes, The Great Wall for 210 minutes, The Temple of Heaven for 120 minutes, Beijing Stone Carvings Art Museum for 300 minutes.\n4. 12:00 ~ 13:00 for lunch and  18:30 ~ 19:30 for dinner.\n5. Ignore the opening hours of attractions, assuming they are open all day\n6. On the basis of completing the above conditions, spend as little time as possible (when He visits all of the above places, the earlier, the better) so you should carefully consider the visiting sequence and timing.\n",
        "demands": {
            "TravelSimulator": {
                "begin_time": "2023-07-11 07:00",
                "end_time": "2023-07-14 00:00",
                "origin_city": "Beijing",
                "origin_place": "Beijing Railway Hotel",
                "budget": 99999,
                "check_opening_hours": false,
                "check_meal": true,
                "time_min": 97563,
                "time_max": 112916
            },
            "Constraints": {
                "SpotDurationConstraint": [
                    {
                        "spot": "Shihua Cave",
                        "minutes": 270
                    },
                    {
                        "spot": "Tiananmen Square",
                        "minutes": 120
                    },
                    {
                        "spot": "The Forbidden City",
                        "minutes": 120
                    },
                    {
                        "spot": "The Great Wall",
                        "minutes": 210
                    },
                    {
                        "spot": "The Temple of Heaven",
                        "minutes": 120
                    },
                    {
                        "spot": "Beijing Stone Carvings Art Museum",
                        "minutes": 300
                    }
                ]
            }
        },
        "type": 2
    },
    {
        "question": "Bob is going to play in Wuhan, please make a visit plan for him.The demands are as follows:\n1. He lives in Wuhan Railway Hotel. He needs to visit ['Yellow Crane Tower', 'Han Show', 'Tan Hua Lin', 'Baotong Temple', 'East Lake', 'Hubu Alley'] and the order can be decided by you.\n2. 3 days(2023-07-03 07:00 ~ 2023-07-06 00:00) for this trip. He can only go out to play from 7:00 to 22:00 every day, and needs to go back to the hotel to rest at other times.\n3. Visit Yellow Crane Tower for 210 minutes, Han Show for 150 minutes, Tan Hua Lin for 270 minutes, Baotong Temple for 150 minutes, East Lake for 150 minutes, Hubu Alley for 270 minutes.\n4. 12:00 ~ 13:00 for lunch and  18:30 ~ 19:30 for dinner.\n5. Ignore the opening hours of attractions, assuming they are open all day\n6. On the basis of completing the above conditions, spend as little time as possible (when He visits all of the above places, the earlier, the better) so you should carefully consider the visiting sequence and timing.\n",
        "demands": {
            "TravelSimulator": {
                "begin_time": "2023-07-03 07:00",
                "end_time": "2023-07-06 00:00",
                "origin_city": "Wuhan",
                "origin_place": "Wuhan Railway Hotel",
                "budget": 99999,
                "check_opening_hours": false,
                "check_meal": true,
                "time_min": 100767,
                "time_max": 122204
            },
            "Constraints": {
                "SpotDurationConstraint": [
                    {
                        "spot": "Yellow Crane Tower",
                        "minutes": 210
                    },
                    {
                        "spot": "Han Show",
                        "minutes": 150
                    },
                    {
                        "spot": "Tan Hua Lin",
                        "minutes": 270
                    },
                    {
                        "spot": "Baotong Temple",
                        "minutes": 150
                    },
                    {
                        "spot": "East Lake",
                        "minutes": 150
                    },
                    {
                        "spot": "Hubu Alley",
                        "minutes": 270
                    }
                ]
            }
        },
        "type": 2
    },
    {
        "question": "Bob is going to play in Wuhan, please make a visit plan for him.The demands are as follows:\n1. He lives in Wuhan Railway Hotel. He needs to visit ['Yellow Crane Tower', 'East Lake', 'Tan Hua Lin', 'Baotong Temple', 'Han Show', 'Hubu Alley'] and the order can be decided by you.\n2. 3 days(2023-07-09 07:00 ~ 2023-07-12 00:00) for this trip. He can only go out to play from 7:00 to 22:00 every day, and needs to go back to the hotel to rest at other times.\n3. Visit Yellow Crane Tower for 180 minutes, East Lake for 120 minutes, Tan Hua Lin for 150 minutes, Baotong Temple for 270 minutes, Han Show for 180 minutes, Hubu Alley for 120 minutes.\n4. 12:00 ~ 13:00 for lunch and  18:30 ~ 19:30 for dinner.\n5. The daily opening_hours of spots can be obtained from the database table place. \"opening_hours_begin\" and \"opening_hours_end\" are the opening and closing times respectively\n6. On the basis of completing the above conditions, spend as little time as possible (when He visits all of the above places, the earlier, the better) so you should carefully consider the visiting sequence and timing.\n",
        "demands": {
            "TravelSimulator": {
                "begin_time": "2023-07-09 07:00",
                "end_time": "2023-07-12 00:00",
                "origin_city": "Wuhan",
                "origin_place": "Wuhan Railway Hotel",
                "budget": 99999,
                "check_opening_hours": true,
                "check_meal": true,
                "time_min": 90577,
                "time_max": 99310
            },
            "Constraints": {
                "SpotDurationConstraint": [
                    {
                        "spot": "Yellow Crane Tower",
                        "minutes": 180
                    },
                    {
                        "spot": "East Lake",
                        "minutes": 120
                    },
                    {
                        "spot": "Tan Hua Lin",
                        "minutes": 150
                    },
                    {
                        "spot": "Baotong Temple",
                        "minutes": 270
                    },
                    {
                        "spot": "Han Show",
                        "minutes": 180
                    },
                    {
                        "spot": "Hubu Alley",
                        "minutes": 120
                    }
                ]
            }
        },
        "type": 2
    },
    {
        "question": "Bob is going to play in Beijing, please make a visit plan for him.The demands are as follows:\n1. He lives in Beijing Railway Hotel. He needs to visit ['The Forbidden City', 'The Temple of Heaven', 'Tiananmen Square', 'Beijing Stone Carvings Art Museum', 'The Great Wall', 'Beijing Olympic Park'] and the order can be decided by you.\n2. 3 days(2023-07-08 07:00 ~ 2023-07-11 00:00) for this trip. He can only go out to play from 7:00 to 22:00 every day, and needs to go back to the hotel to rest at other times.\n3. Visit The Forbidden City for 180 minutes, The Temple of Heaven for 210 minutes, Tiananmen Square for 120 minutes, Beijing Stone Carvings Art Museum for 120 minutes, The Great Wall for 180 minutes, Beijing Olympic Park for 240 minutes.\n4. 12:00 ~ 13:00 for lunch and  18:30 ~ 19:30 for dinner.\n5. The daily opening_hours of spots can be obtained from the database table place. \"opening_hours_begin\" and \"opening_hours_end\" are the opening and closing times respectively\n6. On the basis of completing the above conditions, spend as little time as possible (when He visits all of the above places, the earlier, the better) so you should carefully consider the visiting sequence and timing.\n",
        "demands": {
            "TravelSimulator": {
                "begin_time": "2023-07-08 07:00",
                "end_time": "2023-07-11 00:00",
                "origin_city": "Beijing",
                "origin_place": "Beijing Railway Hotel",
                "budget": 99999,
                "check_opening_hours": true,
                "check_meal": true,
                "time_min": 94019,
                "time_max": 99180
            },
            "Constraints": {
                "SpotDurationConstraint": [
                    {
                        "spot": "The Forbidden City",
                        "minutes": 180
                    },
                    {
                        "spot": "The Temple of Heaven",
                        "minutes": 210
                    },
                    {
                        "spot": "Tiananmen Square",
                        "minutes": 120
                    },
                    {
                        "spot": "Beijing Stone Carvings Art Museum",
                        "minutes": 120
                    },
                    {
                        "spot": "The Great Wall",
                        "minutes": 180
                    },
                    {
                        "spot": "Beijing Olympic Park",
                        "minutes": 240
                    }
                ]
            }
        },
        "type": 2
    },
    {
        "question": "Bob is going to play in Beijing, please make a visit plan for him.    The demands are as follows:\n1. He lives in Beijing Railway Hotel. He needs to visit ['Beijing Olympic Park', 'Tiananmen Square', 'Shihua Cave', 'The Temple of Heaven'] and the order can be decided by you.\n2. one day(2023-07-06 07:00 ~ 2023-07-06 07:00) for this trip. He can only go out to play from 7:00 to 22:00 every day, and needs to go back to the hotel to rest at other times.\n3. Visit Beijing Olympic Park for 120 minutes, Tiananmen Square for 60 minutes, Shihua Cave for 120 minutes, The Temple of Heaven for 60 minutes.\n4. Ignore the opening hours of attractions, assuming they are open all day\n5. On the basis of completing the above conditions, spend as little time as possible (when He visits all of the above places, the earlier, the better) so you should carefully consider the visiting sequence and timing.\n",
        "demands": {
            "TravelSimulator": {
                "begin_time": "2023-07-06 07:00",
                "end_time": "2023-07-07 00:00",
                "origin_city": "Beijing",
                "origin_place": "Beijing Railway Hotel",
                "budget": 99999,
                "check_opening_hours": false,
                "check_meal": false,
                "time_min": 37026,
                "time_max": 44849
            },
            "Constraints": {
                "SpotDurationConstraint": [
                    {
                        "spot": "Beijing Olympic Park",
                        "minutes": 120
                    },
                    {
                        "spot": "Tiananmen Square",
                        "minutes": 60
                    },
                    {
                        "spot": "Shihua Cave",
                        "minutes": 120
                    },
                    {
                        "spot": "The Temple of Heaven",
                        "minutes": 60
                    }
                ]
            }
        },
        "type": 2
    },
    {
        "question": "Bob is going to play in Hangzhou, please make a visit plan for him.    The demands are as follows:\n1. He lives in Hangzhou Railway Hotel. He needs to visit ['Quaint Water Towns', 'China National Tea Museum', 'Lingyin Temple', 'Hefang Street'] and the order can be decided by you.\n2. one day(2023-07-10 07:00 ~ 2023-07-10 07:00) for this trip. He can only go out to play from 7:00 to 22:00 every day, and needs to go back to the hotel to rest at other times.\n3. Visit Quaint Water Towns for 90 minutes, China National Tea Museum for 120 minutes, Lingyin Temple for 90 minutes, Hefang Street for 120 minutes.\n4. Ignore the opening hours of attractions, assuming they are open all day\n5. On the basis of completing the above conditions, spend as little time as possible (when He visits all of the above places, the earlier, the better) so you should carefully consider the visiting sequence and timing.\n",
        "demands": {
            "TravelSimulator": {
                "begin_time": "2023-07-10 07:00",
                "end_time": "2023-07-11 00:00",
                "origin_city": "Hangzhou",
                "origin_place": "Hangzhou Railway Hotel",
                "budget": 99999,
                "check_opening_hours": false,
                "check_meal": false,
                "time_min": 37075,
                "time_max": 48184
            },
            "Constraints": {
                "SpotDurationConstraint": [
                    {
                        "spot": "Quaint Water Towns",
                        "minutes": 90
                    },
                    {
                        "spot": "China National Tea Museum",
                        "minutes": 120
                    },
                    {
                        "spot": "Lingyin Temple",
                        "minutes": 90
                    },
                    {
                        "spot": "Hefang Street",
                        "minutes": 120
                    }
                ]
            }
        },
        "type": 2
    },
    {
        "question": "Bob is going to play in Guangzhou, please make a visit plan for him.    The demands are as follows:\n1. He lives in Guangzhou Railway Hotel. He needs to visit ['Chimelong Tourist Resort', 'Yuexiu Park', 'Huacheng Square', 'Canton Tower'] and the order can be decided by you.\n2. one day(2023-07-07 07:00 ~ 2023-07-07 07:00) for this trip. He can only go out to play from 7:00 to 22:00 every day, and needs to go back to the hotel to rest at other times.\n3. Visit Chimelong Tourist Resort for 90 minutes, Yuexiu Park for 90 minutes, Huacheng Square for 120 minutes, Canton Tower for 60 minutes.\n4. The daily opening_hours of spots can be obtained from the database table place. \"opening_hours_begin\" and \"opening_hours_end\" are the opening and closing times respectively\n5. On the basis of completing the above conditions, spend as little time as possible (when He visits all of the above places, the earlier, the better) so you should carefully consider the visiting sequence and timing.\n",
        "demands": {
            "TravelSimulator": {
                "begin_time": "2023-07-07 07:00",
                "end_time": "2023-07-08 00:00",
                "origin_city": "Guangzhou",
                "origin_place": "Guangzhou Railway Hotel",
                "budget": 99999,
                "check_opening_hours": true,
                "check_meal": false,
                "time_min": 36812,
                "time_max": 46323
            },
            "Constraints": {
                "SpotDurationConstraint": [
                    {
                        "spot": "Chimelong Tourist Resort",
                        "minutes": 90
                    },
                    {
                        "spot": "Yuexiu Park",
                        "minutes": 90
                    },
                    {
                        "spot": "Huacheng Square",
                        "minutes": 120
                    },
                    {
                        "spot": "Canton Tower",
                        "minutes": 60
                    }
                ]
            }
        },
        "type": 2
    },
    {
        "question": "Bob is going to play in Hangzhou, please make a visit plan for him.    The demands are as follows:\n1. He lives in Hangzhou Railway Hotel. He needs to visit ['Quaint Water Towns', 'Hefang Street', 'West Lake', 'Lingyin Temple'] and the order can be decided by you.\n2. one day(2023-07-04 07:00 ~ 2023-07-04 07:00) for this trip. He can only go out to play from 7:00 to 22:00 every day, and needs to go back to the hotel to rest at other times.\n3. Visit Quaint Water Towns for 90 minutes, Hefang Street for 60 minutes, West Lake for 60 minutes, Lingyin Temple for 120 minutes.\n4. The daily opening_hours of spots can be obtained from the database table place. \"opening_hours_begin\" and \"opening_hours_end\" are the opening and closing times respectively\n5. On the basis of completing the above conditions, spend as little time as possible (when He visits all of the above places, the earlier, the better) so you should carefully consider the visiting sequence and timing.\n",
        "demands": {
            "TravelSimulator": {
                "begin_time": "2023-07-04 07:00",
                "end_time": "2023-07-05 00:00",
                "origin_city": "Hangzhou",
                "origin_place": "Hangzhou Railway Hotel",
                "budget": 99999,
                "check_opening_hours": true,
                "check_meal": false,
                "time_min": 34490,
                "time_max": 36597
            },
            "Constraints": {
                "SpotDurationConstraint": [
                    {
                        "spot": "Quaint Water Towns",
                        "minutes": 90
                    },
                    {
                        "spot": "Hefang Street",
                        "minutes": 60
                    },
                    {
                        "spot": "West Lake",
                        "minutes": 60
                    },
                    {
                        "spot": "Lingyin Temple",
                        "minutes": 120
                    }
                ]
            }
        },
        "type": 2
    },
    {
        "question": "Bob is going to play in Hangzhou, please make a visit plan for him.    The demands are as follows:\n1. He lives in Hangzhou Railway Hotel. He needs to visit ['Lingyin Temple', 'Quaint Water Towns', 'China National Tea Museum', 'Hefang Street'] and the order can be decided by you.\n2. one day(2023-07-10 07:00 ~ 2023-07-10 07:00) for this trip. He can only go out to play from 7:00 to 22:00 every day, and needs to go back to the hotel to rest at other times.\n3. Visit Lingyin Temple for 90 minutes, Quaint Water Towns for 120 minutes, China National Tea Museum for 90 minutes, Hefang Street for 90 minutes.\n4. 12:00 ~ 13:00 for lunch and  18:30 ~ 19:30 for dinner.\n5. Ignore the opening hours of attractions, assuming they are open all day\n6. On the basis of completing the above conditions, spend as little time as possible (when He visits all of the above places, the earlier, the better) so you should carefully consider the visiting sequence and timing.\n",
        "demands": {
            "TravelSimulator": {
                "begin_time": "2023-07-10 07:00",
                "end_time": "2023-07-11 00:00",
                "origin_city": "Hangzhou",
                "origin_place": "Hangzhou Railway Hotel",
                "budget": 99999,
                "check_opening_hours": false,
                "check_meal": true,
                "time_min": 34417,
                "time_max": 42910
            },
            "Constraints": {
                "SpotDurationConstraint": [
                    {
                        "spot": "Lingyin Temple",
                        "minutes": 90
                    },
                    {
                        "spot": "Quaint Water Towns",
                        "minutes": 120
                    },
                    {
                        "spot": "China National Tea Museum",
                        "minutes": 90
                    },
                    {
                        "spot": "Hefang Street",
                        "minutes": 90
                    }
                ]
            }
        },
        "type": 2
    },
    {
        "question": "Bob is going to play in Wuhan, please make a visit plan for him.    The demands are as follows:\n1. He lives in Wuhan Railway Hotel. He needs to visit ['East Lake', 'Han Show', 'Hubu Alley', 'Baotong Temple'] and the order can be decided by you.\n2. one day(2023-07-09 07:00 ~ 2023-07-09 07:00) for this trip. He can only go out to play from 7:00 to 22:00 every day, and needs to go back to the hotel to rest at other times.\n3. Visit East Lake for 120 minutes, Han Show for 120 minutes, Hubu Alley for 60 minutes, Baotong Temple for 90 minutes.\n4. 12:00 ~ 13:00 for lunch and  18:30 ~ 19:30 for dinner.\n5. Ignore the opening hours of attractions, assuming they are open all day\n6. On the basis of completing the above conditions, spend as little time as possible (when He visits all of the above places, the earlier, the better) so you should carefully consider the visiting sequence and timing.\n",
        "demands": {
            "TravelSimulator": {
                "begin_time": "2023-07-09 07:00",
                "end_time": "2023-07-10 00:00",
                "origin_city": "Wuhan",
                "origin_place": "Wuhan Railway Hotel",
                "budget": 99999,
                "check_opening_hours": false,
                "check_meal": true,
                "time_min": 45343,
                "time_max": 54364
            },
            "Constraints": {
                "SpotDurationConstraint": [
                    {
                        "spot": "East Lake",
                        "minutes": 120
                    },
                    {
                        "spot": "Han Show",
                        "minutes": 120
                    },
                    {
                        "spot": "Hubu Alley",
                        "minutes": 60
                    },
                    {
                        "spot": "Baotong Temple",
                        "minutes": 90
                    }
                ]
            }
        },
        "type": 2
    },
    {
        "question": "Bob is going to play in Guangzhou, please make a visit plan for him.    The demands are as follows:\n1. He lives in Guangzhou Railway Hotel. He needs to visit ['Baiyun Mountain', 'Canton Tower', 'Yuexiu Park', 'Huacheng Square'] and the order can be decided by you.\n2. one day(2023-07-09 07:00 ~ 2023-07-09 07:00) for this trip. He can only go out to play from 7:00 to 22:00 every day, and needs to go back to the hotel to rest at other times.\n3. Visit Baiyun Mountain for 90 minutes, Canton Tower for 120 minutes, Yuexiu Park for 120 minutes, Huacheng Square for 120 minutes.\n4. 12:00 ~ 13:00 for lunch and  18:30 ~ 19:30 for dinner.\n5. The daily opening_hours of spots can be obtained from the database table place. \"opening_hours_begin\" and \"opening_hours_end\" are the opening and closing times respectively\n6. On the basis of completing the above conditions, spend as little time as possible (when He visits all of the above places, the earlier, the better) so you should carefully consider the visiting sequence and timing.\n",
        "demands": {
            "TravelSimulator": {
                "begin_time": "2023-07-09 07:00",
                "end_time": "2023-07-10 00:00",
                "origin_city": "Guangzhou",
                "origin_place": "Guangzhou Railway Hotel",
                "budget": 99999,
                "check_opening_hours": true,
                "check_meal": true,
                "time_min": 52772,
                "time_max": 55935
            },
            "Constraints": {
                "SpotDurationConstraint": [
                    {
                        "spot": "Baiyun Mountain",
                        "minutes": 90
                    },
                    {
                        "spot": "Canton Tower",
                        "minutes": 120
                    },
                    {
                        "spot": "Yuexiu Park",
                        "minutes": 120
                    },
                    {
                        "spot": "Huacheng Square",
                        "minutes": 120
                    }
                ]
            }
        },
        "type": 2
    },
    {
        "question": "Bob is going to play in Nanjing, please make a visit plan for him.    The demands are as follows:\n1. He lives in Nanjing Railway Hotel. He needs to visit ['Lake Xuanwu', 'Tomb of Ming Emperor Zhu Yuanzhang', 'Taiping Heavenly-Kingdom Palace', 'Bailuzhou Park'] and the order can be decided by you.\n2. one day(2023-07-04 07:00 ~ 2023-07-04 07:00) for this trip. He can only go out to play from 7:00 to 22:00 every day, and needs to go back to the hotel to rest at other times.\n3. Visit Lake Xuanwu for 120 minutes, Tomb of Ming Emperor Zhu Yuanzhang for 90 minutes, Taiping Heavenly-Kingdom Palace for 90 minutes, Bailuzhou Park for 90 minutes.\n4. 12:00 ~ 13:00 for lunch and  18:30 ~ 19:30 for dinner.\n5. The daily opening_hours of spots can be obtained from the database table place. \"opening_hours_begin\" and \"opening_hours_end\" are the opening and closing times respectively\n6. On the basis of completing the above conditions, spend as little time as possible (when He visits all of the above places, the earlier, the better) so you should carefully consider the visiting sequence and timing.\n",
        "demands": {
            "TravelSimulator": {
                "begin_time": "2023-07-04 07:00",
                "end_time": "2023-07-05 00:00",
                "origin_city": "Nanjing",
                "origin_place": "Nanjing Railway Hotel",
                "budget": 99999,
                "check_opening_hours": true,
                "check_meal": true,
                "time_min": 44926,
                "time_max": 52549
            },
            "Constraints": {
                "SpotDurationConstraint": [
                    {
                        "spot": "Lake Xuanwu",
                        "minutes": 120
                    },
                    {
                        "spot": "Tomb of Ming Emperor Zhu Yuanzhang",
                        "minutes": 90
                    },
                    {
                        "spot": "Taiping Heavenly-Kingdom Palace",
                        "minutes": 90
                    },
                    {
                        "spot": "Bailuzhou Park",
                        "minutes": 90
                    }
                ]
            }
        },
        "type": 2
    },
    {
        "question": "Bob is going to play in Wuhan, please make a visit plan for him.    The demands are as follows:\n1. He lives in Wuhan Railway Hotel. He needs to visit ['Hubu Alley', 'Tan Hua Lin'] and the order can be decided by you.\n2. one day(2023-07-10 07:00 ~ 2023-07-10 07:00) for this trip. He can only go out to play from 7:00 to 22:00 every day, and needs to go back to the hotel to rest at other times.\n3. Visit Hubu Alley for 240 minutes, Tan Hua Lin for 240 minutes.\n4. Ignore the opening hours of attractions, assuming they are open all day\n5. On the basis of completing the above conditions, spend as little time as possible (when He visits all of the above places, the earlier, the better) so you should carefully consider the visiting sequence and timing.\n",
        "demands": {
            "TravelSimulator": {
                "begin_time": "2023-07-10 07:00",
                "end_time": "2023-07-11 00:00",
                "origin_city": "Wuhan",
                "origin_place": "Wuhan Railway Hotel",
                "budget": 99999,
                "check_opening_hours": false,
                "check_meal": false,
                "time_min": 39360,
                "time_max": 39360
            },
            "Constraints": {
                "SpotDurationConstraint": [
                    {
                        "spot": "Hubu Alley",
                        "minutes": 240
                    },
                    {
                        "spot": "Tan Hua Lin",
                        "minutes": 240
                    }
                ]
            }
        },
        "type": 2
    },
    {
        "question": "Bob is going to play in Nanjing, please make a visit plan for him.    The demands are as follows:\n1. He lives in Nanjing Railway Hotel. He needs to visit ['Bailuzhou Park', 'Tomb of Ming Emperor Zhu Yuanzhang'] and the order can be decided by you.\n2. one day(2023-07-08 07:00 ~ 2023-07-08 07:00) for this trip. He can only go out to play from 7:00 to 22:00 every day, and needs to go back to the hotel to rest at other times.\n3. Visit Bailuzhou Park for 180 minutes, Tomb of Ming Emperor Zhu Yuanzhang for 270 minutes.\n4. Ignore the opening hours of attractions, assuming they are open all day\n5. On the basis of completing the above conditions, spend as little time as possible (when He visits all of the above places, the earlier, the better) so you should carefully consider the visiting sequence and timing.\n",
        "demands": {
            "TravelSimulator": {
                "begin_time": "2023-07-08 07:00",
                "end_time": "2023-07-09 00:00",
                "origin_city": "Nanjing",
                "origin_place": "Nanjing Railway Hotel",
                "budget": 99999,
                "check_opening_hours": false,
                "check_meal": false,
                "time_min": 39386,
                "time_max": 54141
            },
            "Constraints": {
                "SpotDurationConstraint": [
                    {
                        "spot": "Bailuzhou Park",
                        "minutes": 180
                    },
                    {
                        "spot": "Tomb of Ming Emperor Zhu Yuanzhang",
                        "minutes": 270
                    }
                ]
            }
        },
        "type": 2
    },
    {
        "question": "Bob is going to play in Shanghai, please make a visit plan for him.    The demands are as follows:\n1. He lives in Shanghai Railway Hotel. He needs to visit ['Century Park', 'Huangpu River Cruise'] and the order can be decided by you.\n2. one day(2023-07-07 07:00 ~ 2023-07-07 07:00) for this trip. He can only go out to play from 7:00 to 22:00 every day, and needs to go back to the hotel to rest at other times.\n3. Visit Century Park for 270 minutes, Huangpu River Cruise for 240 minutes.\n4. The daily opening_hours of spots can be obtained from the database table place. \"opening_hours_begin\" and \"opening_hours_end\" are the opening and closing times respectively\n5. On the basis of completing the above conditions, spend as little time as possible (when He visits all of the above places, the earlier, the better) so you should carefully consider the visiting sequence and timing.\n",
        "demands": {
            "TravelSimulator": {
                "begin_time": "2023-07-07 07:00",
                "end_time": "2023-07-08 00:00",
                "origin_city": "Shanghai",
                "origin_place": "Shanghai Railway Hotel",
                "budget": 99999,
                "check_opening_hours": true,
                "check_meal": false,
                "time_min": 59400,
                "time_max": 61200
            },
            "Constraints": {
                "SpotDurationConstraint": [
                    {
                        "spot": "Century Park",
                        "minutes": 270
                    },
                    {
                        "spot": "Huangpu River Cruise",
                        "minutes": 240
                    }
                ]
            }
        },
        "type": 2
    },
    {
        "question": "Bob is going to play in Beijing, please make a visit plan for him.    The demands are as follows:\n1. He lives in Beijing Railway Hotel. He needs to visit ['The Great Wall', 'Shihua Cave'] and the order can be decided by you.\n2. one day(2023-07-02 07:00 ~ 2023-07-02 07:00) for this trip. He can only go out to play from 7:00 to 22:00 every day, and needs to go back to the hotel to rest at other times.\n3. Visit The Great Wall for 300 minutes, Shihua Cave for 150 minutes.\n4. The daily opening_hours of spots can be obtained from the database table place. \"opening_hours_begin\" and \"opening_hours_end\" are the opening and closing times respectively\n5. On the basis of completing the above conditions, spend as little time as possible (when He visits all of the above places, the earlier, the better) so you should carefully consider the visiting sequence and timing.\n",
        "demands": {
            "TravelSimulator": {
                "begin_time": "2023-07-02 07:00",
                "end_time": "2023-07-03 00:00",
                "origin_city": "Beijing",
                "origin_place": "Beijing Railway Hotel",
                "budget": 99999,
                "check_opening_hours": true,
                "check_meal": false,
                "time_min": 48240,
                "time_max": 56880
            },
            "Constraints": {
                "SpotDurationConstraint": [
                    {
                        "spot": "The Great Wall",
                        "minutes": 300
                    },
                    {
                        "spot": "Shihua Cave",
                        "minutes": 150
                    }
                ]
            }
        },
        "type": 2
    },
    {
        "question": "Bob is going to play in Nanjing, please make a visit plan for him.    The demands are as follows:\n1. He lives in Nanjing Railway Hotel. He needs to visit ['Qinhuai River', 'Tomb of Ming Emperor Zhu Yuanzhang'] and the order can be decided by you.\n2. one day(2023-07-11 07:00 ~ 2023-07-11 07:00) for this trip. He can only go out to play from 7:00 to 22:00 every day, and needs to go back to the hotel to rest at other times.\n3. Visit Qinhuai River for 270 minutes, Tomb of Ming Emperor Zhu Yuanzhang for 120 minutes.\n4. 12:00 ~ 13:00 for lunch and  18:30 ~ 19:30 for dinner.\n5. Ignore the opening hours of attractions, assuming they are open all day\n6. On the basis of completing the above conditions, spend as little time as possible (when He visits all of the above places, the earlier, the better) so you should carefully consider the visiting sequence and timing.\n",
        "demands": {
            "TravelSimulator": {
                "begin_time": "2023-07-11 07:00",
                "end_time": "2023-07-12 00:00",
                "origin_city": "Nanjing",
                "origin_place": "Nanjing Railway Hotel",
                "budget": 99999,
                "check_opening_hours": false,
                "check_meal": true,
                "time_min": 34062,
                "time_max": 38177
            },
            "Constraints": {
                "SpotDurationConstraint": [
                    {
                        "spot": "Qinhuai River",
                        "minutes": 270
                    },
                    {
                        "spot": "Tomb of Ming Emperor Zhu Yuanzhang",
                        "minutes": 120
                    }
                ]
            }
        },
        "type": 2
    },
    {
        "question": "Bob is going to play in Guangzhou, please make a visit plan for him.    The demands are as follows:\n1. He lives in Guangzhou Railway Hotel. He needs to visit ['Yuexiu Park', 'Huacheng Square'] and the order can be decided by you.\n2. one day(2023-07-03 07:00 ~ 2023-07-03 07:00) for this trip. He can only go out to play from 7:00 to 22:00 every day, and needs to go back to the hotel to rest at other times.\n3. Visit Yuexiu Park for 300 minutes, Huacheng Square for 240 minutes.\n4. 12:00 ~ 13:00 for lunch and  18:30 ~ 19:30 for dinner.\n5. Ignore the opening hours of attractions, assuming they are open all day\n6. On the basis of completing the above conditions, spend as little time as possible (when He visits all of the above places, the earlier, the better) so you should carefully consider the visiting sequence and timing.\n",
        "demands": {
            "TravelSimulator": {
                "begin_time": "2023-07-03 07:00",
                "end_time": "2023-07-04 00:00",
                "origin_city": "Guangzhou",
                "origin_place": "Guangzhou Railway Hotel",
                "budget": 99999,
                "check_opening_hours": false,
                "check_meal": true,
                "time_min": 61680,
                "time_max": 63000
            },
            "Constraints": {
                "SpotDurationConstraint": [
                    {
                        "spot": "Yuexiu Park",
                        "minutes": 300
                    },
                    {
                        "spot": "Huacheng Square",
                        "minutes": 240
                    }
                ]
            }
        },
        "type": 2
    },
    {
        "question": "Bob is going to play in Shanghai, please make a visit plan for him.    The demands are as follows:\n1. He lives in Shanghai Railway Hotel. He needs to visit ['Huangpu River Cruise', 'Longhua Temple'] and the order can be decided by you.\n2. one day(2023-07-05 07:00 ~ 2023-07-05 07:00) for this trip. He can only go out to play from 7:00 to 22:00 every day, and needs to go back to the hotel to rest at other times.\n3. Visit Huangpu River Cruise for 120 minutes, Longhua Temple for 210 minutes.\n4. 12:00 ~ 13:00 for lunch and  18:30 ~ 19:30 for dinner.\n5. The daily opening_hours of spots can be obtained from the database table place. \"opening_hours_begin\" and \"opening_hours_end\" are the opening and closing times respectively\n6. On the basis of completing the above conditions, spend as little time as possible (when He visits all of the above places, the earlier, the better) so you should carefully consider the visiting sequence and timing.\n",
        "demands": {
            "TravelSimulator": {
                "begin_time": "2023-07-05 07:00",
                "end_time": "2023-07-06 00:00",
                "origin_city": "Shanghai",
                "origin_place": "Shanghai Railway Hotel",
                "budget": 99999,
                "check_opening_hours": true,
                "check_meal": true,
                "time_min": 28314,
                "time_max": 33605
            },
            "Constraints": {
                "SpotDurationConstraint": [
                    {
                        "spot": "Huangpu River Cruise",
                        "minutes": 120
                    },
                    {
                        "spot": "Longhua Temple",
                        "minutes": 210
                    }
                ]
            }
        },
        "type": 2
    },
    {
        "question": "Bob is going to play in Nanjing, please make a visit plan for him.    The demands are as follows:\n1. He lives in Nanjing Railway Hotel. He needs to visit ['Qinhuai River', 'Tomb of Ming Emperor Zhu Yuanzhang'] and the order can be decided by you.\n2. one day(2023-07-07 07:00 ~ 2023-07-07 07:00) for this trip. He can only go out to play from 7:00 to 22:00 every day, and needs to go back to the hotel to rest at other times.\n3. Visit Qinhuai River for 180 minutes, Tomb of Ming Emperor Zhu Yuanzhang for 150 minutes.\n4. 12:00 ~ 13:00 for lunch and  18:30 ~ 19:30 for dinner.\n5. The daily opening_hours of spots can be obtained from the database table place. \"opening_hours_begin\" and \"opening_hours_end\" are the opening and closing times respectively\n6. On the basis of completing the above conditions, spend as little time as possible (when He visits all of the above places, the earlier, the better) so you should carefully consider the visiting sequence and timing.\n",
        "demands": {
            "TravelSimulator": {
                "begin_time": "2023-07-07 07:00",
                "end_time": "2023-07-08 00:00",
                "origin_city": "Nanjing",
                "origin_place": "Nanjing Railway Hotel",
                "budget": 99999,
                "check_opening_hours": true,
                "check_meal": true,
                "time_min": 30600,
                "time_max": 37200
            },
            "Constraints": {
                "SpotDurationConstraint": [
                    {
                        "spot": "Qinhuai River",
                        "minutes": 180
                    },
                    {
                        "spot": "Tomb of Ming Emperor Zhu Yuanzhang",
                        "minutes": 150
                    }
                ]
            }
        },
        "type": 2
    },
    {
        "question": "Bob is going to play in Shanghai, please make a visit plan for him.    The demands are as follows:\n1. He lives in Shanghai Railway Hotel. He needs to visit ['Longhua Temple', 'Shanghai Disney', 'Shanghai Sightseeing Tunnel', 'Century Park'] and the order can be decided by you.\n2. 2 days(2023-07-10 07:00 ~ 2023-07-12 00:00) for this trip. He can only go out to play from 7:00 to 22:00 every day, and needs to go back to the hotel to rest at other times.\n3. Visit Longhua Temple for 270 minutes, Shanghai Disney for 120 minutes, Shanghai Sightseeing Tunnel for 150 minutes, Century Park for 150 minutes.\n4. Ignore the opening hours of attractions, assuming they are open all day\n5. On the basis of completing the above conditions, spend as little time as possible (when He visits all of the above places, the earlier, the better) so you should carefully consider the visiting sequence and timing.\n",
        "demands": {
            "TravelSimulator": {
                "begin_time": "2023-07-10 07:00",
                "end_time": "2023-07-12 00:00",
                "origin_city": "Shanghai",
                "origin_place": "Shanghai Railway Hotel",
                "budget": 99999,
                "check_opening_hours": false,
                "check_meal": false,
                "time_min": 62001,
                "time_max": 69170
            },
            "Constraints": {
                "SpotDurationConstraint": [
                    {
                        "spot": "Longhua Temple",
                        "minutes": 270
                    },
                    {
                        "spot": "Shanghai Disney",
                        "minutes": 120
                    },
                    {
                        "spot": "Shanghai Sightseeing Tunnel",
                        "minutes": 150
                    },
                    {
                        "spot": "Century Park",
                        "minutes": 150
                    }
                ]
            }
        },
        "type": 2
    },
    {
        "question": "Bob is going to play in Nanjing, please make a visit plan for him.    The demands are as follows:\n1. He lives in Nanjing Railway Hotel. He needs to visit ['Lake Xuanwu', 'Qinhuai River', 'Ming Palace', 'Bailuzhou Park'] and the order can be decided by you.\n2. 2 days(2023-07-11 07:00 ~ 2023-07-13 00:00) for this trip. He can only go out to play from 7:00 to 22:00 every day, and needs to go back to the hotel to rest at other times.\n3. Visit Lake Xuanwu for 150 minutes, Qinhuai River for 240 minutes, Ming Palace for 300 minutes, Bailuzhou Park for 300 minutes.\n4. Ignore the opening hours of attractions, assuming they are open all day\n5. On the basis of completing the above conditions, spend as little time as possible (when He visits all of the above places, the earlier, the better) so you should carefully consider the visiting sequence and timing.\n",
        "demands": {
            "TravelSimulator": {
                "begin_time": "2023-07-11 07:00",
                "end_time": "2023-07-13 00:00",
                "origin_city": "Nanjing",
                "origin_place": "Nanjing Railway Hotel",
                "budget": 99999,
                "check_opening_hours": false,
                "check_meal": false,
                "time_min": 79579,
                "time_max": 93340
            },
            "Constraints": {
                "SpotDurationConstraint": [
                    {
                        "spot": "Lake Xuanwu",
                        "minutes": 150
                    },
                    {
                        "spot": "Qinhuai River",
                        "minutes": 240
                    },
                    {
                        "spot": "Ming Palace",
                        "minutes": 300
                    },
                    {
                        "spot": "Bailuzhou Park",
                        "minutes": 300
                    }
                ]
            }
        },
        "type": 2
    },
    {
        "question": "Bob is going to play in Hangzhou, please make a visit plan for him.    The demands are as follows:\n1. He lives in Hangzhou Railway Hotel. He needs to visit ['Lingyin Temple', 'Hefang Street', 'China National Tea Museum', 'Quaint Water Towns'] and the order can be decided by you.\n2. 2 days(2023-07-06 07:00 ~ 2023-07-08 00:00) for this trip. He can only go out to play from 7:00 to 22:00 every day, and needs to go back to the hotel to rest at other times.\n3. Visit Lingyin Temple for 240 minutes, Hefang Street for 300 minutes, China National Tea Museum for 120 minutes, Quaint Water Towns for 150 minutes.\n4. The daily opening_hours of spots can be obtained from the database table place. \"opening_hours_begin\" and \"opening_hours_end\" are the opening and closing times respectively\n5. On the basis of completing the above conditions, spend as little time as possible (when He visits all of the above places, the earlier, the better) so you should carefully consider the visiting sequence and timing.\n",
        "demands": {
            "TravelSimulator": {
                "begin_time": "2023-07-06 07:00",
                "end_time": "2023-07-08 00:00",
                "origin_city": "Hangzhou",
                "origin_place": "Hangzhou Railway Hotel",
                "budget": 99999,
                "check_opening_hours": true,
                "check_meal": false,
                "time_min": 71208,
                "time_max": 78731
            },
            "Constraints": {
                "SpotDurationConstraint": [
                    {
                        "spot": "Lingyin Temple",
                        "minutes": 240
                    },
                    {
                        "spot": "Hefang Street",
                        "minutes": 300
                    },
                    {
                        "spot": "China National Tea Museum",
                        "minutes": 120
                    },
                    {
                        "spot": "Quaint Water Towns",
                        "minutes": 150
                    }
                ]
            }
        },
        "type": 2
    },
    {
        "question": "Bob is going to play in Beijing, please make a visit plan for him.    The demands are as follows:\n1. He lives in Beijing Railway Hotel. He needs to visit ['The Temple of Heaven', 'The Summer Palace', 'Beijing Olympic Park', 'The Forbidden City'] and the order can be decided by you.\n2. 2 days(2023-07-10 07:00 ~ 2023-07-12 00:00) for this trip. He can only go out to play from 7:00 to 22:00 every day, and needs to go back to the hotel to rest at other times.\n3. Visit The Temple of Heaven for 270 minutes, The Summer Palace for 120 minutes, Beijing Olympic Park for 150 minutes, The Forbidden City for 120 minutes.\n4. The daily opening_hours of spots can be obtained from the database table place. \"opening_hours_begin\" and \"opening_hours_end\" are the opening and closing times respectively\n5. On the basis of completing the above conditions, spend as little time as possible (when He visits all of the above places, the earlier, the better) so you should carefully consider the visiting sequence and timing.\n",
        "demands": {
            "TravelSimulator": {
                "begin_time": "2023-07-10 07:00",
                "end_time": "2023-07-12 00:00",
                "origin_city": "Beijing",
                "origin_place": "Beijing Railway Hotel",
                "budget": 99999,
                "check_opening_hours": true,
                "check_meal": false,
                "time_min": 65050,
                "time_max": 74557
            },
            "Constraints": {
                "SpotDurationConstraint": [
                    {
                        "spot": "The Temple of Heaven",
                        "minutes": 270
                    },
                    {
                        "spot": "The Summer Palace",
                        "minutes": 120
                    },
                    {
                        "spot": "Beijing Olympic Park",
                        "minutes": 150
                    },
                    {
                        "spot": "The Forbidden City",
                        "minutes": 120
                    }
                ]
            }
        },
        "type": 2
    },
    {
        "question": "Bob is going to play in Beijing, please make a visit plan for him.    The demands are as follows:\n1. He lives in Beijing Railway Hotel. He needs to visit ['The Forbidden City', 'Beijing Olympic Park', 'The Temple of Heaven', 'Shihua Cave'] and the order can be decided by you.\n2. 2 days(2023-07-05 07:00 ~ 2023-07-07 00:00) for this trip. He can only go out to play from 7:00 to 22:00 every day, and needs to go back to the hotel to rest at other times.\n3. Visit The Forbidden City for 120 minutes, Beijing Olympic Park for 240 minutes, The Temple of Heaven for 270 minutes, Shihua Cave for 210 minutes.\n4. 12:00 ~ 13:00 for lunch and  18:30 ~ 19:30 for dinner.\n5. Ignore the opening hours of attractions, assuming they are open all day\n6. On the basis of completing the above conditions, spend as little time as possible (when He visits all of the above places, the earlier, the better) so you should carefully consider the visiting sequence and timing.\n",
        "demands": {
            "TravelSimulator": {
                "begin_time": "2023-07-05 07:00",
                "end_time": "2023-07-07 00:00",
                "origin_city": "Beijing",
                "origin_place": "Beijing Railway Hotel",
                "budget": 99999,
                "check_opening_hours": false,
                "check_meal": true,
                "time_min": 75660,
                "time_max": 85223
            },
            "Constraints": {
                "SpotDurationConstraint": [
                    {
                        "spot": "The Forbidden City",
                        "minutes": 120
                    },
                    {
                        "spot": "Beijing Olympic Park",
                        "minutes": 240
                    },
                    {
                        "spot": "The Temple of Heaven",
                        "minutes": 270
                    },
                    {
                        "spot": "Shihua Cave",
                        "minutes": 210
                    }
                ]
            }
        },
        "type": 2
    },
    {
        "question": "Bob is going to play in Chengdu, please make a visit plan for him.    The demands are as follows:\n1. He lives in Chengdu Railway Hotel. He needs to visit ['Du Fu Thatched Cottage', 'The Chengdu Wuhou Shrine', 'Chengdu Tea Houses', 'Leshan Giant Buddha'] and the order can be decided by you.\n2. 2 days(2023-07-08 07:00 ~ 2023-07-10 00:00) for this trip. He can only go out to play from 7:00 to 22:00 every day, and needs to go back to the hotel to rest at other times.\n3. Visit Du Fu Thatched Cottage for 210 minutes, The Chengdu Wuhou Shrine for 240 minutes, Chengdu Tea Houses for 120 minutes, Leshan Giant Buddha for 240 minutes.\n4. 12:00 ~ 13:00 for lunch and  18:30 ~ 19:30 for dinner.\n5. Ignore the opening hours of attractions, assuming they are open all day\n6. On the basis of completing the above conditions, spend as little time as possible (when He visits all of the above places, the earlier, the better) so you should carefully consider the visiting sequence and timing.\n",
        "demands": {
            "TravelSimulator": {
                "begin_time": "2023-07-08 07:00",
                "end_time": "2023-07-10 00:00",
                "origin_city": "Chengdu",
                "origin_place": "Chengdu Railway Hotel",
                "budget": 99999,
                "check_opening_hours": false,
                "check_meal": true,
                "time_min": 71113,
                "time_max": 83350
            },
            "Constraints": {
                "SpotDurationConstraint": [
                    {
                        "spot": "Du Fu Thatched Cottage",
                        "minutes": 210
                    },
                    {
                        "spot": "The Chengdu Wuhou Shrine",
                        "minutes": 240
                    },
                    {
                        "spot": "Chengdu Tea Houses",
                        "minutes": 120
                    },
                    {
                        "spot": "Leshan Giant Buddha",
                        "minutes": 240
                    }
                ]
            }
        },
        "type": 2
    },
    {
        "question": "Bob is going to play in Hangzhou, please make a visit plan for him.    The demands are as follows:\n1. He lives in Hangzhou Railway Hotel. He needs to visit ['West Lake', 'China National Tea Museum', 'Lingyin Temple', 'Hefang Street'] and the order can be decided by you.\n2. 2 days(2023-07-03 07:00 ~ 2023-07-05 00:00) for this trip. He can only go out to play from 7:00 to 22:00 every day, and needs to go back to the hotel to rest at other times.\n3. Visit West Lake for 270 minutes, China National Tea Museum for 300 minutes, Lingyin Temple for 210 minutes, Hefang Street for 180 minutes.\n4. 12:00 ~ 13:00 for lunch and  18:30 ~ 19:30 for dinner.\n5. The daily opening_hours of spots can be obtained from the database table place. \"opening_hours_begin\" and \"opening_hours_end\" are the opening and closing times respectively\n6. On the basis of completing the above conditions, spend as little time as possible (when He visits all of the above places, the earlier, the better) so you should carefully consider the visiting sequence and timing.\n",
        "demands": {
            "TravelSimulator": {
                "begin_time": "2023-07-03 07:00",
                "end_time": "2023-07-05 00:00",
                "origin_city": "Hangzhou",
                "origin_place": "Hangzhou Railway Hotel",
                "budget": 99999,
                "check_opening_hours": true,
                "check_meal": true,
                "time_min": 77690,
                "time_max": 88689
            },
            "Constraints": {
                "SpotDurationConstraint": [
                    {
                        "spot": "West Lake",
                        "minutes": 270
                    },
                    {
                        "spot": "China National Tea Museum",
                        "minutes": 300
                    },
                    {
                        "spot": "Lingyin Temple",
                        "minutes": 210
                    },
                    {
                        "spot": "Hefang Street",
                        "minutes": 180
                    }
                ]
            }
        },
        "type": 2
    },
    {
        "question": "Bob is going to play in Beijing, please make a visit plan for him.    The demands are as follows:\n1. He lives in Beijing Railway Hotel. He needs to visit ['Beijing Olympic Park', 'Beijing Stone Carvings Art Museum', 'Tiananmen Square', 'The Great Wall'] and the order can be decided by you.\n2. 2 days(2023-07-07 07:00 ~ 2023-07-09 00:00) for this trip. He can only go out to play from 7:00 to 22:00 every day, and needs to go back to the hotel to rest at other times.\n3. Visit Beijing Olympic Park for 180 minutes, Beijing Stone Carvings Art Museum for 120 minutes, Tiananmen Square for 300 minutes, The Great Wall for 270 minutes.\n4. 12:00 ~ 13:00 for lunch and  18:30 ~ 19:30 for dinner.\n5. The daily opening_hours of spots can be obtained from the database table place. \"opening_hours_begin\" and \"opening_hours_end\" are the opening and closing times respectively\n6. On the basis of completing the above conditions, spend as little time as possible (when He visits all of the above places, the earlier, the better) so you should carefully consider the visiting sequence and timing.\n",
        "demands": {
            "TravelSimulator": {
                "begin_time": "2023-07-07 07:00",
                "end_time": "2023-07-09 00:00",
                "origin_city": "Beijing",
                "origin_place": "Beijing Railway Hotel",
                "budget": 99999,
                "check_opening_hours": true,
                "check_meal": true,
                "time_min": 76809,
                "time_max": 89486
            },
            "Constraints": {
                "SpotDurationConstraint": [
                    {
                        "spot": "Beijing Olympic Park",
                        "minutes": 180
                    },
                    {
                        "spot": "Beijing Stone Carvings Art Museum",
                        "minutes": 120
                    },
                    {
                        "spot": "Tiananmen Square",
                        "minutes": 300
                    },
                    {
                        "spot": "The Great Wall",
                        "minutes": 270
                    }
                ]
            }
        },
        "type": 2
    },
    {
        "question": "Bob is going to play in Beijing, please make a visit plan for him.    The demands are as follows:\n1. He lives in Beijing Railway Hotel. He needs to visit ['Beijing Olympic Park', 'Tiananmen Square', 'Shihua Cave', 'The Forbidden City', 'The Summer Palace', 'Beijing Stone Carvings Art Museum', 'The Great Wall'] and the order can be decided by you.\n2. 3 days(2023-07-09 07:00 ~ 2023-07-12 00:00) for this trip. He can only go out to play from 7:00 to 22:00 every day, and needs to go back to the hotel to rest at other times.\n3. Visit Beijing Olympic Park for 210 minutes, Tiananmen Square for 150 minutes, Shihua Cave for 240 minutes, The Forbidden City for 240 minutes, The Summer Palace for 120 minutes, Beijing Stone Carvings Art Museum for 120 minutes, The Great Wall for 180 minutes.\n4. Ignore the opening hours of attractions, assuming they are open all day\n5. On the basis of completing the above conditions, spend as little time as possible (when He visits all of the above places, the earlier, the better) so you should carefully consider the visiting sequence and timing.\n",
        "demands": {
            "TravelSimulator": {
                "begin_time": "2023-07-09 07:00",
                "end_time": "2023-07-12 00:00",
                "origin_city": "Beijing",
                "origin_place": "Beijing Railway Hotel",
                "budget": 99999,
                "check_opening_hours": false,
                "check_meal": false,
                "time_min": 116824,
                "time_max": 122095
            },
            "Constraints": {
                "SpotDurationConstraint": [
                    {
                        "spot": "Beijing Olympic Park",
                        "minutes": 210
                    },
                    {
                        "spot": "Tiananmen Square",
                        "minutes": 150
                    },
                    {
                        "spot": "Shihua Cave",
                        "minutes": 240
                    },
                    {
                        "spot": "The Forbidden City",
                        "minutes": 240
                    },
                    {
                        "spot": "The Summer Palace",
                        "minutes": 120
                    },
                    {
                        "spot": "Beijing Stone Carvings Art Museum",
                        "minutes": 120
                    },
                    {
                        "spot": "The Great Wall",
                        "minutes": 180
                    }
                ]
            }
        },
        "type": 2
    },
    {
        "question": "Bob is going to play in Beijing, please make a visit plan for him.    The demands are as follows:\n1. He lives in Beijing Railway Hotel. He needs to visit ['The Great Wall', 'Tiananmen Square', 'Shihua Cave', 'The Forbidden City', 'Beijing Olympic Park', 'The Summer Palace', 'Beijing Stone Carvings Art Museum'] and the order can be decided by you.\n2. 3 days(2023-07-03 07:00 ~ 2023-07-06 00:00) for this trip. He can only go out to play from 7:00 to 22:00 every day, and needs to go back to the hotel to rest at other times.\n3. Visit The Great Wall for 240 minutes, Tiananmen Square for 180 minutes, Shihua Cave for 210 minutes, The Forbidden City for 270 minutes, Beijing Olympic Park for 210 minutes, The Summer Palace for 150 minutes, Beijing Stone Carvings Art Museum for 300 minutes.\n4. Ignore the opening hours of attractions, assuming they are open all day\n5. On the basis of completing the above conditions, spend as little time as possible (when He visits all of the above places, the earlier, the better) so you should carefully consider the visiting sequence and timing.\n",
        "demands": {
            "TravelSimulator": {
                "begin_time": "2023-07-03 07:00",
                "end_time": "2023-07-06 00:00",
                "origin_city": "Beijing",
                "origin_place": "Beijing Railway Hotel",
                "budget": 99999,
                "check_opening_hours": false,
                "check_meal": false,
                "time_min": 144300,
                "time_max": 152171
            },
            "Constraints": {
                "SpotDurationConstraint": [
                    {
                        "spot": "The Great Wall",
                        "minutes": 240
                    },
                    {
                        "spot": "Tiananmen Square",
                        "minutes": 180
                    },
                    {
                        "spot": "Shihua Cave",
                        "minutes": 210
                    },
                    {
                        "spot": "The Forbidden City",
                        "minutes": 270
                    },
                    {
                        "spot": "Beijing Olympic Park",
                        "minutes": 210
                    },
                    {
                        "spot": "The Summer Palace",
                        "minutes": 150
                    },
                    {
                        "spot": "Beijing Stone Carvings Art Museum",
                        "minutes": 300
                    }
                ]
            }
        },
        "type": 2
    },
    {
        "question": "Bob is going to play in Beijing, please make a visit plan for him.    The demands are as follows:\n1. He lives in Beijing Railway Hotel. He needs to visit ['Beijing Stone Carvings Art Museum', 'The Forbidden City', 'The Temple of Heaven', 'The Great Wall', 'Tiananmen Square', 'The Summer Palace', 'Beijing Olympic Park'] and the order can be decided by you.\n2. 3 days(2023-07-05 07:00 ~ 2023-07-08 00:00) for this trip. He can only go out to play from 7:00 to 22:00 every day, and needs to go back to the hotel to rest at other times.\n3. Visit Beijing Stone Carvings Art Museum for 270 minutes, The Forbidden City for 120 minutes, The Temple of Heaven for 120 minutes, The Great Wall for 240 minutes, Tiananmen Square for 270 minutes, The Summer Palace for 210 minutes, Beijing Olympic Park for 300 minutes.\n4. The daily opening_hours of spots can be obtained from the database table place. \"opening_hours_begin\" and \"opening_hours_end\" are the opening and closing times respectively\n5. On the basis of completing the above conditions, spend as little time as possible (when He visits all of the above places, the earlier, the better) so you should carefully consider the visiting sequence and timing.\n",
        "demands": {
            "TravelSimulator": {
                "begin_time": "2023-07-05 07:00",
                "end_time": "2023-07-08 00:00",
                "origin_city": "Beijing",
                "origin_place": "Beijing Railway Hotel",
                "budget": 99999,
                "check_opening_hours": true,
                "check_meal": false,
                "time_min": 128572,
                "time_max": 148231
            },
            "Constraints": {
                "SpotDurationConstraint": [
                    {
                        "spot": "Beijing Stone Carvings Art Museum",
                        "minutes": 270
                    },
                    {
                        "spot": "The Forbidden City",
                        "minutes": 120
                    },
                    {
                        "spot": "The Temple of Heaven",
                        "minutes": 120
                    },
                    {
                        "spot": "The Great Wall",
                        "minutes": 240
                    },
                    {
                        "spot": "Tiananmen Square",
                        "minutes": 270
                    },
                    {
                        "spot": "The Summer Palace",
                        "minutes": 210
                    },
                    {
                        "spot": "Beijing Olympic Park",
                        "minutes": 300
                    }
                ]
            }
        },
        "type": 2
    },
    {
        "question": "Bob is going to play in Beijing, please make a visit plan for him.    The demands are as follows:\n1. He lives in Beijing Railway Hotel. He needs to visit ['Shihua Cave', 'Tiananmen Square', 'The Temple of Heaven', 'The Summer Palace', 'Beijing Olympic Park', 'Beijing Stone Carvings Art Museum', 'The Great Wall'] and the order can be decided by you.\n2. 3 days(2023-07-09 07:00 ~ 2023-07-12 00:00) for this trip. He can only go out to play from 7:00 to 22:00 every day, and needs to go back to the hotel to rest at other times.\n3. Visit Shihua Cave for 240 minutes, Tiananmen Square for 300 minutes, The Temple of Heaven for 210 minutes, The Summer Palace for 270 minutes, Beijing Olympic Park for 270 minutes, Beijing Stone Carvings Art Museum for 300 minutes, The Great Wall for 210 minutes.\n4. The daily opening_hours of spots can be obtained from the database table place. \"opening_hours_begin\" and \"opening_hours_end\" are the opening and closing times respectively\n5. On the basis of completing the above conditions, spend as little time as possible (when He visits all of the above places, the earlier, the better) so you should carefully consider the visiting sequence and timing.\n",
        "demands": {
            "TravelSimulator": {
                "begin_time": "2023-07-09 07:00",
                "end_time": "2023-07-12 00:00",
                "origin_city": "Beijing",
                "origin_place": "Beijing Railway Hotel",
                "budget": 99999,
                "check_opening_hours": true,
                "check_meal": false,
                "time_min": 158492,
                "time_max": 173859
            },
            "Constraints": {
                "SpotDurationConstraint": [
                    {
                        "spot": "Shihua Cave",
                        "minutes": 240
                    },
                    {
                        "spot": "Tiananmen Square",
                        "minutes": 300
                    },
                    {
                        "spot": "The Temple of Heaven",
                        "minutes": 210
                    },
                    {
                        "spot": "The Summer Palace",
                        "minutes": 270
                    },
                    {
                        "spot": "Beijing Olympic Park",
                        "minutes": 270
                    },
                    {
                        "spot": "Beijing Stone Carvings Art Museum",
                        "minutes": 300
                    },
                    {
                        "spot": "The Great Wall",
                        "minutes": 210
                    }
                ]
            }
        },
        "type": 2
    },
    {
        "question": "Bob is going to play in Shanghai, please make a visit plan for him.    The demands are as follows:\n1. He lives in Shanghai Railway Hotel. He needs to visit ['Shanghai History Museum', 'Shanghai Disney', 'Huangpu River Cruise', 'Century Park', 'Qibao Ancient Town', 'Shanghai Sightseeing Tunnel', 'Xintiandi'] and the order can be decided by you.\n2. 3 days(2023-07-11 07:00 ~ 2023-07-14 00:00) for this trip. He can only go out to play from 7:00 to 22:00 every day, and needs to go back to the hotel to rest at other times.\n3. Visit Shanghai History Museum for 270 minutes, Shanghai Disney for 300 minutes, Huangpu River Cruise for 240 minutes, Century Park for 120 minutes, Qibao Ancient Town for 120 minutes, Shanghai Sightseeing Tunnel for 180 minutes, Xintiandi for 150 minutes.\n4. 12:00 ~ 13:00 for lunch and  18:30 ~ 19:30 for dinner.\n5. Ignore the opening hours of attractions, assuming they are open all day\n6. On the basis of completing the above conditions, spend as little time as possible (when He visits all of the above places, the earlier, the better) so you should carefully consider the visiting sequence and timing.\n",
        "demands": {
            "TravelSimulator": {
                "begin_time": "2023-07-11 07:00",
                "end_time": "2023-07-14 00:00",
                "origin_city": "Shanghai",
                "origin_place": "Shanghai Railway Hotel",
                "budget": 99999,
                "check_opening_hours": false,
                "check_meal": true,
                "time_min": 130449,
                "time_max": 152714
            },
            "Constraints": {
                "SpotDurationConstraint": [
                    {
                        "spot": "Shanghai History Museum",
                        "minutes": 270
                    },
                    {
                        "spot": "Shanghai Disney",
                        "minutes": 300
                    },
                    {
                        "spot": "Huangpu River Cruise",
                        "minutes": 240
                    },
                    {
                        "spot": "Century Park",
                        "minutes": 120
                    },
                    {
                        "spot": "Qibao Ancient Town",
                        "minutes": 120
                    },
                    {
                        "spot": "Shanghai Sightseeing Tunnel",
                        "minutes": 180
                    },
                    {
                        "spot": "Xintiandi",
                        "minutes": 150
                    }
                ]
            }
        },
        "type": 2
    },
    {
        "question": "Bob is going to play in Shanghai, please make a visit plan for him.    The demands are as follows:\n1. He lives in Shanghai Railway Hotel. He needs to visit ['Qibao Ancient Town', 'Xintiandi', 'Century Park', 'Shanghai Sightseeing Tunnel', 'Longhua Temple', 'Shanghai Disney', 'Shanghai History Museum'] and the order can be decided by you.\n2. 3 days(2023-07-05 07:00 ~ 2023-07-08 00:00) for this trip. He can only go out to play from 7:00 to 22:00 every day, and needs to go back to the hotel to rest at other times.\n3. Visit Qibao Ancient Town for 270 minutes, Xintiandi for 270 minutes, Century Park for 270 minutes, Shanghai Sightseeing Tunnel for 180 minutes, Longhua Temple for 210 minutes, Shanghai Disney for 150 minutes, Shanghai History Museum for 240 minutes.\n4. 12:00 ~ 13:00 for lunch and  18:30 ~ 19:30 for dinner.\n5. Ignore the opening hours of attractions, assuming they are open all day\n6. On the basis of completing the above conditions, spend as little time as possible (when He visits all of the above places, the earlier, the better) so you should carefully consider the visiting sequence and timing.\n",
        "demands": {
            "TravelSimulator": {
                "begin_time": "2023-07-05 07:00",
                "end_time": "2023-07-08 00:00",
                "origin_city": "Shanghai",
                "origin_place": "Shanghai Railway Hotel",
                "budget": 99999,
                "check_opening_hours": false,
                "check_meal": true,
                "time_min": 144838,
                "time_max": 159637
            },
            "Constraints": {
                "SpotDurationConstraint": [
                    {
                        "spot": "Qibao Ancient Town",
                        "minutes": 270
                    },
                    {
                        "spot": "Xintiandi",
                        "minutes": 270
                    },
                    {
                        "spot": "Century Park",
                        "minutes": 270
                    },
                    {
                        "spot": "Shanghai Sightseeing Tunnel",
                        "minutes": 180
                    },
                    {
                        "spot": "Longhua Temple",
                        "minutes": 210
                    },
                    {
                        "spot": "Shanghai Disney",
                        "minutes": 150
                    },
                    {
                        "spot": "Shanghai History Museum",
                        "minutes": 240
                    }
                ]
            }
        },
        "type": 2
    },
    {
        "question": "Bob is going to play in Beijing, please make a visit plan for him.    The demands are as follows:\n1. He lives in Beijing Railway Hotel. He needs to visit ['Tiananmen Square', 'Beijing Stone Carvings Art Museum', 'The Summer Palace', 'The Forbidden City', 'Shihua Cave', 'The Great Wall', 'The Temple of Heaven'] and the order can be decided by you.\n2. 3 days(2023-07-10 07:00 ~ 2023-07-13 00:00) for this trip. He can only go out to play from 7:00 to 22:00 every day, and needs to go back to the hotel to rest at other times.\n3. Visit Tiananmen Square for 180 minutes, Beijing Stone Carvings Art Museum for 150 minutes, The Summer Palace for 150 minutes, The Forbidden City for 210 minutes, Shihua Cave for 270 minutes, The Great Wall for 150 minutes, The Temple of Heaven for 210 minutes.\n4. 12:00 ~ 13:00 for lunch and  18:30 ~ 19:30 for dinner.\n5. The daily opening_hours of spots can be obtained from the database table place. \"opening_hours_begin\" and \"opening_hours_end\" are the opening and closing times respectively\n6. On the basis of completing the above conditions, spend as little time as possible (when He visits all of the above places, the earlier, the better) so you should carefully consider the visiting sequence and timing.\n",
        "demands": {
            "TravelSimulator": {
                "begin_time": "2023-07-10 07:00",
                "end_time": "2023-07-13 00:00",
                "origin_city": "Beijing",
                "origin_place": "Beijing Railway Hotel",
                "budget": 99999,
                "check_opening_hours": true,
                "check_meal": true,
                "time_min": 115161,
                "time_max": 138350
            },
            "Constraints": {
                "SpotDurationConstraint": [
                    {
                        "spot": "Tiananmen Square",
                        "minutes": 180
                    },
                    {
                        "spot": "Beijing Stone Carvings Art Museum",
                        "minutes": 150
                    },
                    {
                        "spot": "The Summer Palace",
                        "minutes": 150
                    },
                    {
                        "spot": "The Forbidden City",
                        "minutes": 210
                    },
                    {
                        "spot": "Shihua Cave",
                        "minutes": 270
                    },
                    {
                        "spot": "The Great Wall",
                        "minutes": 150
                    },
                    {
                        "spot": "The Temple of Heaven",
                        "minutes": 210
                    }
                ]
            }
        },
        "type": 2
    },
    {
        "question": "Bob is going to play in Shanghai, please make a visit plan for him.    The demands are as follows:\n1. He lives in Shanghai Railway Hotel. He needs to visit ['Century Park', 'Shanghai Disney', 'Shanghai Sightseeing Tunnel', 'Xintiandi', 'Qibao Ancient Town', 'Shanghai History Museum', 'Huangpu River Cruise'] and the order can be decided by you.\n2. 3 days(2023-07-08 07:00 ~ 2023-07-11 00:00) for this trip. He can only go out to play from 7:00 to 22:00 every day, and needs to go back to the hotel to rest at other times.\n3. Visit Century Park for 240 minutes, Shanghai Disney for 120 minutes, Shanghai Sightseeing Tunnel for 210 minutes, Xintiandi for 180 minutes, Qibao Ancient Town for 210 minutes, Shanghai History Museum for 180 minutes, Huangpu River Cruise for 270 minutes.\n4. 12:00 ~ 13:00 for lunch and  18:30 ~ 19:30 for dinner.\n5. The daily opening_hours of spots can be obtained from the database table place. \"opening_hours_begin\" and \"opening_hours_end\" are the opening and closing times respectively\n6. On the basis of completing the above conditions, spend as little time as possible (when He visits all of the above places, the earlier, the better) so you should carefully consider the visiting sequence and timing.\n",
        "demands": {
            "TravelSimulator": {
                "begin_time": "2023-07-08 07:00",
                "end_time": "2023-07-11 00:00",
                "origin_city": "Shanghai",
                "origin_place": "Shanghai Railway Hotel",
                "budget": 99999,
                "check_opening_hours": true,
                "check_meal": true,
                "time_min": 120544,
                "time_max": 137959
            },
            "Constraints": {
                "SpotDurationConstraint": [
                    {
                        "spot": "Century Park",
                        "minutes": 240
                    },
                    {
                        "spot": "Shanghai Disney",
                        "minutes": 120
                    },
                    {
                        "spot": "Shanghai Sightseeing Tunnel",
                        "minutes": 210
                    },
                    {
                        "spot": "Xintiandi",
                        "minutes": 180
                    },
                    {
                        "spot": "Qibao Ancient Town",
                        "minutes": 210
                    },
                    {
                        "spot": "Shanghai History Museum",
                        "minutes": 180
                    },
                    {
                        "spot": "Huangpu River Cruise",
                        "minutes": 270
                    }
                ]
            }
        },
        "type": 2
    },
    {
        "question": "Bob is going to play in Nanjing, please make a visit plan for him.    The demands are as follows:\n1. He lives in Nanjing Railway Hotel. He needs to visit ['Tomb of Ming Emperor Zhu Yuanzhang', 'Lake Xuanwu', 'Ming Palace', 'Bailuzhou Park', 'Taiping Heavenly-Kingdom Palace', 'Qinhuai River'] and the order can be decided by you.\n2. one day(2023-07-05 07:00 ~ 2023-07-05 07:00) for this trip. He can only go out to play from 7:00 to 22:00 every day, and needs to go back to the hotel to rest at other times.\n3. Visit Tomb of Ming Emperor Zhu Yuanzhang for 120 minutes, Lake Xuanwu for 120 minutes, Ming Palace for 60 minutes, Bailuzhou Park for 90 minutes, Taiping Heavenly-Kingdom Palace for 120 minutes, Qinhuai River for 90 minutes.\n4. Ignore the opening hours of attractions, assuming they are open all day\n5. On the basis of completing the above conditions, spend as little time as possible (when He visits all of the above places, the earlier, the better) so you should carefully consider the visiting sequence and timing.\n",
        "demands": {
            "TravelSimulator": {
                "begin_time": "2023-07-05 07:00",
                "end_time": "2023-07-06 00:00",
                "origin_city": "Nanjing",
                "origin_place": "Nanjing Railway Hotel",
                "budget": 99999,
                "check_opening_hours": false,
                "check_meal": false,
                "time_min": 67166,
                "time_max": 73185
            },
            "Constraints": {
                "SpotDurationConstraint": [
                    {
                        "spot": "Tomb of Ming Emperor Zhu Yuanzhang",
                        "minutes": 120
                    },
                    {
                        "spot": "Lake Xuanwu",
                        "minutes": 120
                    },
                    {
                        "spot": "Ming Palace",
                        "minutes": 60
                    },
                    {
                        "spot": "Bailuzhou Park",
                        "minutes": 90
                    },
                    {
                        "spot": "Taiping Heavenly-Kingdom Palace",
                        "minutes": 120
                    },
                    {
                        "spot": "Qinhuai River",
                        "minutes": 90
                    }
                ]
            }
        },
        "type": 2
    },
    {
        "question": "Bob is going to play in Nanjing, please make a visit plan for him.    The demands are as follows:\n1. He lives in Nanjing Railway Hotel. He needs to visit ['Qinhuai River', 'Ming Palace', 'Lake Xuanwu', 'Bailuzhou Park', 'Taiping Heavenly-Kingdom Palace', 'Tomb of Ming Emperor Zhu Yuanzhang'] and the order can be decided by you.\n2. one day(2023-07-03 07:00 ~ 2023-07-03 07:00) for this trip. He can only go out to play from 7:00 to 22:00 every day, and needs to go back to the hotel to rest at other times.\n3. Visit Qinhuai River for 60 minutes, Ming Palace for 90 minutes, Lake Xuanwu for 60 minutes, Bailuzhou Park for 120 minutes, Taiping Heavenly-Kingdom Palace for 120 minutes, Tomb of Ming Emperor Zhu Yuanzhang for 120 minutes.\n4. Ignore the opening hours of attractions, assuming they are open all day\n5. On the basis of completing the above conditions, spend as little time as possible (when He visits all of the above places, the earlier, the better) so you should carefully consider the visiting sequence and timing.\n",
        "demands": {
            "TravelSimulator": {
                "begin_time": "2023-07-03 07:00",
                "end_time": "2023-07-04 00:00",
                "origin_city": "Nanjing",
                "origin_place": "Nanjing Railway Hotel",
                "budget": 99999,
                "check_opening_hours": false,
                "check_meal": false,
                "time_min": 61894,
                "time_max": 69805
            },
            "Constraints": {
                "SpotDurationConstraint": [
                    {
                        "spot": "Qinhuai River",
                        "minutes": 60
                    },
                    {
                        "spot": "Ming Palace",
                        "minutes": 90
                    },
                    {
                        "spot": "Lake Xuanwu",
                        "minutes": 60
                    },
                    {
                        "spot": "Bailuzhou Park",
                        "minutes": 120
                    },
                    {
                        "spot": "Taiping Heavenly-Kingdom Palace",
                        "minutes": 120
                    },
                    {
                        "spot": "Tomb of Ming Emperor Zhu Yuanzhang",
                        "minutes": 120
                    }
                ]
            }
        },
        "type": 2
    },
    {
        "question": "Bob is going to play in Shanghai, please make a visit plan for him.    The demands are as follows:\n1. He lives in Shanghai Railway Hotel. He needs to visit ['Longhua Temple', 'Shanghai Disney', 'Huangpu River Cruise', 'Century Park', 'Shanghai History Museum', 'Qibao Ancient Town'] and the order can be decided by you.\n2. one day(2023-07-11 07:00 ~ 2023-07-11 07:00) for this trip. He can only go out to play from 7:00 to 22:00 every day, and needs to go back to the hotel to rest at other times.\n3. Visit Longhua Temple for 120 minutes, Shanghai Disney for 60 minutes, Huangpu River Cruise for 90 minutes, Century Park for 120 minutes, Shanghai History Museum for 60 minutes, Qibao Ancient Town for 60 minutes.\n4. The daily opening_hours of spots can be obtained from the database table place. \"opening_hours_begin\" and \"opening_hours_end\" are the opening and closing times respectively\n5. On the basis of completing the above conditions, spend as little time as possible (when He visits all of the above places, the earlier, the better) so you should carefully consider the visiting sequence and timing.\n",
        "demands": {
            "TravelSimulator": {
                "begin_time": "2023-07-11 07:00",
                "end_time": "2023-07-12 00:00",
                "origin_city": "Shanghai",
                "origin_place": "Shanghai Railway Hotel",
                "budget": 99999,
                "check_opening_hours": true,
                "check_meal": false,
                "time_min": 58212,
                "time_max": 62819
            },
            "Constraints": {
                "SpotDurationConstraint": [
                    {
                        "spot": "Longhua Temple",
                        "minutes": 120
                    },
                    {
                        "spot": "Shanghai Disney",
                        "minutes": 60
                    },
                    {
                        "spot": "Huangpu River Cruise",
                        "minutes": 90
                    },
                    {
                        "spot": "Century Park",
                        "minutes": 120
                    },
                    {
                        "spot": "Shanghai History Museum",
                        "minutes": 60
                    },
                    {
                        "spot": "Qibao Ancient Town",
                        "minutes": 60
                    }
                ]
            }
        },
        "type": 2
    },
    {
        "question": "Bob is going to play in Nanjing, please make a visit plan for him.    The demands are as follows:\n1. He lives in Nanjing Railway Hotel. He needs to visit ['Lake Xuanwu', 'Tomb of Ming Emperor Zhu Yuanzhang', 'Ming Palace', 'Bailuzhou Park', 'Qinhuai River', 'Taiping Heavenly-Kingdom Palace'] and the order can be decided by you.\n2. one day(2023-07-05 07:00 ~ 2023-07-05 07:00) for this trip. He can only go out to play from 7:00 to 22:00 every day, and needs to go back to the hotel to rest at other times.\n3. Visit Lake Xuanwu for 60 minutes, Tomb of Ming Emperor Zhu Yuanzhang for 90 minutes, Ming Palace for 60 minutes, Bailuzhou Park for 90 minutes, Qinhuai River for 120 minutes, Taiping Heavenly-Kingdom Palace for 120 minutes.\n4. The daily opening_hours of spots can be obtained from the database table place. \"opening_hours_begin\" and \"opening_hours_end\" are the opening and closing times respectively\n5. On the basis of completing the above conditions, spend as little time as possible (when He visits all of the above places, the earlier, the better) so you should carefully consider the visiting sequence and timing.\n",
        "demands": {
            "TravelSimulator": {
                "begin_time": "2023-07-05 07:00",
                "end_time": "2023-07-06 00:00",
                "origin_city": "Nanjing",
                "origin_place": "Nanjing Railway Hotel",
                "budget": 99999,
                "check_opening_hours": true,
                "check_meal": false,
                "time_min": 61135,
                "time_max": 68896
            },
            "Constraints": {
                "SpotDurationConstraint": [
                    {
                        "spot": "Lake Xuanwu",
                        "minutes": 60
                    },
                    {
                        "spot": "Tomb of Ming Emperor Zhu Yuanzhang",
                        "minutes": 90
                    },
                    {
                        "spot": "Ming Palace",
                        "minutes": 60
                    },
                    {
                        "spot": "Bailuzhou Park",
                        "minutes": 90
                    },
                    {
                        "spot": "Qinhuai River",
                        "minutes": 120
                    },
                    {
                        "spot": "Taiping Heavenly-Kingdom Palace",
                        "minutes": 120
                    }
                ]
            }
        },
        "type": 2
    },
    {
        "question": "Bob is going to play in Nanjing, please make a visit plan for him.    The demands are as follows:\n1. He lives in Nanjing Railway Hotel. He needs to visit ['Qinhuai River', 'Bailuzhou Park', 'Lake Xuanwu', 'Ming Palace', 'Taiping Heavenly-Kingdom Palace', 'Tomb of Ming Emperor Zhu Yuanzhang'] and the order can be decided by you.\n2. one day(2023-07-06 07:00 ~ 2023-07-06 07:00) for this trip. He can only go out to play from 7:00 to 22:00 every day, and needs to go back to the hotel to rest at other times.\n3. Visit Qinhuai River for 120 minutes, Bailuzhou Park for 90 minutes, Lake Xuanwu for 60 minutes, Ming Palace for 60 minutes, Taiping Heavenly-Kingdom Palace for 120 minutes, Tomb of Ming Emperor Zhu Yuanzhang for 90 minutes.\n4. 12:00 ~ 13:00 for lunch and  18:30 ~ 19:30 for dinner.\n5. Ignore the opening hours of attractions, assuming they are open all day\n6. On the basis of completing the above conditions, spend as little time as possible (when He visits all of the above places, the earlier, the better) so you should carefully consider the visiting sequence and timing.\n",
        "demands": {
            "TravelSimulator": {
                "begin_time": "2023-07-06 07:00",
                "end_time": "2023-07-07 00:00",
                "origin_city": "Nanjing",
                "origin_place": "Nanjing Railway Hotel",
                "budget": 99999,
                "check_opening_hours": false,
                "check_meal": true,
                "time_min": 62827,
                "time_max": 68176
            },
            "Constraints": {
                "SpotDurationConstraint": [
                    {
                        "spot": "Qinhuai River",
                        "minutes": 120
                    },
                    {
                        "spot": "Bailuzhou Park",
                        "minutes": 90
                    },
                    {
                        "spot": "Lake Xuanwu",
                        "minutes": 60
                    },
                    {
                        "spot": "Ming Palace",
                        "minutes": 60
                    },
                    {
                        "spot": "Taiping Heavenly-Kingdom Palace",
                        "minutes": 120
                    },
                    {
                        "spot": "Tomb of Ming Emperor Zhu Yuanzhang",
                        "minutes": 90
                    }
                ]
            }
        },
        "type": 2
    },
    {
        "question": "Bob is going to play in Shanghai, please make a visit plan for him.    The demands are as follows:\n1. He lives in Shanghai Railway Hotel. He needs to visit ['Qibao Ancient Town', 'Shanghai History Museum', 'Shanghai Sightseeing Tunnel', 'Longhua Temple', 'Xintiandi', 'Shanghai Disney'] and the order can be decided by you.\n2. one day(2023-07-09 07:00 ~ 2023-07-09 07:00) for this trip. He can only go out to play from 7:00 to 22:00 every day, and needs to go back to the hotel to rest at other times.\n3. Visit Qibao Ancient Town for 90 minutes, Shanghai History Museum for 90 minutes, Shanghai Sightseeing Tunnel for 120 minutes, Longhua Temple for 90 minutes, Xintiandi for 60 minutes, Shanghai Disney for 60 minutes.\n4. 12:00 ~ 13:00 for lunch and  18:30 ~ 19:30 for dinner.\n5. Ignore the opening hours of attractions, assuming they are open all day\n6. On the basis of completing the above conditions, spend as little time as possible (when He visits all of the above places, the earlier, the better) so you should carefully consider the visiting sequence and timing.\n",
        "demands": {
            "TravelSimulator": {
                "begin_time": "2023-07-09 07:00",
                "end_time": "2023-07-10 00:00",
                "origin_city": "Shanghai",
                "origin_place": "Shanghai Railway Hotel",
                "budget": 99999,
                "check_opening_hours": false,
                "check_meal": true,
                "time_min": 58092,
                "time_max": 63611
            },
            "Constraints": {
                "SpotDurationConstraint": [
                    {
                        "spot": "Qibao Ancient Town",
                        "minutes": 90
                    },
                    {
                        "spot": "Shanghai History Museum",
                        "minutes": 90
                    },
                    {
                        "spot": "Shanghai Sightseeing Tunnel",
                        "minutes": 120
                    },
                    {
                        "spot": "Longhua Temple",
                        "minutes": 90
                    },
                    {
                        "spot": "Xintiandi",
                        "minutes": 60
                    },
                    {
                        "spot": "Shanghai Disney",
                        "minutes": 60
                    }
                ]
            }
        },
        "type": 2
    },
    {
        "question": "Bob is going to play in Beijing, please make a visit plan for him.    The demands are as follows:\n1. He lives in Beijing Railway Hotel. He needs to visit ['The Great Wall', 'The Forbidden City', 'Beijing Stone Carvings Art Museum', 'The Summer Palace', 'Shihua Cave', 'The Temple of Heaven'] and the order can be decided by you.\n2. one day(2023-07-06 07:00 ~ 2023-07-06 07:00) for this trip. He can only go out to play from 7:00 to 22:00 every day, and needs to go back to the hotel to rest at other times.\n3. Visit The Great Wall for 90 minutes, The Forbidden City for 120 minutes, Beijing Stone Carvings Art Museum for 60 minutes, The Summer Palace for 90 minutes, Shihua Cave for 120 minutes, The Temple of Heaven for 120 minutes.\n4. 12:00 ~ 13:00 for lunch and  18:30 ~ 19:30 for dinner.\n5. The daily opening_hours of spots can be obtained from the database table place. \"opening_hours_begin\" and \"opening_hours_end\" are the opening and closing times respectively\n6. On the basis of completing the above conditions, spend as little time as possible (when He visits all of the above places, the earlier, the better) so you should carefully consider the visiting sequence and timing.\n",
        "demands": {
            "TravelSimulator": {
                "begin_time": "2023-07-06 07:00",
                "end_time": "2023-07-07 00:00",
                "origin_city": "Beijing",
                "origin_place": "Beijing Railway Hotel",
                "budget": 99999,
                "check_opening_hours": true,
                "check_meal": true,
                "time_min": 62024,
                "time_max": 69159
            },
            "Constraints": {
                "SpotDurationConstraint": [
                    {
                        "spot": "The Great Wall",
                        "minutes": 90
                    },
                    {
                        "spot": "The Forbidden City",
                        "minutes": 120
                    },
                    {
                        "spot": "Beijing Stone Carvings Art Museum",
                        "minutes": 60
                    },
                    {
                        "spot": "The Summer Palace",
                        "minutes": 90
                    },
                    {
                        "spot": "Shihua Cave",
                        "minutes": 120
                    },
                    {
                        "spot": "The Temple of Heaven",
                        "minutes": 120
                    }
                ]
            }
        },
        "type": 2
    },
    {
        "question": "Bob is going to play in Nanjing, please make a visit plan for him.    The demands are as follows:\n1. He lives in Nanjing Railway Hotel. He needs to visit ['Ming Palace', 'Qinhuai River', 'Tomb of Ming Emperor Zhu Yuanzhang', 'Taiping Heavenly-Kingdom Palace', 'Lake Xuanwu', 'Bailuzhou Park'] and the order can be decided by you.\n2. one day(2023-07-06 07:00 ~ 2023-07-06 07:00) for this trip. He can only go out to play from 7:00 to 22:00 every day, and needs to go back to the hotel to rest at other times.\n3. Visit Ming Palace for 120 minutes, Qinhuai River for 120 minutes, Tomb of Ming Emperor Zhu Yuanzhang for 90 minutes, Taiping Heavenly-Kingdom Palace for 120 minutes, Lake Xuanwu for 60 minutes, Bailuzhou Park for 120 minutes.\n4. 12:00 ~ 13:00 for lunch and  18:30 ~ 19:30 for dinner.\n5. The daily opening_hours of spots can be obtained from the database table place. \"opening_hours_begin\" and \"opening_hours_end\" are the opening and closing times respectively\n6. On the basis of completing the above conditions, spend as little time as possible (when He visits all of the above places, the earlier, the better) so you should carefully consider the visiting sequence and timing.\n",
        "demands": {
            "TravelSimulator": {
                "begin_time": "2023-07-06 07:00",
                "end_time": "2023-07-07 00:00",
                "origin_city": "Nanjing",
                "origin_place": "Nanjing Railway Hotel",
                "budget": 99999,
                "check_opening_hours": true,
                "check_meal": true,
                "time_min": 67610,
                "time_max": 74865
            },
            "Constraints": {
                "SpotDurationConstraint": [
                    {
                        "spot": "Ming Palace",
                        "minutes": 120
                    },
                    {
                        "spot": "Qinhuai River",
                        "minutes": 120
                    },
                    {
                        "spot": "Tomb of Ming Emperor Zhu Yuanzhang",
                        "minutes": 90
                    },
                    {
                        "spot": "Taiping Heavenly-Kingdom Palace",
                        "minutes": 120
                    },
                    {
                        "spot": "Lake Xuanwu",
                        "minutes": 60
                    },
                    {
                        "spot": "Bailuzhou Park",
                        "minutes": 120
                    }
                ]
            }
        },
        "type": 2
    },
    {
        "question": "Bob is going to play in Chengdu, please make a visit plan for him.    The demands are as follows:\n1. He lives in Chengdu Railway Hotel. He needs to visit ['Leshan Giant Buddha', 'Chengdu Panda Base'] and the order can be decided by you.\n2. one day(2023-07-10 07:00 ~ 2023-07-10 07:00) for this trip. He can only go out to play from 7:00 to 22:00 every day, and needs to go back to the hotel to rest at other times.\n3. Visit Leshan Giant Buddha for 270 minutes, Chengdu Panda Base for 120 minutes.\n4. Ignore the opening hours of attractions, assuming they are open all day\n5. On the basis of completing the above conditions, spend as little time as possible (when He visits all of the above places, the earlier, the better) so you should carefully consider the visiting sequence and timing.\n",
        "demands": {
            "TravelSimulator": {
                "begin_time": "2023-07-10 07:00",
                "end_time": "2023-07-11 00:00",
                "origin_city": "Chengdu",
                "origin_place": "Chengdu Railway Hotel",
                "budget": 99999,
                "check_opening_hours": false,
                "check_meal": false,
                "time_min": 33360,
                "time_max": 37800
            },
            "Constraints": {
                "SpotDurationConstraint": [
                    {
                        "spot": "Leshan Giant Buddha",
                        "minutes": 270
                    },
                    {
                        "spot": "Chengdu Panda Base",
                        "minutes": 120
                    }
                ]
            }
        },
        "type": 2
    },
    {
        "question": "Bob is going to play in Guangzhou, please make a visit plan for him.    The demands are as follows:\n1. He lives in Guangzhou Railway Hotel. He needs to visit ['Chimelong Tourist Resort', 'Huacheng Square'] and the order can be decided by you.\n2. one day(2023-07-09 07:00 ~ 2023-07-09 07:00) for this trip. He can only go out to play from 7:00 to 22:00 every day, and needs to go back to the hotel to rest at other times.\n3. Visit Chimelong Tourist Resort for 240 minutes, Huacheng Square for 150 minutes.\n4. Ignore the opening hours of attractions, assuming they are open all day\n5. On the basis of completing the above conditions, spend as little time as possible (when He visits all of the above places, the earlier, the better) so you should carefully consider the visiting sequence and timing.\n",
        "demands": {
            "TravelSimulator": {
                "begin_time": "2023-07-09 07:00",
                "end_time": "2023-07-10 00:00",
                "origin_city": "Guangzhou",
                "origin_place": "Guangzhou Railway Hotel",
                "budget": 99999,
                "check_opening_hours": false,
                "check_meal": false,
                "time_min": 33420,
                "time_max": 36000
            },
            "Constraints": {
                "SpotDurationConstraint": [
                    {
                        "spot": "Chimelong Tourist Resort",
                        "minutes": 240
                    },
                    {
                        "spot": "Huacheng Square",
                        "minutes": 150
                    }
                ]
            }
        },
        "type": 2
    },
    {
        "question": "Bob is going to play in Hangzhou, please make a visit plan for him.    The demands are as follows:\n1. He lives in Hangzhou Railway Hotel. He needs to visit ['Lingyin Temple', 'West Lake'] and the order can be decided by you.\n2. one day(2023-07-03 07:00 ~ 2023-07-03 07:00) for this trip. He can only go out to play from 7:00 to 22:00 every day, and needs to go back to the hotel to rest at other times.\n3. Visit Lingyin Temple for 120 minutes, West Lake for 270 minutes.\n4. The daily opening_hours of spots can be obtained from the database table place. \"opening_hours_begin\" and \"opening_hours_end\" are the opening and closing times respectively\n5. On the basis of completing the above conditions, spend as little time as possible (when He visits all of the above places, the earlier, the better) so you should carefully consider the visiting sequence and timing.\n",
        "demands": {
            "TravelSimulator": {
                "begin_time": "2023-07-03 07:00",
                "end_time": "2023-07-04 00:00",
                "origin_city": "Hangzhou",
                "origin_place": "Hangzhou Railway Hotel",
                "budget": 99999,
                "check_opening_hours": true,
                "check_meal": false,
                "time_min": 37800,
                "time_max": 52200
            },
            "Constraints": {
                "SpotDurationConstraint": [
                    {
                        "spot": "Lingyin Temple",
                        "minutes": 120
                    },
                    {
                        "spot": "West Lake",
                        "minutes": 270
                    }
                ]
            }
        },
        "type": 2
    },
    {
        "question": "Bob is going to play in Wuhan, please make a visit plan for him.    The demands are as follows:\n1. He lives in Wuhan Railway Hotel. He needs to visit ['East Lake', 'Baotong Temple'] and the order can be decided by you.\n2. one day(2023-07-05 07:00 ~ 2023-07-05 07:00) for this trip. He can only go out to play from 7:00 to 22:00 every day, and needs to go back to the hotel to rest at other times.\n3. Visit East Lake for 180 minutes, Baotong Temple for 180 minutes.\n4. The daily opening_hours of spots can be obtained from the database table place. \"opening_hours_begin\" and \"opening_hours_end\" are the opening and closing times respectively\n5. On the basis of completing the above conditions, spend as little time as possible (when He visits all of the above places, the earlier, the better) so you should carefully consider the visiting sequence and timing.\n",
        "demands": {
            "TravelSimulator": {
                "begin_time": "2023-07-05 07:00",
                "end_time": "2023-07-06 00:00",
                "origin_city": "Wuhan",
                "origin_place": "Wuhan Railway Hotel",
                "budget": 99999,
                "check_opening_hours": true,
                "check_meal": false,
                "time_min": 32400,
                "time_max": 32400
            },
            "Constraints": {
                "SpotDurationConstraint": [
                    {
                        "spot": "East Lake",
                        "minutes": 180
                    },
                    {
                        "spot": "Baotong Temple",
                        "minutes": 180
                    }
                ]
            }
        },
        "type": 2
    },
    {
        "question": "Bob is going to play in Beijing, please make a visit plan for him.    The demands are as follows:\n1. He lives in Beijing Railway Hotel. He needs to visit ['The Great Wall', 'The Summer Palace'] and the order can be decided by you.\n2. one day(2023-07-07 07:00 ~ 2023-07-07 07:00) for this trip. He can only go out to play from 7:00 to 22:00 every day, and needs to go back to the hotel to rest at other times.\n3. Visit The Great Wall for 150 minutes, The Summer Palace for 210 minutes.\n4. 12:00 ~ 13:00 for lunch and  18:30 ~ 19:30 for dinner.\n5. Ignore the opening hours of attractions, assuming they are open all day\n6. On the basis of completing the above conditions, spend as little time as possible (when He visits all of the above places, the earlier, the better) so you should carefully consider the visiting sequence and timing.\n",
        "demands": {
            "TravelSimulator": {
                "begin_time": "2023-07-07 07:00",
                "end_time": "2023-07-08 00:00",
                "origin_city": "Beijing",
                "origin_place": "Beijing Railway Hotel",
                "budget": 99999,
                "check_opening_hours": false,
                "check_meal": true,
                "time_min": 30600,
                "time_max": 34200
            },
            "Constraints": {
                "SpotDurationConstraint": [
                    {
                        "spot": "The Great Wall",
                        "minutes": 150
                    },
                    {
                        "spot": "The Summer Palace",
                        "minutes": 210
                    }
                ]
            }
        },
        "type": 2
    },
    {
        "question": "Bob is going to play in Chengdu, please make a visit plan for him.    The demands are as follows:\n1. He lives in Chengdu Railway Hotel. He needs to visit ['Du Fu Thatched Cottage', 'The Chengdu Wuhou Shrine'] and the order can be decided by you.\n2. one day(2023-07-04 07:00 ~ 2023-07-04 07:00) for this trip. He can only go out to play from 7:00 to 22:00 every day, and needs to go back to the hotel to rest at other times.\n3. Visit Du Fu Thatched Cottage for 270 minutes, The Chengdu Wuhou Shrine for 210 minutes.\n4. 12:00 ~ 13:00 for lunch and  18:30 ~ 19:30 for dinner.\n5. Ignore the opening hours of attractions, assuming they are open all day\n6. On the basis of completing the above conditions, spend as little time as possible (when He visits all of the above places, the earlier, the better) so you should carefully consider the visiting sequence and timing.\n",
        "demands": {
            "TravelSimulator": {
                "begin_time": "2023-07-04 07:00",
                "end_time": "2023-07-05 00:00",
                "origin_city": "Chengdu",
                "origin_place": "Chengdu Railway Hotel",
                "budget": 99999,
                "check_opening_hours": false,
                "check_meal": true,
                "time_min": 36456,
                "time_max": 39983
            },
            "Constraints": {
                "SpotDurationConstraint": [
                    {
                        "spot": "Du Fu Thatched Cottage",
                        "minutes": 270
                    },
                    {
                        "spot": "The Chengdu Wuhou Shrine",
                        "minutes": 210
                    }
                ]
            }
        },
        "type": 2
    },
    {
        "question": "Bob is going to play in Nanjing, please make a visit plan for him.    The demands are as follows:\n1. He lives in Nanjing Railway Hotel. He needs to visit ['Taiping Heavenly-Kingdom Palace', 'Ming Palace'] and the order can be decided by you.\n2. one day(2023-07-07 07:00 ~ 2023-07-07 07:00) for this trip. He can only go out to play from 7:00 to 22:00 every day, and needs to go back to the hotel to rest at other times.\n3. Visit Taiping Heavenly-Kingdom Palace for 150 minutes, Ming Palace for 120 minutes.\n4. 12:00 ~ 13:00 for lunch and  18:30 ~ 19:30 for dinner.\n5. The daily opening_hours of spots can be obtained from the database table place. \"opening_hours_begin\" and \"opening_hours_end\" are the opening and closing times respectively\n6. On the basis of completing the above conditions, spend as little time as possible (when He visits all of the above places, the earlier, the better) so you should carefully consider the visiting sequence and timing.\n",
        "demands": {
            "TravelSimulator": {
                "begin_time": "2023-07-07 07:00",
                "end_time": "2023-07-08 00:00",
                "origin_city": "Nanjing",
                "origin_place": "Nanjing Railway Hotel",
                "budget": 99999,
                "check_opening_hours": true,
                "check_meal": true,
                "time_min": 28638,
                "time_max": 30401
            },
            "Constraints": {
                "SpotDurationConstraint": [
                    {
                        "spot": "Taiping Heavenly-Kingdom Palace",
                        "minutes": 150
                    },
                    {
                        "spot": "Ming Palace",
                        "minutes": 120
                    }
                ]
            }
        },
        "type": 2
    },
    {
        "question": "Bob is going to play in Shanghai, please make a visit plan for him.    The demands are as follows:\n1. He lives in Shanghai Railway Hotel. He needs to visit ['Century Park', 'Longhua Temple'] and the order can be decided by you.\n2. one day(2023-07-07 07:00 ~ 2023-07-07 07:00) for this trip. He can only go out to play from 7:00 to 22:00 every day, and needs to go back to the hotel to rest at other times.\n3. Visit Century Park for 150 minutes, Longhua Temple for 180 minutes.\n4. 12:00 ~ 13:00 for lunch and  18:30 ~ 19:30 for dinner.\n5. The daily opening_hours of spots can be obtained from the database table place. \"opening_hours_begin\" and \"opening_hours_end\" are the opening and closing times respectively\n6. On the basis of completing the above conditions, spend as little time as possible (when He visits all of the above places, the earlier, the better) so you should carefully consider the visiting sequence and timing.\n",
        "demands": {
            "TravelSimulator": {
                "begin_time": "2023-07-07 07:00",
                "end_time": "2023-07-08 00:00",
                "origin_city": "Shanghai",
                "origin_place": "Shanghai Railway Hotel",
                "budget": 99999,
                "check_opening_hours": true,
                "check_meal": true,
                "time_min": 30438,
                "time_max": 32201
            },
            "Constraints": {
                "SpotDurationConstraint": [
                    {
                        "spot": "Century Park",
                        "minutes": 150
                    },
                    {
                        "spot": "Longhua Temple",
                        "minutes": 180
                    }
                ]
            }
        },
        "type": 2
    },
    {
        "question": "Bob is going to play in Shanghai, please make a visit plan for him.    The demands are as follows:\n1. He lives in Shanghai Railway Hotel. He needs to visit ['Shanghai Disney', 'Shanghai Sightseeing Tunnel', 'Longhua Temple', 'Huangpu River Cruise', 'Xintiandi'] and the order can be decided by you.\n2. 2 days(2023-07-07 07:00 ~ 2023-07-09 00:00) for this trip. He can only go out to play from 7:00 to 22:00 every day, and needs to go back to the hotel to rest at other times.\n3. Visit Shanghai Disney for 180 minutes, Shanghai Sightseeing Tunnel for 270 minutes, Longhua Temple for 300 minutes, Huangpu River Cruise for 240 minutes, Xintiandi for 120 minutes.\n4. Ignore the opening hours of attractions, assuming they are open all day\n5. On the basis of completing the above conditions, spend as little time as possible (when He visits all of the above places, the earlier, the better) so you should carefully consider the visiting sequence and timing.\n",
        "demands": {
            "TravelSimulator": {
                "begin_time": "2023-07-07 07:00",
                "end_time": "2023-07-09 00:00",
                "origin_city": "Shanghai",
                "origin_place": "Shanghai Railway Hotel",
                "budget": 99999,
                "check_opening_hours": false,
                "check_meal": false,
                "time_min": 96061,
                "time_max": 120214
            },
            "Constraints": {
                "SpotDurationConstraint": [
                    {
                        "spot": "Shanghai Disney",
                        "minutes": 180
                    },
                    {
                        "spot": "Shanghai Sightseeing Tunnel",
                        "minutes": 270
                    },
                    {
                        "spot": "Longhua Temple",
                        "minutes": 300
                    },
                    {
                        "spot": "Huangpu River Cruise",
                        "minutes": 240
                    },
                    {
                        "spot": "Xintiandi",
                        "minutes": 120
                    }
                ]
            }
        },
        "type": 2
    },
    {
        "question": "Bob is going to play in Wuhan, please make a visit plan for him.    The demands are as follows:\n1. He lives in Wuhan Railway Hotel. He needs to visit ['Han Show', 'Hubu Alley', 'Yellow Crane Tower', 'Tan Hua Lin', 'Baotong Temple'] and the order can be decided by you.\n2. 2 days(2023-07-06 07:00 ~ 2023-07-08 00:00) for this trip. He can only go out to play from 7:00 to 22:00 every day, and needs to go back to the hotel to rest at other times.\n3. Visit Han Show for 150 minutes, Hubu Alley for 180 minutes, Yellow Crane Tower for 240 minutes, Tan Hua Lin for 240 minutes, Baotong Temple for 300 minutes.\n4. Ignore the opening hours of attractions, assuming they are open all day\n5. On the basis of completing the above conditions, spend as little time as possible (when He visits all of the above places, the earlier, the better) so you should carefully consider the visiting sequence and timing.\n",
        "demands": {
            "TravelSimulator": {
                "begin_time": "2023-07-06 07:00",
                "end_time": "2023-07-08 00:00",
                "origin_city": "Wuhan",
                "origin_place": "Wuhan Railway Hotel",
                "budget": 99999,
                "check_opening_hours": false,
                "check_meal": false,
                "time_min": 97574,
                "time_max": 124737
            },
            "Constraints": {
                "SpotDurationConstraint": [
                    {
                        "spot": "Han Show",
                        "minutes": 150
                    },
                    {
                        "spot": "Hubu Alley",
                        "minutes": 180
                    },
                    {
                        "spot": "Yellow Crane Tower",
                        "minutes": 240
                    },
                    {
                        "spot": "Tan Hua Lin",
                        "minutes": 240
                    },
                    {
                        "spot": "Baotong Temple",
                        "minutes": 300
                    }
                ]
            }
        },
        "type": 2
    },
    {
        "question": "Bob is going to play in Beijing, please make a visit plan for him.    The demands are as follows:\n1. He lives in Beijing Railway Hotel. He needs to visit ['The Great Wall', 'Shihua Cave', 'The Temple of Heaven', 'Beijing Stone Carvings Art Museum', 'The Summer Palace'] and the order can be decided by you.\n2. 2 days(2023-07-05 07:00 ~ 2023-07-07 00:00) for this trip. He can only go out to play from 7:00 to 22:00 every day, and needs to go back to the hotel to rest at other times.\n3. Visit The Great Wall for 120 minutes, Shihua Cave for 210 minutes, The Temple of Heaven for 300 minutes, Beijing Stone Carvings Art Museum for 210 minutes, The Summer Palace for 210 minutes.\n4. The daily opening_hours of spots can be obtained from the database table place. \"opening_hours_begin\" and \"opening_hours_end\" are the opening and closing times respectively\n5. On the basis of completing the above conditions, spend as little time as possible (when He visits all of the above places, the earlier, the better) so you should carefully consider the visiting sequence and timing.\n",
        "demands": {
            "TravelSimulator": {
                "begin_time": "2023-07-05 07:00",
                "end_time": "2023-07-07 00:00",
                "origin_city": "Beijing",
                "origin_place": "Beijing Railway Hotel",
                "budget": 99999,
                "check_opening_hours": true,
                "check_meal": false,
                "time_min": 86252,
                "time_max": 109779
            },
            "Constraints": {
                "SpotDurationConstraint": [
                    {
                        "spot": "The Great Wall",
                        "minutes": 120
                    },
                    {
                        "spot": "Shihua Cave",
                        "minutes": 210
                    },
                    {
                        "spot": "The Temple of Heaven",
                        "minutes": 300
                    },
                    {
                        "spot": "Beijing Stone Carvings Art Museum",
                        "minutes": 210
                    },
                    {
                        "spot": "The Summer Palace",
                        "minutes": 210
                    }
                ]
            }
        },
        "type": 2
    },
    {
        "question": "Bob is going to play in Hangzhou, please make a visit plan for him.    The demands are as follows:\n1. He lives in Hangzhou Railway Hotel. He needs to visit ['Lingyin Temple', 'West Lake', 'Hefang Street', 'Quaint Water Towns', 'China National Tea Museum'] and the order can be decided by you.\n2. 2 days(2023-07-09 07:00 ~ 2023-07-11 00:00) for this trip. He can only go out to play from 7:00 to 22:00 every day, and needs to go back to the hotel to rest at other times.\n3. Visit Lingyin Temple for 150 minutes, West Lake for 210 minutes, Hefang Street for 210 minutes, Quaint Water Towns for 240 minutes, China National Tea Museum for 210 minutes.\n4. The daily opening_hours of spots can be obtained from the database table place. \"opening_hours_begin\" and \"opening_hours_end\" are the opening and closing times respectively\n5. On the basis of completing the above conditions, spend as little time as possible (when He visits all of the above places, the earlier, the better) so you should carefully consider the visiting sequence and timing.\n",
        "demands": {
            "TravelSimulator": {
                "begin_time": "2023-07-09 07:00",
                "end_time": "2023-07-11 00:00",
                "origin_city": "Hangzhou",
                "origin_place": "Hangzhou Railway Hotel",
                "budget": 99999,
                "check_opening_hours": true,
                "check_meal": false,
                "time_min": 86531,
                "time_max": 90432
            },
            "Constraints": {
                "SpotDurationConstraint": [
                    {
                        "spot": "Lingyin Temple",
                        "minutes": 150
                    },
                    {
                        "spot": "West Lake",
                        "minutes": 210
                    },
                    {
                        "spot": "Hefang Street",
                        "minutes": 210
                    },
                    {
                        "spot": "Quaint Water Towns",
                        "minutes": 240
                    },
                    {
                        "spot": "China National Tea Museum",
                        "minutes": 210
                    }
                ]
            }
        },
        "type": 2
    },
    {
        "question": "Bob is going to play in Beijing, please make a visit plan for him.    The demands are as follows:\n1. He lives in Beijing Railway Hotel. He needs to visit ['Beijing Olympic Park', 'The Summer Palace', 'Beijing Stone Carvings Art Museum', 'Shihua Cave', 'The Forbidden City'] and the order can be decided by you.\n2. 2 days(2023-07-10 07:00 ~ 2023-07-12 00:00) for this trip. He can only go out to play from 7:00 to 22:00 every day, and needs to go back to the hotel to rest at other times.\n3. Visit Beijing Olympic Park for 150 minutes, The Summer Palace for 120 minutes, Beijing Stone Carvings Art Museum for 210 minutes, Shihua Cave for 180 minutes, The Forbidden City for 210 minutes.\n4. 12:00 ~ 13:00 for lunch and  18:30 ~ 19:30 for dinner.\n5. Ignore the opening hours of attractions, assuming they are open all day\n6. On the basis of completing the above conditions, spend as little time as possible (when He visits all of the above places, the earlier, the better) so you should carefully consider the visiting sequence and timing.\n",
        "demands": {
            "TravelSimulator": {
                "begin_time": "2023-07-10 07:00",
                "end_time": "2023-07-12 00:00",
                "origin_city": "Beijing",
                "origin_place": "Beijing Railway Hotel",
                "budget": 99999,
                "check_opening_hours": false,
                "check_meal": true,
                "time_min": 80468,
                "time_max": 84747
            },
            "Constraints": {
                "SpotDurationConstraint": [
                    {
                        "spot": "Beijing Olympic Park",
                        "minutes": 150
                    },
                    {
                        "spot": "The Summer Palace",
                        "minutes": 120
                    },
                    {
                        "spot": "Beijing Stone Carvings Art Museum",
                        "minutes": 210
                    },
                    {
                        "spot": "Shihua Cave",
                        "minutes": 180
                    },
                    {
                        "spot": "The Forbidden City",
                        "minutes": 210
                    }
                ]
            }
        },
        "type": 2
    },
    {
        "question": "Bob is going to play in Wuhan, please make a visit plan for him.    The demands are as follows:\n1. He lives in Wuhan Railway Hotel. He needs to visit ['Hubu Alley', 'Yellow Crane Tower', 'Baotong Temple', 'Tan Hua Lin', 'Han Show'] and the order can be decided by you.\n2. 2 days(2023-07-05 07:00 ~ 2023-07-07 00:00) for this trip. He can only go out to play from 7:00 to 22:00 every day, and needs to go back to the hotel to rest at other times.\n3. Visit Hubu Alley for 150 minutes, Yellow Crane Tower for 120 minutes, Baotong Temple for 150 minutes, Tan Hua Lin for 210 minutes, Han Show for 270 minutes.\n4. 12:00 ~ 13:00 for lunch and  18:30 ~ 19:30 for dinner.\n5. Ignore the opening hours of attractions, assuming they are open all day\n6. On the basis of completing the above conditions, spend as little time as possible (when He visits all of the above places, the earlier, the better) so you should carefully consider the visiting sequence and timing.\n",
        "demands": {
            "TravelSimulator": {
                "begin_time": "2023-07-05 07:00",
                "end_time": "2023-07-07 00:00",
                "origin_city": "Wuhan",
                "origin_place": "Wuhan Railway Hotel",
                "budget": 99999,
                "check_opening_hours": false,
                "check_meal": true,
                "time_min": 81857,
                "time_max": 89310
            },
            "Constraints": {
                "SpotDurationConstraint": [
                    {
                        "spot": "Hubu Alley",
                        "minutes": 150
                    },
                    {
                        "spot": "Yellow Crane Tower",
                        "minutes": 120
                    },
                    {
                        "spot": "Baotong Temple",
                        "minutes": 150
                    },
                    {
                        "spot": "Tan Hua Lin",
                        "minutes": 210
                    },
                    {
                        "spot": "Han Show",
                        "minutes": 270
                    }
                ]
            }
        },
        "type": 2
    },
    {
        "question": "Bob is going to play in Beijing, please make a visit plan for him.    The demands are as follows:\n1. He lives in Beijing Railway Hotel. He needs to visit ['The Great Wall', 'The Temple of Heaven', 'Shihua Cave', 'The Summer Palace', 'The Forbidden City'] and the order can be decided by you.\n2. 2 days(2023-07-09 07:00 ~ 2023-07-11 00:00) for this trip. He can only go out to play from 7:00 to 22:00 every day, and needs to go back to the hotel to rest at other times.\n3. Visit The Great Wall for 150 minutes, The Temple of Heaven for 120 minutes, Shihua Cave for 210 minutes, The Summer Palace for 150 minutes, The Forbidden City for 240 minutes.\n4. 12:00 ~ 13:00 for lunch and  18:30 ~ 19:30 for dinner.\n5. The daily opening_hours of spots can be obtained from the database table place. \"opening_hours_begin\" and \"opening_hours_end\" are the opening and closing times respectively\n6. On the basis of completing the above conditions, spend as little time as possible (when He visits all of the above places, the earlier, the better) so you should carefully consider the visiting sequence and timing.\n",
        "demands": {
            "TravelSimulator": {
                "begin_time": "2023-07-09 07:00",
                "end_time": "2023-07-11 00:00",
                "origin_city": "Beijing",
                "origin_place": "Beijing Railway Hotel",
                "budget": 99999,
                "check_opening_hours": true,
                "check_meal": true,
                "time_min": 79971,
                "time_max": 84656
            },
            "Constraints": {
                "SpotDurationConstraint": [
                    {
                        "spot": "The Great Wall",
                        "minutes": 150
                    },
                    {
                        "spot": "The Temple of Heaven",
                        "minutes": 120
                    },
                    {
                        "spot": "Shihua Cave",
                        "minutes": 210
                    },
                    {
                        "spot": "The Summer Palace",
                        "minutes": 150
                    },
                    {
                        "spot": "The Forbidden City",
                        "minutes": 240
                    }
                ]
            }
        },
        "type": 2
    },
    {
        "question": "Bob is going to play in Beijing, please make a visit plan for him.    The demands are as follows:\n1. He lives in Beijing Railway Hotel. He needs to visit ['Tiananmen Square', 'The Great Wall', 'Beijing Stone Carvings Art Museum', 'The Temple of Heaven', 'The Forbidden City'] and the order can be decided by you.\n2. 2 days(2023-07-02 07:00 ~ 2023-07-04 00:00) for this trip. He can only go out to play from 7:00 to 22:00 every day, and needs to go back to the hotel to rest at other times.\n3. Visit Tiananmen Square for 150 minutes, The Great Wall for 240 minutes, Beijing Stone Carvings Art Museum for 120 minutes, The Temple of Heaven for 300 minutes, The Forbidden City for 300 minutes.\n4. 12:00 ~ 13:00 for lunch and  18:30 ~ 19:30 for dinner.\n5. The daily opening_hours of spots can be obtained from the database table place. \"opening_hours_begin\" and \"opening_hours_end\" are the opening and closing times respectively\n6. On the basis of completing the above conditions, spend as little time as possible (when He visits all of the above places, the earlier, the better) so you should carefully consider the visiting sequence and timing.\n",
        "demands": {
            "TravelSimulator": {
                "begin_time": "2023-07-02 07:00",
                "end_time": "2023-07-04 00:00",
                "origin_city": "Beijing",
                "origin_place": "Beijing Railway Hotel",
                "budget": 99999,
                "check_opening_hours": true,
                "check_meal": true,
                "time_min": 92816,
                "time_max": 114423
            },
            "Constraints": {
                "SpotDurationConstraint": [
                    {
                        "spot": "Tiananmen Square",
                        "minutes": 150
                    },
                    {
                        "spot": "The Great Wall",
                        "minutes": 240
                    },
                    {
                        "spot": "Beijing Stone Carvings Art Museum",
                        "minutes": 120
                    },
                    {
                        "spot": "The Temple of Heaven",
                        "minutes": 300
                    },
                    {
                        "spot": "The Forbidden City",
                        "minutes": 300
                    }
                ]
            }
        },
        "type": 2
    },
    {
        "question": "Bob is going to play in Shanghai, please make a visit plan for him.    The demands are as follows:\n1. He lives in Shanghai Railway Hotel. He needs to visit ['Shanghai History Museum', 'Century Park', 'Shanghai Disney', 'Xintiandi', 'Longhua Temple', 'Qibao Ancient Town', 'Huangpu River Cruise'] and the order can be decided by you.\n2. 3 days(2023-07-05 07:00 ~ 2023-07-08 00:00) for this trip. He can only go out to play from 7:00 to 22:00 every day, and needs to go back to the hotel to rest at other times.\n3. Visit Shanghai History Museum for 120 minutes, Century Park for 210 minutes, Shanghai Disney for 150 minutes, Xintiandi for 300 minutes, Longhua Temple for 120 minutes, Qibao Ancient Town for 240 minutes, Huangpu River Cruise for 150 minutes.\n4. Ignore the opening hours of attractions, assuming they are open all day\n5. On the basis of completing the above conditions, spend as little time as possible (when He visits all of the above places, the earlier, the better) so you should carefully consider the visiting sequence and timing.\n",
        "demands": {
            "TravelSimulator": {
                "begin_time": "2023-07-05 07:00",
                "end_time": "2023-07-08 00:00",
                "origin_city": "Shanghai",
                "origin_place": "Shanghai Railway Hotel",
                "budget": 99999,
                "check_opening_hours": false,
                "check_meal": false,
                "time_min": 120083,
                "time_max": 139152
            },
            "Constraints": {
                "SpotDurationConstraint": [
                    {
                        "spot": "Shanghai History Museum",
                        "minutes": 120
                    },
                    {
                        "spot": "Century Park",
                        "minutes": 210
                    },
                    {
                        "spot": "Shanghai Disney",
                        "minutes": 150
                    },
                    {
                        "spot": "Xintiandi",
                        "minutes": 300
                    },
                    {
                        "spot": "Longhua Temple",
                        "minutes": 120
                    },
                    {
                        "spot": "Qibao Ancient Town",
                        "minutes": 240
                    },
                    {
                        "spot": "Huangpu River Cruise",
                        "minutes": 150
                    }
                ]
            }
        },
        "type": 2
    },
    {
        "question": "Bob is going to play in Shanghai, please make a visit plan for him.    The demands are as follows:\n1. He lives in Shanghai Railway Hotel. He needs to visit ['Longhua Temple', 'Qibao Ancient Town', 'Century Park', 'Shanghai Sightseeing Tunnel', 'Huangpu River Cruise', 'Shanghai Disney', 'Xintiandi'] and the order can be decided by you.\n2. 3 days(2023-07-06 07:00 ~ 2023-07-09 00:00) for this trip. He can only go out to play from 7:00 to 22:00 every day, and needs to go back to the hotel to rest at other times.\n3. Visit Longhua Temple for 180 minutes, Qibao Ancient Town for 210 minutes, Century Park for 150 minutes, Shanghai Sightseeing Tunnel for 210 minutes, Huangpu River Cruise for 150 minutes, Shanghai Disney for 210 minutes, Xintiandi for 180 minutes.\n4. The daily opening_hours of spots can be obtained from the database table place. \"opening_hours_begin\" and \"opening_hours_end\" are the opening and closing times respectively\n5. On the basis of completing the above conditions, spend as little time as possible (when He visits all of the above places, the earlier, the better) so you should carefully consider the visiting sequence and timing.\n",
        "demands": {
            "TravelSimulator": {
                "begin_time": "2023-07-06 07:00",
                "end_time": "2023-07-09 00:00",
                "origin_city": "Shanghai",
                "origin_place": "Shanghai Railway Hotel",
                "budget": 99999,
                "check_opening_hours": true,
                "check_meal": false,
                "time_min": 117583,
                "time_max": 120880
            },
            "Constraints": {
                "SpotDurationConstraint": [
                    {
                        "spot": "Longhua Temple",
                        "minutes": 180
                    },
                    {
                        "spot": "Qibao Ancient Town",
                        "minutes": 210
                    },
                    {
                        "spot": "Century Park",
                        "minutes": 150
                    },
                    {
                        "spot": "Shanghai Sightseeing Tunnel",
                        "minutes": 210
                    },
                    {
                        "spot": "Huangpu River Cruise",
                        "minutes": 150
                    },
                    {
                        "spot": "Shanghai Disney",
                        "minutes": 210
                    },
                    {
                        "spot": "Xintiandi",
                        "minutes": 180
                    }
                ]
            }
        },
        "type": 2
    },
    {
        "question": "Bob is going to play in Beijing, please make a visit plan for him.    The demands are as follows:\n1. He lives in Beijing Railway Hotel. He needs to visit ['Beijing Olympic Park', 'The Summer Palace', 'Tiananmen Square', 'The Great Wall', 'The Temple of Heaven', 'Shihua Cave', 'The Forbidden City'] and the order can be decided by you.\n2. 3 days(2023-07-08 07:00 ~ 2023-07-11 00:00) for this trip. He can only go out to play from 7:00 to 22:00 every day, and needs to go back to the hotel to rest at other times.\n3. Visit Beijing Olympic Park for 270 minutes, The Summer Palace for 150 minutes, Tiananmen Square for 270 minutes, The Great Wall for 240 minutes, The Temple of Heaven for 270 minutes, Shihua Cave for 120 minutes, The Forbidden City for 120 minutes.\n4. The daily opening_hours of spots can be obtained from the database table place. \"opening_hours_begin\" and \"opening_hours_end\" are the opening and closing times respectively\n5. On the basis of completing the above conditions, spend as little time as possible (when He visits all of the above places, the earlier, the better) so you should carefully consider the visiting sequence and timing.\n",
        "demands": {
            "TravelSimulator": {
                "begin_time": "2023-07-08 07:00",
                "end_time": "2023-07-11 00:00",
                "origin_city": "Beijing",
                "origin_place": "Beijing Railway Hotel",
                "budget": 99999,
                "check_opening_hours": true,
                "check_meal": false,
                "time_min": 141468,
                "time_max": 156779
            },
            "Constraints": {
                "SpotDurationConstraint": [
                    {
                        "spot": "Beijing Olympic Park",
                        "minutes": 270
                    },
                    {
                        "spot": "The Summer Palace",
                        "minutes": 150
                    },
                    {
                        "spot": "Tiananmen Square",
                        "minutes": 270
                    },
                    {
                        "spot": "The Great Wall",
                        "minutes": 240
                    },
                    {
                        "spot": "The Temple of Heaven",
                        "minutes": 270
                    },
                    {
                        "spot": "Shihua Cave",
                        "minutes": 120
                    },
                    {
                        "spot": "The Forbidden City",
                        "minutes": 120
                    }
                ]
            }
        },
        "type": 2
    },
    {
        "question": "Bob is going to play in Shanghai, please make a visit plan for him.    The demands are as follows:\n1. He lives in Shanghai Railway Hotel. He needs to visit ['Shanghai Disney', 'Longhua Temple', 'Century Park', 'Huangpu River Cruise', 'Xintiandi', 'Shanghai History Museum', 'Shanghai Sightseeing Tunnel'] and the order can be decided by you.\n2. 3 days(2023-07-02 07:00 ~ 2023-07-05 00:00) for this trip. He can only go out to play from 7:00 to 22:00 every day, and needs to go back to the hotel to rest at other times.\n3. Visit Shanghai Disney for 270 minutes, Longhua Temple for 180 minutes, Century Park for 270 minutes, Huangpu River Cruise for 270 minutes, Xintiandi for 210 minutes, Shanghai History Museum for 240 minutes, Shanghai Sightseeing Tunnel for 120 minutes.\n4. 12:00 ~ 13:00 for lunch and  18:30 ~ 19:30 for dinner.\n5. Ignore the opening hours of attractions, assuming they are open all day\n6. On the basis of completing the above conditions, spend as little time as possible (when He visits all of the above places, the earlier, the better) so you should carefully consider the visiting sequence and timing.\n",
        "demands": {
            "TravelSimulator": {
                "begin_time": "2023-07-02 07:00",
                "end_time": "2023-07-05 00:00",
                "origin_city": "Shanghai",
                "origin_place": "Shanghai Railway Hotel",
                "budget": 99999,
                "check_opening_hours": false,
                "check_meal": true,
                "time_min": 146145,
                "time_max": 164246
            },
            "Constraints": {
                "SpotDurationConstraint": [
                    {
                        "spot": "Shanghai Disney",
                        "minutes": 270
                    },
                    {
                        "spot": "Longhua Temple",
                        "minutes": 180
                    },
                    {
                        "spot": "Century Park",
                        "minutes": 270
                    },
                    {
                        "spot": "Huangpu River Cruise",
                        "minutes": 270
                    },
                    {
                        "spot": "Xintiandi",
                        "minutes": 210
                    },
                    {
                        "spot": "Shanghai History Museum",
                        "minutes": 240
                    },
                    {
                        "spot": "Shanghai Sightseeing Tunnel",
                        "minutes": 120
                    }
                ]
            }
        },
        "type": 2
    },
    {
        "question": "Bob is going to play in Shanghai, please make a visit plan for him.    The demands are as follows:\n1. He lives in Shanghai Railway Hotel. He needs to visit ['Shanghai History Museum', 'Huangpu River Cruise', 'Century Park', 'Xintiandi', 'Longhua Temple', 'Qibao Ancient Town', 'Shanghai Sightseeing Tunnel'] and the order can be decided by you.\n2. 3 days(2023-07-10 07:00 ~ 2023-07-13 00:00) for this trip. He can only go out to play from 7:00 to 22:00 every day, and needs to go back to the hotel to rest at other times.\n3. Visit Shanghai History Museum for 150 minutes, Huangpu River Cruise for 300 minutes, Century Park for 120 minutes, Xintiandi for 270 minutes, Longhua Temple for 300 minutes, Qibao Ancient Town for 210 minutes, Shanghai Sightseeing Tunnel for 270 minutes.\n4. 12:00 ~ 13:00 for lunch and  18:30 ~ 19:30 for dinner.\n5. Ignore the opening hours of attractions, assuming they are open all day\n6. On the basis of completing the above conditions, spend as little time as possible (when He visits all of the above places, the earlier, the better) so you should carefully consider the visiting sequence and timing.\n",
        "demands": {
            "TravelSimulator": {
                "begin_time": "2023-07-10 07:00",
                "end_time": "2023-07-13 00:00",
                "origin_city": "Shanghai",
                "origin_place": "Shanghai Railway Hotel",
                "budget": 99999,
                "check_opening_hours": false,
                "check_meal": true,
                "time_min": 145896,
                "time_max": 164591
            },
            "Constraints": {
                "SpotDurationConstraint": [
                    {
                        "spot": "Shanghai History Museum",
                        "minutes": 150
                    },
                    {
                        "spot": "Huangpu River Cruise",
                        "minutes": 300
                    },
                    {
                        "spot": "Century Park",
                        "minutes": 120
                    },
                    {
                        "spot": "Xintiandi",
                        "minutes": 270
                    },
                    {
                        "spot": "Longhua Temple",
                        "minutes": 300
                    },
                    {
                        "spot": "Qibao Ancient Town",
                        "minutes": 210
                    },
                    {
                        "spot": "Shanghai Sightseeing Tunnel",
                        "minutes": 270
                    }
                ]
            }
        },
        "type": 2
    },
    {
        "question": "Bob is going to play in Shanghai, please make a visit plan for him.    The demands are as follows:\n1. He lives in Shanghai Railway Hotel. He needs to visit ['Shanghai History Museum', 'Qibao Ancient Town', 'Century Park', 'Shanghai Sightseeing Tunnel', 'Xintiandi', 'Longhua Temple', 'Huangpu River Cruise'] and the order can be decided by you.\n2. 3 days(2023-07-02 07:00 ~ 2023-07-05 00:00) for this trip. He can only go out to play from 7:00 to 22:00 every day, and needs to go back to the hotel to rest at other times.\n3. Visit Shanghai History Museum for 210 minutes, Qibao Ancient Town for 180 minutes, Century Park for 270 minutes, Shanghai Sightseeing Tunnel for 300 minutes, Xintiandi for 120 minutes, Longhua Temple for 270 minutes, Huangpu River Cruise for 270 minutes.\n4. 12:00 ~ 13:00 for lunch and  18:30 ~ 19:30 for dinner.\n5. The daily opening_hours of spots can be obtained from the database table place. \"opening_hours_begin\" and \"opening_hours_end\" are the opening and closing times respectively\n6. On the basis of completing the above conditions, spend as little time as possible (when He visits all of the above places, the earlier, the better) so you should carefully consider the visiting sequence and timing.\n",
        "demands": {
            "TravelSimulator": {
                "begin_time": "2023-07-02 07:00",
                "end_time": "2023-07-05 00:00",
                "origin_city": "Shanghai",
                "origin_place": "Shanghai Railway Hotel",
                "budget": 99999,
                "check_opening_hours": true,
                "check_meal": true,
                "time_min": 145115,
                "time_max": 159372
            },
            "Constraints": {
                "SpotDurationConstraint": [
                    {
                        "spot": "Shanghai History Museum",
                        "minutes": 210
                    },
                    {
                        "spot": "Qibao Ancient Town",
                        "minutes": 180
                    },
                    {
                        "spot": "Century Park",
                        "minutes": 270
                    },
                    {
                        "spot": "Shanghai Sightseeing Tunnel",
                        "minutes": 300
                    },
                    {
                        "spot": "Xintiandi",
                        "minutes": 120
                    },
                    {
                        "spot": "Longhua Temple",
                        "minutes": 270
                    },
                    {
                        "spot": "Huangpu River Cruise",
                        "minutes": 270
                    }
                ]
            }
        },
        "type": 2
    },
    {
        "question": "Bob is going to play in Beijing, please make a visit plan for him.    The demands are as follows:\n1. He lives in Beijing Railway Hotel. He needs to visit ['The Summer Palace', 'Shihua Cave', 'Tiananmen Square', 'The Great Wall', 'The Temple of Heaven', 'Beijing Stone Carvings Art Museum', 'The Forbidden City'] and the order can be decided by you.\n2. 3 days(2023-07-08 07:00 ~ 2023-07-11 00:00) for this trip. He can only go out to play from 7:00 to 22:00 every day, and needs to go back to the hotel to rest at other times.\n3. Visit The Summer Palace for 300 minutes, Shihua Cave for 150 minutes, Tiananmen Square for 270 minutes, The Great Wall for 150 minutes, The Temple of Heaven for 300 minutes, Beijing Stone Carvings Art Museum for 300 minutes, The Forbidden City for 210 minutes.\n4. 12:00 ~ 13:00 for lunch and  18:30 ~ 19:30 for dinner.\n5. The daily opening_hours of spots can be obtained from the database table place. \"opening_hours_begin\" and \"opening_hours_end\" are the opening and closing times respectively\n6. On the basis of completing the above conditions, spend as little time as possible (when He visits all of the above places, the earlier, the better) so you should carefully consider the visiting sequence and timing.\n",
        "demands": {
            "TravelSimulator": {
                "begin_time": "2023-07-08 07:00",
                "end_time": "2023-07-11 00:00",
                "origin_city": "Beijing",
                "origin_place": "Beijing Railway Hotel",
                "budget": 99999,
                "check_opening_hours": true,
                "check_meal": true,
                "time_min": 149499,
                "time_max": 160376
            },
            "Constraints": {
                "SpotDurationConstraint": [
                    {
                        "spot": "The Summer Palace",
                        "minutes": 300
                    },
                    {
                        "spot": "Shihua Cave",
                        "minutes": 150
                    },
                    {
                        "spot": "Tiananmen Square",
                        "minutes": 270
                    },
                    {
                        "spot": "The Great Wall",
                        "minutes": 150
                    },
                    {
                        "spot": "The Temple of Heaven",
                        "minutes": 300
                    },
                    {
                        "spot": "Beijing Stone Carvings Art Museum",
                        "minutes": 300
                    },
                    {
                        "spot": "The Forbidden City",
                        "minutes": 210
                    }
                ]
            }
        },
        "type": 2
    }
]