[
    {
        "question": "Bob is going to visit some spots across cities, please make a visit plan for him, including inter-city transportation, intra-city transportation, and visit time for each spot.    The demands are as follows:\n1. He now lives in Hangzhou Railway Hotel in Hangzhou. Every time he takes a train to a city, he lives in f\"{city} Railway Hotel\", such as \"Beijing Railway Hotel\" In Beijing, he needs to visit Beijing Olympic Park for 180 minutes, Tiananmen Square for 240 minutes, Shihua Cave for 150 minutes, The Temple of Heaven for 240 minutes. And the order can be decided by you.\n2. He is free to travel from 2023.7.1 to 2023.7.20. The budget for transportation is 2000.0 CNY.\n3. Ignore the opening hours of attractions, assuming they are open all day. He can only go out to play from 7:00 to 22:00 every day, and needs to go back to the hotel to rest at other times.\n4. On the basis of completing the above conditions (especially the budget), spend as little time as possible.\n",
        "demands": {
            "TravelSimulator": {
                "begin_time": "2023-07-01 07:00",
                "end_time": "2023-07-20 00:00",
                "origin_city": "Hangzhou",
                "origin_place": "Hangzhou Railway Hotel",
                "budget": 99999,
                "check_opening_hours": false,
                "check_meal": false,
                "set_budget": true,
                "type": 3,
                "limit": "money",
                "money_min": 285,
                "money_max": 1611
            },
            "Constraints": {
                "SpotDurationConstraint": [
                    {
                        "spot": "Beijing Olympic Park",
                        "minutes": 180
                    },
                    {
                        "spot": "Tiananmen Square",
                        "minutes": 240
                    },
                    {
                        "spot": "Shihua Cave",
                        "minutes": 150
                    },
                    {
                        "spot": "The Temple of Heaven",
                        "minutes": 240
                    }
                ]
            }
        },
        "type": 3
    },
    {
        "question": "Bob is going to visit some spots across cities, please make a visit plan for him, including inter-city transportation, intra-city transportation, and visit time for each spot.    The demands are as follows:\n1. He now lives in Guangzhou Railway Hotel in Guangzhou. Every time he takes a train to a city, he lives in f\"{city} Railway Hotel\", such as \"Beijing Railway Hotel\" In Wuhan, he needs to visit Hubu Alley for 240 minutes, Tan Hua Lin for 180 minutes, Baotong Temple for 120 minutes, East Lake for 300 minutes, Han Show for 120 minutes. And the order can be decided by you.\n2. He is free to travel from 2023.7.1 to 2023.7.20. The budget for transportation is 1800.0 CNY.\n3. Ignore the opening hours of attractions, assuming they are open all day. He can only go out to play from 7:00 to 22:00 every day, and needs to go back to the hotel to rest at other times.\n4. On the basis of completing the above conditions (especially the budget), spend as little time as possible.\n",
        "demands": {
            "TravelSimulator": {
                "begin_time": "2023-07-01 07:00",
                "end_time": "2023-07-20 00:00",
                "origin_city": "Guangzhou",
                "origin_place": "Guangzhou Railway Hotel",
                "budget": 99999,
                "check_opening_hours": false,
                "check_meal": false,
                "set_budget": true,
                "type": 3,
                "limit": "money",
                "money_min": 1,
                "money_max": 1240
            },
            "Constraints": {
                "SpotDurationConstraint": [
                    {
                        "spot": "Hubu Alley",
                        "minutes": 240
                    },
                    {
                        "spot": "Tan Hua Lin",
                        "minutes": 180
                    },
                    {
                        "spot": "Baotong Temple",
                        "minutes": 120
                    },
                    {
                        "spot": "East Lake",
                        "minutes": 300
                    },
                    {
                        "spot": "Han Show",
                        "minutes": 120
                    }
                ]
            }
        },
        "type": 3
    },
    {
        "question": "Bob is going to visit some spots across cities, please make a visit plan for him, including inter-city transportation, intra-city transportation, and visit time for each spot.    The demands are as follows:\n1. He now lives in Shanghai Railway Hotel in Shanghai. Every time he takes a train to a city, he lives in f\"{city} Railway Hotel\", such as \"Beijing Railway Hotel\" In Chengdu, he needs to visit Leshan Giant Buddha for 150 minutes, Chengdu Panda Base for 120 minutes, Du Fu Thatched Cottage for 150 minutes, Chengdu Tea Houses for 180 minutes, The Chengdu Wuhou Shrine for 150 minutes. And the order can be decided by you.\n2. He is free to travel from 2023.7.1 to 2023.7.20. The budget for transportation is 2900.0 CNY.\n3. The daily opening_hours of spots can be obtained from the database table place. \"opening_hours_begin\" and \"opening_hours_end\" are the opening and closing times respectively\n4. On the basis of completing the above conditions (especially the budget), spend as little time as possible.\n",
        "demands": {
            "TravelSimulator": {
                "begin_time": "2023-07-01 07:00",
                "end_time": "2023-07-20 00:00",
                "origin_city": "Shanghai",
                "origin_place": "Shanghai Railway Hotel",
                "budget": 99999,
                "check_opening_hours": true,
                "check_meal": false,
                "set_budget": true,
                "type": 3,
                "limit": "money",
                "money_min": 1107,
                "money_max": 1805
            },
            "Constraints": {
                "SpotDurationConstraint": [
                    {
                        "spot": "Leshan Giant Buddha",
                        "minutes": 150
                    },
                    {
                        "spot": "Chengdu Panda Base",
                        "minutes": 120
                    },
                    {
                        "spot": "Du Fu Thatched Cottage",
                        "minutes": 150
                    },
                    {
                        "spot": "Chengdu Tea Houses",
                        "minutes": 180
                    },
                    {
                        "spot": "The Chengdu Wuhou Shrine",
                        "minutes": 150
                    }
                ]
            }
        },
        "type": 3
    },
    {
        "question": "Bob is going to visit some spots across cities, please make a visit plan for him, including inter-city transportation, intra-city transportation, and visit time for each spot.    The demands are as follows:\n1. He now lives in Chengdu Railway Hotel in Chengdu. Every time he takes a train to a city, he lives in f\"{city} Railway Hotel\", such as \"Beijing Railway Hotel\" In Hangzhou, he needs to visit Hefang Street for 300 minutes, Quaint Water Towns for 240 minutes, China National Tea Museum for 180 minutes, Lingyin Temple for 180 minutes, West Lake for 300 minutes. And the order can be decided by you.\n2. He is free to travel from 2023.7.1 to 2023.7.20. The budget for transportation is 3100.0 CNY.\n3. The daily opening_hours of spots can be obtained from the database table place. \"opening_hours_begin\" and \"opening_hours_end\" are the opening and closing times respectively\n4. On the basis of completing the above conditions (especially the budget), spend as little time as possible.\n",
        "demands": {
            "TravelSimulator": {
                "begin_time": "2023-07-01 07:00",
                "end_time": "2023-07-20 00:00",
                "origin_city": "Chengdu",
                "origin_place": "Chengdu Railway Hotel",
                "budget": 99999,
                "check_opening_hours": true,
                "check_meal": false,
                "set_budget": true,
                "type": 3,
                "limit": "money",
                "money_min": 0,
                "money_max": 1852
            },
            "Constraints": {
                "SpotDurationConstraint": [
                    {
                        "spot": "Hefang Street",
                        "minutes": 300
                    },
                    {
                        "spot": "Quaint Water Towns",
                        "minutes": 240
                    },
                    {
                        "spot": "China National Tea Museum",
                        "minutes": 180
                    },
                    {
                        "spot": "Lingyin Temple",
                        "minutes": 180
                    },
                    {
                        "spot": "West Lake",
                        "minutes": 300
                    }
                ]
            }
        },
        "type": 3
    },
    {
        "question": "Bob is going to visit some spots across cities, please make a visit plan for him, including inter-city transportation, intra-city transportation, and visit time for each spot.    The demands are as follows:\n1. He now lives in Chengdu Railway Hotel in Chengdu. Every time he takes a train to a city, he lives in f\"{city} Railway Hotel\", such as \"Beijing Railway Hotel\" In Nanjing, he needs to visit Bailuzhou Park for 240 minutes, Taiping Heavenly-Kingdom Palace for 240 minutes, Lake Xuanwu for 300 minutes, Tomb of Ming Emperor Zhu Yuanzhang for 300 minutes, Ming Palace for 180 minutes. And the order can be decided by you.\n2. 5 days (2023-07-09 00:00 ~ 2023-07-14 00:00) for this trip.\n3. Ignore the opening hours of attractions, assuming they are open all day. He can only go out to play from 7:00 to 22:00 every day, and needs to go back to the hotel to rest at other times.\n4. On the basis of completing the above conditions (especially the time limit), spend as little money as possible.\n",
        "demands": {
            "TravelSimulator": {
                "begin_time": "2023-07-09 00:00",
                "end_time": "2023-07-14 00:00",
                "origin_city": "Chengdu",
                "origin_place": "Chengdu Railway Hotel",
                "budget": 99999,
                "check_opening_hours": false,
                "check_meal": false,
                "set_budget": false,
                "type": 3,
                "limit": "time",
                "time_min": 161012,
                "time_max": 368306
            },
            "Constraints": {
                "SpotDurationConstraint": [
                    {
                        "spot": "Bailuzhou Park",
                        "minutes": 240
                    },
                    {
                        "spot": "Taiping Heavenly-Kingdom Palace",
                        "minutes": 240
                    },
                    {
                        "spot": "Lake Xuanwu",
                        "minutes": 300
                    },
                    {
                        "spot": "Tomb of Ming Emperor Zhu Yuanzhang",
                        "minutes": 300
                    },
                    {
                        "spot": "Ming Palace",
                        "minutes": 180
                    }
                ]
            }
        },
        "type": 3
    },
    {
        "question": "Bob is going to visit some spots across cities, please make a visit plan for him, including inter-city transportation, intra-city transportation, and visit time for each spot.    The demands are as follows:\n1. He now lives in Guangzhou Railway Hotel in Guangzhou. Every time he takes a train to a city, he lives in f\"{city} Railway Hotel\", such as \"Beijing Railway Hotel\" In Hangzhou, he needs to visit Hefang Street for 300 minutes, China National Tea Museum for 270 minutes, Quaint Water Towns for 300 minutes, West Lake for 150 minutes, Lingyin Temple for 240 minutes. And the order can be decided by you.\n2. 5 days (2023-07-09 00:00 ~ 2023-07-14 00:00) for this trip.\n3. Ignore the opening hours of attractions, assuming they are open all day. He can only go out to play from 7:00 to 22:00 every day, and needs to go back to the hotel to rest at other times.\n4. On the basis of completing the above conditions (especially the time limit), spend as little money as possible.\n",
        "demands": {
            "TravelSimulator": {
                "begin_time": "2023-07-09 00:00",
                "end_time": "2023-07-14 00:00",
                "origin_city": "Guangzhou",
                "origin_place": "Guangzhou Railway Hotel",
                "budget": 99999,
                "check_opening_hours": false,
                "check_meal": false,
                "set_budget": false,
                "type": 3,
                "limit": "time",
                "time_min": 195847,
                "time_max": 316904
            },
            "Constraints": {
                "SpotDurationConstraint": [
                    {
                        "spot": "Hefang Street",
                        "minutes": 300
                    },
                    {
                        "spot": "China National Tea Museum",
                        "minutes": 270
                    },
                    {
                        "spot": "Quaint Water Towns",
                        "minutes": 300
                    },
                    {
                        "spot": "West Lake",
                        "minutes": 150
                    },
                    {
                        "spot": "Lingyin Temple",
                        "minutes": 240
                    }
                ]
            }
        },
        "type": 3
    },
    {
        "question": "Bob is going to visit some spots across cities, please make a visit plan for him, including inter-city transportation, intra-city transportation, and visit time for each spot.    The demands are as follows:\n1. He now lives in Wuhan Railway Hotel in Wuhan. Every time he takes a train to a city, he lives in f\"{city} Railway Hotel\", such as \"Beijing Railway Hotel\" In Guangzhou, he needs to visit Yuexiu Park for 240 minutes, Baiyun Mountain for 180 minutes, Huacheng Square for 270 minutes, Chimelong Tourist Resort for 240 minutes, Canton Tower for 120 minutes. And the order can be decided by you.\n2. 5 days (2023-07-07 00:00 ~ 2023-07-12 00:00) for this trip.\n3. The daily opening_hours of spots can be obtained from the database table place. \"opening_hours_begin\" and \"opening_hours_end\" are the opening and closing times respectively\n4. On the basis of completing the above conditions (especially the time limit), spend as little money as possible.\n",
        "demands": {
            "TravelSimulator": {
                "begin_time": "2023-07-07 00:00",
                "end_time": "2023-07-12 00:00",
                "origin_city": "Wuhan",
                "origin_place": "Wuhan Railway Hotel",
                "budget": 99999,
                "check_opening_hours": true,
                "check_meal": false,
                "set_budget": false,
                "type": 3,
                "limit": "time",
                "time_min": 167849,
                "time_max": 265502
            },
            "Constraints": {
                "SpotDurationConstraint": [
                    {
                        "spot": "Yuexiu Park",
                        "minutes": 240
                    },
                    {
                        "spot": "Baiyun Mountain",
                        "minutes": 180
                    },
                    {
                        "spot": "Huacheng Square",
                        "minutes": 270
                    },
                    {
                        "spot": "Chimelong Tourist Resort",
                        "minutes": 240
                    },
                    {
                        "spot": "Canton Tower",
                        "minutes": 120
                    }
                ]
            }
        },
        "type": 3
    },
    {
        "question": "Bob is going to visit some spots across cities, please make a visit plan for him, including inter-city transportation, intra-city transportation, and visit time for each spot.    The demands are as follows:\n1. He now lives in Shanghai Railway Hotel in Shanghai. Every time he takes a train to a city, he lives in f\"{city} Railway Hotel\", such as \"Beijing Railway Hotel\" In Wuhan, he needs to visit Han Show for 270 minutes, Yellow Crane Tower for 120 minutes, Tan Hua Lin for 180 minutes, Baotong Temple for 240 minutes. And the order can be decided by you.\n2. 5 days (2023-07-03 00:00 ~ 2023-07-08 00:00) for this trip.\n3. The daily opening_hours of spots can be obtained from the database table place. \"opening_hours_begin\" and \"opening_hours_end\" are the opening and closing times respectively\n4. On the basis of completing the above conditions (especially the time limit), spend as little money as possible.\n",
        "demands": {
            "TravelSimulator": {
                "begin_time": "2023-07-03 00:00",
                "end_time": "2023-07-08 00:00",
                "origin_city": "Shanghai",
                "origin_place": "Shanghai Railway Hotel",
                "budget": 99999,
                "check_opening_hours": true,
                "check_meal": false,
                "set_budget": false,
                "type": 3,
                "limit": "time",
                "time_min": 86708,
                "time_max": 261911
            },
            "Constraints": {
                "SpotDurationConstraint": [
                    {
                        "spot": "Han Show",
                        "minutes": 270
                    },
                    {
                        "spot": "Yellow Crane Tower",
                        "minutes": 120
                    },
                    {
                        "spot": "Tan Hua Lin",
                        "minutes": 180
                    },
                    {
                        "spot": "Baotong Temple",
                        "minutes": 240
                    }
                ]
            }
        },
        "type": 3
    },
    {
        "question": "Bob is going to visit some spots across cities, please make a visit plan for him, including inter-city transportation, intra-city transportation, and visit time for each spot.    The demands are as follows:\n1. He now lives in Shanghai Railway Hotel in Shanghai. Every time he takes a train to a city, he lives in f\"{city} Railway Hotel\", such as \"Beijing Railway Hotel\" In Shanghai, he needs to visit Shanghai Disney for 180 minutes, Xintiandi for 180 minutes.In Chengdu, he needs to visit Chengdu Tea Houses for 150 minutes, Leshan Giant Buddha for 150 minutes. And the order can be decided by you.\n2. He is free to travel from 2023.7.1 to 2023.7.20. The budget for transportation is 1700.0 CNY.\n3. Ignore the opening hours of attractions, assuming they are open all day. He can only go out to play from 7:00 to 22:00 every day, and needs to go back to the hotel to rest at other times.\n4. On the basis of completing the above conditions (especially the budget), spend as little time as possible.\n",
        "demands": {
            "TravelSimulator": {
                "begin_time": "2023-07-01 07:00",
                "end_time": "2023-07-20 00:00",
                "origin_city": "Shanghai",
                "origin_place": "Shanghai Railway Hotel",
                "budget": 99999,
                "check_opening_hours": false,
                "check_meal": false,
                "set_budget": true,
                "type": 3,
                "limit": "money",
                "money_min": 1222,
                "money_max": 2198
            },
            "Constraints": {
                "SpotDurationConstraint": [
                    {
                        "spot": "Shanghai Disney",
                        "minutes": 180
                    },
                    {
                        "spot": "Xintiandi",
                        "minutes": 180
                    },
                    {
                        "spot": "Chengdu Tea Houses",
                        "minutes": 150
                    },
                    {
                        "spot": "Leshan Giant Buddha",
                        "minutes": 150
                    }
                ]
            }
        },
        "type": 3
    },
    {
        "question": "Bob is going to visit some spots across cities, please make a visit plan for him, including inter-city transportation, intra-city transportation, and visit time for each spot.    The demands are as follows:\n1. He now lives in Beijing Railway Hotel in Beijing. Every time he takes a train to a city, he lives in f\"{city} Railway Hotel\", such as \"Beijing Railway Hotel\" In Beijing, he needs to visit The Great Wall for 150 minutes, Tiananmen Square for 300 minutes. And the order can be decided by you.\n2. He is free to travel from 2023.7.1 to 2023.7.20. The budget for transportation is 900 CNY.\n3. Ignore the opening hours of attractions, assuming they are open all day. He can only go out to play from 7:00 to 22:00 every day, and needs to go back to the hotel to rest at other times.\n4. On the basis of completing the above conditions (especially the budget), spend as little time as possible.\n",
        "demands": {
            "TravelSimulator": {
                "begin_time": "2023-07-01 07:00",
                "end_time": "2023-07-20 00:00",
                "origin_city": "Beijing",
                "origin_place": "Beijing Railway Hotel",
                "budget": 99999,
                "check_opening_hours": false,
                "check_meal": false,
                "set_budget": true,
                "type": 3,
                "limit": "money",
                "money_min": 0,
                "money_max": 0
            },
            "Constraints": {
                "SpotDurationConstraint": [
                    {
                        "spot": "The Great Wall",
                        "minutes": 150
                    },
                    {
                        "spot": "Tiananmen Square",
                        "minutes": 300
                    }
                ]
            }
        },
        "type": 3
    },
    {
        "question": "Bob is going to visit some spots across cities, please make a visit plan for him, including inter-city transportation, intra-city transportation, and visit time for each spot.    The demands are as follows:\n1. He now lives in Shanghai Railway Hotel in Shanghai. Every time he takes a train to a city, he lives in f\"{city} Railway Hotel\", such as \"Beijing Railway Hotel\" In Shanghai, he needs to visit Xintiandi for 180 minutes, Century Park for 180 minutes.In Guangzhou, he needs to visit Yuexiu Park for 210 minutes, Chimelong Tourist Resort for 120 minutes. And the order can be decided by you.\n2. He is free to travel from 2023.7.1 to 2023.7.20. The budget for transportation is 1600.0 CNY.\n3. The daily opening_hours of spots can be obtained from the database table place. \"opening_hours_begin\" and \"opening_hours_end\" are the opening and closing times respectively\n4. On the basis of completing the above conditions (especially the budget), spend as little time as possible.\n",
        "demands": {
            "TravelSimulator": {
                "begin_time": "2023-07-01 07:00",
                "end_time": "2023-07-20 00:00",
                "origin_city": "Shanghai",
                "origin_place": "Shanghai Railway Hotel",
                "budget": 99999,
                "check_opening_hours": true,
                "check_meal": false,
                "set_budget": true,
                "type": 3,
                "limit": "money",
                "money_min": 396,
                "money_max": 1824
            },
            "Constraints": {
                "SpotDurationConstraint": [
                    {
                        "spot": "Xintiandi",
                        "minutes": 180
                    },
                    {
                        "spot": "Century Park",
                        "minutes": 180
                    },
                    {
                        "spot": "Yuexiu Park",
                        "minutes": 210
                    },
                    {
                        "spot": "Chimelong Tourist Resort",
                        "minutes": 120
                    }
                ]
            }
        },
        "type": 3
    },
    {
        "question": "Bob is going to visit some spots across cities, please make a visit plan for him, including inter-city transportation, intra-city transportation, and visit time for each spot.    The demands are as follows:\n1. He now lives in Wuhan Railway Hotel in Wuhan. Every time he takes a train to a city, he lives in f\"{city} Railway Hotel\", such as \"Beijing Railway Hotel\" In Wuhan, he needs to visit East Lake for 150 minutes, Tan Hua Lin for 120 minutes.In Nanjing, he needs to visit Taiping Heavenly-Kingdom Palace for 270 minutes, Lake Xuanwu for 270 minutes. And the order can be decided by you.\n2. He is free to travel from 2023.7.1 to 2023.7.20. The budget for transportation is 1100.0 CNY.\n3. The daily opening_hours of spots can be obtained from the database table place. \"opening_hours_begin\" and \"opening_hours_end\" are the opening and closing times respectively\n4. On the basis of completing the above conditions (especially the budget), spend as little time as possible.\n",
        "demands": {
            "TravelSimulator": {
                "begin_time": "2023-07-01 07:00",
                "end_time": "2023-07-20 00:00",
                "origin_city": "Wuhan",
                "origin_place": "Wuhan Railway Hotel",
                "budget": 99999,
                "check_opening_hours": true,
                "check_meal": false,
                "set_budget": true,
                "type": 3,
                "limit": "money",
                "money_min": 399,
                "money_max": 402
            },
            "Constraints": {
                "SpotDurationConstraint": [
                    {
                        "spot": "East Lake",
                        "minutes": 150
                    },
                    {
                        "spot": "Tan Hua Lin",
                        "minutes": 120
                    },
                    {
                        "spot": "Taiping Heavenly-Kingdom Palace",
                        "minutes": 270
                    },
                    {
                        "spot": "Lake Xuanwu",
                        "minutes": 270
                    }
                ]
            }
        },
        "type": 3
    },
    {
        "question": "Bob is going to visit some spots across cities, please make a visit plan for him, including inter-city transportation, intra-city transportation, and visit time for each spot.    The demands are as follows:\n1. He now lives in Chengdu Railway Hotel in Chengdu. Every time he takes a train to a city, he lives in f\"{city} Railway Hotel\", such as \"Beijing Railway Hotel\" In Chengdu, he needs to visit Leshan Giant Buddha for 180 minutes, Du Fu Thatched Cottage for 240 minutes.In Shanghai, he needs to visit Shanghai Sightseeing Tunnel for 210 minutes, Shanghai History Museum for 270 minutes. And the order can be decided by you.\n2. 5 days (2023-07-02 00:00 ~ 2023-07-07 00:00) for this trip.\n3. Ignore the opening hours of attractions, assuming they are open all day. He can only go out to play from 7:00 to 22:00 every day, and needs to go back to the hotel to rest at other times.\n4. On the basis of completing the above conditions (especially the time limit), spend as little money as possible.\n",
        "demands": {
            "TravelSimulator": {
                "begin_time": "2023-07-02 00:00",
                "end_time": "2023-07-07 00:00",
                "origin_city": "Chengdu",
                "origin_place": "Chengdu Railway Hotel",
                "budget": 99999,
                "check_opening_hours": false,
                "check_meal": false,
                "set_budget": false,
                "type": 3,
                "limit": "time",
                "time_min": 99364,
                "time_max": 226435
            },
            "Constraints": {
                "SpotDurationConstraint": [
                    {
                        "spot": "Leshan Giant Buddha",
                        "minutes": 180
                    },
                    {
                        "spot": "Du Fu Thatched Cottage",
                        "minutes": 240
                    },
                    {
                        "spot": "Shanghai Sightseeing Tunnel",
                        "minutes": 210
                    },
                    {
                        "spot": "Shanghai History Museum",
                        "minutes": 270
                    }
                ]
            }
        },
        "type": 3
    },
    {
        "question": "Bob is going to visit some spots across cities, please make a visit plan for him, including inter-city transportation, intra-city transportation, and visit time for each spot.    The demands are as follows:\n1. He now lives in Guangzhou Railway Hotel in Guangzhou. Every time he takes a train to a city, he lives in f\"{city} Railway Hotel\", such as \"Beijing Railway Hotel\" In Guangzhou, he needs to visit Chimelong Tourist Resort for 210 minutes, Huacheng Square for 270 minutes.In Shanghai, he needs to visit Shanghai History Museum for 150 minutes, Xintiandi for 240 minutes. And the order can be decided by you.\n2. 5 days (2023-07-02 00:00 ~ 2023-07-07 00:00) for this trip.\n3. Ignore the opening hours of attractions, assuming they are open all day. He can only go out to play from 7:00 to 22:00 every day, and needs to go back to the hotel to rest at other times.\n4. On the basis of completing the above conditions (especially the time limit), spend as little money as possible.\n",
        "demands": {
            "TravelSimulator": {
                "begin_time": "2023-07-02 00:00",
                "end_time": "2023-07-07 00:00",
                "origin_city": "Guangzhou",
                "origin_place": "Guangzhou Railway Hotel",
                "budget": 99999,
                "check_opening_hours": false,
                "check_meal": false,
                "set_budget": false,
                "type": 3,
                "limit": "time",
                "time_min": 123560,
                "time_max": 165604
            },
            "Constraints": {
                "SpotDurationConstraint": [
                    {
                        "spot": "Chimelong Tourist Resort",
                        "minutes": 210
                    },
                    {
                        "spot": "Huacheng Square",
                        "minutes": 270
                    },
                    {
                        "spot": "Shanghai History Museum",
                        "minutes": 150
                    },
                    {
                        "spot": "Xintiandi",
                        "minutes": 240
                    }
                ]
            }
        },
        "type": 3
    },
    {
        "question": "Bob is going to visit some spots across cities, please make a visit plan for him, including inter-city transportation, intra-city transportation, and visit time for each spot.    The demands are as follows:\n1. He now lives in Guangzhou Railway Hotel in Guangzhou. Every time he takes a train to a city, he lives in f\"{city} Railway Hotel\", such as \"Beijing Railway Hotel\" In Guangzhou, he needs to visit Chimelong Tourist Resort for 270 minutes, Huacheng Square for 210 minutes.In Hangzhou, he needs to visit Hefang Street for 180 minutes, Lingyin Temple for 240 minutes, Quaint Water Towns for 300 minutes. And the order can be decided by you.\n2. 5 days (2023-07-02 00:00 ~ 2023-07-07 00:00) for this trip.\n3. The daily opening_hours of spots can be obtained from the database table place. \"opening_hours_begin\" and \"opening_hours_end\" are the opening and closing times respectively\n4. On the basis of completing the above conditions (especially the time limit), spend as little money as possible.\n",
        "demands": {
            "TravelSimulator": {
                "begin_time": "2023-07-02 00:00",
                "end_time": "2023-07-07 00:00",
                "origin_city": "Guangzhou",
                "origin_place": "Guangzhou Railway Hotel",
                "budget": 99999,
                "check_opening_hours": true,
                "check_meal": false,
                "set_budget": false,
                "type": 3,
                "limit": "time",
                "time_min": 209005,
                "time_max": 319602
            },
            "Constraints": {
                "SpotDurationConstraint": [
                    {
                        "spot": "Chimelong Tourist Resort",
                        "minutes": 270
                    },
                    {
                        "spot": "Huacheng Square",
                        "minutes": 210
                    },
                    {
                        "spot": "Hefang Street",
                        "minutes": 180
                    },
                    {
                        "spot": "Lingyin Temple",
                        "minutes": 240
                    },
                    {
                        "spot": "Quaint Water Towns",
                        "minutes": 300
                    }
                ]
            }
        },
        "type": 3
    },
    {
        "question": "Bob is going to visit some spots across cities, please make a visit plan for him, including inter-city transportation, intra-city transportation, and visit time for each spot.    The demands are as follows:\n1. He now lives in Chengdu Railway Hotel in Chengdu. Every time he takes a train to a city, he lives in f\"{city} Railway Hotel\", such as \"Beijing Railway Hotel\" In Chengdu, he needs to visit The Chengdu Wuhou Shrine for 120 minutes, Chengdu Panda Base for 120 minutes.In Beijing, he needs to visit Beijing Olympic Park for 120 minutes, Shihua Cave for 150 minutes. And the order can be decided by you.\n2. 5 days (2023-07-05 00:00 ~ 2023-07-10 00:00) for this trip.\n3. The daily opening_hours of spots can be obtained from the database table place. \"opening_hours_begin\" and \"opening_hours_end\" are the opening and closing times respectively\n4. On the basis of completing the above conditions (especially the time limit), spend as little money as possible.\n",
        "demands": {
            "TravelSimulator": {
                "begin_time": "2023-07-05 00:00",
                "end_time": "2023-07-10 00:00",
                "origin_city": "Chengdu",
                "origin_place": "Chengdu Railway Hotel",
                "budget": 99999,
                "check_opening_hours": true,
                "check_meal": false,
                "set_budget": false,
                "type": 3,
                "limit": "time",
                "time_min": 40737,
                "time_max": 158366
            },
            "Constraints": {
                "SpotDurationConstraint": [
                    {
                        "spot": "The Chengdu Wuhou Shrine",
                        "minutes": 120
                    },
                    {
                        "spot": "Chengdu Panda Base",
                        "minutes": 120
                    },
                    {
                        "spot": "Beijing Olympic Park",
                        "minutes": 120
                    },
                    {
                        "spot": "Shihua Cave",
                        "minutes": 150
                    }
                ]
            }
        },
        "type": 3
    },
    {
        "question": "Bob is going to visit some spots across cities, please make a visit plan for him, including inter-city transportation, intra-city transportation, and visit time for each spot.    The demands are as follows:\n1. He now lives in Chengdu Railway Hotel in Chengdu. Every time he takes a train to a city, he lives in f\"{city} Railway Hotel\", such as \"Beijing Railway Hotel\" In Nanjing, he needs to visit Lake Xuanwu for 270 minutes, Tomb of Ming Emperor Zhu Yuanzhang for 300 minutes, Ming Palace for 150 minutes, Bailuzhou Park for 270 minutes, Taiping Heavenly-Kingdom Palace for 300 minutes, Qinhuai River for 210 minutes. And the order can be decided by you.\n2. He is free to travel from 2023.7.1 to 2023.7.20. The budget for transportation is 2300.0 CNY.\n3. Ignore the opening hours of attractions, assuming they are open all day. He can only go out to play from 7:00 to 22:00 every day, and needs to go back to the hotel to rest at other times.\n4. On the basis of completing the above conditions (especially the budget), spend as little time as possible.\n",
        "demands": {
            "TravelSimulator": {
                "begin_time": "2023-07-01 07:00",
                "end_time": "2023-07-20 00:00",
                "origin_city": "Chengdu",
                "origin_place": "Chengdu Railway Hotel",
                "budget": 99999,
                "check_opening_hours": false,
                "check_meal": false,
                "set_budget": true,
                "type": 3,
                "limit": "money",
                "money_min": 573,
                "money_max": 1902
            },
            "Constraints": {
                "SpotDurationConstraint": [
                    {
                        "spot": "Lake Xuanwu",
                        "minutes": 270
                    },
                    {
                        "spot": "Tomb of Ming Emperor Zhu Yuanzhang",
                        "minutes": 300
                    },
                    {
                        "spot": "Ming Palace",
                        "minutes": 150
                    },
                    {
                        "spot": "Bailuzhou Park",
                        "minutes": 270
                    },
                    {
                        "spot": "Taiping Heavenly-Kingdom Palace",
                        "minutes": 300
                    },
                    {
                        "spot": "Qinhuai River",
                        "minutes": 210
                    }
                ]
            }
        },
        "type": 3
    },
    {
        "question": "Bob is going to visit some spots across cities, please make a visit plan for him, including inter-city transportation, intra-city transportation, and visit time for each spot.    The demands are as follows:\n1. He now lives in Guangzhou Railway Hotel in Guangzhou. Every time he takes a train to a city, he lives in f\"{city} Railway Hotel\", such as \"Beijing Railway Hotel\" In Shanghai, he needs to visit Longhua Temple for 120 minutes, Shanghai Sightseeing Tunnel for 240 minutes, Shanghai Disney for 180 minutes, Shanghai History Museum for 180 minutes, Xintiandi for 270 minutes, Huangpu River Cruise for 180 minutes. And the order can be decided by you.\n2. He is free to travel from 2023.7.1 to 2023.7.20. The budget for transportation is 3100.0 CNY.\n3. Ignore the opening hours of attractions, assuming they are open all day. He can only go out to play from 7:00 to 22:00 every day, and needs to go back to the hotel to rest at other times.\n4. On the basis of completing the above conditions (especially the budget), spend as little time as possible.\n",
        "demands": {
            "TravelSimulator": {
                "begin_time": "2023-07-01 07:00",
                "end_time": "2023-07-20 00:00",
                "origin_city": "Guangzhou",
                "origin_place": "Guangzhou Railway Hotel",
                "budget": 99999,
                "check_opening_hours": false,
                "check_meal": false,
                "set_budget": true,
                "type": 3,
                "limit": "money",
                "money_min": 0,
                "money_max": 2119
            },
            "Constraints": {
                "SpotDurationConstraint": [
                    {
                        "spot": "Longhua Temple",
                        "minutes": 120
                    },
                    {
                        "spot": "Shanghai Sightseeing Tunnel",
                        "minutes": 240
                    },
                    {
                        "spot": "Shanghai Disney",
                        "minutes": 180
                    },
                    {
                        "spot": "Shanghai History Museum",
                        "minutes": 180
                    },
                    {
                        "spot": "Xintiandi",
                        "minutes": 270
                    },
                    {
                        "spot": "Huangpu River Cruise",
                        "minutes": 180
                    }
                ]
            }
        },
        "type": 3
    },
    {
        "question": "Bob is going to visit some spots across cities, please make a visit plan for him, including inter-city transportation, intra-city transportation, and visit time for each spot.    The demands are as follows:\n1. He now lives in Guangzhou Railway Hotel in Guangzhou. Every time he takes a train to a city, he lives in f\"{city} Railway Hotel\", such as \"Beijing Railway Hotel\" In Beijing, he needs to visit Beijing Olympic Park for 270 minutes, Tiananmen Square for 210 minutes, Shihua Cave for 210 minutes, The Forbidden City for 150 minutes, The Summer Palace for 240 minutes, Beijing Stone Carvings Art Museum for 240 minutes, The Great Wall for 120 minutes. And the order can be decided by you.\n2. He is free to travel from 2023.7.1 to 2023.7.20. The budget for transportation is 3400.0 CNY.\n3. The daily opening_hours of spots can be obtained from the database table place. \"opening_hours_begin\" and \"opening_hours_end\" are the opening and closing times respectively\n4. On the basis of completing the above conditions (especially the budget), spend as little time as possible.\n",
        "demands": {
            "TravelSimulator": {
                "begin_time": "2023-07-01 07:00",
                "end_time": "2023-07-20 00:00",
                "origin_city": "Guangzhou",
                "origin_place": "Guangzhou Railway Hotel",
                "budget": 99999,
                "check_opening_hours": true,
                "check_meal": false,
                "set_budget": true,
                "type": 3,
                "limit": "money",
                "money_min": 0,
                "money_max": 2859
            },
            "Constraints": {
                "SpotDurationConstraint": [
                    {
                        "spot": "Beijing Olympic Park",
                        "minutes": 270
                    },
                    {
                        "spot": "Tiananmen Square",
                        "minutes": 210
                    },
                    {
                        "spot": "Shihua Cave",
                        "minutes": 210
                    },
                    {
                        "spot": "The Forbidden City",
                        "minutes": 150
                    },
                    {
                        "spot": "The Summer Palace",
                        "minutes": 240
                    },
                    {
                        "spot": "Beijing Stone Carvings Art Museum",
                        "minutes": 240
                    },
                    {
                        "spot": "The Great Wall",
                        "minutes": 120
                    }
                ]
            }
        },
        "type": 3
    },
    {
        "question": "Bob is going to visit some spots across cities, please make a visit plan for him, including inter-city transportation, intra-city transportation, and visit time for each spot.    The demands are as follows:\n1. He now lives in Guangzhou Railway Hotel in Guangzhou. Every time he takes a train to a city, he lives in f\"{city} Railway Hotel\", such as \"Beijing Railway Hotel\" In Beijing, he needs to visit The Summer Palace for 210 minutes, The Temple of Heaven for 270 minutes, Shihua Cave for 210 minutes, Beijing Olympic Park for 150 minutes, The Forbidden City for 300 minutes, Tiananmen Square for 180 minutes, Beijing Stone Carvings Art Museum for 210 minutes. And the order can be decided by you.\n2. He is free to travel from 2023.7.1 to 2023.7.20. The budget for transportation is 2900.0 CNY.\n3. The daily opening_hours of spots can be obtained from the database table place. \"opening_hours_begin\" and \"opening_hours_end\" are the opening and closing times respectively\n4. On the basis of completing the above conditions (especially the budget), spend as little time as possible.\n",
        "demands": {
            "TravelSimulator": {
                "begin_time": "2023-07-01 07:00",
                "end_time": "2023-07-20 00:00",
                "origin_city": "Guangzhou",
                "origin_place": "Guangzhou Railway Hotel",
                "budget": 99999,
                "check_opening_hours": true,
                "check_meal": false,
                "set_budget": true,
                "type": 3,
                "limit": "money",
                "money_min": 0,
                "money_max": 2630
            },
            "Constraints": {
                "SpotDurationConstraint": [
                    {
                        "spot": "The Summer Palace",
                        "minutes": 210
                    },
                    {
                        "spot": "The Temple of Heaven",
                        "minutes": 270
                    },
                    {
                        "spot": "Shihua Cave",
                        "minutes": 210
                    },
                    {
                        "spot": "Beijing Olympic Park",
                        "minutes": 150
                    },
                    {
                        "spot": "The Forbidden City",
                        "minutes": 300
                    },
                    {
                        "spot": "Tiananmen Square",
                        "minutes": 180
                    },
                    {
                        "spot": "Beijing Stone Carvings Art Museum",
                        "minutes": 210
                    }
                ]
            }
        },
        "type": 3
    },
    {
        "question": "Bob is going to visit some spots across cities, please make a visit plan for him, including inter-city transportation, intra-city transportation, and visit time for each spot.    The demands are as follows:\n1. He now lives in Nanjing Railway Hotel in Nanjing. Every time he takes a train to a city, he lives in f\"{city} Railway Hotel\", such as \"Beijing Railway Hotel\" In Wuhan, he needs to visit Baotong Temple for 240 minutes, East Lake for 270 minutes, Han Show for 210 minutes, Hubu Alley for 300 minutes, Yellow Crane Tower for 120 minutes, Tan Hua Lin for 270 minutes. And the order can be decided by you.\n2. 6 days (2023-07-09 00:00 ~ 2023-07-15 00:00) for this trip.\n3. Ignore the opening hours of attractions, assuming they are open all day. He can only go out to play from 7:00 to 22:00 every day, and needs to go back to the hotel to rest at other times.\n4. On the basis of completing the above conditions (especially the time limit), spend as little money as possible.\n",
        "demands": {
            "TravelSimulator": {
                "begin_time": "2023-07-09 00:00",
                "end_time": "2023-07-15 00:00",
                "origin_city": "Nanjing",
                "origin_place": "Nanjing Railway Hotel",
                "budget": 99999,
                "check_opening_hours": false,
                "check_meal": false,
                "set_budget": false,
                "type": 3,
                "limit": "time",
                "time_min": 199723,
                "time_max": 334850
            },
            "Constraints": {
                "SpotDurationConstraint": [
                    {
                        "spot": "Baotong Temple",
                        "minutes": 240
                    },
                    {
                        "spot": "East Lake",
                        "minutes": 270
                    },
                    {
                        "spot": "Han Show",
                        "minutes": 210
                    },
                    {
                        "spot": "Hubu Alley",
                        "minutes": 300
                    },
                    {
                        "spot": "Yellow Crane Tower",
                        "minutes": 120
                    },
                    {
                        "spot": "Tan Hua Lin",
                        "minutes": 270
                    }
                ]
            }
        },
        "type": 3
    },
    {
        "question": "Bob is going to visit some spots across cities, please make a visit plan for him, including inter-city transportation, intra-city transportation, and visit time for each spot.    The demands are as follows:\n1. He now lives in Chengdu Railway Hotel in Chengdu. Every time he takes a train to a city, he lives in f\"{city} Railway Hotel\", such as \"Beijing Railway Hotel\" In Shanghai, he needs to visit Shanghai Sightseeing Tunnel for 210 minutes, Shanghai History Museum for 300 minutes, Shanghai Disney for 270 minutes, Huangpu River Cruise for 180 minutes, Century Park for 210 minutes, Qibao Ancient Town for 150 minutes, Longhua Temple for 150 minutes. And the order can be decided by you.\n2. 6 days (2023-07-11 00:00 ~ 2023-07-17 00:00) for this trip.\n3. Ignore the opening hours of attractions, assuming they are open all day. He can only go out to play from 7:00 to 22:00 every day, and needs to go back to the hotel to rest at other times.\n4. On the basis of completing the above conditions (especially the time limit), spend as little money as possible.\n",
        "demands": {
            "TravelSimulator": {
                "begin_time": "2023-07-11 00:00",
                "end_time": "2023-07-17 00:00",
                "origin_city": "Chengdu",
                "origin_place": "Chengdu Railway Hotel",
                "budget": 99999,
                "check_opening_hours": false,
                "check_meal": false,
                "set_budget": false,
                "type": 3,
                "limit": "time",
                "time_min": 202384,
                "time_max": 396459
            },
            "Constraints": {
                "SpotDurationConstraint": [
                    {
                        "spot": "Shanghai Sightseeing Tunnel",
                        "minutes": 210
                    },
                    {
                        "spot": "Shanghai History Museum",
                        "minutes": 300
                    },
                    {
                        "spot": "Shanghai Disney",
                        "minutes": 270
                    },
                    {
                        "spot": "Huangpu River Cruise",
                        "minutes": 180
                    },
                    {
                        "spot": "Century Park",
                        "minutes": 210
                    },
                    {
                        "spot": "Qibao Ancient Town",
                        "minutes": 150
                    },
                    {
                        "spot": "Longhua Temple",
                        "minutes": 150
                    }
                ]
            }
        },
        "type": 3
    },
    {
        "question": "Bob is going to visit some spots across cities, please make a visit plan for him, including inter-city transportation, intra-city transportation, and visit time for each spot.    The demands are as follows:\n1. He now lives in Guangzhou Railway Hotel in Guangzhou. Every time he takes a train to a city, he lives in f\"{city} Railway Hotel\", such as \"Beijing Railway Hotel\" In Beijing, he needs to visit Beijing Olympic Park for 300 minutes, The Forbidden City for 120 minutes, Tiananmen Square for 270 minutes, Shihua Cave for 300 minutes, Beijing Stone Carvings Art Museum for 270 minutes, The Summer Palace for 120 minutes, The Temple of Heaven for 150 minutes. And the order can be decided by you.\n2. 6 days (2023-07-08 00:00 ~ 2023-07-14 00:00) for this trip.\n3. The daily opening_hours of spots can be obtained from the database table place. \"opening_hours_begin\" and \"opening_hours_end\" are the opening and closing times respectively\n4. On the basis of completing the above conditions (especially the time limit), spend as little money as possible.\n",
        "demands": {
            "TravelSimulator": {
                "begin_time": "2023-07-08 00:00",
                "end_time": "2023-07-14 00:00",
                "origin_city": "Guangzhou",
                "origin_place": "Guangzhou Railway Hotel",
                "budget": 99999,
                "check_opening_hours": true,
                "check_meal": false,
                "set_budget": false,
                "type": 3,
                "limit": "time",
                "time_min": 242775,
                "time_max": 390145
            },
            "Constraints": {
                "SpotDurationConstraint": [
                    {
                        "spot": "Beijing Olympic Park",
                        "minutes": 300
                    },
                    {
                        "spot": "The Forbidden City",
                        "minutes": 120
                    },
                    {
                        "spot": "Tiananmen Square",
                        "minutes": 270
                    },
                    {
                        "spot": "Shihua Cave",
                        "minutes": 300
                    },
                    {
                        "spot": "Beijing Stone Carvings Art Museum",
                        "minutes": 270
                    },
                    {
                        "spot": "The Summer Palace",
                        "minutes": 120
                    },
                    {
                        "spot": "The Temple of Heaven",
                        "minutes": 150
                    }
                ]
            }
        },
        "type": 3
    },
    {
        "question": "Bob is going to visit some spots across cities, please make a visit plan for him, including inter-city transportation, intra-city transportation, and visit time for each spot.    The demands are as follows:\n1. He now lives in Hangzhou Railway Hotel in Hangzhou. Every time he takes a train to a city, he lives in f\"{city} Railway Hotel\", such as \"Beijing Railway Hotel\" In Nanjing, he needs to visit Tomb of Ming Emperor Zhu Yuanzhang for 150 minutes, Ming Palace for 240 minutes, Lake Xuanwu for 300 minutes, Qinhuai River for 210 minutes, Taiping Heavenly-Kingdom Palace for 120 minutes, Bailuzhou Park for 180 minutes. And the order can be decided by you.\n2. 6 days (2023-07-05 00:00 ~ 2023-07-11 00:00) for this trip.\n3. The daily opening_hours of spots can be obtained from the database table place. \"opening_hours_begin\" and \"opening_hours_end\" are the opening and closing times respectively\n4. On the basis of completing the above conditions (especially the time limit), spend as little money as possible.\n",
        "demands": {
            "TravelSimulator": {
                "begin_time": "2023-07-05 00:00",
                "end_time": "2023-07-11 00:00",
                "origin_city": "Hangzhou",
                "origin_place": "Hangzhou Railway Hotel",
                "budget": 99999,
                "check_opening_hours": true,
                "check_meal": false,
                "set_budget": false,
                "type": 3,
                "limit": "time",
                "time_min": 179036,
                "time_max": 324177
            },
            "Constraints": {
                "SpotDurationConstraint": [
                    {
                        "spot": "Tomb of Ming Emperor Zhu Yuanzhang",
                        "minutes": 150
                    },
                    {
                        "spot": "Ming Palace",
                        "minutes": 240
                    },
                    {
                        "spot": "Lake Xuanwu",
                        "minutes": 300
                    },
                    {
                        "spot": "Qinhuai River",
                        "minutes": 210
                    },
                    {
                        "spot": "Taiping Heavenly-Kingdom Palace",
                        "minutes": 120
                    },
                    {
                        "spot": "Bailuzhou Park",
                        "minutes": 180
                    }
                ]
            }
        },
        "type": 3
    },
    {
        "question": "Bob is going to visit some spots across cities, please make a visit plan for him, including inter-city transportation, intra-city transportation, and visit time for each spot.    The demands are as follows:\n1. He now lives in Shanghai Railway Hotel in Shanghai. Every time he takes a train to a city, he lives in f\"{city} Railway Hotel\", such as \"Beijing Railway Hotel\" In Shanghai, he needs to visit Century Park for 270 minutes, Shanghai Sightseeing Tunnel for 120 minutes, Longhua Temple for 300 minutes.In Chengdu, he needs to visit Du Fu Thatched Cottage for 240 minutes, Chengdu Panda Base for 210 minutes, The Chengdu Wuhou Shrine for 270 minutes, Leshan Giant Buddha for 150 minutes. And the order can be decided by you.\n2. He is free to travel from 2023.7.1 to 2023.7.20. The budget for transportation is 2400.0 CNY.\n3. Ignore the opening hours of attractions, assuming they are open all day. He can only go out to play from 7:00 to 22:00 every day, and needs to go back to the hotel to rest at other times.\n4. On the basis of completing the above conditions (especially the budget), spend as little time as possible.\n",
        "demands": {
            "TravelSimulator": {
                "begin_time": "2023-07-01 07:00",
                "end_time": "2023-07-20 00:00",
                "origin_city": "Shanghai",
                "origin_place": "Shanghai Railway Hotel",
                "budget": 99999,
                "check_opening_hours": false,
                "check_meal": false,
                "set_budget": true,
                "type": 3,
                "limit": "money",
                "money_min": 1026,
                "money_max": 2292
            },
            "Constraints": {
                "SpotDurationConstraint": [
                    {
                        "spot": "Century Park",
                        "minutes": 270
                    },
                    {
                        "spot": "Shanghai Sightseeing Tunnel",
                        "minutes": 120
                    },
                    {
                        "spot": "Longhua Temple",
                        "minutes": 300
                    },
                    {
                        "spot": "Du Fu Thatched Cottage",
                        "minutes": 240
                    },
                    {
                        "spot": "Chengdu Panda Base",
                        "minutes": 210
                    },
                    {
                        "spot": "The Chengdu Wuhou Shrine",
                        "minutes": 270
                    },
                    {
                        "spot": "Leshan Giant Buddha",
                        "minutes": 150
                    }
                ]
            }
        },
        "type": 3
    },
    {
        "question": "Bob is going to visit some spots across cities, please make a visit plan for him, including inter-city transportation, intra-city transportation, and visit time for each spot.    The demands are as follows:\n1. He now lives in Guangzhou Railway Hotel in Guangzhou. Every time he takes a train to a city, he lives in f\"{city} Railway Hotel\", such as \"Beijing Railway Hotel\" In Guangzhou, he needs to visit Baiyun Mountain for 240 minutes, Canton Tower for 180 minutes, Yuexiu Park for 270 minutes.In Nanjing, he needs to visit Lake Xuanwu for 270 minutes, Tomb of Ming Emperor Zhu Yuanzhang for 270 minutes, Ming Palace for 120 minutes. And the order can be decided by you.\n2. He is free to travel from 2023.7.1 to 2023.7.20. The budget for transportation is 2000.0 CNY.\n3. Ignore the opening hours of attractions, assuming they are open all day. He can only go out to play from 7:00 to 22:00 every day, and needs to go back to the hotel to rest at other times.\n4. On the basis of completing the above conditions (especially the budget), spend as little time as possible.\n",
        "demands": {
            "TravelSimulator": {
                "begin_time": "2023-07-01 07:00",
                "end_time": "2023-07-20 00:00",
                "origin_city": "Guangzhou",
                "origin_place": "Guangzhou Railway Hotel",
                "budget": 99999,
                "check_opening_hours": false,
                "check_meal": false,
                "set_budget": true,
                "type": 3,
                "limit": "money",
                "money_min": 0,
                "money_max": 1788
            },
            "Constraints": {
                "SpotDurationConstraint": [
                    {
                        "spot": "Baiyun Mountain",
                        "minutes": 240
                    },
                    {
                        "spot": "Canton Tower",
                        "minutes": 180
                    },
                    {
                        "spot": "Yuexiu Park",
                        "minutes": 270
                    },
                    {
                        "spot": "Lake Xuanwu",
                        "minutes": 270
                    },
                    {
                        "spot": "Tomb of Ming Emperor Zhu Yuanzhang",
                        "minutes": 270
                    },
                    {
                        "spot": "Ming Palace",
                        "minutes": 120
                    }
                ]
            }
        },
        "type": 3
    },
    {
        "question": "Bob is going to visit some spots across cities, please make a visit plan for him, including inter-city transportation, intra-city transportation, and visit time for each spot.    The demands are as follows:\n1. He now lives in Shanghai Railway Hotel in Shanghai. Every time he takes a train to a city, he lives in f\"{city} Railway Hotel\", such as \"Beijing Railway Hotel\" In Wuhan, he needs to visit Hubu Alley for 210 minutes, East Lake for 240 minutes.In Nanjing, he needs to visit Qinhuai River for 270 minutes, Ming Palace for 210 minutes. And the order can be decided by you.\n2. He is free to travel from 2023.7.1 to 2023.7.20. The budget for transportation is 1500.0 CNY.\n3. Ignore the opening hours of attractions, assuming they are open all day. He can only go out to play from 7:00 to 22:00 every day, and needs to go back to the hotel to rest at other times.\n4. On the basis of completing the above conditions (especially the budget), spend as little time as possible.\n",
        "demands": {
            "TravelSimulator": {
                "begin_time": "2023-07-01 07:00",
                "end_time": "2023-07-20 00:00",
                "origin_city": "Shanghai",
                "origin_place": "Shanghai Railway Hotel",
                "budget": 99999,
                "check_opening_hours": false,
                "check_meal": false,
                "set_budget": true,
                "type": 3,
                "limit": "money",
                "money_min": 487,
                "money_max": 777
            },
            "Constraints": {
                "SpotDurationConstraint": [
                    {
                        "spot": "Hubu Alley",
                        "minutes": 210
                    },
                    {
                        "spot": "East Lake",
                        "minutes": 240
                    },
                    {
                        "spot": "Qinhuai River",
                        "minutes": 270
                    },
                    {
                        "spot": "Ming Palace",
                        "minutes": 210
                    }
                ]
            }
        },
        "type": 3
    },
    {
        "question": "Bob is going to visit some spots across cities, please make a visit plan for him, including inter-city transportation, intra-city transportation, and visit time for each spot.    The demands are as follows:\n1. He now lives in Guangzhou Railway Hotel in Guangzhou. Every time he takes a train to a city, he lives in f\"{city} Railway Hotel\", such as \"Beijing Railway Hotel\" In Nanjing, he needs to visit Bailuzhou Park for 300 minutes, Tomb of Ming Emperor Zhu Yuanzhang for 240 minutes.In Chengdu, he needs to visit Chengdu Panda Base for 300 minutes, Chengdu Tea Houses for 300 minutes, Leshan Giant Buddha for 150 minutes. And the order can be decided by you.\n2. He is free to travel from 2023.7.1 to 2023.7.20. The budget for transportation is 2800.0 CNY.\n3. Ignore the opening hours of attractions, assuming they are open all day. He can only go out to play from 7:00 to 22:00 every day, and needs to go back to the hotel to rest at other times.\n4. On the basis of completing the above conditions (especially the budget), spend as little time as possible.\n",
        "demands": {
            "TravelSimulator": {
                "begin_time": "2023-07-01 07:00",
                "end_time": "2023-07-20 00:00",
                "origin_city": "Guangzhou",
                "origin_place": "Guangzhou Railway Hotel",
                "budget": 99999,
                "check_opening_hours": false,
                "check_meal": false,
                "set_budget": true,
                "type": 3,
                "limit": "money",
                "money_min": 574,
                "money_max": 2451
            },
            "Constraints": {
                "SpotDurationConstraint": [
                    {
                        "spot": "Bailuzhou Park",
                        "minutes": 300
                    },
                    {
                        "spot": "Tomb of Ming Emperor Zhu Yuanzhang",
                        "minutes": 240
                    },
                    {
                        "spot": "Chengdu Panda Base",
                        "minutes": 300
                    },
                    {
                        "spot": "Chengdu Tea Houses",
                        "minutes": 300
                    },
                    {
                        "spot": "Leshan Giant Buddha",
                        "minutes": 150
                    }
                ]
            }
        },
        "type": 3
    },
    {
        "question": "Bob is going to visit some spots across cities, please make a visit plan for him, including inter-city transportation, intra-city transportation, and visit time for each spot.    The demands are as follows:\n1. He now lives in Beijing Railway Hotel in Beijing. Every time he takes a train to a city, he lives in f\"{city} Railway Hotel\", such as \"Beijing Railway Hotel\" In Beijing, he needs to visit The Temple of Heaven for 300 minutes, The Summer Palace for 120 minutes, Tiananmen Square for 180 minutes.In Hangzhou, he needs to visit Hefang Street for 120 minutes, Quaint Water Towns for 210 minutes, China National Tea Museum for 240 minutes, West Lake for 300 minutes. And the order can be decided by you.\n2. He is free to travel from 2023.7.1 to 2023.7.20. The budget for transportation is 2100.0 CNY.\n3. The daily opening_hours of spots can be obtained from the database table place. \"opening_hours_begin\" and \"opening_hours_end\" are the opening and closing times respectively\n4. On the basis of completing the above conditions (especially the budget), spend as little time as possible.\n",
        "demands": {
            "TravelSimulator": {
                "begin_time": "2023-07-01 07:00",
                "end_time": "2023-07-20 00:00",
                "origin_city": "Beijing",
                "origin_place": "Beijing Railway Hotel",
                "budget": 99999,
                "check_opening_hours": true,
                "check_meal": false,
                "set_budget": true,
                "type": 3,
                "limit": "money",
                "money_min": 336,
                "money_max": 1454
            },
            "Constraints": {
                "SpotDurationConstraint": [
                    {
                        "spot": "The Temple of Heaven",
                        "minutes": 300
                    },
                    {
                        "spot": "The Summer Palace",
                        "minutes": 120
                    },
                    {
                        "spot": "Tiananmen Square",
                        "minutes": 180
                    },
                    {
                        "spot": "Hefang Street",
                        "minutes": 120
                    },
                    {
                        "spot": "Quaint Water Towns",
                        "minutes": 210
                    },
                    {
                        "spot": "China National Tea Museum",
                        "minutes": 240
                    },
                    {
                        "spot": "West Lake",
                        "minutes": 300
                    }
                ]
            }
        },
        "type": 3
    },
    {
        "question": "Bob is going to visit some spots across cities, please make a visit plan for him, including inter-city transportation, intra-city transportation, and visit time for each spot.    The demands are as follows:\n1. He now lives in Chengdu Railway Hotel in Chengdu. Every time he takes a train to a city, he lives in f\"{city} Railway Hotel\", such as \"Beijing Railway Hotel\" In Chengdu, he needs to visit Du Fu Thatched Cottage for 180 minutes, The Chengdu Wuhou Shrine for 270 minutes, Chengdu Tea Houses for 270 minutes, Leshan Giant Buddha for 300 minutes.In Hangzhou, he needs to visit Lingyin Temple for 300 minutes, Quaint Water Towns for 300 minutes, China National Tea Museum for 270 minutes. And the order can be decided by you.\n2. He is free to travel from 2023.7.1 to 2023.7.20. The budget for transportation is 2100.0 CNY.\n3. The daily opening_hours of spots can be obtained from the database table place. \"opening_hours_begin\" and \"opening_hours_end\" are the opening and closing times respectively\n4. On the basis of completing the above conditions (especially the budget), spend as little time as possible.\n",
        "demands": {
            "TravelSimulator": {
                "begin_time": "2023-07-01 07:00",
                "end_time": "2023-07-20 00:00",
                "origin_city": "Chengdu",
                "origin_place": "Chengdu Railway Hotel",
                "budget": 99999,
                "check_opening_hours": true,
                "check_meal": false,
                "set_budget": true,
                "type": 3,
                "limit": "money",
                "money_min": 0,
                "money_max": 2266
            },
            "Constraints": {
                "SpotDurationConstraint": [
                    {
                        "spot": "Du Fu Thatched Cottage",
                        "minutes": 180
                    },
                    {
                        "spot": "The Chengdu Wuhou Shrine",
                        "minutes": 270
                    },
                    {
                        "spot": "Chengdu Tea Houses",
                        "minutes": 270
                    },
                    {
                        "spot": "Leshan Giant Buddha",
                        "minutes": 300
                    },
                    {
                        "spot": "Lingyin Temple",
                        "minutes": 300
                    },
                    {
                        "spot": "Quaint Water Towns",
                        "minutes": 300
                    },
                    {
                        "spot": "China National Tea Museum",
                        "minutes": 270
                    }
                ]
            }
        },
        "type": 3
    },
    {
        "question": "Bob is going to visit some spots across cities, please make a visit plan for him, including inter-city transportation, intra-city transportation, and visit time for each spot.    The demands are as follows:\n1. He now lives in Beijing Railway Hotel in Beijing. Every time he takes a train to a city, he lives in f\"{city} Railway Hotel\", such as \"Beijing Railway Hotel\" In Chengdu, he needs to visit The Chengdu Wuhou Shrine for 240 minutes, Du Fu Thatched Cottage for 210 minutes.In Shanghai, he needs to visit Xintiandi for 120 minutes, Shanghai History Museum for 180 minutes. And the order can be decided by you.\n2. He is free to travel from 2023.7.1 to 2023.7.20. The budget for transportation is 3600.0 CNY.\n3. The daily opening_hours of spots can be obtained from the database table place. \"opening_hours_begin\" and \"opening_hours_end\" are the opening and closing times respectively\n4. On the basis of completing the above conditions (especially the budget), spend as little time as possible.\n",
        "demands": {
            "TravelSimulator": {
                "begin_time": "2023-07-01 07:00",
                "end_time": "2023-07-20 00:00",
                "origin_city": "Beijing",
                "origin_place": "Beijing Railway Hotel",
                "budget": 99999,
                "check_opening_hours": true,
                "check_meal": false,
                "set_budget": true,
                "type": 3,
                "limit": "money",
                "money_min": 1021,
                "money_max": 2797
            },
            "Constraints": {
                "SpotDurationConstraint": [
                    {
                        "spot": "The Chengdu Wuhou Shrine",
                        "minutes": 240
                    },
                    {
                        "spot": "Du Fu Thatched Cottage",
                        "minutes": 210
                    },
                    {
                        "spot": "Xintiandi",
                        "minutes": 120
                    },
                    {
                        "spot": "Shanghai History Museum",
                        "minutes": 180
                    }
                ]
            }
        },
        "type": 3
    },
    {
        "question": "Bob is going to visit some spots across cities, please make a visit plan for him, including inter-city transportation, intra-city transportation, and visit time for each spot.    The demands are as follows:\n1. He now lives in Guangzhou Railway Hotel in Guangzhou. Every time he takes a train to a city, he lives in f\"{city} Railway Hotel\", such as \"Beijing Railway Hotel\" In Shanghai, he needs to visit Century Park for 240 minutes, Shanghai Sightseeing Tunnel for 270 minutes. And the order can be decided by you.\n2. He is free to travel from 2023.7.1 to 2023.7.20. The budget for transportation is 2300.0 CNY.\n3. The daily opening_hours of spots can be obtained from the database table place. \"opening_hours_begin\" and \"opening_hours_end\" are the opening and closing times respectively\n4. On the basis of completing the above conditions (especially the budget), spend as little time as possible.\n",
        "demands": {
            "TravelSimulator": {
                "begin_time": "2023-07-01 07:00",
                "end_time": "2023-07-20 00:00",
                "origin_city": "Guangzhou",
                "origin_place": "Guangzhou Railway Hotel",
                "budget": 99999,
                "check_opening_hours": true,
                "check_meal": false,
                "set_budget": true,
                "type": 3,
                "limit": "money",
                "money_min": 0,
                "money_max": 1586
            },
            "Constraints": {
                "SpotDurationConstraint": [
                    {
                        "spot": "Century Park",
                        "minutes": 240
                    },
                    {
                        "spot": "Shanghai Sightseeing Tunnel",
                        "minutes": 270
                    }
                ]
            }
        },
        "type": 3
    },
    {
        "question": "Bob is going to visit some spots across cities, please make a visit plan for him, including inter-city transportation, intra-city transportation, and visit time for each spot.    The demands are as follows:\n1. He now lives in Guangzhou Railway Hotel in Guangzhou. Every time he takes a train to a city, he lives in f\"{city} Railway Hotel\", such as \"Beijing Railway Hotel\" In Guangzhou, he needs to visit Canton Tower for 240 minutes, Baiyun Mountain for 300 minutes, Yuexiu Park for 300 minutes, Chimelong Tourist Resort for 150 minutes.In Hangzhou, he needs to visit Quaint Water Towns for 300 minutes, China National Tea Museum for 240 minutes, Lingyin Temple for 270 minutes. And the order can be decided by you.\n2. 6 days (2023-07-03 00:00 ~ 2023-07-09 00:00) for this trip.\n3. Ignore the opening hours of attractions, assuming they are open all day. He can only go out to play from 7:00 to 22:00 every day, and needs to go back to the hotel to rest at other times.\n4. On the basis of completing the above conditions (especially the time limit), spend as little money as possible.\n",
        "demands": {
            "TravelSimulator": {
                "begin_time": "2023-07-03 00:00",
                "end_time": "2023-07-09 00:00",
                "origin_city": "Guangzhou",
                "origin_place": "Guangzhou Railway Hotel",
                "budget": 99999,
                "check_opening_hours": false,
                "check_meal": false,
                "set_budget": false,
                "type": 3,
                "limit": "time",
                "time_min": 218178,
                "time_max": 345098
            },
            "Constraints": {
                "SpotDurationConstraint": [
                    {
                        "spot": "Canton Tower",
                        "minutes": 240
                    },
                    {
                        "spot": "Baiyun Mountain",
                        "minutes": 300
                    },
                    {
                        "spot": "Yuexiu Park",
                        "minutes": 300
                    },
                    {
                        "spot": "Chimelong Tourist Resort",
                        "minutes": 150
                    },
                    {
                        "spot": "Quaint Water Towns",
                        "minutes": 300
                    },
                    {
                        "spot": "China National Tea Museum",
                        "minutes": 240
                    },
                    {
                        "spot": "Lingyin Temple",
                        "minutes": 270
                    }
                ]
            }
        },
        "type": 3
    },
    {
        "question": "Bob is going to visit some spots across cities, please make a visit plan for him, including inter-city transportation, intra-city transportation, and visit time for each spot.    The demands are as follows:\n1. He now lives in Shanghai Railway Hotel in Shanghai. Every time he takes a train to a city, he lives in f\"{city} Railway Hotel\", such as \"Beijing Railway Hotel\" In Shanghai, he needs to visit Huangpu River Cruise for 300 minutes, Xintiandi for 180 minutes, Qibao Ancient Town for 150 minutes, Shanghai Sightseeing Tunnel for 180 minutes, Shanghai Disney for 180 minutes. And the order can be decided by you.\n2. 6 days (2023-07-03 00:00 ~ 2023-07-09 00:00) for this trip.\n3. Ignore the opening hours of attractions, assuming they are open all day. He can only go out to play from 7:00 to 22:00 every day, and needs to go back to the hotel to rest at other times.\n4. On the basis of completing the above conditions (especially the time limit), spend as little money as possible.\n",
        "demands": {
            "TravelSimulator": {
                "begin_time": "2023-07-03 00:00",
                "end_time": "2023-07-09 00:00",
                "origin_city": "Shanghai",
                "origin_place": "Shanghai Railway Hotel",
                "budget": 99999,
                "check_opening_hours": false,
                "check_meal": false,
                "set_budget": false,
                "type": 3,
                "limit": "time",
                "time_min": 230400,
                "time_max": 230400
            },
            "Constraints": {
                "SpotDurationConstraint": [
                    {
                        "spot": "Huangpu River Cruise",
                        "minutes": 300
                    },
                    {
                        "spot": "Xintiandi",
                        "minutes": 180
                    },
                    {
                        "spot": "Qibao Ancient Town",
                        "minutes": 150
                    },
                    {
                        "spot": "Shanghai Sightseeing Tunnel",
                        "minutes": 180
                    },
                    {
                        "spot": "Shanghai Disney",
                        "minutes": 180
                    }
                ]
            }
        },
        "type": 3
    },
    {
        "question": "Bob is going to visit some spots across cities, please make a visit plan for him, including inter-city transportation, intra-city transportation, and visit time for each spot.    The demands are as follows:\n1. He now lives in Shanghai Railway Hotel in Shanghai. Every time he takes a train to a city, he lives in f\"{city} Railway Hotel\", such as \"Beijing Railway Hotel\" In Guangzhou, he needs to visit Huacheng Square for 150 minutes, Baiyun Mountain for 270 minutes, Yuexiu Park for 210 minutes.In Wuhan, he needs to visit Baotong Temple for 270 minutes, East Lake for 150 minutes. And the order can be decided by you.\n2. 6 days (2023-07-03 00:00 ~ 2023-07-09 00:00) for this trip.\n3. Ignore the opening hours of attractions, assuming they are open all day. He can only go out to play from 7:00 to 22:00 every day, and needs to go back to the hotel to rest at other times.\n4. On the basis of completing the above conditions (especially the time limit), spend as little money as possible.\n",
        "demands": {
            "TravelSimulator": {
                "begin_time": "2023-07-03 00:00",
                "end_time": "2023-07-09 00:00",
                "origin_city": "Shanghai",
                "origin_place": "Shanghai Railway Hotel",
                "budget": 99999,
                "check_opening_hours": false,
                "check_meal": false,
                "set_budget": false,
                "type": 3,
                "limit": "time",
                "time_min": 144177,
                "time_max": 281322
            },
            "Constraints": {
                "SpotDurationConstraint": [
                    {
                        "spot": "Huacheng Square",
                        "minutes": 150
                    },
                    {
                        "spot": "Baiyun Mountain",
                        "minutes": 270
                    },
                    {
                        "spot": "Yuexiu Park",
                        "minutes": 210
                    },
                    {
                        "spot": "Baotong Temple",
                        "minutes": 270
                    },
                    {
                        "spot": "East Lake",
                        "minutes": 150
                    }
                ]
            }
        },
        "type": 3
    },
    {
        "question": "Bob is going to visit some spots across cities, please make a visit plan for him, including inter-city transportation, intra-city transportation, and visit time for each spot.    The demands are as follows:\n1. He now lives in Nanjing Railway Hotel in Nanjing. Every time he takes a train to a city, he lives in f\"{city} Railway Hotel\", such as \"Beijing Railway Hotel\" In Shanghai, he needs to visit Shanghai Sightseeing Tunnel for 150 minutes, Longhua Temple for 180 minutes.In Guangzhou, he needs to visit Huacheng Square for 300 minutes, Yuexiu Park for 240 minutes. And the order can be decided by you.\n2. 6 days (2023-07-08 00:00 ~ 2023-07-14 00:00) for this trip.\n3. Ignore the opening hours of attractions, assuming they are open all day. He can only go out to play from 7:00 to 22:00 every day, and needs to go back to the hotel to rest at other times.\n4. On the basis of completing the above conditions (especially the time limit), spend as little money as possible.\n",
        "demands": {
            "TravelSimulator": {
                "begin_time": "2023-07-08 00:00",
                "end_time": "2023-07-14 00:00",
                "origin_city": "Nanjing",
                "origin_place": "Nanjing Railway Hotel",
                "budget": 99999,
                "check_opening_hours": false,
                "check_meal": false,
                "set_budget": false,
                "type": 3,
                "limit": "time",
                "time_min": 84064,
                "time_max": 248903
            },
            "Constraints": {
                "SpotDurationConstraint": [
                    {
                        "spot": "Shanghai Sightseeing Tunnel",
                        "minutes": 150
                    },
                    {
                        "spot": "Longhua Temple",
                        "minutes": 180
                    },
                    {
                        "spot": "Huacheng Square",
                        "minutes": 300
                    },
                    {
                        "spot": "Yuexiu Park",
                        "minutes": 240
                    }
                ]
            }
        },
        "type": 3
    },
    {
        "question": "Bob is going to visit some spots across cities, please make a visit plan for him, including inter-city transportation, intra-city transportation, and visit time for each spot.    The demands are as follows:\n1. He now lives in Guangzhou Railway Hotel in Guangzhou. Every time he takes a train to a city, he lives in f\"{city} Railway Hotel\", such as \"Beijing Railway Hotel\" In Guangzhou, he needs to visit Yuexiu Park for 180 minutes, Canton Tower for 180 minutes, Baiyun Mountain for 210 minutes, Huacheng Square for 210 minutes.In Wuhan, he needs to visit Hubu Alley for 150 minutes, Baotong Temple for 180 minutes, Yellow Crane Tower for 180 minutes. And the order can be decided by you.\n2. 6 days (2023-07-09 00:00 ~ 2023-07-15 00:00) for this trip.\n3. The daily opening_hours of spots can be obtained from the database table place. \"opening_hours_begin\" and \"opening_hours_end\" are the opening and closing times respectively\n4. On the basis of completing the above conditions (especially the time limit), spend as little money as possible.\n",
        "demands": {
            "TravelSimulator": {
                "begin_time": "2023-07-09 00:00",
                "end_time": "2023-07-15 00:00",
                "origin_city": "Guangzhou",
                "origin_place": "Guangzhou Railway Hotel",
                "budget": 99999,
                "check_opening_hours": true,
                "check_meal": false,
                "set_budget": false,
                "type": 3,
                "limit": "time",
                "time_min": 186815,
                "time_max": 334142
            },
            "Constraints": {
                "SpotDurationConstraint": [
                    {
                        "spot": "Yuexiu Park",
                        "minutes": 180
                    },
                    {
                        "spot": "Canton Tower",
                        "minutes": 180
                    },
                    {
                        "spot": "Baiyun Mountain",
                        "minutes": 210
                    },
                    {
                        "spot": "Huacheng Square",
                        "minutes": 210
                    },
                    {
                        "spot": "Hubu Alley",
                        "minutes": 150
                    },
                    {
                        "spot": "Baotong Temple",
                        "minutes": 180
                    },
                    {
                        "spot": "Yellow Crane Tower",
                        "minutes": 180
                    }
                ]
            }
        },
        "type": 3
    },
    {
        "question": "Bob is going to visit some spots across cities, please make a visit plan for him, including inter-city transportation, intra-city transportation, and visit time for each spot.    The demands are as follows:\n1. He now lives in Shanghai Railway Hotel in Shanghai. Every time he takes a train to a city, he lives in f\"{city} Railway Hotel\", such as \"Beijing Railway Hotel\" In Shanghai, he needs to visit Xintiandi for 120 minutes, Century Park for 270 minutes, Shanghai History Museum for 300 minutes, Longhua Temple for 270 minutes, Shanghai Sightseeing Tunnel for 210 minutes. And the order can be decided by you.\n2. 6 days (2023-07-02 00:00 ~ 2023-07-08 00:00) for this trip.\n3. The daily opening_hours of spots can be obtained from the database table place. \"opening_hours_begin\" and \"opening_hours_end\" are the opening and closing times respectively\n4. On the basis of completing the above conditions (especially the time limit), spend as little money as possible.\n",
        "demands": {
            "TravelSimulator": {
                "begin_time": "2023-07-02 00:00",
                "end_time": "2023-07-08 00:00",
                "origin_city": "Shanghai",
                "origin_place": "Shanghai Railway Hotel",
                "budget": 99999,
                "check_opening_hours": true,
                "check_meal": false,
                "set_budget": false,
                "type": 3,
                "limit": "time",
                "time_min": 237000,
                "time_max": 237000
            },
            "Constraints": {
                "SpotDurationConstraint": [
                    {
                        "spot": "Xintiandi",
                        "minutes": 120
                    },
                    {
                        "spot": "Century Park",
                        "minutes": 270
                    },
                    {
                        "spot": "Shanghai History Museum",
                        "minutes": 300
                    },
                    {
                        "spot": "Longhua Temple",
                        "minutes": 270
                    },
                    {
                        "spot": "Shanghai Sightseeing Tunnel",
                        "minutes": 210
                    }
                ]
            }
        },
        "type": 3
    },
    {
        "question": "Bob is going to visit some spots across cities, please make a visit plan for him, including inter-city transportation, intra-city transportation, and visit time for each spot.    The demands are as follows:\n1. He now lives in Beijing Railway Hotel in Beijing. Every time he takes a train to a city, he lives in f\"{city} Railway Hotel\", such as \"Beijing Railway Hotel\" In Wuhan, he needs to visit Tan Hua Lin for 150 minutes, East Lake for 180 minutes.In Hangzhou, he needs to visit Lingyin Temple for 180 minutes, China National Tea Museum for 150 minutes, Hefang Street for 210 minutes. And the order can be decided by you.\n2. 6 days (2023-07-04 00:00 ~ 2023-07-10 00:00) for this trip.\n3. The daily opening_hours of spots can be obtained from the database table place. \"opening_hours_begin\" and \"opening_hours_end\" are the opening and closing times respectively\n4. On the basis of completing the above conditions (especially the time limit), spend as little money as possible.\n",
        "demands": {
            "TravelSimulator": {
                "begin_time": "2023-07-04 00:00",
                "end_time": "2023-07-10 00:00",
                "origin_city": "Beijing",
                "origin_place": "Beijing Railway Hotel",
                "budget": 99999,
                "check_opening_hours": true,
                "check_meal": false,
                "set_budget": false,
                "type": 3,
                "limit": "time",
                "time_min": 116547,
                "time_max": 260767
            },
            "Constraints": {
                "SpotDurationConstraint": [
                    {
                        "spot": "Tan Hua Lin",
                        "minutes": 150
                    },
                    {
                        "spot": "East Lake",
                        "minutes": 180
                    },
                    {
                        "spot": "Lingyin Temple",
                        "minutes": 180
                    },
                    {
                        "spot": "China National Tea Museum",
                        "minutes": 150
                    },
                    {
                        "spot": "Hefang Street",
                        "minutes": 210
                    }
                ]
            }
        },
        "type": 3
    },
    {
        "question": "Bob is going to visit some spots across cities, please make a visit plan for him, including inter-city transportation, intra-city transportation, and visit time for each spot.    The demands are as follows:\n1. He now lives in Shanghai Railway Hotel in Shanghai. Every time he takes a train to a city, he lives in f\"{city} Railway Hotel\", such as \"Beijing Railway Hotel\" In Guangzhou, he needs to visit Canton Tower for 180 minutes, Chimelong Tourist Resort for 150 minutes. And the order can be decided by you.\n2. 6 days (2023-07-05 00:00 ~ 2023-07-11 00:00) for this trip.\n3. The daily opening_hours of spots can be obtained from the database table place. \"opening_hours_begin\" and \"opening_hours_end\" are the opening and closing times respectively\n4. On the basis of completing the above conditions (especially the time limit), spend as little money as possible.\n",
        "demands": {
            "TravelSimulator": {
                "begin_time": "2023-07-05 00:00",
                "end_time": "2023-07-11 00:00",
                "origin_city": "Shanghai",
                "origin_place": "Shanghai Railway Hotel",
                "budget": 99999,
                "check_opening_hours": true,
                "check_meal": false,
                "set_budget": false,
                "type": 3,
                "limit": "time",
                "time_min": 17008,
                "time_max": 116526
            },
            "Constraints": {
                "SpotDurationConstraint": [
                    {
                        "spot": "Canton Tower",
                        "minutes": 180
                    },
                    {
                        "spot": "Chimelong Tourist Resort",
                        "minutes": 150
                    }
                ]
            }
        },
        "type": 3
    },
    {
        "question": "Bob is going to visit some spots across cities, please make a visit plan for him, including inter-city transportation, intra-city transportation, and visit time for each spot.    The demands are as follows:\n1. He now lives in Nanjing Railway Hotel in Nanjing. Every time he takes a train to a city, he lives in f\"{city} Railway Hotel\", such as \"Beijing Railway Hotel\" In Shanghai, he needs to visit Century Park for 150 minutes, Longhua Temple for 210 minutes, Qibao Ancient Town for 210 minutes, Shanghai History Museum for 210 minutes, Huangpu River Cruise for 300 minutes, Xintiandi for 210 minutes, Shanghai Disney for 300 minutes, Shanghai Sightseeing Tunnel for 150 minutes. And the order can be decided by you.\n2. He is free to travel from 2023.7.1 to 2023.7.20. The budget for transportation is 1800.0 CNY.\n3. Ignore the opening hours of attractions, assuming they are open all day. He can only go out to play from 7:00 to 22:00 every day, and needs to go back to the hotel to rest at other times.\n4. On the basis of completing the above conditions (especially the budget), spend as little time as possible.\n",
        "demands": {
            "TravelSimulator": {
                "begin_time": "2023-07-01 07:00",
                "end_time": "2023-07-20 00:00",
                "origin_city": "Nanjing",
                "origin_place": "Nanjing Railway Hotel",
                "budget": 99999,
                "check_opening_hours": false,
                "check_meal": false,
                "set_budget": true,
                "type": 3,
                "limit": "money",
                "money_min": 0,
                "money_max": 282
            },
            "Constraints": {
                "SpotDurationConstraint": [
                    {
                        "spot": "Century Park",
                        "minutes": 150
                    },
                    {
                        "spot": "Longhua Temple",
                        "minutes": 210
                    },
                    {
                        "spot": "Qibao Ancient Town",
                        "minutes": 210
                    },
                    {
                        "spot": "Shanghai History Museum",
                        "minutes": 210
                    },
                    {
                        "spot": "Huangpu River Cruise",
                        "minutes": 300
                    },
                    {
                        "spot": "Xintiandi",
                        "minutes": 210
                    },
                    {
                        "spot": "Shanghai Disney",
                        "minutes": 300
                    },
                    {
                        "spot": "Shanghai Sightseeing Tunnel",
                        "minutes": 150
                    }
                ]
            }
        },
        "type": 3
    },
    {
        "question": "Bob is going to visit some spots across cities, please make a visit plan for him, including inter-city transportation, intra-city transportation, and visit time for each spot.    The demands are as follows:\n1. He now lives in Guangzhou Railway Hotel in Guangzhou. Every time he takes a train to a city, he lives in f\"{city} Railway Hotel\", such as \"Beijing Railway Hotel\" In Beijing, he needs to visit The Forbidden City for 240 minutes, The Great Wall for 180 minutes, The Summer Palace for 150 minutes, Beijing Olympic Park for 180 minutes, Shihua Cave for 120 minutes, Beijing Stone Carvings Art Museum for 270 minutes, Tiananmen Square for 210 minutes, The Temple of Heaven for 240 minutes. And the order can be decided by you.\n2. 7 days (2023-07-10 00:00 ~ 2023-07-17 00:00) for this trip.\n3. The daily opening_hours of spots can be obtained from the database table place. \"opening_hours_begin\" and \"opening_hours_end\" are the opening and closing times respectively\n4. On the basis of completing the above conditions (especially the time limit), spend as little money as possible.\n",
        "demands": {
            "TravelSimulator": {
                "begin_time": "2023-07-10 00:00",
                "end_time": "2023-07-17 00:00",
                "origin_city": "Guangzhou",
                "origin_place": "Guangzhou Railway Hotel",
                "budget": 99999,
                "check_opening_hours": true,
                "check_meal": false,
                "set_budget": false,
                "type": 3,
                "limit": "time",
                "time_min": 311318,
                "time_max": 367376
            },
            "Constraints": {
                "SpotDurationConstraint": [
                    {
                        "spot": "The Forbidden City",
                        "minutes": 240
                    },
                    {
                        "spot": "The Great Wall",
                        "minutes": 180
                    },
                    {
                        "spot": "The Summer Palace",
                        "minutes": 150
                    },
                    {
                        "spot": "Beijing Olympic Park",
                        "minutes": 180
                    },
                    {
                        "spot": "Shihua Cave",
                        "minutes": 120
                    },
                    {
                        "spot": "Beijing Stone Carvings Art Museum",
                        "minutes": 270
                    },
                    {
                        "spot": "Tiananmen Square",
                        "minutes": 210
                    },
                    {
                        "spot": "The Temple of Heaven",
                        "minutes": 240
                    }
                ]
            }
        },
        "type": 3
    },
    {
        "question": "Bob is going to visit some spots across cities, please make a visit plan for him, including inter-city transportation, intra-city transportation, and visit time for each spot.    The demands are as follows:\n1. He now lives in Nanjing Railway Hotel in Nanjing. Every time he takes a train to a city, he lives in f\"{city} Railway Hotel\", such as \"Beijing Railway Hotel\" In Nanjing, he needs to visit Bailuzhou Park for 150 minutes, Tomb of Ming Emperor Zhu Yuanzhang for 120 minutes, Taiping Heavenly-Kingdom Palace for 150 minutes, Ming Palace for 240 minutes, Lake Xuanwu for 210 minutes.In Wuhan, he needs to visit Tan Hua Lin for 120 minutes, East Lake for 120 minutes, Hubu Alley for 210 minutes. And the order can be decided by you.\n2. He is free to travel from 2023.7.1 to 2023.7.20. The budget for transportation is 1900.0 CNY.\n3. Ignore the opening hours of attractions, assuming they are open all day. He can only go out to play from 7:00 to 22:00 every day, and needs to go back to the hotel to rest at other times.\n4. On the basis of completing the above conditions (especially the budget), spend as little time as possible.\n",
        "demands": {
            "TravelSimulator": {
                "begin_time": "2023-07-01 07:00",
                "end_time": "2023-07-20 00:00",
                "origin_city": "Nanjing",
                "origin_place": "Nanjing Railway Hotel",
                "budget": 99999,
                "check_opening_hours": false,
                "check_meal": false,
                "set_budget": true,
                "type": 3,
                "limit": "money",
                "money_min": 398,
                "money_max": 403
            },
            "Constraints": {
                "SpotDurationConstraint": [
                    {
                        "spot": "Bailuzhou Park",
                        "minutes": 150
                    },
                    {
                        "spot": "Tomb of Ming Emperor Zhu Yuanzhang",
                        "minutes": 120
                    },
                    {
                        "spot": "Taiping Heavenly-Kingdom Palace",
                        "minutes": 150
                    },
                    {
                        "spot": "Ming Palace",
                        "minutes": 240
                    },
                    {
                        "spot": "Lake Xuanwu",
                        "minutes": 210
                    },
                    {
                        "spot": "Tan Hua Lin",
                        "minutes": 120
                    },
                    {
                        "spot": "East Lake",
                        "minutes": 120
                    },
                    {
                        "spot": "Hubu Alley",
                        "minutes": 210
                    }
                ]
            }
        },
        "type": 3
    },
    {
        "question": "Bob is going to visit some spots across cities, please make a visit plan for him, including inter-city transportation, intra-city transportation, and visit time for each spot.    The demands are as follows:\n1. He now lives in Hangzhou Railway Hotel in Hangzhou. Every time he takes a train to a city, he lives in f\"{city} Railway Hotel\", such as \"Beijing Railway Hotel\" In Hangzhou, he needs to visit West Lake for 150 minutes, China National Tea Museum for 300 minutes, Hefang Street for 300 minutes.In Beijing, he needs to visit Beijing Stone Carvings Art Museum for 240 minutes, Shihua Cave for 300 minutes, The Temple of Heaven for 240 minutes, Beijing Olympic Park for 210 minutes, The Summer Palace for 120 minutes, The Forbidden City for 180 minutes. And the order can be decided by you.\n2. He is free to travel from 2023.7.1 to 2023.7.20. The budget for transportation is 2400.0 CNY.\n3. Ignore the opening hours of attractions, assuming they are open all day. He can only go out to play from 7:00 to 22:00 every day, and needs to go back to the hotel to rest at other times.\n4. On the basis of completing the above conditions (especially the budget), spend as little time as possible.\n",
        "demands": {
            "TravelSimulator": {
                "begin_time": "2023-07-01 07:00",
                "end_time": "2023-07-20 00:00",
                "origin_city": "Hangzhou",
                "origin_place": "Hangzhou Railway Hotel",
                "budget": 99999,
                "check_opening_hours": false,
                "check_meal": false,
                "set_budget": true,
                "type": 3,
                "limit": "money",
                "money_min": 279,
                "money_max": 1670
            },
            "Constraints": {
                "SpotDurationConstraint": [
                    {
                        "spot": "West Lake",
                        "minutes": 150
                    },
                    {
                        "spot": "China National Tea Museum",
                        "minutes": 300
                    },
                    {
                        "spot": "Hefang Street",
                        "minutes": 300
                    },
                    {
                        "spot": "Beijing Stone Carvings Art Museum",
                        "minutes": 240
                    },
                    {
                        "spot": "Shihua Cave",
                        "minutes": 300
                    },
                    {
                        "spot": "The Temple of Heaven",
                        "minutes": 240
                    },
                    {
                        "spot": "Beijing Olympic Park",
                        "minutes": 210
                    },
                    {
                        "spot": "The Summer Palace",
                        "minutes": 120
                    },
                    {
                        "spot": "The Forbidden City",
                        "minutes": 180
                    }
                ]
            }
        },
        "type": 3
    },
    {
        "question": "Bob is going to visit some spots across cities, please make a visit plan for him, including inter-city transportation, intra-city transportation, and visit time for each spot.    The demands are as follows:\n1. He now lives in Shanghai Railway Hotel in Shanghai. Every time he takes a train to a city, he lives in f\"{city} Railway Hotel\", such as \"Beijing Railway Hotel\" In Beijing, he needs to visit Beijing Olympic Park for 240 minutes, Beijing Stone Carvings Art Museum for 180 minutes, The Summer Palace for 210 minutes, The Great Wall for 300 minutes, Shihua Cave for 300 minutes. And the order can be decided by you.\n2. He is free to travel from 2023.7.1 to 2023.7.20. The budget for transportation is 3000.0 CNY.\n3. Ignore the opening hours of attractions, assuming they are open all day. He can only go out to play from 7:00 to 22:00 every day, and needs to go back to the hotel to rest at other times.\n4. On the basis of completing the above conditions (especially the budget), spend as little time as possible.\n",
        "demands": {
            "TravelSimulator": {
                "begin_time": "2023-07-01 07:00",
                "end_time": "2023-07-20 00:00",
                "origin_city": "Shanghai",
                "origin_place": "Shanghai Railway Hotel",
                "budget": 99999,
                "check_opening_hours": false,
                "check_meal": false,
                "set_budget": true,
                "type": 3,
                "limit": "money",
                "money_min": 708,
                "money_max": 1623
            },
            "Constraints": {
                "SpotDurationConstraint": [
                    {
                        "spot": "Beijing Olympic Park",
                        "minutes": 240
                    },
                    {
                        "spot": "Beijing Stone Carvings Art Museum",
                        "minutes": 180
                    },
                    {
                        "spot": "The Summer Palace",
                        "minutes": 210
                    },
                    {
                        "spot": "The Great Wall",
                        "minutes": 300
                    },
                    {
                        "spot": "Shihua Cave",
                        "minutes": 300
                    }
                ]
            }
        },
        "type": 3
    },
    {
        "question": "Bob is going to visit some spots across cities, please make a visit plan for him, including inter-city transportation, intra-city transportation, and visit time for each spot.    The demands are as follows:\n1. He now lives in Guangzhou Railway Hotel in Guangzhou. Every time he takes a train to a city, he lives in f\"{city} Railway Hotel\", such as \"Beijing Railway Hotel\" In Wuhan, he needs to visit Yellow Crane Tower for 240 minutes, Hubu Alley for 240 minutes, Han Show for 120 minutes.In Shanghai, he needs to visit Xintiandi for 150 minutes, Longhua Temple for 210 minutes, Qibao Ancient Town for 300 minutes. And the order can be decided by you.\n2. He is free to travel from 2023.7.1 to 2023.7.20. The budget for transportation is 2800.0 CNY.\n3. Ignore the opening hours of attractions, assuming they are open all day. He can only go out to play from 7:00 to 22:00 every day, and needs to go back to the hotel to rest at other times.\n4. On the basis of completing the above conditions (especially the budget), spend as little time as possible.\n",
        "demands": {
            "TravelSimulator": {
                "begin_time": "2023-07-01 07:00",
                "end_time": "2023-07-20 00:00",
                "origin_city": "Guangzhou",
                "origin_place": "Guangzhou Railway Hotel",
                "budget": 99999,
                "check_opening_hours": false,
                "check_meal": false,
                "set_budget": true,
                "type": 3,
                "limit": "money",
                "money_min": 617,
                "money_max": 2216
            },
            "Constraints": {
                "SpotDurationConstraint": [
                    {
                        "spot": "Yellow Crane Tower",
                        "minutes": 240
                    },
                    {
                        "spot": "Hubu Alley",
                        "minutes": 240
                    },
                    {
                        "spot": "Han Show",
                        "minutes": 120
                    },
                    {
                        "spot": "Xintiandi",
                        "minutes": 150
                    },
                    {
                        "spot": "Longhua Temple",
                        "minutes": 210
                    },
                    {
                        "spot": "Qibao Ancient Town",
                        "minutes": 300
                    }
                ]
            }
        },
        "type": 3
    },
    {
        "question": "Bob is going to visit some spots across cities, please make a visit plan for him, including inter-city transportation, intra-city transportation, and visit time for each spot.    The demands are as follows:\n1. He now lives in Beijing Railway Hotel in Beijing. Every time he takes a train to a city, he lives in f\"{city} Railway Hotel\", such as \"Beijing Railway Hotel\" In Beijing, he needs to visit The Forbidden City for 150 minutes, Beijing Stone Carvings Art Museum for 180 minutes, The Summer Palace for 210 minutes, Beijing Olympic Park for 240 minutes, The Temple of Heaven for 210 minutes, Shihua Cave for 150 minutes, The Great Wall for 150 minutes. And the order can be decided by you.\n2. He is free to travel from 2023.7.1 to 2023.7.20. The budget for transportation is 2100 CNY.\n3. The daily opening_hours of spots can be obtained from the database table place. \"opening_hours_begin\" and \"opening_hours_end\" are the opening and closing times respectively\n4. On the basis of completing the above conditions (especially the budget), spend as little time as possible.\n",
        "demands": {
            "TravelSimulator": {
                "begin_time": "2023-07-01 07:00",
                "end_time": "2023-07-20 00:00",
                "origin_city": "Beijing",
                "origin_place": "Beijing Railway Hotel",
                "budget": 99999,
                "check_opening_hours": true,
                "check_meal": false,
                "set_budget": true,
                "type": 3,
                "limit": "money",
                "money_min": 0,
                "money_max": 0
            },
            "Constraints": {
                "SpotDurationConstraint": [
                    {
                        "spot": "The Forbidden City",
                        "minutes": 150
                    },
                    {
                        "spot": "Beijing Stone Carvings Art Museum",
                        "minutes": 180
                    },
                    {
                        "spot": "The Summer Palace",
                        "minutes": 210
                    },
                    {
                        "spot": "Beijing Olympic Park",
                        "minutes": 240
                    },
                    {
                        "spot": "The Temple of Heaven",
                        "minutes": 210
                    },
                    {
                        "spot": "Shihua Cave",
                        "minutes": 150
                    },
                    {
                        "spot": "The Great Wall",
                        "minutes": 150
                    }
                ]
            }
        },
        "type": 3
    },
    {
        "question": "Bob is going to visit some spots across cities, please make a visit plan for him, including inter-city transportation, intra-city transportation, and visit time for each spot.    The demands are as follows:\n1. He now lives in Shanghai Railway Hotel in Shanghai. Every time he takes a train to a city, he lives in f\"{city} Railway Hotel\", such as \"Beijing Railway Hotel\" In Shanghai, he needs to visit Shanghai Disney for 120 minutes, Shanghai History Museum for 270 minutes. And the order can be decided by you.\n2. He is free to travel from 2023.7.1 to 2023.7.20. The budget for transportation is 1900 CNY.\n3. The daily opening_hours of spots can be obtained from the database table place. \"opening_hours_begin\" and \"opening_hours_end\" are the opening and closing times respectively\n4. On the basis of completing the above conditions (especially the budget), spend as little time as possible.\n",
        "demands": {
            "TravelSimulator": {
                "begin_time": "2023-07-01 07:00",
                "end_time": "2023-07-20 00:00",
                "origin_city": "Shanghai",
                "origin_place": "Shanghai Railway Hotel",
                "budget": 99999,
                "check_opening_hours": true,
                "check_meal": false,
                "set_budget": true,
                "type": 3,
                "limit": "money",
                "money_min": 0,
                "money_max": 0
            },
            "Constraints": {
                "SpotDurationConstraint": [
                    {
                        "spot": "Shanghai Disney",
                        "minutes": 120
                    },
                    {
                        "spot": "Shanghai History Museum",
                        "minutes": 270
                    }
                ]
            }
        },
        "type": 3
    },
    {
        "question": "Bob is going to visit some spots across cities, please make a visit plan for him, including inter-city transportation, intra-city transportation, and visit time for each spot.    The demands are as follows:\n1. He now lives in Beijing Railway Hotel in Beijing. Every time he takes a train to a city, he lives in f\"{city} Railway Hotel\", such as \"Beijing Railway Hotel\" In Guangzhou, he needs to visit Huacheng Square for 150 minutes, Canton Tower for 180 minutes, Chimelong Tourist Resort for 300 minutes, Yuexiu Park for 180 minutes.In Nanjing, he needs to visit Lake Xuanwu for 240 minutes, Taiping Heavenly-Kingdom Palace for 300 minutes. And the order can be decided by you.\n2. He is free to travel from 2023.7.1 to 2023.7.20. The budget for transportation is 3600.0 CNY.\n3. The daily opening_hours of spots can be obtained from the database table place. \"opening_hours_begin\" and \"opening_hours_end\" are the opening and closing times respectively\n4. On the basis of completing the above conditions (especially the budget), spend as little time as possible.\n",
        "demands": {
            "TravelSimulator": {
                "begin_time": "2023-07-01 07:00",
                "end_time": "2023-07-20 00:00",
                "origin_city": "Beijing",
                "origin_place": "Beijing Railway Hotel",
                "budget": 99999,
                "check_opening_hours": true,
                "check_meal": false,
                "set_budget": true,
                "type": 3,
                "limit": "money",
                "money_min": 0,
                "money_max": 2409
            },
            "Constraints": {
                "SpotDurationConstraint": [
                    {
                        "spot": "Huacheng Square",
                        "minutes": 150
                    },
                    {
                        "spot": "Canton Tower",
                        "minutes": 180
                    },
                    {
                        "spot": "Chimelong Tourist Resort",
                        "minutes": 300
                    },
                    {
                        "spot": "Yuexiu Park",
                        "minutes": 180
                    },
                    {
                        "spot": "Lake Xuanwu",
                        "minutes": 240
                    },
                    {
                        "spot": "Taiping Heavenly-Kingdom Palace",
                        "minutes": 300
                    }
                ]
            }
        },
        "type": 3
    },
    {
        "question": "Bob is going to visit some spots across cities, please make a visit plan for him, including inter-city transportation, intra-city transportation, and visit time for each spot.    The demands are as follows:\n1. He now lives in Chengdu Railway Hotel in Chengdu. Every time he takes a train to a city, he lives in f\"{city} Railway Hotel\", such as \"Beijing Railway Hotel\" In Shanghai, he needs to visit Longhua Temple for 120 minutes, Shanghai History Museum for 210 minutes, Qibao Ancient Town for 300 minutes, Shanghai Sightseeing Tunnel for 120 minutes.In Beijing, he needs to visit Tiananmen Square for 270 minutes, The Forbidden City for 150 minutes. And the order can be decided by you.\n2. He is free to travel from 2023.7.1 to 2023.7.20. The budget for transportation is 4000.0 CNY.\n3. The daily opening_hours of spots can be obtained from the database table place. \"opening_hours_begin\" and \"opening_hours_end\" are the opening and closing times respectively\n4. On the basis of completing the above conditions (especially the budget), spend as little time as possible.\n",
        "demands": {
            "TravelSimulator": {
                "begin_time": "2023-07-01 07:00",
                "end_time": "2023-07-20 00:00",
                "origin_city": "Chengdu",
                "origin_place": "Chengdu Railway Hotel",
                "budget": 99999,
                "check_opening_hours": true,
                "check_meal": false,
                "set_budget": true,
                "type": 3,
                "limit": "money",
                "money_min": 1635,
                "money_max": 2821
            },
            "Constraints": {
                "SpotDurationConstraint": [
                    {
                        "spot": "Longhua Temple",
                        "minutes": 120
                    },
                    {
                        "spot": "Shanghai History Museum",
                        "minutes": 210
                    },
                    {
                        "spot": "Qibao Ancient Town",
                        "minutes": 300
                    },
                    {
                        "spot": "Shanghai Sightseeing Tunnel",
                        "minutes": 120
                    },
                    {
                        "spot": "Tiananmen Square",
                        "minutes": 270
                    },
                    {
                        "spot": "The Forbidden City",
                        "minutes": 150
                    }
                ]
            }
        },
        "type": 3
    },
    {
        "question": "Bob is going to visit some spots across cities, please make a visit plan for him, including inter-city transportation, intra-city transportation, and visit time for each spot.    The demands are as follows:\n1. He now lives in Guangzhou Railway Hotel in Guangzhou. Every time he takes a train to a city, he lives in f\"{city} Railway Hotel\", such as \"Beijing Railway Hotel\" In Guangzhou, he needs to visit Canton Tower for 300 minutes, Yuexiu Park for 120 minutes, Chimelong Tourist Resort for 120 minutes.In Shanghai, he needs to visit Longhua Temple for 120 minutes, Qibao Ancient Town for 270 minutes, Xintiandi for 240 minutes, Huangpu River Cruise for 270 minutes, Shanghai Sightseeing Tunnel for 300 minutes, Shanghai History Museum for 210 minutes. And the order can be decided by you.\n2. 7 days (2023-07-09 00:00 ~ 2023-07-16 00:00) for this trip.\n3. Ignore the opening hours of attractions, assuming they are open all day. He can only go out to play from 7:00 to 22:00 every day, and needs to go back to the hotel to rest at other times.\n4. On the basis of completing the above conditions (especially the time limit), spend as little money as possible.\n",
        "demands": {
            "TravelSimulator": {
                "begin_time": "2023-07-09 00:00",
                "end_time": "2023-07-16 00:00",
                "origin_city": "Guangzhou",
                "origin_place": "Guangzhou Railway Hotel",
                "budget": 99999,
                "check_opening_hours": false,
                "check_meal": false,
                "set_budget": false,
                "type": 3,
                "limit": "time",
                "time_min": 320538,
                "time_max": 492110
            },
            "Constraints": {
                "SpotDurationConstraint": [
                    {
                        "spot": "Canton Tower",
                        "minutes": 300
                    },
                    {
                        "spot": "Yuexiu Park",
                        "minutes": 120
                    },
                    {
                        "spot": "Chimelong Tourist Resort",
                        "minutes": 120
                    },
                    {
                        "spot": "Longhua Temple",
                        "minutes": 120
                    },
                    {
                        "spot": "Qibao Ancient Town",
                        "minutes": 270
                    },
                    {
                        "spot": "Xintiandi",
                        "minutes": 240
                    },
                    {
                        "spot": "Huangpu River Cruise",
                        "minutes": 270
                    },
                    {
                        "spot": "Shanghai Sightseeing Tunnel",
                        "minutes": 300
                    },
                    {
                        "spot": "Shanghai History Museum",
                        "minutes": 210
                    }
                ]
            }
        },
        "type": 3
    },
    {
        "question": "Bob is going to visit some spots across cities, please make a visit plan for him, including inter-city transportation, intra-city transportation, and visit time for each spot.    The demands are as follows:\n1. He now lives in Beijing Railway Hotel in Beijing. Every time he takes a train to a city, he lives in f\"{city} Railway Hotel\", such as \"Beijing Railway Hotel\" In Beijing, he needs to visit The Forbidden City for 300 minutes, Shihua Cave for 240 minutes, Beijing Olympic Park for 150 minutes, The Great Wall for 180 minutes, The Temple of Heaven for 180 minutes, Beijing Stone Carvings Art Museum for 120 minutes, Tiananmen Square for 150 minutes.In Chengdu, he needs to visit The Chengdu Wuhou Shrine for 240 minutes, Leshan Giant Buddha for 180 minutes, Du Fu Thatched Cottage for 300 minutes. And the order can be decided by you.\n2. 7 days (2023-07-11 00:00 ~ 2023-07-18 00:00) for this trip.\n3. Ignore the opening hours of attractions, assuming they are open all day. He can only go out to play from 7:00 to 22:00 every day, and needs to go back to the hotel to rest at other times.\n4. On the basis of completing the above conditions (especially the time limit), spend as little money as possible.\n",
        "demands": {
            "TravelSimulator": {
                "begin_time": "2023-07-11 00:00",
                "end_time": "2023-07-18 00:00",
                "origin_city": "Beijing",
                "origin_place": "Beijing Railway Hotel",
                "budget": 99999,
                "check_opening_hours": false,
                "check_meal": false,
                "set_budget": false,
                "type": 3,
                "limit": "time",
                "time_min": 390777,
                "time_max": 495740
            },
            "Constraints": {
                "SpotDurationConstraint": [
                    {
                        "spot": "The Forbidden City",
                        "minutes": 300
                    },
                    {
                        "spot": "Shihua Cave",
                        "minutes": 240
                    },
                    {
                        "spot": "Beijing Olympic Park",
                        "minutes": 150
                    },
                    {
                        "spot": "The Great Wall",
                        "minutes": 180
                    },
                    {
                        "spot": "The Temple of Heaven",
                        "minutes": 180
                    },
                    {
                        "spot": "Beijing Stone Carvings Art Museum",
                        "minutes": 120
                    },
                    {
                        "spot": "Tiananmen Square",
                        "minutes": 150
                    },
                    {
                        "spot": "The Chengdu Wuhou Shrine",
                        "minutes": 240
                    },
                    {
                        "spot": "Leshan Giant Buddha",
                        "minutes": 180
                    },
                    {
                        "spot": "Du Fu Thatched Cottage",
                        "minutes": 300
                    }
                ]
            }
        },
        "type": 3
    },
    {
        "question": "Bob is going to visit some spots across cities, please make a visit plan for him, including inter-city transportation, intra-city transportation, and visit time for each spot.    The demands are as follows:\n1. He now lives in Nanjing Railway Hotel in Nanjing. Every time he takes a train to a city, he lives in f\"{city} Railway Hotel\", such as \"Beijing Railway Hotel\" In Hangzhou, he needs to visit Lingyin Temple for 120 minutes, China National Tea Museum for 300 minutes.In Wuhan, he needs to visit Yellow Crane Tower for 120 minutes, East Lake for 210 minutes, Hubu Alley for 180 minutes, Baotong Temple for 120 minutes. And the order can be decided by you.\n2. 7 days (2023-07-11 00:00 ~ 2023-07-18 00:00) for this trip.\n3. Ignore the opening hours of attractions, assuming they are open all day. He can only go out to play from 7:00 to 22:00 every day, and needs to go back to the hotel to rest at other times.\n4. On the basis of completing the above conditions (especially the time limit), spend as little money as possible.\n",
        "demands": {
            "TravelSimulator": {
                "begin_time": "2023-07-11 00:00",
                "end_time": "2023-07-18 00:00",
                "origin_city": "Nanjing",
                "origin_place": "Nanjing Railway Hotel",
                "budget": 99999,
                "check_opening_hours": false,
                "check_meal": false,
                "set_budget": false,
                "type": 3,
                "limit": "time",
                "time_min": 131418,
                "time_max": 296657
            },
            "Constraints": {
                "SpotDurationConstraint": [
                    {
                        "spot": "Lingyin Temple",
                        "minutes": 120
                    },
                    {
                        "spot": "China National Tea Museum",
                        "minutes": 300
                    },
                    {
                        "spot": "Yellow Crane Tower",
                        "minutes": 120
                    },
                    {
                        "spot": "East Lake",
                        "minutes": 210
                    },
                    {
                        "spot": "Hubu Alley",
                        "minutes": 180
                    },
                    {
                        "spot": "Baotong Temple",
                        "minutes": 120
                    }
                ]
            }
        },
        "type": 3
    },
    {
        "question": "Bob is going to visit some spots across cities, please make a visit plan for him, including inter-city transportation, intra-city transportation, and visit time for each spot.    The demands are as follows:\n1. He now lives in Shanghai Railway Hotel in Shanghai. Every time he takes a train to a city, he lives in f\"{city} Railway Hotel\", such as \"Beijing Railway Hotel\" In Chengdu, he needs to visit Chengdu Tea Houses for 150 minutes, The Chengdu Wuhou Shrine for 180 minutes, Chengdu Panda Base for 180 minutes.In Hangzhou, he needs to visit Hefang Street for 240 minutes, West Lake for 150 minutes, Quaint Water Towns for 120 minutes. And the order can be decided by you.\n2. 7 days (2023-07-05 00:00 ~ 2023-07-12 00:00) for this trip.\n3. Ignore the opening hours of attractions, assuming they are open all day. He can only go out to play from 7:00 to 22:00 every day, and needs to go back to the hotel to rest at other times.\n4. On the basis of completing the above conditions (especially the time limit), spend as little money as possible.\n",
        "demands": {
            "TravelSimulator": {
                "begin_time": "2023-07-05 00:00",
                "end_time": "2023-07-12 00:00",
                "origin_city": "Shanghai",
                "origin_place": "Shanghai Railway Hotel",
                "budget": 99999,
                "check_opening_hours": false,
                "check_meal": false,
                "set_budget": false,
                "type": 3,
                "limit": "time",
                "time_min": 133385,
                "time_max": 280167
            },
            "Constraints": {
                "SpotDurationConstraint": [
                    {
                        "spot": "Chengdu Tea Houses",
                        "minutes": 150
                    },
                    {
                        "spot": "The Chengdu Wuhou Shrine",
                        "minutes": 180
                    },
                    {
                        "spot": "Chengdu Panda Base",
                        "minutes": 180
                    },
                    {
                        "spot": "Hefang Street",
                        "minutes": 240
                    },
                    {
                        "spot": "West Lake",
                        "minutes": 150
                    },
                    {
                        "spot": "Quaint Water Towns",
                        "minutes": 120
                    }
                ]
            }
        },
        "type": 3
    },
    {
        "question": "Bob is going to visit some spots across cities, please make a visit plan for him, including inter-city transportation, intra-city transportation, and visit time for each spot.    The demands are as follows:\n1. He now lives in Hangzhou Railway Hotel in Hangzhou. Every time he takes a train to a city, he lives in f\"{city} Railway Hotel\", such as \"Beijing Railway Hotel\" In Hangzhou, he needs to visit West Lake for 240 minutes, Hefang Street for 270 minutes.In Beijing, he needs to visit Beijing Olympic Park for 270 minutes, The Forbidden City for 270 minutes, The Great Wall for 270 minutes, Beijing Stone Carvings Art Museum for 210 minutes, Shihua Cave for 150 minutes, The Summer Palace for 270 minutes. And the order can be decided by you.\n2. 7 days (2023-07-03 00:00 ~ 2023-07-10 00:00) for this trip.\n3. The daily opening_hours of spots can be obtained from the database table place. \"opening_hours_begin\" and \"opening_hours_end\" are the opening and closing times respectively\n4. On the basis of completing the above conditions (especially the time limit), spend as little money as possible.\n",
        "demands": {
            "TravelSimulator": {
                "begin_time": "2023-07-03 00:00",
                "end_time": "2023-07-10 00:00",
                "origin_city": "Hangzhou",
                "origin_place": "Hangzhou Railway Hotel",
                "budget": 99999,
                "check_opening_hours": true,
                "check_meal": false,
                "set_budget": false,
                "type": 3,
                "limit": "time",
                "time_min": 323899,
                "time_max": 502067
            },
            "Constraints": {
                "SpotDurationConstraint": [
                    {
                        "spot": "West Lake",
                        "minutes": 240
                    },
                    {
                        "spot": "Hefang Street",
                        "minutes": 270
                    },
                    {
                        "spot": "Beijing Olympic Park",
                        "minutes": 270
                    },
                    {
                        "spot": "The Forbidden City",
                        "minutes": 270
                    },
                    {
                        "spot": "The Great Wall",
                        "minutes": 270
                    },
                    {
                        "spot": "Beijing Stone Carvings Art Museum",
                        "minutes": 210
                    },
                    {
                        "spot": "Shihua Cave",
                        "minutes": 150
                    },
                    {
                        "spot": "The Summer Palace",
                        "minutes": 270
                    }
                ]
            }
        },
        "type": 3
    },
    {
        "question": "Bob is going to visit some spots across cities, please make a visit plan for him, including inter-city transportation, intra-city transportation, and visit time for each spot.    The demands are as follows:\n1. He now lives in Nanjing Railway Hotel in Nanjing. Every time he takes a train to a city, he lives in f\"{city} Railway Hotel\", such as \"Beijing Railway Hotel\" In Nanjing, he needs to visit Qinhuai River for 120 minutes, Ming Palace for 150 minutes, Taiping Heavenly-Kingdom Palace for 150 minutes, Tomb of Ming Emperor Zhu Yuanzhang for 210 minutes, Lake Xuanwu for 300 minutes.In Chengdu, he needs to visit The Chengdu Wuhou Shrine for 180 minutes, Leshan Giant Buddha for 300 minutes, Du Fu Thatched Cottage for 150 minutes. And the order can be decided by you.\n2. 7 days (2023-07-06 00:00 ~ 2023-07-13 00:00) for this trip.\n3. The daily opening_hours of spots can be obtained from the database table place. \"opening_hours_begin\" and \"opening_hours_end\" are the opening and closing times respectively\n4. On the basis of completing the above conditions (especially the time limit), spend as little money as possible.\n",
        "demands": {
            "TravelSimulator": {
                "begin_time": "2023-07-06 00:00",
                "end_time": "2023-07-13 00:00",
                "origin_city": "Nanjing",
                "origin_place": "Nanjing Railway Hotel",
                "budget": 99999,
                "check_opening_hours": true,
                "check_meal": false,
                "set_budget": false,
                "type": 3,
                "limit": "time",
                "time_min": 311138,
                "time_max": 399649
            },
            "Constraints": {
                "SpotDurationConstraint": [
                    {
                        "spot": "Qinhuai River",
                        "minutes": 120
                    },
                    {
                        "spot": "Ming Palace",
                        "minutes": 150
                    },
                    {
                        "spot": "Taiping Heavenly-Kingdom Palace",
                        "minutes": 150
                    },
                    {
                        "spot": "Tomb of Ming Emperor Zhu Yuanzhang",
                        "minutes": 210
                    },
                    {
                        "spot": "Lake Xuanwu",
                        "minutes": 300
                    },
                    {
                        "spot": "The Chengdu Wuhou Shrine",
                        "minutes": 180
                    },
                    {
                        "spot": "Leshan Giant Buddha",
                        "minutes": 300
                    },
                    {
                        "spot": "Du Fu Thatched Cottage",
                        "minutes": 150
                    }
                ]
            }
        },
        "type": 3
    },
    {
        "question": "Bob is going to visit some spots across cities, please make a visit plan for him, including inter-city transportation, intra-city transportation, and visit time for each spot.    The demands are as follows:\n1. He now lives in Wuhan Railway Hotel in Wuhan. Every time he takes a train to a city, he lives in f\"{city} Railway Hotel\", such as \"Beijing Railway Hotel\" In Nanjing, he needs to visit Qinhuai River for 120 minutes, Lake Xuanwu for 240 minutes, Bailuzhou Park for 120 minutes.In Chengdu, he needs to visit The Chengdu Wuhou Shrine for 270 minutes, Leshan Giant Buddha for 240 minutes, Du Fu Thatched Cottage for 150 minutes. And the order can be decided by you.\n2. 7 days (2023-07-11 00:00 ~ 2023-07-18 00:00) for this trip.\n3. The daily opening_hours of spots can be obtained from the database table place. \"opening_hours_begin\" and \"opening_hours_end\" are the opening and closing times respectively\n4. On the basis of completing the above conditions (especially the time limit), spend as little money as possible.\n",
        "demands": {
            "TravelSimulator": {
                "begin_time": "2023-07-11 00:00",
                "end_time": "2023-07-18 00:00",
                "origin_city": "Wuhan",
                "origin_place": "Wuhan Railway Hotel",
                "budget": 99999,
                "check_opening_hours": true,
                "check_meal": false,
                "set_budget": false,
                "type": 3,
                "limit": "time",
                "time_min": 171550,
                "time_max": 301335
            },
            "Constraints": {
                "SpotDurationConstraint": [
                    {
                        "spot": "Qinhuai River",
                        "minutes": 120
                    },
                    {
                        "spot": "Lake Xuanwu",
                        "minutes": 240
                    },
                    {
                        "spot": "Bailuzhou Park",
                        "minutes": 120
                    },
                    {
                        "spot": "The Chengdu Wuhou Shrine",
                        "minutes": 270
                    },
                    {
                        "spot": "Leshan Giant Buddha",
                        "minutes": 240
                    },
                    {
                        "spot": "Du Fu Thatched Cottage",
                        "minutes": 150
                    }
                ]
            }
        },
        "type": 3
    },
    {
        "question": "Bob is going to visit some spots across cities, please make a visit plan for him, including inter-city transportation, intra-city transportation, and visit time for each spot.    The demands are as follows:\n1. He now lives in Beijing Railway Hotel in Beijing. Every time he takes a train to a city, he lives in f\"{city} Railway Hotel\", such as \"Beijing Railway Hotel\" In Shanghai, he needs to visit Shanghai Disney for 240 minutes, Century Park for 240 minutes, Shanghai Sightseeing Tunnel for 270 minutes.In Wuhan, he needs to visit Yellow Crane Tower for 270 minutes, East Lake for 240 minutes, Han Show for 270 minutes, Tan Hua Lin for 240 minutes. And the order can be decided by you.\n2. 7 days (2023-07-05 00:00 ~ 2023-07-12 00:00) for this trip.\n3. The daily opening_hours of spots can be obtained from the database table place. \"opening_hours_begin\" and \"opening_hours_end\" are the opening and closing times respectively\n4. On the basis of completing the above conditions (especially the time limit), spend as little money as possible.\n",
        "demands": {
            "TravelSimulator": {
                "begin_time": "2023-07-05 00:00",
                "end_time": "2023-07-12 00:00",
                "origin_city": "Beijing",
                "origin_place": "Beijing Railway Hotel",
                "budget": 99999,
                "check_opening_hours": true,
                "check_meal": false,
                "set_budget": false,
                "type": 3,
                "limit": "time",
                "time_min": 220766,
                "time_max": 449479
            },
            "Constraints": {
                "SpotDurationConstraint": [
                    {
                        "spot": "Shanghai Disney",
                        "minutes": 240
                    },
                    {
                        "spot": "Century Park",
                        "minutes": 240
                    },
                    {
                        "spot": "Shanghai Sightseeing Tunnel",
                        "minutes": 270
                    },
                    {
                        "spot": "Yellow Crane Tower",
                        "minutes": 270
                    },
                    {
                        "spot": "East Lake",
                        "minutes": 240
                    },
                    {
                        "spot": "Han Show",
                        "minutes": 270
                    },
                    {
                        "spot": "Tan Hua Lin",
                        "minutes": 240
                    }
                ]
            }
        },
        "type": 3
    },
    {
        "question": "Bob is going to visit some spots across cities, please make a visit plan for him, including inter-city transportation, intra-city transportation, and visit time for each spot.    The demands are as follows:\n1. He now lives in Beijing Railway Hotel in Beijing. Every time he takes a train to a city, he lives in f\"{city} Railway Hotel\", such as \"Beijing Railway Hotel\" In Guangzhou, he needs to visit Chimelong Tourist Resort for 180 minutes, Baiyun Mountain for 180 minutes, Canton Tower for 180 minutes, Huacheng Square for 270 minutes, Yuexiu Park for 120 minutes. And the order can be decided by you.\n2. He is free to travel from 2023.7.1 to 2023.7.20. The budget for transportation is 2500.0 CNY.\n3. Ignore the opening hours of attractions, assuming they are open all day. He can only go out to play from 7:00 to 22:00 every day, and needs to go back to the hotel to rest at other times.\n4. On the basis of completing the above conditions (especially the budget), spend as little time as possible.\n",
        "demands": {
            "TravelSimulator": {
                "begin_time": "2023-07-01 07:00",
                "end_time": "2023-07-20 00:00",
                "origin_city": "Beijing",
                "origin_place": "Beijing Railway Hotel",
                "budget": 99999,
                "check_opening_hours": false,
                "check_meal": false,
                "set_budget": true,
                "type": 3,
                "limit": "money",
                "money_min": 0,
                "money_max": 2945
            },
            "Constraints": {
                "SpotDurationConstraint": [
                    {
                        "spot": "Chimelong Tourist Resort",
                        "minutes": 180
                    },
                    {
                        "spot": "Baiyun Mountain",
                        "minutes": 180
                    },
                    {
                        "spot": "Canton Tower",
                        "minutes": 180
                    },
                    {
                        "spot": "Huacheng Square",
                        "minutes": 270
                    },
                    {
                        "spot": "Yuexiu Park",
                        "minutes": 120
                    }
                ]
            }
        },
        "type": 3
    },
    {
        "question": "Bob is going to visit some spots across cities, please make a visit plan for him, including inter-city transportation, intra-city transportation, and visit time for each spot.    The demands are as follows:\n1. He now lives in Nanjing Railway Hotel in Nanjing. Every time he takes a train to a city, he lives in f\"{city} Railway Hotel\", such as \"Beijing Railway Hotel\" In Beijing, he needs to visit The Forbidden City for 270 minutes, The Temple of Heaven for 180 minutes, The Great Wall for 240 minutes, Shihua Cave for 210 minutes, Beijing Stone Carvings Art Museum for 270 minutes. And the order can be decided by you.\n2. He is free to travel from 2023.7.1 to 2023.7.20. The budget for transportation is 1900.0 CNY.\n3. Ignore the opening hours of attractions, assuming they are open all day. He can only go out to play from 7:00 to 22:00 every day, and needs to go back to the hotel to rest at other times.\n4. On the basis of completing the above conditions (especially the budget), spend as little time as possible.\n",
        "demands": {
            "TravelSimulator": {
                "begin_time": "2023-07-01 07:00",
                "end_time": "2023-07-20 00:00",
                "origin_city": "Nanjing",
                "origin_place": "Nanjing Railway Hotel",
                "budget": 99999,
                "check_opening_hours": false,
                "check_meal": false,
                "set_budget": true,
                "type": 3,
                "limit": "money",
                "money_min": 368,
                "money_max": 1359
            },
            "Constraints": {
                "SpotDurationConstraint": [
                    {
                        "spot": "The Forbidden City",
                        "minutes": 270
                    },
                    {
                        "spot": "The Temple of Heaven",
                        "minutes": 180
                    },
                    {
                        "spot": "The Great Wall",
                        "minutes": 240
                    },
                    {
                        "spot": "Shihua Cave",
                        "minutes": 210
                    },
                    {
                        "spot": "Beijing Stone Carvings Art Museum",
                        "minutes": 270
                    }
                ]
            }
        },
        "type": 3
    },
    {
        "question": "Bob is going to visit some spots across cities, please make a visit plan for him, including inter-city transportation, intra-city transportation, and visit time for each spot.    The demands are as follows:\n1. He now lives in Guangzhou Railway Hotel in Guangzhou. Every time he takes a train to a city, he lives in f\"{city} Railway Hotel\", such as \"Beijing Railway Hotel\" In Nanjing, he needs to visit Tomb of Ming Emperor Zhu Yuanzhang for 240 minutes, Ming Palace for 300 minutes, Taiping Heavenly-Kingdom Palace for 240 minutes, Qinhuai River for 180 minutes. And the order can be decided by you.\n2. He is free to travel from 2023.7.1 to 2023.7.20. The budget for transportation is 2300.0 CNY.\n3. The daily opening_hours of spots can be obtained from the database table place. \"opening_hours_begin\" and \"opening_hours_end\" are the opening and closing times respectively\n4. On the basis of completing the above conditions (especially the budget), spend as little time as possible.\n",
        "demands": {
            "TravelSimulator": {
                "begin_time": "2023-07-01 07:00",
                "end_time": "2023-07-20 00:00",
                "origin_city": "Guangzhou",
                "origin_place": "Guangzhou Railway Hotel",
                "budget": 99999,
                "check_opening_hours": true,
                "check_meal": false,
                "set_budget": true,
                "type": 3,
                "limit": "money",
                "money_min": 0,
                "money_max": 1938
            },
            "Constraints": {
                "SpotDurationConstraint": [
                    {
                        "spot": "Tomb of Ming Emperor Zhu Yuanzhang",
                        "minutes": 240
                    },
                    {
                        "spot": "Ming Palace",
                        "minutes": 300
                    },
                    {
                        "spot": "Taiping Heavenly-Kingdom Palace",
                        "minutes": 240
                    },
                    {
                        "spot": "Qinhuai River",
                        "minutes": 180
                    }
                ]
            }
        },
        "type": 3
    },
    {
        "question": "Bob is going to visit some spots across cities, please make a visit plan for him, including inter-city transportation, intra-city transportation, and visit time for each spot.    The demands are as follows:\n1. He now lives in Chengdu Railway Hotel in Chengdu. Every time he takes a train to a city, he lives in f\"{city} Railway Hotel\", such as \"Beijing Railway Hotel\" In Wuhan, he needs to visit Hubu Alley for 120 minutes, Baotong Temple for 240 minutes, Han Show for 300 minutes, East Lake for 270 minutes, Tan Hua Lin for 150 minutes. And the order can be decided by you.\n2. He is free to travel from 2023.7.1 to 2023.7.20. The budget for transportation is 1900.0 CNY.\n3. The daily opening_hours of spots can be obtained from the database table place. \"opening_hours_begin\" and \"opening_hours_end\" are the opening and closing times respectively\n4. On the basis of completing the above conditions (especially the budget), spend as little time as possible.\n",
        "demands": {
            "TravelSimulator": {
                "begin_time": "2023-07-01 07:00",
                "end_time": "2023-07-20 00:00",
                "origin_city": "Chengdu",
                "origin_place": "Chengdu Railway Hotel",
                "budget": 99999,
                "check_opening_hours": true,
                "check_meal": false,
                "set_budget": true,
                "type": 3,
                "limit": "money",
                "money_min": 225,
                "money_max": 1395
            },
            "Constraints": {
                "SpotDurationConstraint": [
                    {
                        "spot": "Hubu Alley",
                        "minutes": 120
                    },
                    {
                        "spot": "Baotong Temple",
                        "minutes": 240
                    },
                    {
                        "spot": "Han Show",
                        "minutes": 300
                    },
                    {
                        "spot": "East Lake",
                        "minutes": 270
                    },
                    {
                        "spot": "Tan Hua Lin",
                        "minutes": 150
                    }
                ]
            }
        },
        "type": 3
    },
    {
        "question": "Bob is going to visit some spots across cities, please make a visit plan for him, including inter-city transportation, intra-city transportation, and visit time for each spot.    The demands are as follows:\n1. He now lives in Guangzhou Railway Hotel in Guangzhou. Every time he takes a train to a city, he lives in f\"{city} Railway Hotel\", such as \"Beijing Railway Hotel\" In Hangzhou, he needs to visit Quaint Water Towns for 210 minutes, China National Tea Museum for 210 minutes, Hefang Street for 180 minutes, Lingyin Temple for 180 minutes. And the order can be decided by you.\n2. 5 days (2023-07-10 00:00 ~ 2023-07-15 00:00) for this trip.\n3. Ignore the opening hours of attractions, assuming they are open all day. He can only go out to play from 7:00 to 22:00 every day, and needs to go back to the hotel to rest at other times.\n4. On the basis of completing the above conditions (especially the time limit), spend as little money as possible.\n",
        "demands": {
            "TravelSimulator": {
                "begin_time": "2023-07-10 00:00",
                "end_time": "2023-07-15 00:00",
                "origin_city": "Guangzhou",
                "origin_place": "Guangzhou Railway Hotel",
                "budget": 99999,
                "check_opening_hours": false,
                "check_meal": false,
                "set_budget": false,
                "type": 3,
                "limit": "time",
                "time_min": 156552,
                "time_max": 179497
            },
            "Constraints": {
                "SpotDurationConstraint": [
                    {
                        "spot": "Quaint Water Towns",
                        "minutes": 210
                    },
                    {
                        "spot": "China National Tea Museum",
                        "minutes": 210
                    },
                    {
                        "spot": "Hefang Street",
                        "minutes": 180
                    },
                    {
                        "spot": "Lingyin Temple",
                        "minutes": 180
                    }
                ]
            }
        },
        "type": 3
    },
    {
        "question": "Bob is going to visit some spots across cities, please make a visit plan for him, including inter-city transportation, intra-city transportation, and visit time for each spot.    The demands are as follows:\n1. He now lives in Shanghai Railway Hotel in Shanghai. Every time he takes a train to a city, he lives in f\"{city} Railway Hotel\", such as \"Beijing Railway Hotel\" In Nanjing, he needs to visit Lake Xuanwu for 240 minutes, Taiping Heavenly-Kingdom Palace for 150 minutes, Tomb of Ming Emperor Zhu Yuanzhang for 240 minutes, Qinhuai River for 210 minutes. And the order can be decided by you.\n2. 5 days (2023-07-03 00:00 ~ 2023-07-08 00:00) for this trip.\n3. Ignore the opening hours of attractions, assuming they are open all day. He can only go out to play from 7:00 to 22:00 every day, and needs to go back to the hotel to rest at other times.\n4. On the basis of completing the above conditions (especially the time limit), spend as little money as possible.\n",
        "demands": {
            "TravelSimulator": {
                "begin_time": "2023-07-03 00:00",
                "end_time": "2023-07-08 00:00",
                "origin_city": "Shanghai",
                "origin_place": "Shanghai Railway Hotel",
                "budget": 99999,
                "check_opening_hours": false,
                "check_meal": false,
                "set_budget": false,
                "type": 3,
                "limit": "time",
                "time_min": 151508,
                "time_max": 187039
            },
            "Constraints": {
                "SpotDurationConstraint": [
                    {
                        "spot": "Lake Xuanwu",
                        "minutes": 240
                    },
                    {
                        "spot": "Taiping Heavenly-Kingdom Palace",
                        "minutes": 150
                    },
                    {
                        "spot": "Tomb of Ming Emperor Zhu Yuanzhang",
                        "minutes": 240
                    },
                    {
                        "spot": "Qinhuai River",
                        "minutes": 210
                    }
                ]
            }
        },
        "type": 3
    },
    {
        "question": "Bob is going to visit some spots across cities, please make a visit plan for him, including inter-city transportation, intra-city transportation, and visit time for each spot.    The demands are as follows:\n1. He now lives in Hangzhou Railway Hotel in Hangzhou. Every time he takes a train to a city, he lives in f\"{city} Railway Hotel\", such as \"Beijing Railway Hotel\" In Shanghai, he needs to visit Shanghai Disney for 270 minutes, Century Park for 270 minutes, Xintiandi for 180 minutes, Shanghai Sightseeing Tunnel for 210 minutes, Longhua Temple for 210 minutes. And the order can be decided by you.\n2. 5 days (2023-07-04 00:00 ~ 2023-07-09 00:00) for this trip.\n3. The daily opening_hours of spots can be obtained from the database table place. \"opening_hours_begin\" and \"opening_hours_end\" are the opening and closing times respectively\n4. On the basis of completing the above conditions (especially the time limit), spend as little money as possible.\n",
        "demands": {
            "TravelSimulator": {
                "begin_time": "2023-07-04 00:00",
                "end_time": "2023-07-09 00:00",
                "origin_city": "Hangzhou",
                "origin_place": "Hangzhou Railway Hotel",
                "budget": 99999,
                "check_opening_hours": true,
                "check_meal": false,
                "set_budget": false,
                "type": 3,
                "limit": "time",
                "time_min": 160427,
                "time_max": 281681
            },
            "Constraints": {
                "SpotDurationConstraint": [
                    {
                        "spot": "Shanghai Disney",
                        "minutes": 270
                    },
                    {
                        "spot": "Century Park",
                        "minutes": 270
                    },
                    {
                        "spot": "Xintiandi",
                        "minutes": 180
                    },
                    {
                        "spot": "Shanghai Sightseeing Tunnel",
                        "minutes": 210
                    },
                    {
                        "spot": "Longhua Temple",
                        "minutes": 210
                    }
                ]
            }
        },
        "type": 3
    },
    {
        "question": "Bob is going to visit some spots across cities, please make a visit plan for him, including inter-city transportation, intra-city transportation, and visit time for each spot.    The demands are as follows:\n1. He now lives in Hangzhou Railway Hotel in Hangzhou. Every time he takes a train to a city, he lives in f\"{city} Railway Hotel\", such as \"Beijing Railway Hotel\" In Wuhan, he needs to visit Hubu Alley for 300 minutes, Yellow Crane Tower for 120 minutes, Baotong Temple for 180 minutes, Han Show for 180 minutes, Tan Hua Lin for 300 minutes. And the order can be decided by you.\n2. 5 days (2023-07-03 00:00 ~ 2023-07-08 00:00) for this trip.\n3. The daily opening_hours of spots can be obtained from the database table place. \"opening_hours_begin\" and \"opening_hours_end\" are the opening and closing times respectively\n4. On the basis of completing the above conditions (especially the time limit), spend as little money as possible.\n",
        "demands": {
            "TravelSimulator": {
                "begin_time": "2023-07-03 00:00",
                "end_time": "2023-07-08 00:00",
                "origin_city": "Hangzhou",
                "origin_place": "Hangzhou Railway Hotel",
                "budget": 99999,
                "check_opening_hours": true,
                "check_meal": false,
                "set_budget": false,
                "type": 3,
                "limit": "time",
                "time_min": 174035,
                "time_max": 287520
            },
            "Constraints": {
                "SpotDurationConstraint": [
                    {
                        "spot": "Hubu Alley",
                        "minutes": 300
                    },
                    {
                        "spot": "Yellow Crane Tower",
                        "minutes": 120
                    },
                    {
                        "spot": "Baotong Temple",
                        "minutes": 180
                    },
                    {
                        "spot": "Han Show",
                        "minutes": 180
                    },
                    {
                        "spot": "Tan Hua Lin",
                        "minutes": 300
                    }
                ]
            }
        },
        "type": 3
    },
    {
        "question": "Bob is going to visit some spots across cities, please make a visit plan for him, including inter-city transportation, intra-city transportation, and visit time for each spot.    The demands are as follows:\n1. He now lives in Beijing Railway Hotel in Beijing. Every time he takes a train to a city, he lives in f\"{city} Railway Hotel\", such as \"Beijing Railway Hotel\" In Beijing, he needs to visit Shihua Cave for 240 minutes, The Summer Palace for 150 minutes.In Guangzhou, he needs to visit Canton Tower for 300 minutes, Baiyun Mountain for 210 minutes. And the order can be decided by you.\n2. He is free to travel from 2023.7.1 to 2023.7.20. The budget for transportation is 1800.0 CNY.\n3. Ignore the opening hours of attractions, assuming they are open all day. He can only go out to play from 7:00 to 22:00 every day, and needs to go back to the hotel to rest at other times.\n4. On the basis of completing the above conditions (especially the budget), spend as little time as possible.\n",
        "demands": {
            "TravelSimulator": {
                "begin_time": "2023-07-01 07:00",
                "end_time": "2023-07-20 00:00",
                "origin_city": "Beijing",
                "origin_place": "Beijing Railway Hotel",
                "budget": 99999,
                "check_opening_hours": false,
                "check_meal": false,
                "set_budget": true,
                "type": 3,
                "limit": "money",
                "money_min": 0,
                "money_max": 2346
            },
            "Constraints": {
                "SpotDurationConstraint": [
                    {
                        "spot": "Shihua Cave",
                        "minutes": 240
                    },
                    {
                        "spot": "The Summer Palace",
                        "minutes": 150
                    },
                    {
                        "spot": "Canton Tower",
                        "minutes": 300
                    },
                    {
                        "spot": "Baiyun Mountain",
                        "minutes": 210
                    }
                ]
            }
        },
        "type": 3
    },
    {
        "question": "Bob is going to visit some spots across cities, please make a visit plan for him, including inter-city transportation, intra-city transportation, and visit time for each spot.    The demands are as follows:\n1. He now lives in Chengdu Railway Hotel in Chengdu. Every time he takes a train to a city, he lives in f\"{city} Railway Hotel\", such as \"Beijing Railway Hotel\" In Chengdu, he needs to visit Du Fu Thatched Cottage for 240 minutes, The Chengdu Wuhou Shrine for 180 minutes, Leshan Giant Buddha for 210 minutes.In Nanjing, he needs to visit Taiping Heavenly-Kingdom Palace for 300 minutes, Ming Palace for 120 minutes. And the order can be decided by you.\n2. He is free to travel from 2023.7.1 to 2023.7.20. The budget for transportation is 1900.0 CNY.\n3. Ignore the opening hours of attractions, assuming they are open all day. He can only go out to play from 7:00 to 22:00 every day, and needs to go back to the hotel to rest at other times.\n4. On the basis of completing the above conditions (especially the budget), spend as little time as possible.\n",
        "demands": {
            "TravelSimulator": {
                "begin_time": "2023-07-01 07:00",
                "end_time": "2023-07-20 00:00",
                "origin_city": "Chengdu",
                "origin_place": "Chengdu Railway Hotel",
                "budget": 99999,
                "check_opening_hours": false,
                "check_meal": false,
                "set_budget": true,
                "type": 3,
                "limit": "money",
                "money_min": 244,
                "money_max": 1644
            },
            "Constraints": {
                "SpotDurationConstraint": [
                    {
                        "spot": "Du Fu Thatched Cottage",
                        "minutes": 240
                    },
                    {
                        "spot": "The Chengdu Wuhou Shrine",
                        "minutes": 180
                    },
                    {
                        "spot": "Leshan Giant Buddha",
                        "minutes": 210
                    },
                    {
                        "spot": "Taiping Heavenly-Kingdom Palace",
                        "minutes": 300
                    },
                    {
                        "spot": "Ming Palace",
                        "minutes": 120
                    }
                ]
            }
        },
        "type": 3
    },
    {
        "question": "Bob is going to visit some spots across cities, please make a visit plan for him, including inter-city transportation, intra-city transportation, and visit time for each spot.    The demands are as follows:\n1. He now lives in Shanghai Railway Hotel in Shanghai. Every time he takes a train to a city, he lives in f\"{city} Railway Hotel\", such as \"Beijing Railway Hotel\" In Shanghai, he needs to visit Shanghai Sightseeing Tunnel for 240 minutes, Shanghai Disney for 150 minutes.In Beijing, he needs to visit The Temple of Heaven for 300 minutes, The Forbidden City for 300 minutes. And the order can be decided by you.\n2. He is free to travel from 2023.7.1 to 2023.7.20. The budget for transportation is 1400.0 CNY.\n3. The daily opening_hours of spots can be obtained from the database table place. \"opening_hours_begin\" and \"opening_hours_end\" are the opening and closing times respectively\n4. On the basis of completing the above conditions (especially the budget), spend as little time as possible.\n",
        "demands": {
            "TravelSimulator": {
                "begin_time": "2023-07-01 07:00",
                "end_time": "2023-07-20 00:00",
                "origin_city": "Shanghai",
                "origin_place": "Shanghai Railway Hotel",
                "budget": 99999,
                "check_opening_hours": true,
                "check_meal": false,
                "set_budget": true,
                "type": 3,
                "limit": "money",
                "money_min": 222,
                "money_max": 1785
            },
            "Constraints": {
                "SpotDurationConstraint": [
                    {
                        "spot": "Shanghai Sightseeing Tunnel",
                        "minutes": 240
                    },
                    {
                        "spot": "Shanghai Disney",
                        "minutes": 150
                    },
                    {
                        "spot": "The Temple of Heaven",
                        "minutes": 300
                    },
                    {
                        "spot": "The Forbidden City",
                        "minutes": 300
                    }
                ]
            }
        },
        "type": 3
    },
    {
        "question": "Bob is going to visit some spots across cities, please make a visit plan for him, including inter-city transportation, intra-city transportation, and visit time for each spot.    The demands are as follows:\n1. He now lives in Beijing Railway Hotel in Beijing. Every time he takes a train to a city, he lives in f\"{city} Railway Hotel\", such as \"Beijing Railway Hotel\" In Beijing, he needs to visit The Summer Palace for 180 minutes, The Great Wall for 300 minutes.In Hangzhou, he needs to visit Quaint Water Towns for 210 minutes, West Lake for 270 minutes. And the order can be decided by you.\n2. He is free to travel from 2023.7.1 to 2023.7.20. The budget for transportation is 1400.0 CNY.\n3. The daily opening_hours of spots can be obtained from the database table place. \"opening_hours_begin\" and \"opening_hours_end\" are the opening and closing times respectively\n4. On the basis of completing the above conditions (especially the budget), spend as little time as possible.\n",
        "demands": {
            "TravelSimulator": {
                "begin_time": "2023-07-01 07:00",
                "end_time": "2023-07-20 00:00",
                "origin_city": "Beijing",
                "origin_place": "Beijing Railway Hotel",
                "budget": 99999,
                "check_opening_hours": true,
                "check_meal": false,
                "set_budget": true,
                "type": 3,
                "limit": "money",
                "money_min": 496,
                "money_max": 1454
            },
            "Constraints": {
                "SpotDurationConstraint": [
                    {
                        "spot": "The Summer Palace",
                        "minutes": 180
                    },
                    {
                        "spot": "The Great Wall",
                        "minutes": 300
                    },
                    {
                        "spot": "Quaint Water Towns",
                        "minutes": 210
                    },
                    {
                        "spot": "West Lake",
                        "minutes": 270
                    }
                ]
            }
        },
        "type": 3
    },
    {
        "question": "Bob is going to visit some spots across cities, please make a visit plan for him, including inter-city transportation, intra-city transportation, and visit time for each spot.    The demands are as follows:\n1. He now lives in Beijing Railway Hotel in Beijing. Every time he takes a train to a city, he lives in f\"{city} Railway Hotel\", such as \"Beijing Railway Hotel\" In Beijing, he needs to visit Beijing Olympic Park for 270 minutes, Tiananmen Square for 120 minutes, The Temple of Heaven for 120 minutes.In Wuhan, he needs to visit Yellow Crane Tower for 180 minutes, Tan Hua Lin for 270 minutes. And the order can be decided by you.\n2. 5 days (2023-07-04 00:00 ~ 2023-07-09 00:00) for this trip.\n3. Ignore the opening hours of attractions, assuming they are open all day. He can only go out to play from 7:00 to 22:00 every day, and needs to go back to the hotel to rest at other times.\n4. On the basis of completing the above conditions (especially the time limit), spend as little money as possible.\n",
        "demands": {
            "TravelSimulator": {
                "begin_time": "2023-07-04 00:00",
                "end_time": "2023-07-09 00:00",
                "origin_city": "Beijing",
                "origin_place": "Beijing Railway Hotel",
                "budget": 99999,
                "check_opening_hours": false,
                "check_meal": false,
                "set_budget": false,
                "type": 3,
                "limit": "time",
                "time_min": 195758,
                "time_max": 231777
            },
            "Constraints": {
                "SpotDurationConstraint": [
                    {
                        "spot": "Beijing Olympic Park",
                        "minutes": 270
                    },
                    {
                        "spot": "Tiananmen Square",
                        "minutes": 120
                    },
                    {
                        "spot": "The Temple of Heaven",
                        "minutes": 120
                    },
                    {
                        "spot": "Yellow Crane Tower",
                        "minutes": 180
                    },
                    {
                        "spot": "Tan Hua Lin",
                        "minutes": 270
                    }
                ]
            }
        },
        "type": 3
    },
    {
        "question": "Bob is going to visit some spots across cities, please make a visit plan for him, including inter-city transportation, intra-city transportation, and visit time for each spot.    The demands are as follows:\n1. He now lives in Beijing Railway Hotel in Beijing. Every time he takes a train to a city, he lives in f\"{city} Railway Hotel\", such as \"Beijing Railway Hotel\" In Beijing, he needs to visit The Forbidden City for 210 minutes, The Temple of Heaven for 240 minutes, Beijing Stone Carvings Art Museum for 180 minutes.In Nanjing, he needs to visit Taiping Heavenly-Kingdom Palace for 120 minutes, Tomb of Ming Emperor Zhu Yuanzhang for 150 minutes. And the order can be decided by you.\n2. 5 days (2023-07-11 00:00 ~ 2023-07-16 00:00) for this trip.\n3. Ignore the opening hours of attractions, assuming they are open all day. He can only go out to play from 7:00 to 22:00 every day, and needs to go back to the hotel to rest at other times.\n4. On the basis of completing the above conditions (especially the time limit), spend as little money as possible.\n",
        "demands": {
            "TravelSimulator": {
                "begin_time": "2023-07-11 00:00",
                "end_time": "2023-07-16 00:00",
                "origin_city": "Beijing",
                "origin_place": "Beijing Railway Hotel",
                "budget": 99999,
                "check_opening_hours": false,
                "check_meal": false,
                "set_budget": false,
                "type": 3,
                "limit": "time",
                "time_min": 137505,
                "time_max": 229046
            },
            "Constraints": {
                "SpotDurationConstraint": [
                    {
                        "spot": "The Forbidden City",
                        "minutes": 210
                    },
                    {
                        "spot": "The Temple of Heaven",
                        "minutes": 240
                    },
                    {
                        "spot": "Beijing Stone Carvings Art Museum",
                        "minutes": 180
                    },
                    {
                        "spot": "Taiping Heavenly-Kingdom Palace",
                        "minutes": 120
                    },
                    {
                        "spot": "Tomb of Ming Emperor Zhu Yuanzhang",
                        "minutes": 150
                    }
                ]
            }
        },
        "type": 3
    },
    {
        "question": "Bob is going to visit some spots across cities, please make a visit plan for him, including inter-city transportation, intra-city transportation, and visit time for each spot.    The demands are as follows:\n1. He now lives in Shanghai Railway Hotel in Shanghai. Every time he takes a train to a city, he lives in f\"{city} Railway Hotel\", such as \"Beijing Railway Hotel\" In Shanghai, he needs to visit Shanghai Sightseeing Tunnel for 120 minutes, Shanghai Disney for 210 minutes.In Hangzhou, he needs to visit Hefang Street for 300 minutes, China National Tea Museum for 270 minutes. And the order can be decided by you.\n2. 5 days (2023-07-09 00:00 ~ 2023-07-14 00:00) for this trip.\n3. The daily opening_hours of spots can be obtained from the database table place. \"opening_hours_begin\" and \"opening_hours_end\" are the opening and closing times respectively\n4. On the basis of completing the above conditions (especially the time limit), spend as little money as possible.\n",
        "demands": {
            "TravelSimulator": {
                "begin_time": "2023-07-09 00:00",
                "end_time": "2023-07-14 00:00",
                "origin_city": "Shanghai",
                "origin_place": "Shanghai Railway Hotel",
                "budget": 99999,
                "check_opening_hours": true,
                "check_meal": false,
                "set_budget": false,
                "type": 3,
                "limit": "time",
                "time_min": 115525,
                "time_max": 277918
            },
            "Constraints": {
                "SpotDurationConstraint": [
                    {
                        "spot": "Shanghai Sightseeing Tunnel",
                        "minutes": 120
                    },
                    {
                        "spot": "Shanghai Disney",
                        "minutes": 210
                    },
                    {
                        "spot": "Hefang Street",
                        "minutes": 300
                    },
                    {
                        "spot": "China National Tea Museum",
                        "minutes": 270
                    }
                ]
            }
        },
        "type": 3
    },
    {
        "question": "Bob is going to visit some spots across cities, please make a visit plan for him, including inter-city transportation, intra-city transportation, and visit time for each spot.    The demands are as follows:\n1. He now lives in Nanjing Railway Hotel in Nanjing. Every time he takes a train to a city, he lives in f\"{city} Railway Hotel\", such as \"Beijing Railway Hotel\" In Nanjing, he needs to visit Tomb of Ming Emperor Zhu Yuanzhang for 120 minutes, Qinhuai River for 180 minutes.In Beijing, he needs to visit Tiananmen Square for 210 minutes, Beijing Olympic Park for 120 minutes. And the order can be decided by you.\n2. 5 days (2023-07-02 00:00 ~ 2023-07-07 00:00) for this trip.\n3. The daily opening_hours of spots can be obtained from the database table place. \"opening_hours_begin\" and \"opening_hours_end\" are the opening and closing times respectively\n4. On the basis of completing the above conditions (especially the time limit), spend as little money as possible.\n",
        "demands": {
            "TravelSimulator": {
                "begin_time": "2023-07-02 00:00",
                "end_time": "2023-07-07 00:00",
                "origin_city": "Nanjing",
                "origin_place": "Nanjing Railway Hotel",
                "budget": 99999,
                "check_opening_hours": true,
                "check_meal": false,
                "set_budget": false,
                "type": 3,
                "limit": "time",
                "time_min": 116143,
                "time_max": 152354
            },
            "Constraints": {
                "SpotDurationConstraint": [
                    {
                        "spot": "Tomb of Ming Emperor Zhu Yuanzhang",
                        "minutes": 120
                    },
                    {
                        "spot": "Qinhuai River",
                        "minutes": 180
                    },
                    {
                        "spot": "Tiananmen Square",
                        "minutes": 210
                    },
                    {
                        "spot": "Beijing Olympic Park",
                        "minutes": 120
                    }
                ]
            }
        },
        "type": 3
    },
    {
        "question": "Bob is going to visit some spots across cities, please make a visit plan for him, including inter-city transportation, intra-city transportation, and visit time for each spot.    The demands are as follows:\n1. He now lives in Hangzhou Railway Hotel in Hangzhou. Every time he takes a train to a city, he lives in f\"{city} Railway Hotel\", such as \"Beijing Railway Hotel\" In Beijing, he needs to visit The Temple of Heaven for 300 minutes, The Great Wall for 240 minutes, Shihua Cave for 270 minutes, The Summer Palace for 180 minutes, Beijing Stone Carvings Art Museum for 180 minutes, Tiananmen Square for 240 minutes, Beijing Olympic Park for 300 minutes. And the order can be decided by you.\n2. He is free to travel from 2023.7.1 to 2023.7.20. The budget for transportation is 2700.0 CNY.\n3. Ignore the opening hours of attractions, assuming they are open all day. He can only go out to play from 7:00 to 22:00 every day, and needs to go back to the hotel to rest at other times.\n4. On the basis of completing the above conditions (especially the budget), spend as little time as possible.\n",
        "demands": {
            "TravelSimulator": {
                "begin_time": "2023-07-01 07:00",
                "end_time": "2023-07-20 00:00",
                "origin_city": "Hangzhou",
                "origin_place": "Hangzhou Railway Hotel",
                "budget": 99999,
                "check_opening_hours": false,
                "check_meal": false,
                "set_budget": true,
                "type": 3,
                "limit": "money",
                "money_min": 390,
                "money_max": 1507
            },
            "Constraints": {
                "SpotDurationConstraint": [
                    {
                        "spot": "The Temple of Heaven",
                        "minutes": 300
                    },
                    {
                        "spot": "The Great Wall",
                        "minutes": 240
                    },
                    {
                        "spot": "Shihua Cave",
                        "minutes": 270
                    },
                    {
                        "spot": "The Summer Palace",
                        "minutes": 180
                    },
                    {
                        "spot": "Beijing Stone Carvings Art Museum",
                        "minutes": 180
                    },
                    {
                        "spot": "Tiananmen Square",
                        "minutes": 240
                    },
                    {
                        "spot": "Beijing Olympic Park",
                        "minutes": 300
                    }
                ]
            }
        },
        "type": 3
    },
    {
        "question": "Bob is going to visit some spots across cities, please make a visit plan for him, including inter-city transportation, intra-city transportation, and visit time for each spot.    The demands are as follows:\n1. He now lives in Hangzhou Railway Hotel in Hangzhou. Every time he takes a train to a city, he lives in f\"{city} Railway Hotel\", such as \"Beijing Railway Hotel\" In Beijing, he needs to visit Tiananmen Square for 210 minutes, The Great Wall for 150 minutes, Beijing Olympic Park for 270 minutes, Shihua Cave for 150 minutes, Beijing Stone Carvings Art Museum for 120 minutes, The Forbidden City for 180 minutes, The Summer Palace for 270 minutes. And the order can be decided by you.\n2. He is free to travel from 2023.7.1 to 2023.7.20. The budget for transportation is 2700.0 CNY.\n3. Ignore the opening hours of attractions, assuming they are open all day. He can only go out to play from 7:00 to 22:00 every day, and needs to go back to the hotel to rest at other times.\n4. On the basis of completing the above conditions (especially the budget), spend as little time as possible.\n",
        "demands": {
            "TravelSimulator": {
                "begin_time": "2023-07-01 07:00",
                "end_time": "2023-07-20 00:00",
                "origin_city": "Hangzhou",
                "origin_place": "Hangzhou Railway Hotel",
                "budget": 99999,
                "check_opening_hours": false,
                "check_meal": false,
                "set_budget": true,
                "type": 3,
                "limit": "money",
                "money_min": 490,
                "money_max": 1512
            },
            "Constraints": {
                "SpotDurationConstraint": [
                    {
                        "spot": "Tiananmen Square",
                        "minutes": 210
                    },
                    {
                        "spot": "The Great Wall",
                        "minutes": 150
                    },
                    {
                        "spot": "Beijing Olympic Park",
                        "minutes": 270
                    },
                    {
                        "spot": "Shihua Cave",
                        "minutes": 150
                    },
                    {
                        "spot": "Beijing Stone Carvings Art Museum",
                        "minutes": 120
                    },
                    {
                        "spot": "The Forbidden City",
                        "minutes": 180
                    },
                    {
                        "spot": "The Summer Palace",
                        "minutes": 270
                    }
                ]
            }
        },
        "type": 3
    },
    {
        "question": "Bob is going to visit some spots across cities, please make a visit plan for him, including inter-city transportation, intra-city transportation, and visit time for each spot.    The demands are as follows:\n1. He now lives in Hangzhou Railway Hotel in Hangzhou. Every time he takes a train to a city, he lives in f\"{city} Railway Hotel\", such as \"Beijing Railway Hotel\" In Shanghai, he needs to visit Longhua Temple for 210 minutes, Shanghai Disney for 300 minutes, Huangpu River Cruise for 180 minutes, Qibao Ancient Town for 210 minutes, Shanghai History Museum for 240 minutes, Shanghai Sightseeing Tunnel for 210 minutes. And the order can be decided by you.\n2. He is free to travel from 2023.7.1 to 2023.7.20. The budget for transportation is 1400.0 CNY.\n3. The daily opening_hours of spots can be obtained from the database table place. \"opening_hours_begin\" and \"opening_hours_end\" are the opening and closing times respectively\n4. On the basis of completing the above conditions (especially the budget), spend as little time as possible.\n",
        "demands": {
            "TravelSimulator": {
                "begin_time": "2023-07-01 07:00",
                "end_time": "2023-07-20 00:00",
                "origin_city": "Hangzhou",
                "origin_place": "Hangzhou Railway Hotel",
                "budget": 99999,
                "check_opening_hours": true,
                "check_meal": false,
                "set_budget": true,
                "type": 3,
                "limit": "money",
                "money_min": 0,
                "money_max": 216
            },
            "Constraints": {
                "SpotDurationConstraint": [
                    {
                        "spot": "Longhua Temple",
                        "minutes": 210
                    },
                    {
                        "spot": "Shanghai Disney",
                        "minutes": 300
                    },
                    {
                        "spot": "Huangpu River Cruise",
                        "minutes": 180
                    },
                    {
                        "spot": "Qibao Ancient Town",
                        "minutes": 210
                    },
                    {
                        "spot": "Shanghai History Museum",
                        "minutes": 240
                    },
                    {
                        "spot": "Shanghai Sightseeing Tunnel",
                        "minutes": 210
                    }
                ]
            }
        },
        "type": 3
    },
    {
        "question": "Bob is going to visit some spots across cities, please make a visit plan for him, including inter-city transportation, intra-city transportation, and visit time for each spot.    The demands are as follows:\n1. He now lives in Guangzhou Railway Hotel in Guangzhou. Every time he takes a train to a city, he lives in f\"{city} Railway Hotel\", such as \"Beijing Railway Hotel\" In Shanghai, he needs to visit Century Park for 270 minutes, Huangpu River Cruise for 270 minutes, Qibao Ancient Town for 270 minutes, Shanghai Disney for 240 minutes, Xintiandi for 150 minutes, Longhua Temple for 150 minutes. And the order can be decided by you.\n2. He is free to travel from 2023.7.1 to 2023.7.20. The budget for transportation is 2600.0 CNY.\n3. The daily opening_hours of spots can be obtained from the database table place. \"opening_hours_begin\" and \"opening_hours_end\" are the opening and closing times respectively\n4. On the basis of completing the above conditions (especially the budget), spend as little time as possible.\n",
        "demands": {
            "TravelSimulator": {
                "begin_time": "2023-07-01 07:00",
                "end_time": "2023-07-20 00:00",
                "origin_city": "Guangzhou",
                "origin_place": "Guangzhou Railway Hotel",
                "budget": 99999,
                "check_opening_hours": true,
                "check_meal": false,
                "set_budget": true,
                "type": 3,
                "limit": "money",
                "money_min": 44,
                "money_max": 2413
            },
            "Constraints": {
                "SpotDurationConstraint": [
                    {
                        "spot": "Century Park",
                        "minutes": 270
                    },
                    {
                        "spot": "Huangpu River Cruise",
                        "minutes": 270
                    },
                    {
                        "spot": "Qibao Ancient Town",
                        "minutes": 270
                    },
                    {
                        "spot": "Shanghai Disney",
                        "minutes": 240
                    },
                    {
                        "spot": "Xintiandi",
                        "minutes": 150
                    },
                    {
                        "spot": "Longhua Temple",
                        "minutes": 150
                    }
                ]
            }
        },
        "type": 3
    },
    {
        "question": "Bob is going to visit some spots across cities, please make a visit plan for him, including inter-city transportation, intra-city transportation, and visit time for each spot.    The demands are as follows:\n1. He now lives in Guangzhou Railway Hotel in Guangzhou. Every time he takes a train to a city, he lives in f\"{city} Railway Hotel\", such as \"Beijing Railway Hotel\" In Beijing, he needs to visit Beijing Stone Carvings Art Museum for 210 minutes, Beijing Olympic Park for 120 minutes, The Forbidden City for 180 minutes, The Summer Palace for 210 minutes, Shihua Cave for 150 minutes, The Temple of Heaven for 240 minutes, The Great Wall for 150 minutes. And the order can be decided by you.\n2. 6 days (2023-07-10 00:00 ~ 2023-07-16 00:00) for this trip.\n3. Ignore the opening hours of attractions, assuming they are open all day. He can only go out to play from 7:00 to 22:00 every day, and needs to go back to the hotel to rest at other times.\n4. On the basis of completing the above conditions (especially the time limit), spend as little money as possible.\n",
        "demands": {
            "TravelSimulator": {
                "begin_time": "2023-07-10 00:00",
                "end_time": "2023-07-16 00:00",
                "origin_city": "Guangzhou",
                "origin_place": "Guangzhou Railway Hotel",
                "budget": 99999,
                "check_opening_hours": false,
                "check_meal": false,
                "set_budget": false,
                "type": 3,
                "limit": "time",
                "time_min": 196845,
                "time_max": 317688
            },
            "Constraints": {
                "SpotDurationConstraint": [
                    {
                        "spot": "Beijing Stone Carvings Art Museum",
                        "minutes": 210
                    },
                    {
                        "spot": "Beijing Olympic Park",
                        "minutes": 120
                    },
                    {
                        "spot": "The Forbidden City",
                        "minutes": 180
                    },
                    {
                        "spot": "The Summer Palace",
                        "minutes": 210
                    },
                    {
                        "spot": "Shihua Cave",
                        "minutes": 150
                    },
                    {
                        "spot": "The Temple of Heaven",
                        "minutes": 240
                    },
                    {
                        "spot": "The Great Wall",
                        "minutes": 150
                    }
                ]
            }
        },
        "type": 3
    },
    {
        "question": "Bob is going to visit some spots across cities, please make a visit plan for him, including inter-city transportation, intra-city transportation, and visit time for each spot.    The demands are as follows:\n1. He now lives in Beijing Railway Hotel in Beijing. Every time he takes a train to a city, he lives in f\"{city} Railway Hotel\", such as \"Beijing Railway Hotel\" In Wuhan, he needs to visit Han Show for 210 minutes, East Lake for 150 minutes, Yellow Crane Tower for 240 minutes, Baotong Temple for 180 minutes, Tan Hua Lin for 150 minutes, Hubu Alley for 210 minutes. And the order can be decided by you.\n2. 6 days (2023-07-09 00:00 ~ 2023-07-15 00:00) for this trip.\n3. Ignore the opening hours of attractions, assuming they are open all day. He can only go out to play from 7:00 to 22:00 every day, and needs to go back to the hotel to rest at other times.\n4. On the basis of completing the above conditions (especially the time limit), spend as little money as possible.\n",
        "demands": {
            "TravelSimulator": {
                "begin_time": "2023-07-09 00:00",
                "end_time": "2023-07-15 00:00",
                "origin_city": "Beijing",
                "origin_place": "Beijing Railway Hotel",
                "budget": 99999,
                "check_opening_hours": false,
                "check_meal": false,
                "set_budget": false,
                "type": 3,
                "limit": "time",
                "time_min": 153687,
                "time_max": 276157
            },
            "Constraints": {
                "SpotDurationConstraint": [
                    {
                        "spot": "Han Show",
                        "minutes": 210
                    },
                    {
                        "spot": "East Lake",
                        "minutes": 150
                    },
                    {
                        "spot": "Yellow Crane Tower",
                        "minutes": 240
                    },
                    {
                        "spot": "Baotong Temple",
                        "minutes": 180
                    },
                    {
                        "spot": "Tan Hua Lin",
                        "minutes": 150
                    },
                    {
                        "spot": "Hubu Alley",
                        "minutes": 210
                    }
                ]
            }
        },
        "type": 3
    },
    {
        "question": "Bob is going to visit some spots across cities, please make a visit plan for him, including inter-city transportation, intra-city transportation, and visit time for each spot.    The demands are as follows:\n1. He now lives in Nanjing Railway Hotel in Nanjing. Every time he takes a train to a city, he lives in f\"{city} Railway Hotel\", such as \"Beijing Railway Hotel\" In Wuhan, he needs to visit Tan Hua Lin for 150 minutes, Yellow Crane Tower for 240 minutes, East Lake for 300 minutes, Baotong Temple for 300 minutes, Hubu Alley for 240 minutes, Han Show for 270 minutes. And the order can be decided by you.\n2. 6 days (2023-07-11 00:00 ~ 2023-07-17 00:00) for this trip.\n3. The daily opening_hours of spots can be obtained from the database table place. \"opening_hours_begin\" and \"opening_hours_end\" are the opening and closing times respectively\n4. On the basis of completing the above conditions (especially the time limit), spend as little money as possible.\n",
        "demands": {
            "TravelSimulator": {
                "begin_time": "2023-07-11 00:00",
                "end_time": "2023-07-17 00:00",
                "origin_city": "Nanjing",
                "origin_place": "Nanjing Railway Hotel",
                "budget": 99999,
                "check_opening_hours": true,
                "check_meal": false,
                "set_budget": false,
                "type": 3,
                "limit": "time",
                "time_min": 195019,
                "time_max": 386668
            },
            "Constraints": {
                "SpotDurationConstraint": [
                    {
                        "spot": "Tan Hua Lin",
                        "minutes": 150
                    },
                    {
                        "spot": "Yellow Crane Tower",
                        "minutes": 240
                    },
                    {
                        "spot": "East Lake",
                        "minutes": 300
                    },
                    {
                        "spot": "Baotong Temple",
                        "minutes": 300
                    },
                    {
                        "spot": "Hubu Alley",
                        "minutes": 240
                    },
                    {
                        "spot": "Han Show",
                        "minutes": 270
                    }
                ]
            }
        },
        "type": 3
    },
    {
        "question": "Bob is going to visit some spots across cities, please make a visit plan for him, including inter-city transportation, intra-city transportation, and visit time for each spot.    The demands are as follows:\n1. He now lives in Chengdu Railway Hotel in Chengdu. Every time he takes a train to a city, he lives in f\"{city} Railway Hotel\", such as \"Beijing Railway Hotel\" In Beijing, he needs to visit Tiananmen Square for 180 minutes, The Temple of Heaven for 270 minutes, The Great Wall for 120 minutes, Shihua Cave for 300 minutes, Beijing Stone Carvings Art Museum for 300 minutes, The Forbidden City for 210 minutes. And the order can be decided by you.\n2. 6 days (2023-07-02 00:00 ~ 2023-07-08 00:00) for this trip.\n3. The daily opening_hours of spots can be obtained from the database table place. \"opening_hours_begin\" and \"opening_hours_end\" are the opening and closing times respectively\n4. On the basis of completing the above conditions (especially the time limit), spend as little money as possible.\n",
        "demands": {
            "TravelSimulator": {
                "begin_time": "2023-07-02 00:00",
                "end_time": "2023-07-08 00:00",
                "origin_city": "Chengdu",
                "origin_place": "Chengdu Railway Hotel",
                "budget": 99999,
                "check_opening_hours": true,
                "check_meal": false,
                "set_budget": false,
                "type": 3,
                "limit": "time",
                "time_min": 195935,
                "time_max": 381263
            },
            "Constraints": {
                "SpotDurationConstraint": [
                    {
                        "spot": "Tiananmen Square",
                        "minutes": 180
                    },
                    {
                        "spot": "The Temple of Heaven",
                        "minutes": 270
                    },
                    {
                        "spot": "The Great Wall",
                        "minutes": 120
                    },
                    {
                        "spot": "Shihua Cave",
                        "minutes": 300
                    },
                    {
                        "spot": "Beijing Stone Carvings Art Museum",
                        "minutes": 300
                    },
                    {
                        "spot": "The Forbidden City",
                        "minutes": 210
                    }
                ]
            }
        },
        "type": 3
    },
    {
        "question": "Bob is going to visit some spots across cities, please make a visit plan for him, including inter-city transportation, intra-city transportation, and visit time for each spot.    The demands are as follows:\n1. He now lives in Wuhan Railway Hotel in Wuhan. Every time he takes a train to a city, he lives in f\"{city} Railway Hotel\", such as \"Beijing Railway Hotel\" In Wuhan, he needs to visit Hubu Alley for 120 minutes, East Lake for 180 minutes, Baotong Temple for 300 minutes, Tan Hua Lin for 210 minutes.In Beijing, he needs to visit The Great Wall for 180 minutes, The Temple of Heaven for 270 minutes, The Forbidden City for 270 minutes. And the order can be decided by you.\n2. He is free to travel from 2023.7.1 to 2023.7.20. The budget for transportation is 2000.0 CNY.\n3. Ignore the opening hours of attractions, assuming they are open all day. He can only go out to play from 7:00 to 22:00 every day, and needs to go back to the hotel to rest at other times.\n4. On the basis of completing the above conditions (especially the budget), spend as little time as possible.\n",
        "demands": {
            "TravelSimulator": {
                "begin_time": "2023-07-01 07:00",
                "end_time": "2023-07-20 00:00",
                "origin_city": "Wuhan",
                "origin_place": "Wuhan Railway Hotel",
                "budget": 99999,
                "check_opening_hours": false,
                "check_meal": false,
                "set_budget": true,
                "type": 3,
                "limit": "money",
                "money_min": 114,
                "money_max": 1305
            },
            "Constraints": {
                "SpotDurationConstraint": [
                    {
                        "spot": "Hubu Alley",
                        "minutes": 120
                    },
                    {
                        "spot": "East Lake",
                        "minutes": 180
                    },
                    {
                        "spot": "Baotong Temple",
                        "minutes": 300
                    },
                    {
                        "spot": "Tan Hua Lin",
                        "minutes": 210
                    },
                    {
                        "spot": "The Great Wall",
                        "minutes": 180
                    },
                    {
                        "spot": "The Temple of Heaven",
                        "minutes": 270
                    },
                    {
                        "spot": "The Forbidden City",
                        "minutes": 270
                    }
                ]
            }
        },
        "type": 3
    },
    {
        "question": "Bob is going to visit some spots across cities, please make a visit plan for him, including inter-city transportation, intra-city transportation, and visit time for each spot.    The demands are as follows:\n1. He now lives in Beijing Railway Hotel in Beijing. Every time he takes a train to a city, he lives in f\"{city} Railway Hotel\", such as \"Beijing Railway Hotel\" In Beijing, he needs to visit The Forbidden City for 120 minutes, The Great Wall for 120 minutes, Tiananmen Square for 180 minutes, Beijing Stone Carvings Art Museum for 300 minutes, The Summer Palace for 120 minutes.In Hangzhou, he needs to visit West Lake for 210 minutes, Quaint Water Towns for 300 minutes. And the order can be decided by you.\n2. He is free to travel from 2023.7.1 to 2023.7.20. The budget for transportation is 2100.0 CNY.\n3. Ignore the opening hours of attractions, assuming they are open all day. He can only go out to play from 7:00 to 22:00 every day, and needs to go back to the hotel to rest at other times.\n4. On the basis of completing the above conditions (especially the budget), spend as little time as possible.\n",
        "demands": {
            "TravelSimulator": {
                "begin_time": "2023-07-01 07:00",
                "end_time": "2023-07-20 00:00",
                "origin_city": "Beijing",
                "origin_place": "Beijing Railway Hotel",
                "budget": 99999,
                "check_opening_hours": false,
                "check_meal": false,
                "set_budget": true,
                "type": 3,
                "limit": "money",
                "money_min": 378,
                "money_max": 1572
            },
            "Constraints": {
                "SpotDurationConstraint": [
                    {
                        "spot": "The Forbidden City",
                        "minutes": 120
                    },
                    {
                        "spot": "The Great Wall",
                        "minutes": 120
                    },
                    {
                        "spot": "Tiananmen Square",
                        "minutes": 180
                    },
                    {
                        "spot": "Beijing Stone Carvings Art Museum",
                        "minutes": 300
                    },
                    {
                        "spot": "The Summer Palace",
                        "minutes": 120
                    },
                    {
                        "spot": "West Lake",
                        "minutes": 210
                    },
                    {
                        "spot": "Quaint Water Towns",
                        "minutes": 300
                    }
                ]
            }
        },
        "type": 3
    },
    {
        "question": "Bob is going to visit some spots across cities, please make a visit plan for him, including inter-city transportation, intra-city transportation, and visit time for each spot.    The demands are as follows:\n1. He now lives in Wuhan Railway Hotel in Wuhan. Every time he takes a train to a city, he lives in f\"{city} Railway Hotel\", such as \"Beijing Railway Hotel\" In Shanghai, he needs to visit Century Park for 270 minutes, Longhua Temple for 240 minutes, Huangpu River Cruise for 150 minutes.In Guangzhou, he needs to visit Chimelong Tourist Resort for 120 minutes, Yuexiu Park for 150 minutes. And the order can be decided by you.\n2. He is free to travel from 2023.7.1 to 2023.7.20. The budget for transportation is 2300.0 CNY.\n3. Ignore the opening hours of attractions, assuming they are open all day. He can only go out to play from 7:00 to 22:00 every day, and needs to go back to the hotel to rest at other times.\n4. On the basis of completing the above conditions (especially the budget), spend as little time as possible.\n",
        "demands": {
            "TravelSimulator": {
                "begin_time": "2023-07-01 07:00",
                "end_time": "2023-07-20 00:00",
                "origin_city": "Wuhan",
                "origin_place": "Wuhan Railway Hotel",
                "budget": 99999,
                "check_opening_hours": false,
                "check_meal": false,
                "set_budget": true,
                "type": 3,
                "limit": "money",
                "money_min": 9,
                "money_max": 2021
            },
            "Constraints": {
                "SpotDurationConstraint": [
                    {
                        "spot": "Century Park",
                        "minutes": 270
                    },
                    {
                        "spot": "Longhua Temple",
                        "minutes": 240
                    },
                    {
                        "spot": "Huangpu River Cruise",
                        "minutes": 150
                    },
                    {
                        "spot": "Chimelong Tourist Resort",
                        "minutes": 120
                    },
                    {
                        "spot": "Yuexiu Park",
                        "minutes": 150
                    }
                ]
            }
        },
        "type": 3
    },
    {
        "question": "Bob is going to visit some spots across cities, please make a visit plan for him, including inter-city transportation, intra-city transportation, and visit time for each spot.    The demands are as follows:\n1. He now lives in Guangzhou Railway Hotel in Guangzhou. Every time he takes a train to a city, he lives in f\"{city} Railway Hotel\", such as \"Beijing Railway Hotel\" In Hangzhou, he needs to visit Hefang Street for 210 minutes, West Lake for 210 minutes.In Chengdu, he needs to visit Chengdu Panda Base for 210 minutes, The Chengdu Wuhou Shrine for 270 minutes. And the order can be decided by you.\n2. He is free to travel from 2023.7.1 to 2023.7.20. The budget for transportation is 2700.0 CNY.\n3. Ignore the opening hours of attractions, assuming they are open all day. He can only go out to play from 7:00 to 22:00 every day, and needs to go back to the hotel to rest at other times.\n4. On the basis of completing the above conditions (especially the budget), spend as little time as possible.\n",
        "demands": {
            "TravelSimulator": {
                "begin_time": "2023-07-01 07:00",
                "end_time": "2023-07-20 00:00",
                "origin_city": "Guangzhou",
                "origin_place": "Guangzhou Railway Hotel",
                "budget": 99999,
                "check_opening_hours": false,
                "check_meal": false,
                "set_budget": true,
                "type": 3,
                "limit": "money",
                "money_min": 44,
                "money_max": 2537
            },
            "Constraints": {
                "SpotDurationConstraint": [
                    {
                        "spot": "Hefang Street",
                        "minutes": 210
                    },
                    {
                        "spot": "West Lake",
                        "minutes": 210
                    },
                    {
                        "spot": "Chengdu Panda Base",
                        "minutes": 210
                    },
                    {
                        "spot": "The Chengdu Wuhou Shrine",
                        "minutes": 270
                    }
                ]
            }
        },
        "type": 3
    },
    {
        "question": "Bob is going to visit some spots across cities, please make a visit plan for him, including inter-city transportation, intra-city transportation, and visit time for each spot.    The demands are as follows:\n1. He now lives in Chengdu Railway Hotel in Chengdu. Every time he takes a train to a city, he lives in f\"{city} Railway Hotel\", such as \"Beijing Railway Hotel\" In Chengdu, he needs to visit Du Fu Thatched Cottage for 240 minutes, Chengdu Panda Base for 240 minutes.In Wuhan, he needs to visit Tan Hua Lin for 180 minutes, East Lake for 270 minutes, Baotong Temple for 180 minutes, Yellow Crane Tower for 270 minutes. And the order can be decided by you.\n2. He is free to travel from 2023.7.1 to 2023.7.20. The budget for transportation is 1700.0 CNY.\n3. The daily opening_hours of spots can be obtained from the database table place. \"opening_hours_begin\" and \"opening_hours_end\" are the opening and closing times respectively\n4. On the basis of completing the above conditions (especially the budget), spend as little time as possible.\n",
        "demands": {
            "TravelSimulator": {
                "begin_time": "2023-07-01 07:00",
                "end_time": "2023-07-20 00:00",
                "origin_city": "Chengdu",
                "origin_place": "Chengdu Railway Hotel",
                "budget": 99999,
                "check_opening_hours": true,
                "check_meal": false,
                "set_budget": true,
                "type": 3,
                "limit": "money",
                "money_min": 289,
                "money_max": 1254
            },
            "Constraints": {
                "SpotDurationConstraint": [
                    {
                        "spot": "Du Fu Thatched Cottage",
                        "minutes": 240
                    },
                    {
                        "spot": "Chengdu Panda Base",
                        "minutes": 240
                    },
                    {
                        "spot": "Tan Hua Lin",
                        "minutes": 180
                    },
                    {
                        "spot": "East Lake",
                        "minutes": 270
                    },
                    {
                        "spot": "Baotong Temple",
                        "minutes": 180
                    },
                    {
                        "spot": "Yellow Crane Tower",
                        "minutes": 270
                    }
                ]
            }
        },
        "type": 3
    },
    {
        "question": "Bob is going to visit some spots across cities, please make a visit plan for him, including inter-city transportation, intra-city transportation, and visit time for each spot.    The demands are as follows:\n1. He now lives in Beijing Railway Hotel in Beijing. Every time he takes a train to a city, he lives in f\"{city} Railway Hotel\", such as \"Beijing Railway Hotel\" In Beijing, he needs to visit Shihua Cave for 180 minutes, The Forbidden City for 210 minutes, Tiananmen Square for 240 minutes.In Hangzhou, he needs to visit Quaint Water Towns for 240 minutes, Lingyin Temple for 300 minutes, China National Tea Museum for 210 minutes, Hefang Street for 240 minutes. And the order can be decided by you.\n2. He is free to travel from 2023.7.1 to 2023.7.20. The budget for transportation is 2000.0 CNY.\n3. The daily opening_hours of spots can be obtained from the database table place. \"opening_hours_begin\" and \"opening_hours_end\" are the opening and closing times respectively\n4. On the basis of completing the above conditions (especially the budget), spend as little time as possible.\n",
        "demands": {
            "TravelSimulator": {
                "begin_time": "2023-07-01 07:00",
                "end_time": "2023-07-20 00:00",
                "origin_city": "Beijing",
                "origin_place": "Beijing Railway Hotel",
                "budget": 99999,
                "check_opening_hours": true,
                "check_meal": false,
                "set_budget": true,
                "type": 3,
                "limit": "money",
                "money_min": 390,
                "money_max": 1507
            },
            "Constraints": {
                "SpotDurationConstraint": [
                    {
                        "spot": "Shihua Cave",
                        "minutes": 180
                    },
                    {
                        "spot": "The Forbidden City",
                        "minutes": 210
                    },
                    {
                        "spot": "Tiananmen Square",
                        "minutes": 240
                    },
                    {
                        "spot": "Quaint Water Towns",
                        "minutes": 240
                    },
                    {
                        "spot": "Lingyin Temple",
                        "minutes": 300
                    },
                    {
                        "spot": "China National Tea Museum",
                        "minutes": 210
                    },
                    {
                        "spot": "Hefang Street",
                        "minutes": 240
                    }
                ]
            }
        },
        "type": 3
    },
    {
        "question": "Bob is going to visit some spots across cities, please make a visit plan for him, including inter-city transportation, intra-city transportation, and visit time for each spot.    The demands are as follows:\n1. He now lives in Beijing Railway Hotel in Beijing. Every time he takes a train to a city, he lives in f\"{city} Railway Hotel\", such as \"Beijing Railway Hotel\" In Shanghai, he needs to visit Century Park for 120 minutes, Shanghai Disney for 120 minutes.In Chengdu, he needs to visit Chengdu Tea Houses for 300 minutes, Chengdu Panda Base for 120 minutes. And the order can be decided by you.\n2. He is free to travel from 2023.7.1 to 2023.7.20. The budget for transportation is 3500.0 CNY.\n3. The daily opening_hours of spots can be obtained from the database table place. \"opening_hours_begin\" and \"opening_hours_end\" are the opening and closing times respectively\n4. On the basis of completing the above conditions (especially the budget), spend as little time as possible.\n",
        "demands": {
            "TravelSimulator": {
                "begin_time": "2023-07-01 07:00",
                "end_time": "2023-07-20 00:00",
                "origin_city": "Beijing",
                "origin_place": "Beijing Railway Hotel",
                "budget": 99999,
                "check_opening_hours": true,
                "check_meal": false,
                "set_budget": true,
                "type": 3,
                "limit": "money",
                "money_min": 1158,
                "money_max": 2730
            },
            "Constraints": {
                "SpotDurationConstraint": [
                    {
                        "spot": "Century Park",
                        "minutes": 120
                    },
                    {
                        "spot": "Shanghai Disney",
                        "minutes": 120
                    },
                    {
                        "spot": "Chengdu Tea Houses",
                        "minutes": 300
                    },
                    {
                        "spot": "Chengdu Panda Base",
                        "minutes": 120
                    }
                ]
            }
        },
        "type": 3
    },
    {
        "question": "Bob is going to visit some spots across cities, please make a visit plan for him, including inter-city transportation, intra-city transportation, and visit time for each spot.    The demands are as follows:\n1. He now lives in Guangzhou Railway Hotel in Guangzhou. Every time he takes a train to a city, he lives in f\"{city} Railway Hotel\", such as \"Beijing Railway Hotel\" In Hangzhou, he needs to visit West Lake for 300 minutes, Hefang Street for 120 minutes. And the order can be decided by you.\n2. He is free to travel from 2023.7.1 to 2023.7.20. The budget for transportation is 2700.0 CNY.\n3. The daily opening_hours of spots can be obtained from the database table place. \"opening_hours_begin\" and \"opening_hours_end\" are the opening and closing times respectively\n4. On the basis of completing the above conditions (especially the budget), spend as little time as possible.\n",
        "demands": {
            "TravelSimulator": {
                "begin_time": "2023-07-01 07:00",
                "end_time": "2023-07-20 00:00",
                "origin_city": "Guangzhou",
                "origin_place": "Guangzhou Railway Hotel",
                "budget": 99999,
                "check_opening_hours": true,
                "check_meal": false,
                "set_budget": true,
                "type": 3,
                "limit": "money",
                "money_min": 0,
                "money_max": 2112
            },
            "Constraints": {
                "SpotDurationConstraint": [
                    {
                        "spot": "West Lake",
                        "minutes": 300
                    },
                    {
                        "spot": "Hefang Street",
                        "minutes": 120
                    }
                ]
            }
        },
        "type": 3
    },
    {
        "question": "Bob is going to visit some spots across cities, please make a visit plan for him, including inter-city transportation, intra-city transportation, and visit time for each spot.    The demands are as follows:\n1. He now lives in Shanghai Railway Hotel in Shanghai. Every time he takes a train to a city, he lives in f\"{city} Railway Hotel\", such as \"Beijing Railway Hotel\" In Shanghai, he needs to visit Qibao Ancient Town for 270 minutes, Huangpu River Cruise for 180 minutes, Century Park for 150 minutes, Xintiandi for 300 minutes, Shanghai Disney for 210 minutes.In Guangzhou, he needs to visit Baiyun Mountain for 120 minutes, Canton Tower for 270 minutes. And the order can be decided by you.\n2. 6 days (2023-07-10 00:00 ~ 2023-07-16 00:00) for this trip.\n3. Ignore the opening hours of attractions, assuming they are open all day. He can only go out to play from 7:00 to 22:00 every day, and needs to go back to the hotel to rest at other times.\n4. On the basis of completing the above conditions (especially the time limit), spend as little money as possible.\n",
        "demands": {
            "TravelSimulator": {
                "begin_time": "2023-07-10 00:00",
                "end_time": "2023-07-16 00:00",
                "origin_city": "Shanghai",
                "origin_place": "Shanghai Railway Hotel",
                "budget": 99999,
                "check_opening_hours": false,
                "check_meal": false,
                "set_budget": false,
                "type": 3,
                "limit": "time",
                "time_min": 254333,
                "time_max": 351647
            },
            "Constraints": {
                "SpotDurationConstraint": [
                    {
                        "spot": "Qibao Ancient Town",
                        "minutes": 270
                    },
                    {
                        "spot": "Huangpu River Cruise",
                        "minutes": 180
                    },
                    {
                        "spot": "Century Park",
                        "minutes": 150
                    },
                    {
                        "spot": "Xintiandi",
                        "minutes": 300
                    },
                    {
                        "spot": "Shanghai Disney",
                        "minutes": 210
                    },
                    {
                        "spot": "Baiyun Mountain",
                        "minutes": 120
                    },
                    {
                        "spot": "Canton Tower",
                        "minutes": 270
                    }
                ]
            }
        },
        "type": 3
    },
    {
        "question": "Bob is going to visit some spots across cities, please make a visit plan for him, including inter-city transportation, intra-city transportation, and visit time for each spot.    The demands are as follows:\n1. He now lives in Guangzhou Railway Hotel in Guangzhou. Every time he takes a train to a city, he lives in f\"{city} Railway Hotel\", such as \"Beijing Railway Hotel\" In Guangzhou, he needs to visit Baiyun Mountain for 240 minutes, Chimelong Tourist Resort for 180 minutes.In Nanjing, he needs to visit Taiping Heavenly-Kingdom Palace for 120 minutes, Qinhuai River for 210 minutes, Tomb of Ming Emperor Zhu Yuanzhang for 300 minutes, Bailuzhou Park for 240 minutes, Ming Palace for 270 minutes. And the order can be decided by you.\n2. 6 days (2023-07-04 00:00 ~ 2023-07-10 00:00) for this trip.\n3. Ignore the opening hours of attractions, assuming they are open all day. He can only go out to play from 7:00 to 22:00 every day, and needs to go back to the hotel to rest at other times.\n4. On the basis of completing the above conditions (especially the time limit), spend as little money as possible.\n",
        "demands": {
            "TravelSimulator": {
                "begin_time": "2023-07-04 00:00",
                "end_time": "2023-07-10 00:00",
                "origin_city": "Guangzhou",
                "origin_place": "Guangzhou Railway Hotel",
                "budget": 99999,
                "check_opening_hours": false,
                "check_meal": false,
                "set_budget": false,
                "type": 3,
                "limit": "time",
                "time_min": 272305,
                "time_max": 322566
            },
            "Constraints": {
                "SpotDurationConstraint": [
                    {
                        "spot": "Baiyun Mountain",
                        "minutes": 240
                    },
                    {
                        "spot": "Chimelong Tourist Resort",
                        "minutes": 180
                    },
                    {
                        "spot": "Taiping Heavenly-Kingdom Palace",
                        "minutes": 120
                    },
                    {
                        "spot": "Qinhuai River",
                        "minutes": 210
                    },
                    {
                        "spot": "Tomb of Ming Emperor Zhu Yuanzhang",
                        "minutes": 300
                    },
                    {
                        "spot": "Bailuzhou Park",
                        "minutes": 240
                    },
                    {
                        "spot": "Ming Palace",
                        "minutes": 270
                    }
                ]
            }
        },
        "type": 3
    },
    {
        "question": "Bob is going to visit some spots across cities, please make a visit plan for him, including inter-city transportation, intra-city transportation, and visit time for each spot.    The demands are as follows:\n1. He now lives in Chengdu Railway Hotel in Chengdu. Every time he takes a train to a city, he lives in f\"{city} Railway Hotel\", such as \"Beijing Railway Hotel\" In Shanghai, he needs to visit Huangpu River Cruise for 210 minutes, Shanghai Sightseeing Tunnel for 300 minutes. And the order can be decided by you.\n2. 6 days (2023-07-05 00:00 ~ 2023-07-11 00:00) for this trip.\n3. Ignore the opening hours of attractions, assuming they are open all day. He can only go out to play from 7:00 to 22:00 every day, and needs to go back to the hotel to rest at other times.\n4. On the basis of completing the above conditions (especially the time limit), spend as little money as possible.\n",
        "demands": {
            "TravelSimulator": {
                "begin_time": "2023-07-05 00:00",
                "end_time": "2023-07-11 00:00",
                "origin_city": "Chengdu",
                "origin_place": "Chengdu Railway Hotel",
                "budget": 99999,
                "check_opening_hours": false,
                "check_meal": false,
                "set_budget": false,
                "type": 3,
                "limit": "time",
                "time_min": 126254,
                "time_max": 143245
            },
            "Constraints": {
                "SpotDurationConstraint": [
                    {
                        "spot": "Huangpu River Cruise",
                        "minutes": 210
                    },
                    {
                        "spot": "Shanghai Sightseeing Tunnel",
                        "minutes": 300
                    }
                ]
            }
        },
        "type": 3
    },
    {
        "question": "Bob is going to visit some spots across cities, please make a visit plan for him, including inter-city transportation, intra-city transportation, and visit time for each spot.    The demands are as follows:\n1. He now lives in Nanjing Railway Hotel in Nanjing. Every time he takes a train to a city, he lives in f\"{city} Railway Hotel\", such as \"Beijing Railway Hotel\" In Guangzhou, he needs to visit Canton Tower for 120 minutes, Chimelong Tourist Resort for 270 minutes.In Hangzhou, he needs to visit Quaint Water Towns for 150 minutes, Lingyin Temple for 150 minutes. And the order can be decided by you.\n2. 6 days (2023-07-11 00:00 ~ 2023-07-17 00:00) for this trip.\n3. Ignore the opening hours of attractions, assuming they are open all day. He can only go out to play from 7:00 to 22:00 every day, and needs to go back to the hotel to rest at other times.\n4. On the basis of completing the above conditions (especially the time limit), spend as little money as possible.\n",
        "demands": {
            "TravelSimulator": {
                "begin_time": "2023-07-11 00:00",
                "end_time": "2023-07-17 00:00",
                "origin_city": "Nanjing",
                "origin_place": "Nanjing Railway Hotel",
                "budget": 99999,
                "check_opening_hours": false,
                "check_meal": false,
                "set_budget": false,
                "type": 3,
                "limit": "time",
                "time_min": 70316,
                "time_max": 198351
            },
            "Constraints": {
                "SpotDurationConstraint": [
                    {
                        "spot": "Canton Tower",
                        "minutes": 120
                    },
                    {
                        "spot": "Chimelong Tourist Resort",
                        "minutes": 270
                    },
                    {
                        "spot": "Quaint Water Towns",
                        "minutes": 150
                    },
                    {
                        "spot": "Lingyin Temple",
                        "minutes": 150
                    }
                ]
            }
        },
        "type": 3
    },
    {
        "question": "Bob is going to visit some spots across cities, please make a visit plan for him, including inter-city transportation, intra-city transportation, and visit time for each spot.    The demands are as follows:\n1. He now lives in Chengdu Railway Hotel in Chengdu. Every time he takes a train to a city, he lives in f\"{city} Railway Hotel\", such as \"Beijing Railway Hotel\" In Chengdu, he needs to visit Chengdu Panda Base for 300 minutes, Chengdu Tea Houses for 300 minutes, Du Fu Thatched Cottage for 180 minutes.In Hangzhou, he needs to visit Quaint Water Towns for 210 minutes, West Lake for 210 minutes, Hefang Street for 120 minutes. And the order can be decided by you.\n2. 6 days (2023-07-07 00:00 ~ 2023-07-13 00:00) for this trip.\n3. The daily opening_hours of spots can be obtained from the database table place. \"opening_hours_begin\" and \"opening_hours_end\" are the opening and closing times respectively\n4. On the basis of completing the above conditions (especially the time limit), spend as little money as possible.\n",
        "demands": {
            "TravelSimulator": {
                "begin_time": "2023-07-07 00:00",
                "end_time": "2023-07-13 00:00",
                "origin_city": "Chengdu",
                "origin_place": "Chengdu Railway Hotel",
                "budget": 99999,
                "check_opening_hours": true,
                "check_meal": false,
                "set_budget": false,
                "type": 3,
                "limit": "time",
                "time_min": 200518,
                "time_max": 324505
            },
            "Constraints": {
                "SpotDurationConstraint": [
                    {
                        "spot": "Chengdu Panda Base",
                        "minutes": 300
                    },
                    {
                        "spot": "Chengdu Tea Houses",
                        "minutes": 300
                    },
                    {
                        "spot": "Du Fu Thatched Cottage",
                        "minutes": 180
                    },
                    {
                        "spot": "Quaint Water Towns",
                        "minutes": 210
                    },
                    {
                        "spot": "West Lake",
                        "minutes": 210
                    },
                    {
                        "spot": "Hefang Street",
                        "minutes": 120
                    }
                ]
            }
        },
        "type": 3
    },
    {
        "question": "Bob is going to visit some spots across cities, please make a visit plan for him, including inter-city transportation, intra-city transportation, and visit time for each spot.    The demands are as follows:\n1. He now lives in Nanjing Railway Hotel in Nanjing. Every time he takes a train to a city, he lives in f\"{city} Railway Hotel\", such as \"Beijing Railway Hotel\" In Nanjing, he needs to visit Taiping Heavenly-Kingdom Palace for 270 minutes, Lake Xuanwu for 210 minutes, Bailuzhou Park for 300 minutes.In Beijing, he needs to visit Shihua Cave for 270 minutes, The Great Wall for 300 minutes, The Forbidden City for 150 minutes. And the order can be decided by you.\n2. 6 days (2023-07-05 00:00 ~ 2023-07-11 00:00) for this trip.\n3. The daily opening_hours of spots can be obtained from the database table place. \"opening_hours_begin\" and \"opening_hours_end\" are the opening and closing times respectively\n4. On the basis of completing the above conditions (especially the time limit), spend as little money as possible.\n",
        "demands": {
            "TravelSimulator": {
                "begin_time": "2023-07-05 00:00",
                "end_time": "2023-07-11 00:00",
                "origin_city": "Nanjing",
                "origin_place": "Nanjing Railway Hotel",
                "budget": 99999,
                "check_opening_hours": true,
                "check_meal": false,
                "set_budget": false,
                "type": 3,
                "limit": "time",
                "time_min": 286554,
                "time_max": 315177
            },
            "Constraints": {
                "SpotDurationConstraint": [
                    {
                        "spot": "Taiping Heavenly-Kingdom Palace",
                        "minutes": 270
                    },
                    {
                        "spot": "Lake Xuanwu",
                        "minutes": 210
                    },
                    {
                        "spot": "Bailuzhou Park",
                        "minutes": 300
                    },
                    {
                        "spot": "Shihua Cave",
                        "minutes": 270
                    },
                    {
                        "spot": "The Great Wall",
                        "minutes": 300
                    },
                    {
                        "spot": "The Forbidden City",
                        "minutes": 150
                    }
                ]
            }
        },
        "type": 3
    },
    {
        "question": "Bob is going to visit some spots across cities, please make a visit plan for him, including inter-city transportation, intra-city transportation, and visit time for each spot.    The demands are as follows:\n1. He now lives in Nanjing Railway Hotel in Nanjing. Every time he takes a train to a city, he lives in f\"{city} Railway Hotel\", such as \"Beijing Railway Hotel\" In Hangzhou, he needs to visit China National Tea Museum for 180 minutes, Lingyin Temple for 210 minutes, Quaint Water Towns for 240 minutes. And the order can be decided by you.\n2. 6 days (2023-07-02 00:00 ~ 2023-07-08 00:00) for this trip.\n3. The daily opening_hours of spots can be obtained from the database table place. \"opening_hours_begin\" and \"opening_hours_end\" are the opening and closing times respectively\n4. On the basis of completing the above conditions (especially the time limit), spend as little money as possible.\n",
        "demands": {
            "TravelSimulator": {
                "begin_time": "2023-07-02 00:00",
                "end_time": "2023-07-08 00:00",
                "origin_city": "Nanjing",
                "origin_place": "Nanjing Railway Hotel",
                "budget": 99999,
                "check_opening_hours": true,
                "check_meal": false,
                "set_budget": false,
                "type": 3,
                "limit": "time",
                "time_min": 90462,
                "time_max": 153335
            },
            "Constraints": {
                "SpotDurationConstraint": [
                    {
                        "spot": "China National Tea Museum",
                        "minutes": 180
                    },
                    {
                        "spot": "Lingyin Temple",
                        "minutes": 210
                    },
                    {
                        "spot": "Quaint Water Towns",
                        "minutes": 240
                    }
                ]
            }
        },
        "type": 3
    },
    {
        "question": "Bob is going to visit some spots across cities, please make a visit plan for him, including inter-city transportation, intra-city transportation, and visit time for each spot.    The demands are as follows:\n1. He now lives in Chengdu Railway Hotel in Chengdu. Every time he takes a train to a city, he lives in f\"{city} Railway Hotel\", such as \"Beijing Railway Hotel\" In Shanghai, he needs to visit Century Park for 150 minutes, Xintiandi for 240 minutes. And the order can be decided by you.\n2. 6 days (2023-07-06 00:00 ~ 2023-07-12 00:00) for this trip.\n3. The daily opening_hours of spots can be obtained from the database table place. \"opening_hours_begin\" and \"opening_hours_end\" are the opening and closing times respectively\n4. On the basis of completing the above conditions (especially the time limit), spend as little money as possible.\n",
        "demands": {
            "TravelSimulator": {
                "begin_time": "2023-07-06 00:00",
                "end_time": "2023-07-12 00:00",
                "origin_city": "Chengdu",
                "origin_place": "Chengdu Railway Hotel",
                "budget": 99999,
                "check_opening_hours": true,
                "check_meal": false,
                "set_budget": false,
                "type": 3,
                "limit": "time",
                "time_min": 60048,
                "time_max": 95516
            },
            "Constraints": {
                "SpotDurationConstraint": [
                    {
                        "spot": "Century Park",
                        "minutes": 150
                    },
                    {
                        "spot": "Xintiandi",
                        "minutes": 240
                    }
                ]
            }
        },
        "type": 3
    },
    {
        "question": "Bob is going to visit some spots across cities, please make a visit plan for him, including inter-city transportation, intra-city transportation, and visit time for each spot.    The demands are as follows:\n1. He now lives in Shanghai Railway Hotel in Shanghai. Every time he takes a train to a city, he lives in f\"{city} Railway Hotel\", such as \"Beijing Railway Hotel\" In Beijing, he needs to visit Shihua Cave for 300 minutes, Tiananmen Square for 300 minutes, Beijing Olympic Park for 240 minutes, The Summer Palace for 150 minutes, The Temple of Heaven for 180 minutes, The Forbidden City for 150 minutes, The Great Wall for 120 minutes, Beijing Stone Carvings Art Museum for 210 minutes. And the order can be decided by you.\n2. 7 days (2023-07-06 00:00 ~ 2023-07-13 00:00) for this trip.\n3. Ignore the opening hours of attractions, assuming they are open all day. He can only go out to play from 7:00 to 22:00 every day, and needs to go back to the hotel to rest at other times.\n4. On the basis of completing the above conditions (especially the time limit), spend as little money as possible.\n",
        "demands": {
            "TravelSimulator": {
                "begin_time": "2023-07-06 00:00",
                "end_time": "2023-07-13 00:00",
                "origin_city": "Shanghai",
                "origin_place": "Shanghai Railway Hotel",
                "budget": 99999,
                "check_opening_hours": false,
                "check_meal": false,
                "set_budget": false,
                "type": 3,
                "limit": "time",
                "time_min": 257652,
                "time_max": 382644
            },
            "Constraints": {
                "SpotDurationConstraint": [
                    {
                        "spot": "Shihua Cave",
                        "minutes": 300
                    },
                    {
                        "spot": "Tiananmen Square",
                        "minutes": 300
                    },
                    {
                        "spot": "Beijing Olympic Park",
                        "minutes": 240
                    },
                    {
                        "spot": "The Summer Palace",
                        "minutes": 150
                    },
                    {
                        "spot": "The Temple of Heaven",
                        "minutes": 180
                    },
                    {
                        "spot": "The Forbidden City",
                        "minutes": 150
                    },
                    {
                        "spot": "The Great Wall",
                        "minutes": 120
                    },
                    {
                        "spot": "Beijing Stone Carvings Art Museum",
                        "minutes": 210
                    }
                ]
            }
        },
        "type": 3
    },
    {
        "question": "Bob is going to visit some spots across cities, please make a visit plan for him, including inter-city transportation, intra-city transportation, and visit time for each spot.    The demands are as follows:\n1. He now lives in Hangzhou Railway Hotel in Hangzhou. Every time he takes a train to a city, he lives in f\"{city} Railway Hotel\", such as \"Beijing Railway Hotel\" In Shanghai, he needs to visit Xintiandi for 270 minutes, Shanghai Sightseeing Tunnel for 270 minutes, Century Park for 300 minutes, Longhua Temple for 270 minutes, Shanghai Disney for 120 minutes, Shanghai History Museum for 270 minutes, Qibao Ancient Town for 120 minutes, Huangpu River Cruise for 210 minutes. And the order can be decided by you.\n2. 7 days (2023-07-09 00:00 ~ 2023-07-16 00:00) for this trip.\n3. The daily opening_hours of spots can be obtained from the database table place. \"opening_hours_begin\" and \"opening_hours_end\" are the opening and closing times respectively\n4. On the basis of completing the above conditions (especially the time limit), spend as little money as possible.\n",
        "demands": {
            "TravelSimulator": {
                "begin_time": "2023-07-09 00:00",
                "end_time": "2023-07-16 00:00",
                "origin_city": "Hangzhou",
                "origin_place": "Hangzhou Railway Hotel",
                "budget": 99999,
                "check_opening_hours": true,
                "check_meal": false,
                "set_budget": false,
                "type": 3,
                "limit": "time",
                "time_min": 285889,
                "time_max": 512821
            },
            "Constraints": {
                "SpotDurationConstraint": [
                    {
                        "spot": "Xintiandi",
                        "minutes": 270
                    },
                    {
                        "spot": "Shanghai Sightseeing Tunnel",
                        "minutes": 270
                    },
                    {
                        "spot": "Century Park",
                        "minutes": 300
                    },
                    {
                        "spot": "Longhua Temple",
                        "minutes": 270
                    },
                    {
                        "spot": "Shanghai Disney",
                        "minutes": 120
                    },
                    {
                        "spot": "Shanghai History Museum",
                        "minutes": 270
                    },
                    {
                        "spot": "Qibao Ancient Town",
                        "minutes": 120
                    },
                    {
                        "spot": "Huangpu River Cruise",
                        "minutes": 210
                    }
                ]
            }
        },
        "type": 3
    },
    {
        "question": "Bob is going to visit some spots across cities, please make a visit plan for him, including inter-city transportation, intra-city transportation, and visit time for each spot.    The demands are as follows:\n1. He now lives in Shanghai Railway Hotel in Shanghai. Every time he takes a train to a city, he lives in f\"{city} Railway Hotel\", such as \"Beijing Railway Hotel\" In Shanghai, he needs to visit Qibao Ancient Town for 180 minutes, Century Park for 180 minutes, Xintiandi for 150 minutes, Longhua Temple for 300 minutes, Shanghai History Museum for 150 minutes, Huangpu River Cruise for 300 minutes, Shanghai Disney for 240 minutes, Shanghai Sightseeing Tunnel for 150 minutes.In Hangzhou, he needs to visit China National Tea Museum for 270 minutes, Hefang Street for 150 minutes. And the order can be decided by you.\n2. He is free to travel from 2023.7.1 to 2023.7.20. The budget for transportation is 2100.0 CNY.\n3. Ignore the opening hours of attractions, assuming they are open all day. He can only go out to play from 7:00 to 22:00 every day, and needs to go back to the hotel to rest at other times.\n4. On the basis of completing the above conditions (especially the budget), spend as little time as possible.\n",
        "demands": {
            "TravelSimulator": {
                "begin_time": "2023-07-01 07:00",
                "end_time": "2023-07-20 00:00",
                "origin_city": "Shanghai",
                "origin_place": "Shanghai Railway Hotel",
                "budget": 99999,
                "check_opening_hours": false,
                "check_meal": false,
                "set_budget": true,
                "type": 3,
                "limit": "money",
                "money_min": 34,
                "money_max": 177
            },
            "Constraints": {
                "SpotDurationConstraint": [
                    {
                        "spot": "Qibao Ancient Town",
                        "minutes": 180
                    },
                    {
                        "spot": "Century Park",
                        "minutes": 180
                    },
                    {
                        "spot": "Xintiandi",
                        "minutes": 150
                    },
                    {
                        "spot": "Longhua Temple",
                        "minutes": 300
                    },
                    {
                        "spot": "Shanghai History Museum",
                        "minutes": 150
                    },
                    {
                        "spot": "Huangpu River Cruise",
                        "minutes": 300
                    },
                    {
                        "spot": "Shanghai Disney",
                        "minutes": 240
                    },
                    {
                        "spot": "Shanghai Sightseeing Tunnel",
                        "minutes": 150
                    },
                    {
                        "spot": "China National Tea Museum",
                        "minutes": 270
                    },
                    {
                        "spot": "Hefang Street",
                        "minutes": 150
                    }
                ]
            }
        },
        "type": 3
    },
    {
        "question": "Bob is going to visit some spots across cities, please make a visit plan for him, including inter-city transportation, intra-city transportation, and visit time for each spot.    The demands are as follows:\n1. He now lives in Chengdu Railway Hotel in Chengdu. Every time he takes a train to a city, he lives in f\"{city} Railway Hotel\", such as \"Beijing Railway Hotel\" In Chengdu, he needs to visit The Chengdu Wuhou Shrine for 210 minutes, Chengdu Panda Base for 270 minutes, Leshan Giant Buddha for 300 minutes, Du Fu Thatched Cottage for 270 minutes. And the order can be decided by you.\n2. He is free to travel from 2023.7.1 to 2023.7.20. The budget for transportation is 1900 CNY.\n3. Ignore the opening hours of attractions, assuming they are open all day. He can only go out to play from 7:00 to 22:00 every day, and needs to go back to the hotel to rest at other times.\n4. On the basis of completing the above conditions (especially the budget), spend as little time as possible.\n",
        "demands": {
            "TravelSimulator": {
                "begin_time": "2023-07-01 07:00",
                "end_time": "2023-07-20 00:00",
                "origin_city": "Chengdu",
                "origin_place": "Chengdu Railway Hotel",
                "budget": 99999,
                "check_opening_hours": false,
                "check_meal": false,
                "set_budget": true,
                "type": 3,
                "limit": "money",
                "money_min": 0,
                "money_max": 0
            },
            "Constraints": {
                "SpotDurationConstraint": [
                    {
                        "spot": "The Chengdu Wuhou Shrine",
                        "minutes": 210
                    },
                    {
                        "spot": "Chengdu Panda Base",
                        "minutes": 270
                    },
                    {
                        "spot": "Leshan Giant Buddha",
                        "minutes": 300
                    },
                    {
                        "spot": "Du Fu Thatched Cottage",
                        "minutes": 270
                    }
                ]
            }
        },
        "type": 3
    },
    {
        "question": "Bob is going to visit some spots across cities, please make a visit plan for him, including inter-city transportation, intra-city transportation, and visit time for each spot.    The demands are as follows:\n1. He now lives in Chengdu Railway Hotel in Chengdu. Every time he takes a train to a city, he lives in f\"{city} Railway Hotel\", such as \"Beijing Railway Hotel\" In Hangzhou, he needs to visit Hefang Street for 240 minutes, China National Tea Museum for 300 minutes, West Lake for 300 minutes.In Guangzhou, he needs to visit Canton Tower for 120 minutes, Baiyun Mountain for 120 minutes, Chimelong Tourist Resort for 210 minutes, Yuexiu Park for 240 minutes. And the order can be decided by you.\n2. He is free to travel from 2023.7.1 to 2023.7.20. The budget for transportation is 2900.0 CNY.\n3. Ignore the opening hours of attractions, assuming they are open all day. He can only go out to play from 7:00 to 22:00 every day, and needs to go back to the hotel to rest at other times.\n4. On the basis of completing the above conditions (especially the budget), spend as little time as possible.\n",
        "demands": {
            "TravelSimulator": {
                "begin_time": "2023-07-01 07:00",
                "end_time": "2023-07-20 00:00",
                "origin_city": "Chengdu",
                "origin_place": "Chengdu Railway Hotel",
                "budget": 99999,
                "check_opening_hours": false,
                "check_meal": false,
                "set_budget": true,
                "type": 3,
                "limit": "money",
                "money_min": 263,
                "money_max": 2784
            },
            "Constraints": {
                "SpotDurationConstraint": [
                    {
                        "spot": "Hefang Street",
                        "minutes": 240
                    },
                    {
                        "spot": "China National Tea Museum",
                        "minutes": 300
                    },
                    {
                        "spot": "West Lake",
                        "minutes": 300
                    },
                    {
                        "spot": "Canton Tower",
                        "minutes": 120
                    },
                    {
                        "spot": "Baiyun Mountain",
                        "minutes": 120
                    },
                    {
                        "spot": "Chimelong Tourist Resort",
                        "minutes": 210
                    },
                    {
                        "spot": "Yuexiu Park",
                        "minutes": 240
                    }
                ]
            }
        },
        "type": 3
    },
    {
        "question": "Bob is going to visit some spots across cities, please make a visit plan for him, including inter-city transportation, intra-city transportation, and visit time for each spot.    The demands are as follows:\n1. He now lives in Wuhan Railway Hotel in Wuhan. Every time he takes a train to a city, he lives in f\"{city} Railway Hotel\", such as \"Beijing Railway Hotel\" In Guangzhou, he needs to visit Chimelong Tourist Resort for 120 minutes, Canton Tower for 300 minutes.In Nanjing, he needs to visit Bailuzhou Park for 240 minutes, Lake Xuanwu for 300 minutes, Qinhuai River for 300 minutes, Ming Palace for 120 minutes. And the order can be decided by you.\n2. He is free to travel from 2023.7.1 to 2023.7.20. The budget for transportation is 2400.0 CNY.\n3. Ignore the opening hours of attractions, assuming they are open all day. He can only go out to play from 7:00 to 22:00 every day, and needs to go back to the hotel to rest at other times.\n4. On the basis of completing the above conditions (especially the budget), spend as little time as possible.\n",
        "demands": {
            "TravelSimulator": {
                "begin_time": "2023-07-01 07:00",
                "end_time": "2023-07-20 00:00",
                "origin_city": "Wuhan",
                "origin_place": "Wuhan Railway Hotel",
                "budget": 99999,
                "check_opening_hours": false,
                "check_meal": false,
                "set_budget": true,
                "type": 3,
                "limit": "money",
                "money_min": 163,
                "money_max": 1418
            },
            "Constraints": {
                "SpotDurationConstraint": [
                    {
                        "spot": "Chimelong Tourist Resort",
                        "minutes": 120
                    },
                    {
                        "spot": "Canton Tower",
                        "minutes": 300
                    },
                    {
                        "spot": "Bailuzhou Park",
                        "minutes": 240
                    },
                    {
                        "spot": "Lake Xuanwu",
                        "minutes": 300
                    },
                    {
                        "spot": "Qinhuai River",
                        "minutes": 300
                    },
                    {
                        "spot": "Ming Palace",
                        "minutes": 120
                    }
                ]
            }
        },
        "type": 3
    },
    {
        "question": "Bob is going to visit some spots across cities, please make a visit plan for him, including inter-city transportation, intra-city transportation, and visit time for each spot.    The demands are as follows:\n1. He now lives in Hangzhou Railway Hotel in Hangzhou. Every time he takes a train to a city, he lives in f\"{city} Railway Hotel\", such as \"Beijing Railway Hotel\" In Hangzhou, he needs to visit Hefang Street for 120 minutes, Lingyin Temple for 240 minutes.In Beijing, he needs to visit The Forbidden City for 120 minutes, Shihua Cave for 180 minutes, The Great Wall for 240 minutes, The Summer Palace for 120 minutes, The Temple of Heaven for 150 minutes, Beijing Olympic Park for 300 minutes, Beijing Stone Carvings Art Museum for 180 minutes. And the order can be decided by you.\n2. He is free to travel from 2023.7.1 to 2023.7.20. The budget for transportation is 2500.0 CNY.\n3. The daily opening_hours of spots can be obtained from the database table place. \"opening_hours_begin\" and \"opening_hours_end\" are the opening and closing times respectively\n4. On the basis of completing the above conditions (especially the budget), spend as little time as possible.\n",
        "demands": {
            "TravelSimulator": {
                "begin_time": "2023-07-01 07:00",
                "end_time": "2023-07-20 00:00",
                "origin_city": "Hangzhou",
                "origin_place": "Hangzhou Railway Hotel",
                "budget": 99999,
                "check_opening_hours": true,
                "check_meal": false,
                "set_budget": true,
                "type": 3,
                "limit": "money",
                "money_min": 390,
                "money_max": 1507
            },
            "Constraints": {
                "SpotDurationConstraint": [
                    {
                        "spot": "Hefang Street",
                        "minutes": 120
                    },
                    {
                        "spot": "Lingyin Temple",
                        "minutes": 240
                    },
                    {
                        "spot": "The Forbidden City",
                        "minutes": 120
                    },
                    {
                        "spot": "Shihua Cave",
                        "minutes": 180
                    },
                    {
                        "spot": "The Great Wall",
                        "minutes": 240
                    },
                    {
                        "spot": "The Summer Palace",
                        "minutes": 120
                    },
                    {
                        "spot": "The Temple of Heaven",
                        "minutes": 150
                    },
                    {
                        "spot": "Beijing Olympic Park",
                        "minutes": 300
                    },
                    {
                        "spot": "Beijing Stone Carvings Art Museum",
                        "minutes": 180
                    }
                ]
            }
        },
        "type": 3
    },
    {
        "question": "Bob is going to visit some spots across cities, please make a visit plan for him, including inter-city transportation, intra-city transportation, and visit time for each spot.    The demands are as follows:\n1. He now lives in Chengdu Railway Hotel in Chengdu. Every time he takes a train to a city, he lives in f\"{city} Railway Hotel\", such as \"Beijing Railway Hotel\" In Chengdu, he needs to visit Chengdu Tea Houses for 150 minutes, Chengdu Panda Base for 210 minutes, The Chengdu Wuhou Shrine for 120 minutes, Leshan Giant Buddha for 300 minutes.In Shanghai, he needs to visit Xintiandi for 150 minutes, Longhua Temple for 300 minutes, Century Park for 120 minutes, Qibao Ancient Town for 180 minutes. And the order can be decided by you.\n2. He is free to travel from 2023.7.1 to 2023.7.20. The budget for transportation is 2600.0 CNY.\n3. The daily opening_hours of spots can be obtained from the database table place. \"opening_hours_begin\" and \"opening_hours_end\" are the opening and closing times respectively\n4. On the basis of completing the above conditions (especially the budget), spend as little time as possible.\n",
        "demands": {
            "TravelSimulator": {
                "begin_time": "2023-07-01 07:00",
                "end_time": "2023-07-20 00:00",
                "origin_city": "Chengdu",
                "origin_place": "Chengdu Railway Hotel",
                "budget": 99999,
                "check_opening_hours": true,
                "check_meal": false,
                "set_budget": true,
                "type": 3,
                "limit": "money",
                "money_min": 940,
                "money_max": 2378
            },
            "Constraints": {
                "SpotDurationConstraint": [
                    {
                        "spot": "Chengdu Tea Houses",
                        "minutes": 150
                    },
                    {
                        "spot": "Chengdu Panda Base",
                        "minutes": 210
                    },
                    {
                        "spot": "The Chengdu Wuhou Shrine",
                        "minutes": 120
                    },
                    {
                        "spot": "Leshan Giant Buddha",
                        "minutes": 300
                    },
                    {
                        "spot": "Xintiandi",
                        "minutes": 150
                    },
                    {
                        "spot": "Longhua Temple",
                        "minutes": 300
                    },
                    {
                        "spot": "Century Park",
                        "minutes": 120
                    },
                    {
                        "spot": "Qibao Ancient Town",
                        "minutes": 180
                    }
                ]
            }
        },
        "type": 3
    },
    {
        "question": "Bob is going to visit some spots across cities, please make a visit plan for him, including inter-city transportation, intra-city transportation, and visit time for each spot.    The demands are as follows:\n1. He now lives in Guangzhou Railway Hotel in Guangzhou. Every time he takes a train to a city, he lives in f\"{city} Railway Hotel\", such as \"Beijing Railway Hotel\" In Wuhan, he needs to visit East Lake for 210 minutes, Hubu Alley for 300 minutes, Baotong Temple for 240 minutes.In Beijing, he needs to visit The Summer Palace for 240 minutes, Beijing Stone Carvings Art Museum for 300 minutes, The Forbidden City for 300 minutes, Tiananmen Square for 240 minutes. And the order can be decided by you.\n2. He is free to travel from 2023.7.1 to 2023.7.20. The budget for transportation is 3200.0 CNY.\n3. The daily opening_hours of spots can be obtained from the database table place. \"opening_hours_begin\" and \"opening_hours_end\" are the opening and closing times respectively\n4. On the basis of completing the above conditions (especially the budget), spend as little time as possible.\n",
        "demands": {
            "TravelSimulator": {
                "begin_time": "2023-07-01 07:00",
                "end_time": "2023-07-20 00:00",
                "origin_city": "Guangzhou",
                "origin_place": "Guangzhou Railway Hotel",
                "budget": 99999,
                "check_opening_hours": true,
                "check_meal": false,
                "set_budget": true,
                "type": 3,
                "limit": "money",
                "money_min": 175,
                "money_max": 1887
            },
            "Constraints": {
                "SpotDurationConstraint": [
                    {
                        "spot": "East Lake",
                        "minutes": 210
                    },
                    {
                        "spot": "Hubu Alley",
                        "minutes": 300
                    },
                    {
                        "spot": "Baotong Temple",
                        "minutes": 240
                    },
                    {
                        "spot": "The Summer Palace",
                        "minutes": 240
                    },
                    {
                        "spot": "Beijing Stone Carvings Art Museum",
                        "minutes": 300
                    },
                    {
                        "spot": "The Forbidden City",
                        "minutes": 300
                    },
                    {
                        "spot": "Tiananmen Square",
                        "minutes": 240
                    }
                ]
            }
        },
        "type": 3
    },
    {
        "question": "Bob is going to visit some spots across cities, please make a visit plan for him, including inter-city transportation, intra-city transportation, and visit time for each spot.    The demands are as follows:\n1. He now lives in Hangzhou Railway Hotel in Hangzhou. Every time he takes a train to a city, he lives in f\"{city} Railway Hotel\", such as \"Beijing Railway Hotel\" In Guangzhou, he needs to visit Yuexiu Park for 120 minutes, Chimelong Tourist Resort for 210 minutes, Canton Tower for 150 minutes, Huacheng Square for 150 minutes.In Wuhan, he needs to visit Tan Hua Lin for 270 minutes, Yellow Crane Tower for 240 minutes. And the order can be decided by you.\n2. He is free to travel from 2023.7.1 to 2023.7.20. The budget for transportation is 2200.0 CNY.\n3. The daily opening_hours of spots can be obtained from the database table place. \"opening_hours_begin\" and \"opening_hours_end\" are the opening and closing times respectively\n4. On the basis of completing the above conditions (especially the budget), spend as little time as possible.\n",
        "demands": {
            "TravelSimulator": {
                "begin_time": "2023-07-01 07:00",
                "end_time": "2023-07-20 00:00",
                "origin_city": "Hangzhou",
                "origin_place": "Hangzhou Railway Hotel",
                "budget": 99999,
                "check_opening_hours": true,
                "check_meal": false,
                "set_budget": true,
                "type": 3,
                "limit": "money",
                "money_min": 356,
                "money_max": 1664
            },
            "Constraints": {
                "SpotDurationConstraint": [
                    {
                        "spot": "Yuexiu Park",
                        "minutes": 120
                    },
                    {
                        "spot": "Chimelong Tourist Resort",
                        "minutes": 210
                    },
                    {
                        "spot": "Canton Tower",
                        "minutes": 150
                    },
                    {
                        "spot": "Huacheng Square",
                        "minutes": 150
                    },
                    {
                        "spot": "Tan Hua Lin",
                        "minutes": 270
                    },
                    {
                        "spot": "Yellow Crane Tower",
                        "minutes": 240
                    }
                ]
            }
        },
        "type": 3
    },
    {
        "question": "Bob is going to visit some spots across cities, please make a visit plan for him, including inter-city transportation, intra-city transportation, and visit time for each spot.    The demands are as follows:\n1. He now lives in Beijing Railway Hotel in Beijing. Every time he takes a train to a city, he lives in f\"{city} Railway Hotel\", such as \"Beijing Railway Hotel\" In Beijing, he needs to visit Shihua Cave for 120 minutes, The Great Wall for 270 minutes, The Temple of Heaven for 120 minutes, Tiananmen Square for 210 minutes, The Forbidden City for 270 minutes, Beijing Stone Carvings Art Museum for 210 minutes, Beijing Olympic Park for 240 minutes, The Summer Palace for 150 minutes.In Wuhan, he needs to visit Yellow Crane Tower for 180 minutes, Baotong Temple for 180 minutes. And the order can be decided by you.\n2. 7 days (2023-07-10 00:00 ~ 2023-07-17 00:00) for this trip.\n3. Ignore the opening hours of attractions, assuming they are open all day. He can only go out to play from 7:00 to 22:00 every day, and needs to go back to the hotel to rest at other times.\n4. On the basis of completing the above conditions (especially the time limit), spend as little money as possible.\n",
        "demands": {
            "TravelSimulator": {
                "begin_time": "2023-07-10 00:00",
                "end_time": "2023-07-17 00:00",
                "origin_city": "Beijing",
                "origin_place": "Beijing Railway Hotel",
                "budget": 99999,
                "check_opening_hours": false,
                "check_meal": false,
                "set_budget": false,
                "type": 3,
                "limit": "time",
                "time_min": 386733,
                "time_max": 405038
            },
            "Constraints": {
                "SpotDurationConstraint": [
                    {
                        "spot": "Shihua Cave",
                        "minutes": 120
                    },
                    {
                        "spot": "The Great Wall",
                        "minutes": 270
                    },
                    {
                        "spot": "The Temple of Heaven",
                        "minutes": 120
                    },
                    {
                        "spot": "Tiananmen Square",
                        "minutes": 210
                    },
                    {
                        "spot": "The Forbidden City",
                        "minutes": 270
                    },
                    {
                        "spot": "Beijing Stone Carvings Art Museum",
                        "minutes": 210
                    },
                    {
                        "spot": "Beijing Olympic Park",
                        "minutes": 240
                    },
                    {
                        "spot": "The Summer Palace",
                        "minutes": 150
                    },
                    {
                        "spot": "Yellow Crane Tower",
                        "minutes": 180
                    },
                    {
                        "spot": "Baotong Temple",
                        "minutes": 180
                    }
                ]
            }
        },
        "type": 3
    },
    {
        "question": "Bob is going to visit some spots across cities, please make a visit plan for him, including inter-city transportation, intra-city transportation, and visit time for each spot.    The demands are as follows:\n1. He now lives in Wuhan Railway Hotel in Wuhan. Every time he takes a train to a city, he lives in f\"{city} Railway Hotel\", such as \"Beijing Railway Hotel\" In Wuhan, he needs to visit Han Show for 120 minutes, Yellow Crane Tower for 270 minutes, Baotong Temple for 120 minutes, Hubu Alley for 210 minutes.In Beijing, he needs to visit Tiananmen Square for 180 minutes, The Summer Palace for 270 minutes, The Temple of Heaven for 210 minutes, Shihua Cave for 180 minutes, The Forbidden City for 270 minutes. And the order can be decided by you.\n2. 7 days (2023-07-02 00:00 ~ 2023-07-09 00:00) for this trip.\n3. Ignore the opening hours of attractions, assuming they are open all day. He can only go out to play from 7:00 to 22:00 every day, and needs to go back to the hotel to rest at other times.\n4. On the basis of completing the above conditions (especially the time limit), spend as little money as possible.\n",
        "demands": {
            "TravelSimulator": {
                "begin_time": "2023-07-02 00:00",
                "end_time": "2023-07-09 00:00",
                "origin_city": "Wuhan",
                "origin_place": "Wuhan Railway Hotel",
                "budget": 99999,
                "check_opening_hours": false,
                "check_meal": false,
                "set_budget": false,
                "type": 3,
                "limit": "time",
                "time_min": 337464,
                "time_max": 379744
            },
            "Constraints": {
                "SpotDurationConstraint": [
                    {
                        "spot": "Han Show",
                        "minutes": 120
                    },
                    {
                        "spot": "Yellow Crane Tower",
                        "minutes": 270
                    },
                    {
                        "spot": "Baotong Temple",
                        "minutes": 120
                    },
                    {
                        "spot": "Hubu Alley",
                        "minutes": 210
                    },
                    {
                        "spot": "Tiananmen Square",
                        "minutes": 180
                    },
                    {
                        "spot": "The Summer Palace",
                        "minutes": 270
                    },
                    {
                        "spot": "The Temple of Heaven",
                        "minutes": 210
                    },
                    {
                        "spot": "Shihua Cave",
                        "minutes": 180
                    },
                    {
                        "spot": "The Forbidden City",
                        "minutes": 270
                    }
                ]
            }
        },
        "type": 3
    },
    {
        "question": "Bob is going to visit some spots across cities, please make a visit plan for him, including inter-city transportation, intra-city transportation, and visit time for each spot.    The demands are as follows:\n1. He now lives in Beijing Railway Hotel in Beijing. Every time he takes a train to a city, he lives in f\"{city} Railway Hotel\", such as \"Beijing Railway Hotel\" In Shanghai, he needs to visit Century Park for 300 minutes, Xintiandi for 120 minutes.In Chengdu, he needs to visit Leshan Giant Buddha for 150 minutes, The Chengdu Wuhou Shrine for 300 minutes, Chengdu Panda Base for 300 minutes, Chengdu Tea Houses for 150 minutes. And the order can be decided by you.\n2. 7 days (2023-07-06 00:00 ~ 2023-07-13 00:00) for this trip.\n3. Ignore the opening hours of attractions, assuming they are open all day. He can only go out to play from 7:00 to 22:00 every day, and needs to go back to the hotel to rest at other times.\n4. On the basis of completing the above conditions (especially the time limit), spend as little money as possible.\n",
        "demands": {
            "TravelSimulator": {
                "begin_time": "2023-07-06 00:00",
                "end_time": "2023-07-13 00:00",
                "origin_city": "Beijing",
                "origin_place": "Beijing Railway Hotel",
                "budget": 99999,
                "check_opening_hours": false,
                "check_meal": false,
                "set_budget": false,
                "type": 3,
                "limit": "time",
                "time_min": 158631,
                "time_max": 347710
            },
            "Constraints": {
                "SpotDurationConstraint": [
                    {
                        "spot": "Century Park",
                        "minutes": 300
                    },
                    {
                        "spot": "Xintiandi",
                        "minutes": 120
                    },
                    {
                        "spot": "Leshan Giant Buddha",
                        "minutes": 150
                    },
                    {
                        "spot": "The Chengdu Wuhou Shrine",
                        "minutes": 300
                    },
                    {
                        "spot": "Chengdu Panda Base",
                        "minutes": 300
                    },
                    {
                        "spot": "Chengdu Tea Houses",
                        "minutes": 150
                    }
                ]
            }
        },
        "type": 3
    },
    {
        "question": "Bob is going to visit some spots across cities, please make a visit plan for him, including inter-city transportation, intra-city transportation, and visit time for each spot.    The demands are as follows:\n1. He now lives in Chengdu Railway Hotel in Chengdu. Every time he takes a train to a city, he lives in f\"{city} Railway Hotel\", such as \"Beijing Railway Hotel\" In Hangzhou, he needs to visit Hefang Street for 210 minutes, West Lake for 300 minutes, China National Tea Museum for 300 minutes, Quaint Water Towns for 180 minutes.In Beijing, he needs to visit The Forbidden City for 240 minutes, Tiananmen Square for 150 minutes. And the order can be decided by you.\n2. 7 days (2023-07-08 00:00 ~ 2023-07-15 00:00) for this trip.\n3. Ignore the opening hours of attractions, assuming they are open all day. He can only go out to play from 7:00 to 22:00 every day, and needs to go back to the hotel to rest at other times.\n4. On the basis of completing the above conditions (especially the time limit), spend as little money as possible.\n",
        "demands": {
            "TravelSimulator": {
                "begin_time": "2023-07-08 00:00",
                "end_time": "2023-07-15 00:00",
                "origin_city": "Chengdu",
                "origin_place": "Chengdu Railway Hotel",
                "budget": 99999,
                "check_opening_hours": false,
                "check_meal": false,
                "set_budget": false,
                "type": 3,
                "limit": "time",
                "time_min": 183987,
                "time_max": 340771
            },
            "Constraints": {
                "SpotDurationConstraint": [
                    {
                        "spot": "Hefang Street",
                        "minutes": 210
                    },
                    {
                        "spot": "West Lake",
                        "minutes": 300
                    },
                    {
                        "spot": "China National Tea Museum",
                        "minutes": 300
                    },
                    {
                        "spot": "Quaint Water Towns",
                        "minutes": 180
                    },
                    {
                        "spot": "The Forbidden City",
                        "minutes": 240
                    },
                    {
                        "spot": "Tiananmen Square",
                        "minutes": 150
                    }
                ]
            }
        },
        "type": 3
    },
    {
        "question": "Bob is going to visit some spots across cities, please make a visit plan for him, including inter-city transportation, intra-city transportation, and visit time for each spot.    The demands are as follows:\n1. He now lives in Beijing Railway Hotel in Beijing. Every time he takes a train to a city, he lives in f\"{city} Railway Hotel\", such as \"Beijing Railway Hotel\" In Beijing, he needs to visit The Summer Palace for 210 minutes, The Great Wall for 270 minutes, The Temple of Heaven for 210 minutes.In Wuhan, he needs to visit Hubu Alley for 120 minutes, East Lake for 240 minutes, Baotong Temple for 150 minutes, Yellow Crane Tower for 180 minutes, Han Show for 300 minutes, Tan Hua Lin for 210 minutes. And the order can be decided by you.\n2. 7 days (2023-07-06 00:00 ~ 2023-07-13 00:00) for this trip.\n3. The daily opening_hours of spots can be obtained from the database table place. \"opening_hours_begin\" and \"opening_hours_end\" are the opening and closing times respectively\n4. On the basis of completing the above conditions (especially the time limit), spend as little money as possible.\n",
        "demands": {
            "TravelSimulator": {
                "begin_time": "2023-07-06 00:00",
                "end_time": "2023-07-13 00:00",
                "origin_city": "Beijing",
                "origin_place": "Beijing Railway Hotel",
                "budget": 99999,
                "check_opening_hours": true,
                "check_meal": false,
                "set_budget": false,
                "type": 3,
                "limit": "time",
                "time_min": 285828,
                "time_max": 440307
            },
            "Constraints": {
                "SpotDurationConstraint": [
                    {
                        "spot": "The Summer Palace",
                        "minutes": 210
                    },
                    {
                        "spot": "The Great Wall",
                        "minutes": 270
                    },
                    {
                        "spot": "The Temple of Heaven",
                        "minutes": 210
                    },
                    {
                        "spot": "Hubu Alley",
                        "minutes": 120
                    },
                    {
                        "spot": "East Lake",
                        "minutes": 240
                    },
                    {
                        "spot": "Baotong Temple",
                        "minutes": 150
                    },
                    {
                        "spot": "Yellow Crane Tower",
                        "minutes": 180
                    },
                    {
                        "spot": "Han Show",
                        "minutes": 300
                    },
                    {
                        "spot": "Tan Hua Lin",
                        "minutes": 210
                    }
                ]
            }
        },
        "type": 3
    },
    {
        "question": "Bob is going to visit some spots across cities, please make a visit plan for him, including inter-city transportation, intra-city transportation, and visit time for each spot.    The demands are as follows:\n1. He now lives in Guangzhou Railway Hotel in Guangzhou. Every time he takes a train to a city, he lives in f\"{city} Railway Hotel\", such as \"Beijing Railway Hotel\" In Guangzhou, he needs to visit Yuexiu Park for 300 minutes, Baiyun Mountain for 240 minutes, Huacheng Square for 150 minutes.In Chengdu, he needs to visit Chengdu Panda Base for 270 minutes, The Chengdu Wuhou Shrine for 180 minutes, Leshan Giant Buddha for 120 minutes, Chengdu Tea Houses for 270 minutes, Du Fu Thatched Cottage for 180 minutes. And the order can be decided by you.\n2. 7 days (2023-07-10 00:00 ~ 2023-07-17 00:00) for this trip.\n3. The daily opening_hours of spots can be obtained from the database table place. \"opening_hours_begin\" and \"opening_hours_end\" are the opening and closing times respectively\n4. On the basis of completing the above conditions (especially the time limit), spend as little money as possible.\n",
        "demands": {
            "TravelSimulator": {
                "begin_time": "2023-07-10 00:00",
                "end_time": "2023-07-17 00:00",
                "origin_city": "Guangzhou",
                "origin_place": "Guangzhou Railway Hotel",
                "budget": 99999,
                "check_opening_hours": true,
                "check_meal": false,
                "set_budget": false,
                "type": 3,
                "limit": "time",
                "time_min": 339971,
                "time_max": 415333
            },
            "Constraints": {
                "SpotDurationConstraint": [
                    {
                        "spot": "Yuexiu Park",
                        "minutes": 300
                    },
                    {
                        "spot": "Baiyun Mountain",
                        "minutes": 240
                    },
                    {
                        "spot": "Huacheng Square",
                        "minutes": 150
                    },
                    {
                        "spot": "Chengdu Panda Base",
                        "minutes": 270
                    },
                    {
                        "spot": "The Chengdu Wuhou Shrine",
                        "minutes": 180
                    },
                    {
                        "spot": "Leshan Giant Buddha",
                        "minutes": 120
                    },
                    {
                        "spot": "Chengdu Tea Houses",
                        "minutes": 270
                    },
                    {
                        "spot": "Du Fu Thatched Cottage",
                        "minutes": 180
                    }
                ]
            }
        },
        "type": 3
    },
    {
        "question": "Bob is going to visit some spots across cities, please make a visit plan for him, including inter-city transportation, intra-city transportation, and visit time for each spot.    The demands are as follows:\n1. He now lives in Guangzhou Railway Hotel in Guangzhou. Every time he takes a train to a city, he lives in f\"{city} Railway Hotel\", such as \"Beijing Railway Hotel\" In Shanghai, he needs to visit Century Park for 180 minutes, Huangpu River Cruise for 300 minutes.In Wuhan, he needs to visit East Lake for 240 minutes, Hubu Alley for 300 minutes, Tan Hua Lin for 180 minutes, Baotong Temple for 180 minutes, Han Show for 300 minutes. And the order can be decided by you.\n2. 7 days (2023-07-07 00:00 ~ 2023-07-14 00:00) for this trip.\n3. The daily opening_hours of spots can be obtained from the database table place. \"opening_hours_begin\" and \"opening_hours_end\" are the opening and closing times respectively\n4. On the basis of completing the above conditions (especially the time limit), spend as little money as possible.\n",
        "demands": {
            "TravelSimulator": {
                "begin_time": "2023-07-07 00:00",
                "end_time": "2023-07-14 00:00",
                "origin_city": "Guangzhou",
                "origin_place": "Guangzhou Railway Hotel",
                "budget": 99999,
                "check_opening_hours": true,
                "check_meal": false,
                "set_budget": false,
                "type": 3,
                "limit": "time",
                "time_min": 296522,
                "time_max": 363181
            },
            "Constraints": {
                "SpotDurationConstraint": [
                    {
                        "spot": "Century Park",
                        "minutes": 180
                    },
                    {
                        "spot": "Huangpu River Cruise",
                        "minutes": 300
                    },
                    {
                        "spot": "East Lake",
                        "minutes": 240
                    },
                    {
                        "spot": "Hubu Alley",
                        "minutes": 300
                    },
                    {
                        "spot": "Tan Hua Lin",
                        "minutes": 180
                    },
                    {
                        "spot": "Baotong Temple",
                        "minutes": 180
                    },
                    {
                        "spot": "Han Show",
                        "minutes": 300
                    }
                ]
            }
        },
        "type": 3
    },
    {
        "question": "Bob is going to visit some spots across cities, please make a visit plan for him, including inter-city transportation, intra-city transportation, and visit time for each spot.    The demands are as follows:\n1. He now lives in Nanjing Railway Hotel in Nanjing. Every time he takes a train to a city, he lives in f\"{city} Railway Hotel\", such as \"Beijing Railway Hotel\" In Shanghai, he needs to visit Xintiandi for 270 minutes, Shanghai History Museum for 240 minutes.In Guangzhou, he needs to visit Canton Tower for 300 minutes, Chimelong Tourist Resort for 270 minutes, Baiyun Mountain for 210 minutes, Huacheng Square for 180 minutes. And the order can be decided by you.\n2. 7 days (2023-07-03 00:00 ~ 2023-07-10 00:00) for this trip.\n3. The daily opening_hours of spots can be obtained from the database table place. \"opening_hours_begin\" and \"opening_hours_end\" are the opening and closing times respectively\n4. On the basis of completing the above conditions (especially the time limit), spend as little money as possible.\n",
        "demands": {
            "TravelSimulator": {
                "begin_time": "2023-07-03 00:00",
                "end_time": "2023-07-10 00:00",
                "origin_city": "Nanjing",
                "origin_place": "Nanjing Railway Hotel",
                "budget": 99999,
                "check_opening_hours": true,
                "check_meal": false,
                "set_budget": false,
                "type": 3,
                "limit": "time",
                "time_min": 197566,
                "time_max": 380904
            },
            "Constraints": {
                "SpotDurationConstraint": [
                    {
                        "spot": "Xintiandi",
                        "minutes": 270
                    },
                    {
                        "spot": "Shanghai History Museum",
                        "minutes": 240
                    },
                    {
                        "spot": "Canton Tower",
                        "minutes": 300
                    },
                    {
                        "spot": "Chimelong Tourist Resort",
                        "minutes": 270
                    },
                    {
                        "spot": "Baiyun Mountain",
                        "minutes": 210
                    },
                    {
                        "spot": "Huacheng Square",
                        "minutes": 180
                    }
                ]
            }
        },
        "type": 3
    },
    {
        "question": "Bob is going to visit some spots across cities, please make a visit plan for him, including inter-city transportation, intra-city transportation, and visit time for each spot.The demands are as follows:\n1. He now lives in Wuhan Railway Hotel in Wuhan. Every time he takes a train to a city, he lives in f\"{city} Railway Hotel\", such as \"Beijing Railway Hotel\" In Beijing, he needs to visit Shihua Cave for 300 minutes, The Temple of Heaven for 150 minutes, The Summer Palace for 120 minutes, The Great Wall for 210 minutes, Beijing Stone Carvings Art Museum for 120 minutes. And the order can be decided by you.\n2. He is free to travel from 2023.7.1 to 2023.7.20. The budget for transportation is 2200.0 CNY.\n3. Ignore the opening hours of attractions, assuming they are open all day. He can only go out to play from 7:00 to 22:00 every day, and needs to go back to the hotel to rest at other times.\n4. On the basis of completing the above conditions (especially the budget), spend as little time as possible.\n",
        "demands": {
            "TravelSimulator": {
                "begin_time": "2023-07-01 07:00",
                "end_time": "2023-07-20 00:00",
                "origin_city": "Wuhan",
                "origin_place": "Wuhan Railway Hotel",
                "budget": 99999,
                "check_opening_hours": false,
                "check_meal": false,
                "set_budget": true,
                "type": 3,
                "limit": "money",
                "money_min": 74,
                "money_max": 1495
            },
            "Constraints": {
                "SpotDurationConstraint": [
                    {
                        "spot": "Shihua Cave",
                        "minutes": 300
                    },
                    {
                        "spot": "The Temple of Heaven",
                        "minutes": 150
                    },
                    {
                        "spot": "The Summer Palace",
                        "minutes": 120
                    },
                    {
                        "spot": "The Great Wall",
                        "minutes": 210
                    },
                    {
                        "spot": "Beijing Stone Carvings Art Museum",
                        "minutes": 120
                    }
                ]
            }
        },
        "type": 3
    },
    {
        "question": "Bob is going to visit some spots across cities, please make a visit plan for him, including inter-city transportation, intra-city transportation, and visit time for each spot.The demands are as follows:\n1. He now lives in Beijing Railway Hotel in Beijing. Every time he takes a train to a city, he lives in f\"{city} Railway Hotel\", such as \"Beijing Railway Hotel\" In Nanjing, he needs to visit Lake Xuanwu for 120 minutes, Ming Palace for 180 minutes, Taiping Heavenly-Kingdom Palace for 120 minutes, Bailuzhou Park for 120 minutes. And the order can be decided by you.\n2. He is free to travel from 2023.7.1 to 2023.7.20. The budget for transportation is 1600.0 CNY.\n3. Ignore the opening hours of attractions, assuming they are open all day. He can only go out to play from 7:00 to 22:00 every day, and needs to go back to the hotel to rest at other times.\n4. On the basis of completing the above conditions (especially the budget), spend as little time as possible.\n",
        "demands": {
            "TravelSimulator": {
                "begin_time": "2023-07-01 07:00",
                "end_time": "2023-07-20 00:00",
                "origin_city": "Beijing",
                "origin_place": "Beijing Railway Hotel",
                "budget": 99999,
                "check_opening_hours": false,
                "check_meal": false,
                "set_budget": true,
                "type": 3,
                "limit": "money",
                "money_min": 337,
                "money_max": 1142
            },
            "Constraints": {
                "SpotDurationConstraint": [
                    {
                        "spot": "Lake Xuanwu",
                        "minutes": 120
                    },
                    {
                        "spot": "Ming Palace",
                        "minutes": 180
                    },
                    {
                        "spot": "Taiping Heavenly-Kingdom Palace",
                        "minutes": 120
                    },
                    {
                        "spot": "Bailuzhou Park",
                        "minutes": 120
                    }
                ]
            }
        },
        "type": 3
    },
    {
        "question": "Bob is going to visit some spots across cities, please make a visit plan for him, including inter-city transportation, intra-city transportation, and visit time for each spot.The demands are as follows:\n1. He now lives in Guangzhou Railway Hotel in Guangzhou. Every time he takes a train to a city, he lives in f\"{city} Railway Hotel\", such as \"Beijing Railway Hotel\" In Nanjing, he needs to visit Taiping Heavenly-Kingdom Palace for 300 minutes, Lake Xuanwu for 210 minutes, Qinhuai River for 210 minutes, Ming Palace for 240 minutes, Bailuzhou Park for 150 minutes. And the order can be decided by you.\n2. He is free to travel from 2023.7.1 to 2023.7.20. The budget for transportation is 2600.0 CNY.\n3. The daily opening_hours of spots can be obtained from the database table place. \"opening_hours_begin\" and \"opening_hours_end\" are the opening and closing times respectively\n4. On the basis of completing the above conditions (especially the budget), spend as little time as possible.\n",
        "demands": {
            "TravelSimulator": {
                "begin_time": "2023-07-01 07:00",
                "end_time": "2023-07-20 00:00",
                "origin_city": "Guangzhou",
                "origin_place": "Guangzhou Railway Hotel",
                "budget": 99999,
                "check_opening_hours": true,
                "check_meal": false,
                "set_budget": true,
                "type": 3,
                "limit": "money",
                "money_min": 0,
                "money_max": 1788
            },
            "Constraints": {
                "SpotDurationConstraint": [
                    {
                        "spot": "Taiping Heavenly-Kingdom Palace",
                        "minutes": 300
                    },
                    {
                        "spot": "Lake Xuanwu",
                        "minutes": 210
                    },
                    {
                        "spot": "Qinhuai River",
                        "minutes": 210
                    },
                    {
                        "spot": "Ming Palace",
                        "minutes": 240
                    },
                    {
                        "spot": "Bailuzhou Park",
                        "minutes": 150
                    }
                ]
            }
        },
        "type": 3
    },
    {
        "question": "Bob is going to visit some spots across cities, please make a visit plan for him, including inter-city transportation, intra-city transportation, and visit time for each spot.The demands are as follows:\n1. He now lives in Shanghai Railway Hotel in Shanghai. Every time he takes a train to a city, he lives in f\"{city} Railway Hotel\", such as \"Beijing Railway Hotel\" In Wuhan, he needs to visit East Lake for 300 minutes, Baotong Temple for 240 minutes, Yellow Crane Tower for 270 minutes, Han Show for 120 minutes. And the order can be decided by you.\n2. He is free to travel from 2023.7.1 to 2023.7.20. The budget for transportation is 1500.0 CNY.\n3. The daily opening_hours of spots can be obtained from the database table place. \"opening_hours_begin\" and \"opening_hours_end\" are the opening and closing times respectively\n4. On the basis of completing the above conditions (especially the budget), spend as little time as possible.\n",
        "demands": {
            "TravelSimulator": {
                "begin_time": "2023-07-01 07:00",
                "end_time": "2023-07-20 00:00",
                "origin_city": "Shanghai",
                "origin_place": "Shanghai Railway Hotel",
                "budget": 99999,
                "check_opening_hours": true,
                "check_meal": false,
                "set_budget": true,
                "type": 3,
                "limit": "money",
                "money_min": 564,
                "money_max": 751
            },
            "Constraints": {
                "SpotDurationConstraint": [
                    {
                        "spot": "East Lake",
                        "minutes": 300
                    },
                    {
                        "spot": "Baotong Temple",
                        "minutes": 240
                    },
                    {
                        "spot": "Yellow Crane Tower",
                        "minutes": 270
                    },
                    {
                        "spot": "Han Show",
                        "minutes": 120
                    }
                ]
            }
        },
        "type": 3
    },
    {
        "question": "Bob is going to visit some spots across cities, please make a visit plan for him, including inter-city transportation, intra-city transportation, and visit time for each spot.The demands are as follows:\n1. He now lives in Hangzhou Railway Hotel in Hangzhou. Every time he takes a train to a city, he lives in f\"{city} Railway Hotel\", such as \"Beijing Railway Hotel\" In Nanjing, he needs to visit Tomb of Ming Emperor Zhu Yuanzhang for 180 minutes, Bailuzhou Park for 180 minutes, Lake Xuanwu for 240 minutes, Ming Palace for 210 minutes, Qinhuai River for 300 minutes. And the order can be decided by you.\n2. 5 days (2023-07-08 00:00 ~ 2023-07-13 00:00) for this trip.\n3. Ignore the opening hours of attractions, assuming they are open all day. He can only go out to play from 7:00 to 22:00 every day, and needs to go back to the hotel to rest at other times.\n4. On the basis of completing the above conditions (especially the time limit), spend as little money as possible.\n",
        "demands": {
            "TravelSimulator": {
                "begin_time": "2023-07-08 00:00",
                "end_time": "2023-07-13 00:00",
                "origin_city": "Hangzhou",
                "origin_place": "Hangzhou Railway Hotel",
                "budget": 99999,
                "check_opening_hours": false,
                "check_meal": false,
                "set_budget": false,
                "type": 3,
                "limit": "time",
                "time_min": 170991,
                "time_max": 273357
            },
            "Constraints": {
                "SpotDurationConstraint": [
                    {
                        "spot": "Tomb of Ming Emperor Zhu Yuanzhang",
                        "minutes": 180
                    },
                    {
                        "spot": "Bailuzhou Park",
                        "minutes": 180
                    },
                    {
                        "spot": "Lake Xuanwu",
                        "minutes": 240
                    },
                    {
                        "spot": "Ming Palace",
                        "minutes": 210
                    },
                    {
                        "spot": "Qinhuai River",
                        "minutes": 300
                    }
                ]
            }
        },
        "type": 3
    },
    {
        "question": "Bob is going to visit some spots across cities, please make a visit plan for him, including inter-city transportation, intra-city transportation, and visit time for each spot.The demands are as follows:\n1. He now lives in Nanjing Railway Hotel in Nanjing. Every time he takes a train to a city, he lives in f\"{city} Railway Hotel\", such as \"Beijing Railway Hotel\" In Chengdu, he needs to visit Chengdu Panda Base for 180 minutes, The Chengdu Wuhou Shrine for 240 minutes, Leshan Giant Buddha for 270 minutes, Chengdu Tea Houses for 300 minutes. And the order can be decided by you.\n2. 5 days (2023-07-07 00:00 ~ 2023-07-12 00:00) for this trip.\n3. Ignore the opening hours of attractions, assuming they are open all day. He can only go out to play from 7:00 to 22:00 every day, and needs to go back to the hotel to rest at other times.\n4. On the basis of completing the above conditions (especially the time limit), spend as little money as possible.\n",
        "demands": {
            "TravelSimulator": {
                "begin_time": "2023-07-07 00:00",
                "end_time": "2023-07-12 00:00",
                "origin_city": "Nanjing",
                "origin_place": "Nanjing Railway Hotel",
                "budget": 99999,
                "check_opening_hours": false,
                "check_meal": false,
                "set_budget": false,
                "type": 3,
                "limit": "time",
                "time_min": 96237,
                "time_max": 298623
            },
            "Constraints": {
                "SpotDurationConstraint": [
                    {
                        "spot": "Chengdu Panda Base",
                        "minutes": 180
                    },
                    {
                        "spot": "The Chengdu Wuhou Shrine",
                        "minutes": 240
                    },
                    {
                        "spot": "Leshan Giant Buddha",
                        "minutes": 270
                    },
                    {
                        "spot": "Chengdu Tea Houses",
                        "minutes": 300
                    }
                ]
            }
        },
        "type": 3
    },
    {
        "question": "Bob is going to visit some spots across cities, please make a visit plan for him, including inter-city transportation, intra-city transportation, and visit time for each spot.The demands are as follows:\n1. He now lives in Beijing Railway Hotel in Beijing. Every time he takes a train to a city, he lives in f\"{city} Railway Hotel\", such as \"Beijing Railway Hotel\" In Chengdu, he needs to visit Leshan Giant Buddha for 180 minutes, Chengdu Tea Houses for 210 minutes, The Chengdu Wuhou Shrine for 270 minutes, Chengdu Panda Base for 120 minutes. And the order can be decided by you.\n2. 5 days (2023-07-06 00:00 ~ 2023-07-11 00:00) for this trip.\n3. The daily opening_hours of spots can be obtained from the database table place. \"opening_hours_begin\" and \"opening_hours_end\" are the opening and closing times respectively\n4. On the basis of completing the above conditions (especially the time limit), spend as little money as possible.\n",
        "demands": {
            "TravelSimulator": {
                "begin_time": "2023-07-06 00:00",
                "end_time": "2023-07-11 00:00",
                "origin_city": "Beijing",
                "origin_place": "Beijing Railway Hotel",
                "budget": 99999,
                "check_opening_hours": true,
                "check_meal": false,
                "set_budget": false,
                "type": 3,
                "limit": "time",
                "time_min": 114692,
                "time_max": 233743
            },
            "Constraints": {
                "SpotDurationConstraint": [
                    {
                        "spot": "Leshan Giant Buddha",
                        "minutes": 180
                    },
                    {
                        "spot": "Chengdu Tea Houses",
                        "minutes": 210
                    },
                    {
                        "spot": "The Chengdu Wuhou Shrine",
                        "minutes": 270
                    },
                    {
                        "spot": "Chengdu Panda Base",
                        "minutes": 120
                    }
                ]
            }
        },
        "type": 3
    },
    {
        "question": "Bob is going to visit some spots across cities, please make a visit plan for him, including inter-city transportation, intra-city transportation, and visit time for each spot.The demands are as follows:\n1. He now lives in Hangzhou Railway Hotel in Hangzhou. Every time he takes a train to a city, he lives in f\"{city} Railway Hotel\", such as \"Beijing Railway Hotel\" In Nanjing, he needs to visit Taiping Heavenly-Kingdom Palace for 240 minutes, Tomb of Ming Emperor Zhu Yuanzhang for 300 minutes, Bailuzhou Park for 240 minutes, Qinhuai River for 150 minutes, Ming Palace for 210 minutes. And the order can be decided by you.\n2. 5 days (2023-07-07 00:00 ~ 2023-07-12 00:00) for this trip.\n3. The daily opening_hours of spots can be obtained from the database table place. \"opening_hours_begin\" and \"opening_hours_end\" are the opening and closing times respectively\n4. On the basis of completing the above conditions (especially the time limit), spend as little money as possible.\n",
        "demands": {
            "TravelSimulator": {
                "begin_time": "2023-07-07 00:00",
                "end_time": "2023-07-12 00:00",
                "origin_city": "Hangzhou",
                "origin_place": "Hangzhou Railway Hotel",
                "budget": 99999,
                "check_opening_hours": true,
                "check_meal": false,
                "set_budget": false,
                "type": 3,
                "limit": "time",
                "time_min": 137490,
                "time_max": 327061
            },
            "Constraints": {
                "SpotDurationConstraint": [
                    {
                        "spot": "Taiping Heavenly-Kingdom Palace",
                        "minutes": 240
                    },
                    {
                        "spot": "Tomb of Ming Emperor Zhu Yuanzhang",
                        "minutes": 300
                    },
                    {
                        "spot": "Bailuzhou Park",
                        "minutes": 240
                    },
                    {
                        "spot": "Qinhuai River",
                        "minutes": 150
                    },
                    {
                        "spot": "Ming Palace",
                        "minutes": 210
                    }
                ]
            }
        },
        "type": 3
    },
    {
        "question": "Bob is going to visit some spots across cities, please make a visit plan for him, including inter-city transportation, intra-city transportation, and visit time for each spot.The demands are as follows:\n1. He now lives in Guangzhou Railway Hotel in Guangzhou. Every time he takes a train to a city, he lives in f\"{city} Railway Hotel\", such as \"Beijing Railway Hotel\" In Guangzhou, he needs to visit Yuexiu Park for 300 minutes, Chimelong Tourist Resort for 150 minutes, Huacheng Square for 240 minutes.In Wuhan, he needs to visit Hubu Alley for 300 minutes, Tan Hua Lin for 240 minutes. And the order can be decided by you.\n2. He is free to travel from 2023.7.1 to 2023.7.20. The budget for transportation is 1500.0 CNY.\n3. Ignore the opening hours of attractions, assuming they are open all day. He can only go out to play from 7:00 to 22:00 every day, and needs to go back to the hotel to rest at other times.\n4. On the basis of completing the above conditions (especially the budget), spend as little time as possible.\n",
        "demands": {
            "TravelSimulator": {
                "begin_time": "2023-07-01 07:00",
                "end_time": "2023-07-20 00:00",
                "origin_city": "Guangzhou",
                "origin_place": "Guangzhou Railway Hotel",
                "budget": 99999,
                "check_opening_hours": false,
                "check_meal": false,
                "set_budget": true,
                "type": 3,
                "limit": "money",
                "money_min": 0,
                "money_max": 1276
            },
            "Constraints": {
                "SpotDurationConstraint": [
                    {
                        "spot": "Yuexiu Park",
                        "minutes": 300
                    },
                    {
                        "spot": "Chimelong Tourist Resort",
                        "minutes": 150
                    },
                    {
                        "spot": "Huacheng Square",
                        "minutes": 240
                    },
                    {
                        "spot": "Hubu Alley",
                        "minutes": 300
                    },
                    {
                        "spot": "Tan Hua Lin",
                        "minutes": 240
                    }
                ]
            }
        },
        "type": 3
    },
    {
        "question": "Bob is going to visit some spots across cities, please make a visit plan for him, including inter-city transportation, intra-city transportation, and visit time for each spot.The demands are as follows:\n1. He now lives in Wuhan Railway Hotel in Wuhan. Every time he takes a train to a city, he lives in f\"{city} Railway Hotel\", such as \"Beijing Railway Hotel\" In Wuhan, he needs to visit Baotong Temple for 210 minutes, Tan Hua Lin for 300 minutes.In Hangzhou, he needs to visit Quaint Water Towns for 180 minutes, China National Tea Museum for 210 minutes. And the order can be decided by you.\n2. He is free to travel from 2023.7.1 to 2023.7.20. The budget for transportation is 1100.0 CNY.\n3. Ignore the opening hours of attractions, assuming they are open all day. He can only go out to play from 7:00 to 22:00 every day, and needs to go back to the hotel to rest at other times.\n4. On the basis of completing the above conditions (especially the budget), spend as little time as possible.\n",
        "demands": {
            "TravelSimulator": {
                "begin_time": "2023-07-01 07:00",
                "end_time": "2023-07-20 00:00",
                "origin_city": "Wuhan",
                "origin_place": "Wuhan Railway Hotel",
                "budget": 99999,
                "check_opening_hours": false,
                "check_meal": false,
                "set_budget": true,
                "type": 3,
                "limit": "money",
                "money_min": 112,
                "money_max": 800
            },
            "Constraints": {
                "SpotDurationConstraint": [
                    {
                        "spot": "Baotong Temple",
                        "minutes": 210
                    },
                    {
                        "spot": "Tan Hua Lin",
                        "minutes": 300
                    },
                    {
                        "spot": "Quaint Water Towns",
                        "minutes": 180
                    },
                    {
                        "spot": "China National Tea Museum",
                        "minutes": 210
                    }
                ]
            }
        },
        "type": 3
    },
    {
        "question": "Bob is going to visit some spots across cities, please make a visit plan for him, including inter-city transportation, intra-city transportation, and visit time for each spot.The demands are as follows:\n1. He now lives in Nanjing Railway Hotel in Nanjing. Every time he takes a train to a city, he lives in f\"{city} Railway Hotel\", such as \"Beijing Railway Hotel\" In Nanjing, he needs to visit Taiping Heavenly-Kingdom Palace for 300 minutes, Bailuzhou Park for 240 minutes.In Hangzhou, he needs to visit Quaint Water Towns for 300 minutes, West Lake for 300 minutes. And the order can be decided by you.\n2. He is free to travel from 2023.7.1 to 2023.7.20. The budget for transportation is 900.0 CNY.\n3. The daily opening_hours of spots can be obtained from the database table place. \"opening_hours_begin\" and \"opening_hours_end\" are the opening and closing times respectively\n4. On the basis of completing the above conditions (especially the budget), spend as little time as possible.\n",
        "demands": {
            "TravelSimulator": {
                "begin_time": "2023-07-01 07:00",
                "end_time": "2023-07-20 00:00",
                "origin_city": "Nanjing",
                "origin_place": "Nanjing Railway Hotel",
                "budget": 99999,
                "check_opening_hours": true,
                "check_meal": false,
                "set_budget": true,
                "type": 3,
                "limit": "money",
                "money_min": 64,
                "money_max": 311
            },
            "Constraints": {
                "SpotDurationConstraint": [
                    {
                        "spot": "Taiping Heavenly-Kingdom Palace",
                        "minutes": 300
                    },
                    {
                        "spot": "Bailuzhou Park",
                        "minutes": 240
                    },
                    {
                        "spot": "Quaint Water Towns",
                        "minutes": 300
                    },
                    {
                        "spot": "West Lake",
                        "minutes": 300
                    }
                ]
            }
        },
        "type": 3
    },
    {
        "question": "Bob is going to visit some spots across cities, please make a visit plan for him, including inter-city transportation, intra-city transportation, and visit time for each spot.The demands are as follows:\n1. He now lives in Wuhan Railway Hotel in Wuhan. Every time he takes a train to a city, he lives in f\"{city} Railway Hotel\", such as \"Beijing Railway Hotel\" In Wuhan, he needs to visit Yellow Crane Tower for 180 minutes, East Lake for 120 minutes.In Beijing, he needs to visit Beijing Stone Carvings Art Museum for 300 minutes, Beijing Olympic Park for 240 minutes. And the order can be decided by you.\n2. He is free to travel from 2023.7.1 to 2023.7.20. The budget for transportation is 1400.0 CNY.\n3. The daily opening_hours of spots can be obtained from the database table place. \"opening_hours_begin\" and \"opening_hours_end\" are the opening and closing times respectively\n4. On the basis of completing the above conditions (especially the budget), spend as little time as possible.\n",
        "demands": {
            "TravelSimulator": {
                "begin_time": "2023-07-01 07:00",
                "end_time": "2023-07-20 00:00",
                "origin_city": "Wuhan",
                "origin_place": "Wuhan Railway Hotel",
                "budget": 99999,
                "check_opening_hours": true,
                "check_meal": false,
                "set_budget": true,
                "type": 3,
                "limit": "money",
                "money_min": 304,
                "money_max": 1412
            },
            "Constraints": {
                "SpotDurationConstraint": [
                    {
                        "spot": "Yellow Crane Tower",
                        "minutes": 180
                    },
                    {
                        "spot": "East Lake",
                        "minutes": 120
                    },
                    {
                        "spot": "Beijing Stone Carvings Art Museum",
                        "minutes": 300
                    },
                    {
                        "spot": "Beijing Olympic Park",
                        "minutes": 240
                    }
                ]
            }
        },
        "type": 3
    },
    {
        "question": "Bob is going to visit some spots across cities, please make a visit plan for him, including inter-city transportation, intra-city transportation, and visit time for each spot.The demands are as follows:\n1. He now lives in Guangzhou Railway Hotel in Guangzhou. Every time he takes a train to a city, he lives in f\"{city} Railway Hotel\", such as \"Beijing Railway Hotel\" In Guangzhou, he needs to visit Yuexiu Park for 210 minutes, Huacheng Square for 270 minutes.In Nanjing, he needs to visit Ming Palace for 180 minutes, Tomb of Ming Emperor Zhu Yuanzhang for 210 minutes. And the order can be decided by you.\n2. 5 days (2023-07-09 00:00 ~ 2023-07-14 00:00) for this trip.\n3. Ignore the opening hours of attractions, assuming they are open all day. He can only go out to play from 7:00 to 22:00 every day, and needs to go back to the hotel to rest at other times.\n4. On the basis of completing the above conditions (especially the time limit), spend as little money as possible.\n",
        "demands": {
            "TravelSimulator": {
                "begin_time": "2023-07-09 00:00",
                "end_time": "2023-07-14 00:00",
                "origin_city": "Guangzhou",
                "origin_place": "Guangzhou Railway Hotel",
                "budget": 99999,
                "check_opening_hours": false,
                "check_meal": false,
                "set_budget": false,
                "type": 3,
                "limit": "time",
                "time_min": 111562,
                "time_max": 175523
            },
            "Constraints": {
                "SpotDurationConstraint": [
                    {
                        "spot": "Yuexiu Park",
                        "minutes": 210
                    },
                    {
                        "spot": "Huacheng Square",
                        "minutes": 270
                    },
                    {
                        "spot": "Ming Palace",
                        "minutes": 180
                    },
                    {
                        "spot": "Tomb of Ming Emperor Zhu Yuanzhang",
                        "minutes": 210
                    }
                ]
            }
        },
        "type": 3
    },
    {
        "question": "Bob is going to visit some spots across cities, please make a visit plan for him, including inter-city transportation, intra-city transportation, and visit time for each spot.The demands are as follows:\n1. He now lives in Guangzhou Railway Hotel in Guangzhou. Every time he takes a train to a city, he lives in f\"{city} Railway Hotel\", such as \"Beijing Railway Hotel\" In Guangzhou, he needs to visit Baiyun Mountain for 120 minutes, Canton Tower for 180 minutes.In Chengdu, he needs to visit Chengdu Panda Base for 270 minutes, Du Fu Thatched Cottage for 240 minutes. And the order can be decided by you.\n2. 5 days (2023-07-05 00:00 ~ 2023-07-10 00:00) for this trip.\n3. Ignore the opening hours of attractions, assuming they are open all day. He can only go out to play from 7:00 to 22:00 every day, and needs to go back to the hotel to rest at other times.\n4. On the basis of completing the above conditions (especially the time limit), spend as little money as possible.\n",
        "demands": {
            "TravelSimulator": {
                "begin_time": "2023-07-05 00:00",
                "end_time": "2023-07-10 00:00",
                "origin_city": "Guangzhou",
                "origin_place": "Guangzhou Railway Hotel",
                "budget": 99999,
                "check_opening_hours": false,
                "check_meal": false,
                "set_budget": false,
                "type": 3,
                "limit": "time",
                "time_min": 112611,
                "time_max": 199201
            },
            "Constraints": {
                "SpotDurationConstraint": [
                    {
                        "spot": "Baiyun Mountain",
                        "minutes": 120
                    },
                    {
                        "spot": "Canton Tower",
                        "minutes": 180
                    },
                    {
                        "spot": "Chengdu Panda Base",
                        "minutes": 270
                    },
                    {
                        "spot": "Du Fu Thatched Cottage",
                        "minutes": 240
                    }
                ]
            }
        },
        "type": 3
    },
    {
        "question": "Bob is going to visit some spots across cities, please make a visit plan for him, including inter-city transportation, intra-city transportation, and visit time for each spot.The demands are as follows:\n1. He now lives in Chengdu Railway Hotel in Chengdu. Every time he takes a train to a city, he lives in f\"{city} Railway Hotel\", such as \"Beijing Railway Hotel\" In Chengdu, he needs to visit Chengdu Panda Base for 270 minutes, Chengdu Tea Houses for 240 minutes.In Nanjing, he needs to visit Taiping Heavenly-Kingdom Palace for 270 minutes, Lake Xuanwu for 210 minutes. And the order can be decided by you.\n2. 5 days (2023-07-10 00:00 ~ 2023-07-15 00:00) for this trip.\n3. The daily opening_hours of spots can be obtained from the database table place. \"opening_hours_begin\" and \"opening_hours_end\" are the opening and closing times respectively\n4. On the basis of completing the above conditions (especially the time limit), spend as little money as possible.\n",
        "demands": {
            "TravelSimulator": {
                "begin_time": "2023-07-10 00:00",
                "end_time": "2023-07-15 00:00",
                "origin_city": "Chengdu",
                "origin_place": "Chengdu Railway Hotel",
                "budget": 99999,
                "check_opening_hours": true,
                "check_meal": false,
                "set_budget": false,
                "type": 3,
                "limit": "time",
                "time_min": 150121,
                "time_max": 309688
            },
            "Constraints": {
                "SpotDurationConstraint": [
                    {
                        "spot": "Chengdu Panda Base",
                        "minutes": 270
                    },
                    {
                        "spot": "Chengdu Tea Houses",
                        "minutes": 240
                    },
                    {
                        "spot": "Taiping Heavenly-Kingdom Palace",
                        "minutes": 270
                    },
                    {
                        "spot": "Lake Xuanwu",
                        "minutes": 210
                    }
                ]
            }
        },
        "type": 3
    },
    {
        "question": "Bob is going to visit some spots across cities, please make a visit plan for him, including inter-city transportation, intra-city transportation, and visit time for each spot.The demands are as follows:\n1. He now lives in Shanghai Railway Hotel in Shanghai. Every time he takes a train to a city, he lives in f\"{city} Railway Hotel\", such as \"Beijing Railway Hotel\" In Shanghai, he needs to visit Xintiandi for 270 minutes, Shanghai Disney for 270 minutes.In Nanjing, he needs to visit Bailuzhou Park for 210 minutes, Ming Palace for 120 minutes. And the order can be decided by you.\n2. 5 days (2023-07-06 00:00 ~ 2023-07-11 00:00) for this trip.\n3. The daily opening_hours of spots can be obtained from the database table place. \"opening_hours_begin\" and \"opening_hours_end\" are the opening and closing times respectively\n4. On the basis of completing the above conditions (especially the time limit), spend as little money as possible.\n",
        "demands": {
            "TravelSimulator": {
                "begin_time": "2023-07-06 00:00",
                "end_time": "2023-07-11 00:00",
                "origin_city": "Shanghai",
                "origin_place": "Shanghai Railway Hotel",
                "budget": 99999,
                "check_opening_hours": true,
                "check_meal": false,
                "set_budget": false,
                "type": 3,
                "limit": "time",
                "time_min": 192901,
                "time_max": 213682
            },
            "Constraints": {
                "SpotDurationConstraint": [
                    {
                        "spot": "Xintiandi",
                        "minutes": 270
                    },
                    {
                        "spot": "Shanghai Disney",
                        "minutes": 270
                    },
                    {
                        "spot": "Bailuzhou Park",
                        "minutes": 210
                    },
                    {
                        "spot": "Ming Palace",
                        "minutes": 120
                    }
                ]
            }
        },
        "type": 3
    },
    {
        "question": "Bob is going to visit some spots across cities, please make a visit plan for him, including inter-city transportation, intra-city transportation, and visit time for each spot.The demands are as follows:\n1. He now lives in Hangzhou Railway Hotel in Hangzhou. Every time he takes a train to a city, he lives in f\"{city} Railway Hotel\", such as \"Beijing Railway Hotel\" In Beijing, he needs to visit Beijing Olympic Park for 180 minutes, Tiananmen Square for 150 minutes, The Temple of Heaven for 120 minutes, Shihua Cave for 240 minutes, The Summer Palace for 300 minutes, The Great Wall for 120 minutes. And the order can be decided by you.\n2. He is free to travel from 2023.7.1 to 2023.7.20. The budget for transportation is 2500.0 CNY.\n3. Ignore the opening hours of attractions, assuming they are open all day. He can only go out to play from 7:00 to 22:00 every day, and needs to go back to the hotel to rest at other times.\n4. On the basis of completing the above conditions (especially the budget), spend as little time as possible.\n",
        "demands": {
            "TravelSimulator": {
                "begin_time": "2023-07-01 07:00",
                "end_time": "2023-07-20 00:00",
                "origin_city": "Hangzhou",
                "origin_place": "Hangzhou Railway Hotel",
                "budget": 99999,
                "check_opening_hours": false,
                "check_meal": false,
                "set_budget": true,
                "type": 3,
                "limit": "money",
                "money_min": 417,
                "money_max": 1426
            },
            "Constraints": {
                "SpotDurationConstraint": [
                    {
                        "spot": "Beijing Olympic Park",
                        "minutes": 180
                    },
                    {
                        "spot": "Tiananmen Square",
                        "minutes": 150
                    },
                    {
                        "spot": "The Temple of Heaven",
                        "minutes": 120
                    },
                    {
                        "spot": "Shihua Cave",
                        "minutes": 240
                    },
                    {
                        "spot": "The Summer Palace",
                        "minutes": 300
                    },
                    {
                        "spot": "The Great Wall",
                        "minutes": 120
                    }
                ]
            }
        },
        "type": 3
    },
    {
        "question": "Bob is going to visit some spots across cities, please make a visit plan for him, including inter-city transportation, intra-city transportation, and visit time for each spot.The demands are as follows:\n1. He now lives in Hangzhou Railway Hotel in Hangzhou. Every time he takes a train to a city, he lives in f\"{city} Railway Hotel\", such as \"Beijing Railway Hotel\" In Shanghai, he needs to visit Xintiandi for 240 minutes, Shanghai Disney for 150 minutes, Longhua Temple for 210 minutes, Shanghai History Museum for 120 minutes, Century Park for 270 minutes, Qibao Ancient Town for 210 minutes, Shanghai Sightseeing Tunnel for 180 minutes. And the order can be decided by you.\n2. He is free to travel from 2023.7.1 to 2023.7.20. The budget for transportation is 1600.0 CNY.\n3. Ignore the opening hours of attractions, assuming they are open all day. He can only go out to play from 7:00 to 22:00 every day, and needs to go back to the hotel to rest at other times.\n4. On the basis of completing the above conditions (especially the budget), spend as little time as possible.\n",
        "demands": {
            "TravelSimulator": {
                "begin_time": "2023-07-01 07:00",
                "end_time": "2023-07-20 00:00",
                "origin_city": "Hangzhou",
                "origin_place": "Hangzhou Railway Hotel",
                "budget": 99999,
                "check_opening_hours": false,
                "check_meal": false,
                "set_budget": true,
                "type": 3,
                "limit": "money",
                "money_min": 0,
                "money_max": 192
            },
            "Constraints": {
                "SpotDurationConstraint": [
                    {
                        "spot": "Xintiandi",
                        "minutes": 240
                    },
                    {
                        "spot": "Shanghai Disney",
                        "minutes": 150
                    },
                    {
                        "spot": "Longhua Temple",
                        "minutes": 210
                    },
                    {
                        "spot": "Shanghai History Museum",
                        "minutes": 120
                    },
                    {
                        "spot": "Century Park",
                        "minutes": 270
                    },
                    {
                        "spot": "Qibao Ancient Town",
                        "minutes": 210
                    },
                    {
                        "spot": "Shanghai Sightseeing Tunnel",
                        "minutes": 180
                    }
                ]
            }
        },
        "type": 3
    },
    {
        "question": "Bob is going to visit some spots across cities, please make a visit plan for him, including inter-city transportation, intra-city transportation, and visit time for each spot.The demands are as follows:\n1. He now lives in Guangzhou Railway Hotel in Guangzhou. Every time he takes a train to a city, he lives in f\"{city} Railway Hotel\", such as \"Beijing Railway Hotel\" In Beijing, he needs to visit Tiananmen Square for 150 minutes, Beijing Olympic Park for 180 minutes, Shihua Cave for 270 minutes, Beijing Stone Carvings Art Museum for 120 minutes, The Temple of Heaven for 300 minutes, The Summer Palace for 210 minutes, The Great Wall for 240 minutes. And the order can be decided by you.\n2. He is free to travel from 2023.7.1 to 2023.7.20. The budget for transportation is 3700.0 CNY.\n3. The daily opening_hours of spots can be obtained from the database table place. \"opening_hours_begin\" and \"opening_hours_end\" are the opening and closing times respectively\n4. On the basis of completing the above conditions (especially the budget), spend as little time as possible.\n",
        "demands": {
            "TravelSimulator": {
                "begin_time": "2023-07-01 07:00",
                "end_time": "2023-07-20 00:00",
                "origin_city": "Guangzhou",
                "origin_place": "Guangzhou Railway Hotel",
                "budget": 99999,
                "check_opening_hours": true,
                "check_meal": false,
                "set_budget": true,
                "type": 3,
                "limit": "money",
                "money_min": 0,
                "money_max": 2772
            },
            "Constraints": {
                "SpotDurationConstraint": [
                    {
                        "spot": "Tiananmen Square",
                        "minutes": 150
                    },
                    {
                        "spot": "Beijing Olympic Park",
                        "minutes": 180
                    },
                    {
                        "spot": "Shihua Cave",
                        "minutes": 270
                    },
                    {
                        "spot": "Beijing Stone Carvings Art Museum",
                        "minutes": 120
                    },
                    {
                        "spot": "The Temple of Heaven",
                        "minutes": 300
                    },
                    {
                        "spot": "The Summer Palace",
                        "minutes": 210
                    },
                    {
                        "spot": "The Great Wall",
                        "minutes": 240
                    }
                ]
            }
        },
        "type": 3
    },
    {
        "question": "Bob is going to visit some spots across cities, please make a visit plan for him, including inter-city transportation, intra-city transportation, and visit time for each spot.The demands are as follows:\n1. He now lives in Wuhan Railway Hotel in Wuhan. Every time he takes a train to a city, he lives in f\"{city} Railway Hotel\", such as \"Beijing Railway Hotel\" In Beijing, he needs to visit The Forbidden City for 150 minutes, Shihua Cave for 180 minutes, Beijing Olympic Park for 300 minutes, The Great Wall for 180 minutes, Beijing Stone Carvings Art Museum for 240 minutes, Tiananmen Square for 240 minutes. And the order can be decided by you.\n2. He is free to travel from 2023.7.1 to 2023.7.20. The budget for transportation is 2300.0 CNY.\n3. The daily opening_hours of spots can be obtained from the database table place. \"opening_hours_begin\" and \"opening_hours_end\" are the opening and closing times respectively\n4. On the basis of completing the above conditions (especially the budget), spend as little time as possible.\n",
        "demands": {
            "TravelSimulator": {
                "begin_time": "2023-07-01 07:00",
                "end_time": "2023-07-20 00:00",
                "origin_city": "Wuhan",
                "origin_place": "Wuhan Railway Hotel",
                "budget": 99999,
                "check_opening_hours": true,
                "check_meal": false,
                "set_budget": true,
                "type": 3,
                "limit": "money",
                "money_min": 0,
                "money_max": 1647
            },
            "Constraints": {
                "SpotDurationConstraint": [
                    {
                        "spot": "The Forbidden City",
                        "minutes": 150
                    },
                    {
                        "spot": "Shihua Cave",
                        "minutes": 180
                    },
                    {
                        "spot": "Beijing Olympic Park",
                        "minutes": 300
                    },
                    {
                        "spot": "The Great Wall",
                        "minutes": 180
                    },
                    {
                        "spot": "Beijing Stone Carvings Art Museum",
                        "minutes": 240
                    },
                    {
                        "spot": "Tiananmen Square",
                        "minutes": 240
                    }
                ]
            }
        },
        "type": 3
    },
    {
        "question": "Bob is going to visit some spots across cities, please make a visit plan for him, including inter-city transportation, intra-city transportation, and visit time for each spot.The demands are as follows:\n1. He now lives in Shanghai Railway Hotel in Shanghai. Every time he takes a train to a city, he lives in f\"{city} Railway Hotel\", such as \"Beijing Railway Hotel\" In Beijing, he needs to visit Beijing Stone Carvings Art Museum for 180 minutes, Beijing Olympic Park for 120 minutes, Shihua Cave for 210 minutes, The Summer Palace for 120 minutes, The Temple of Heaven for 210 minutes, Tiananmen Square for 300 minutes, The Forbidden City for 300 minutes. And the order can be decided by you.\n2. 6 days (2023-07-04 00:00 ~ 2023-07-10 00:00) for this trip.\n3. Ignore the opening hours of attractions, assuming they are open all day. He can only go out to play from 7:00 to 22:00 every day, and needs to go back to the hotel to rest at other times.\n4. On the basis of completing the above conditions (especially the time limit), spend as little money as possible.\n",
        "demands": {
            "TravelSimulator": {
                "begin_time": "2023-07-04 00:00",
                "end_time": "2023-07-10 00:00",
                "origin_city": "Shanghai",
                "origin_place": "Shanghai Railway Hotel",
                "budget": 99999,
                "check_opening_hours": false,
                "check_meal": false,
                "set_budget": false,
                "type": 3,
                "limit": "time",
                "time_min": 214440,
                "time_max": 390775
            },
            "Constraints": {
                "SpotDurationConstraint": [
                    {
                        "spot": "Beijing Stone Carvings Art Museum",
                        "minutes": 180
                    },
                    {
                        "spot": "Beijing Olympic Park",
                        "minutes": 120
                    },
                    {
                        "spot": "Shihua Cave",
                        "minutes": 210
                    },
                    {
                        "spot": "The Summer Palace",
                        "minutes": 120
                    },
                    {
                        "spot": "The Temple of Heaven",
                        "minutes": 210
                    },
                    {
                        "spot": "Tiananmen Square",
                        "minutes": 300
                    },
                    {
                        "spot": "The Forbidden City",
                        "minutes": 300
                    }
                ]
            }
        },
        "type": 3
    },
    {
        "question": "Bob is going to visit some spots across cities, please make a visit plan for him, including inter-city transportation, intra-city transportation, and visit time for each spot.The demands are as follows:\n1. He now lives in Guangzhou Railway Hotel in Guangzhou. Every time he takes a train to a city, he lives in f\"{city} Railway Hotel\", such as \"Beijing Railway Hotel\" In Beijing, he needs to visit The Temple of Heaven for 180 minutes, The Forbidden City for 180 minutes, Beijing Stone Carvings Art Museum for 180 minutes, The Great Wall for 240 minutes, Beijing Olympic Park for 240 minutes, Tiananmen Square for 120 minutes, Shihua Cave for 210 minutes. And the order can be decided by you.\n2. 6 days (2023-07-03 00:00 ~ 2023-07-09 00:00) for this trip.\n3. Ignore the opening hours of attractions, assuming they are open all day. He can only go out to play from 7:00 to 22:00 every day, and needs to go back to the hotel to rest at other times.\n4. On the basis of completing the above conditions (especially the time limit), spend as little money as possible.\n",
        "demands": {
            "TravelSimulator": {
                "begin_time": "2023-07-03 00:00",
                "end_time": "2023-07-09 00:00",
                "origin_city": "Guangzhou",
                "origin_place": "Guangzhou Railway Hotel",
                "budget": 99999,
                "check_opening_hours": false,
                "check_meal": false,
                "set_budget": false,
                "type": 3,
                "limit": "time",
                "time_min": 209941,
                "time_max": 359602
            },
            "Constraints": {
                "SpotDurationConstraint": [
                    {
                        "spot": "The Temple of Heaven",
                        "minutes": 180
                    },
                    {
                        "spot": "The Forbidden City",
                        "minutes": 180
                    },
                    {
                        "spot": "Beijing Stone Carvings Art Museum",
                        "minutes": 180
                    },
                    {
                        "spot": "The Great Wall",
                        "minutes": 240
                    },
                    {
                        "spot": "Beijing Olympic Park",
                        "minutes": 240
                    },
                    {
                        "spot": "Tiananmen Square",
                        "minutes": 120
                    },
                    {
                        "spot": "Shihua Cave",
                        "minutes": 210
                    }
                ]
            }
        },
        "type": 3
    },
    {
        "question": "Bob is going to visit some spots across cities, please make a visit plan for him, including inter-city transportation, intra-city transportation, and visit time for each spot.The demands are as follows:\n1. He now lives in Hangzhou Railway Hotel in Hangzhou. Every time he takes a train to a city, he lives in f\"{city} Railway Hotel\", such as \"Beijing Railway Hotel\" In Wuhan, he needs to visit Baotong Temple for 300 minutes, Yellow Crane Tower for 300 minutes, Tan Hua Lin for 120 minutes, East Lake for 150 minutes, Han Show for 150 minutes, Hubu Alley for 300 minutes. And the order can be decided by you.\n2. 6 days (2023-07-08 00:00 ~ 2023-07-14 00:00) for this trip.\n3. The daily opening_hours of spots can be obtained from the database table place. \"opening_hours_begin\" and \"opening_hours_end\" are the opening and closing times respectively\n4. On the basis of completing the above conditions (especially the time limit), spend as little money as possible.\n",
        "demands": {
            "TravelSimulator": {
                "begin_time": "2023-07-08 00:00",
                "end_time": "2023-07-14 00:00",
                "origin_city": "Hangzhou",
                "origin_place": "Hangzhou Railway Hotel",
                "budget": 99999,
                "check_opening_hours": true,
                "check_meal": false,
                "set_budget": false,
                "type": 3,
                "limit": "time",
                "time_min": 202585,
                "time_max": 342393
            },
            "Constraints": {
                "SpotDurationConstraint": [
                    {
                        "spot": "Baotong Temple",
                        "minutes": 300
                    },
                    {
                        "spot": "Yellow Crane Tower",
                        "minutes": 300
                    },
                    {
                        "spot": "Tan Hua Lin",
                        "minutes": 120
                    },
                    {
                        "spot": "East Lake",
                        "minutes": 150
                    },
                    {
                        "spot": "Han Show",
                        "minutes": 150
                    },
                    {
                        "spot": "Hubu Alley",
                        "minutes": 300
                    }
                ]
            }
        },
        "type": 3
    },
    {
        "question": "Bob is going to visit some spots across cities, please make a visit plan for him, including inter-city transportation, intra-city transportation, and visit time for each spot.The demands are as follows:\n1. He now lives in Wuhan Railway Hotel in Wuhan. Every time he takes a train to a city, he lives in f\"{city} Railway Hotel\", such as \"Beijing Railway Hotel\" In Beijing, he needs to visit Shihua Cave for 300 minutes, Beijing Olympic Park for 120 minutes, The Great Wall for 210 minutes, The Temple of Heaven for 210 minutes, Beijing Stone Carvings Art Museum for 300 minutes, Tiananmen Square for 240 minutes. And the order can be decided by you.\n2. 6 days (2023-07-06 00:00 ~ 2023-07-12 00:00) for this trip.\n3. The daily opening_hours of spots can be obtained from the database table place. \"opening_hours_begin\" and \"opening_hours_end\" are the opening and closing times respectively\n4. On the basis of completing the above conditions (especially the time limit), spend as little money as possible.\n",
        "demands": {
            "TravelSimulator": {
                "begin_time": "2023-07-06 00:00",
                "end_time": "2023-07-12 00:00",
                "origin_city": "Wuhan",
                "origin_place": "Wuhan Railway Hotel",
                "budget": 99999,
                "check_opening_hours": true,
                "check_meal": false,
                "set_budget": false,
                "type": 3,
                "limit": "time",
                "time_min": 175277,
                "time_max": 359623
            },
            "Constraints": {
                "SpotDurationConstraint": [
                    {
                        "spot": "Shihua Cave",
                        "minutes": 300
                    },
                    {
                        "spot": "Beijing Olympic Park",
                        "minutes": 120
                    },
                    {
                        "spot": "The Great Wall",
                        "minutes": 210
                    },
                    {
                        "spot": "The Temple of Heaven",
                        "minutes": 210
                    },
                    {
                        "spot": "Beijing Stone Carvings Art Museum",
                        "minutes": 300
                    },
                    {
                        "spot": "Tiananmen Square",
                        "minutes": 240
                    }
                ]
            }
        },
        "type": 3
    },
    {
        "question": "Bob is going to visit some spots across cities, please make a visit plan for him, including inter-city transportation, intra-city transportation, and visit time for each spot.The demands are as follows:\n1. He now lives in Guangzhou Railway Hotel in Guangzhou. Every time he takes a train to a city, he lives in f\"{city} Railway Hotel\", such as \"Beijing Railway Hotel\" In Guangzhou, he needs to visit Chimelong Tourist Resort for 180 minutes, Huacheng Square for 270 minutes, Canton Tower for 240 minutes, Baiyun Mountain for 180 minutes, Yuexiu Park for 210 minutes.In Beijing, he needs to visit The Forbidden City for 210 minutes, The Temple of Heaven for 180 minutes. And the order can be decided by you.\n2. He is free to travel from 2023.7.1 to 2023.7.20. The budget for transportation is 2100.0 CNY.\n3. Ignore the opening hours of attractions, assuming they are open all day. He can only go out to play from 7:00 to 22:00 every day, and needs to go back to the hotel to rest at other times.\n4. On the basis of completing the above conditions (especially the budget), spend as little time as possible.\n",
        "demands": {
            "TravelSimulator": {
                "begin_time": "2023-07-01 07:00",
                "end_time": "2023-07-20 00:00",
                "origin_city": "Guangzhou",
                "origin_place": "Guangzhou Railway Hotel",
                "budget": 99999,
                "check_opening_hours": false,
                "check_meal": false,
                "set_budget": true,
                "type": 3,
                "limit": "money",
                "money_min": 0,
                "money_max": 2660
            },
            "Constraints": {
                "SpotDurationConstraint": [
                    {
                        "spot": "Chimelong Tourist Resort",
                        "minutes": 180
                    },
                    {
                        "spot": "Huacheng Square",
                        "minutes": 270
                    },
                    {
                        "spot": "Canton Tower",
                        "minutes": 240
                    },
                    {
                        "spot": "Baiyun Mountain",
                        "minutes": 180
                    },
                    {
                        "spot": "Yuexiu Park",
                        "minutes": 210
                    },
                    {
                        "spot": "The Forbidden City",
                        "minutes": 210
                    },
                    {
                        "spot": "The Temple of Heaven",
                        "minutes": 180
                    }
                ]
            }
        },
        "type": 3
    },
    {
        "question": "Bob is going to visit some spots across cities, please make a visit plan for him, including inter-city transportation, intra-city transportation, and visit time for each spot.The demands are as follows:\n1. He now lives in Hangzhou Railway Hotel in Hangzhou. Every time he takes a train to a city, he lives in f\"{city} Railway Hotel\", such as \"Beijing Railway Hotel\" In Hangzhou, he needs to visit China National Tea Museum for 180 minutes, West Lake for 150 minutes, Quaint Water Towns for 240 minutes.In Shanghai, he needs to visit Century Park for 150 minutes, Shanghai Sightseeing Tunnel for 180 minutes, Shanghai History Museum for 150 minutes. And the order can be decided by you.\n2. He is free to travel from 2023.7.1 to 2023.7.20. The budget for transportation is 1300.0 CNY.\n3. Ignore the opening hours of attractions, assuming they are open all day. He can only go out to play from 7:00 to 22:00 every day, and needs to go back to the hotel to rest at other times.\n4. On the basis of completing the above conditions (especially the budget), spend as little time as possible.\n",
        "demands": {
            "TravelSimulator": {
                "begin_time": "2023-07-01 07:00",
                "end_time": "2023-07-20 00:00",
                "origin_city": "Hangzhou",
                "origin_place": "Hangzhou Railway Hotel",
                "budget": 99999,
                "check_opening_hours": false,
                "check_meal": false,
                "set_budget": true,
                "type": 3,
                "limit": "money",
                "money_min": 12,
                "money_max": 199
            },
            "Constraints": {
                "SpotDurationConstraint": [
                    {
                        "spot": "China National Tea Museum",
                        "minutes": 180
                    },
                    {
                        "spot": "West Lake",
                        "minutes": 150
                    },
                    {
                        "spot": "Quaint Water Towns",
                        "minutes": 240
                    },
                    {
                        "spot": "Century Park",
                        "minutes": 150
                    },
                    {
                        "spot": "Shanghai Sightseeing Tunnel",
                        "minutes": 180
                    },
                    {
                        "spot": "Shanghai History Museum",
                        "minutes": 150
                    }
                ]
            }
        },
        "type": 3
    },
    {
        "question": "Bob is going to visit some spots across cities, please make a visit plan for him, including inter-city transportation, intra-city transportation, and visit time for each spot.The demands are as follows:\n1. He now lives in Guangzhou Railway Hotel in Guangzhou. Every time he takes a train to a city, he lives in f\"{city} Railway Hotel\", such as \"Beijing Railway Hotel\" In Beijing, he needs to visit Shihua Cave for 150 minutes, The Forbidden City for 210 minutes.In Nanjing, he needs to visit Bailuzhou Park for 180 minutes, Ming Palace for 120 minutes. And the order can be decided by you.\n2. He is free to travel from 2023.7.1 to 2023.7.20. The budget for transportation is 2900.0 CNY.\n3. Ignore the opening hours of attractions, assuming they are open all day. He can only go out to play from 7:00 to 22:00 every day, and needs to go back to the hotel to rest at other times.\n4. On the basis of completing the above conditions (especially the budget), spend as little time as possible.\n",
        "demands": {
            "TravelSimulator": {
                "begin_time": "2023-07-01 07:00",
                "end_time": "2023-07-20 00:00",
                "origin_city": "Guangzhou",
                "origin_place": "Guangzhou Railway Hotel",
                "budget": 99999,
                "check_opening_hours": false,
                "check_meal": false,
                "set_budget": true,
                "type": 3,
                "limit": "money",
                "money_min": 240,
                "money_max": 2779
            },
            "Constraints": {
                "SpotDurationConstraint": [
                    {
                        "spot": "Shihua Cave",
                        "minutes": 150
                    },
                    {
                        "spot": "The Forbidden City",
                        "minutes": 210
                    },
                    {
                        "spot": "Bailuzhou Park",
                        "minutes": 180
                    },
                    {
                        "spot": "Ming Palace",
                        "minutes": 120
                    }
                ]
            }
        },
        "type": 3
    },
    {
        "question": "Bob is going to visit some spots across cities, please make a visit plan for him, including inter-city transportation, intra-city transportation, and visit time for each spot.The demands are as follows:\n1. He now lives in Beijing Railway Hotel in Beijing. Every time he takes a train to a city, he lives in f\"{city} Railway Hotel\", such as \"Beijing Railway Hotel\" In Guangzhou, he needs to visit Chimelong Tourist Resort for 210 minutes, Yuexiu Park for 120 minutes.In Shanghai, he needs to visit Shanghai Disney for 180 minutes, Xintiandi for 240 minutes, Longhua Temple for 300 minutes. And the order can be decided by you.\n2. He is free to travel from 2023.7.1 to 2023.7.20. The budget for transportation is 2700.0 CNY.\n3. Ignore the opening hours of attractions, assuming they are open all day. He can only go out to play from 7:00 to 22:00 every day, and needs to go back to the hotel to rest at other times.\n4. On the basis of completing the above conditions (especially the budget), spend as little time as possible.\n",
        "demands": {
            "TravelSimulator": {
                "begin_time": "2023-07-01 07:00",
                "end_time": "2023-07-20 00:00",
                "origin_city": "Beijing",
                "origin_place": "Beijing Railway Hotel",
                "budget": 99999,
                "check_opening_hours": false,
                "check_meal": false,
                "set_budget": true,
                "type": 3,
                "limit": "money",
                "money_min": 0,
                "money_max": 3309
            },
            "Constraints": {
                "SpotDurationConstraint": [
                    {
                        "spot": "Chimelong Tourist Resort",
                        "minutes": 210
                    },
                    {
                        "spot": "Yuexiu Park",
                        "minutes": 120
                    },
                    {
                        "spot": "Shanghai Disney",
                        "minutes": 180
                    },
                    {
                        "spot": "Xintiandi",
                        "minutes": 240
                    },
                    {
                        "spot": "Longhua Temple",
                        "minutes": 300
                    }
                ]
            }
        },
        "type": 3
    },
    {
        "question": "Bob is going to visit some spots across cities, please make a visit plan for him, including inter-city transportation, intra-city transportation, and visit time for each spot.The demands are as follows:\n1. He now lives in Wuhan Railway Hotel in Wuhan. Every time he takes a train to a city, he lives in f\"{city} Railway Hotel\", such as \"Beijing Railway Hotel\" In Wuhan, he needs to visit Han Show for 120 minutes, Yellow Crane Tower for 240 minutes, Baotong Temple for 270 minutes. And the order can be decided by you.\n2. He is free to travel from 2023.7.1 to 2023.7.20. The budget for transportation is 1300 CNY.\n3. The daily opening_hours of spots can be obtained from the database table place. \"opening_hours_begin\" and \"opening_hours_end\" are the opening and closing times respectively\n4. On the basis of completing the above conditions (especially the budget), spend as little time as possible.\n",
        "demands": {
            "TravelSimulator": {
                "begin_time": "2023-07-01 07:00",
                "end_time": "2023-07-20 00:00",
                "origin_city": "Wuhan",
                "origin_place": "Wuhan Railway Hotel",
                "budget": 99999,
                "check_opening_hours": true,
                "check_meal": false,
                "set_budget": true,
                "type": 3,
                "limit": "money",
                "money_min": 0,
                "money_max": 0
            },
            "Constraints": {
                "SpotDurationConstraint": [
                    {
                        "spot": "Han Show",
                        "minutes": 120
                    },
                    {
                        "spot": "Yellow Crane Tower",
                        "minutes": 240
                    },
                    {
                        "spot": "Baotong Temple",
                        "minutes": 270
                    }
                ]
            }
        },
        "type": 3
    },
    {
        "question": "Bob is going to visit some spots across cities, please make a visit plan for him, including inter-city transportation, intra-city transportation, and visit time for each spot.The demands are as follows:\n1. He now lives in Wuhan Railway Hotel in Wuhan. Every time he takes a train to a city, he lives in f\"{city} Railway Hotel\", such as \"Beijing Railway Hotel\" In Wuhan, he needs to visit Baotong Temple for 240 minutes, Hubu Alley for 270 minutes.In Beijing, he needs to visit Beijing Stone Carvings Art Museum for 120 minutes, Beijing Olympic Park for 300 minutes, The Temple of Heaven for 180 minutes, The Great Wall for 300 minutes. And the order can be decided by you.\n2. He is free to travel from 2023.7.1 to 2023.7.20. The budget for transportation is 1900.0 CNY.\n3. The daily opening_hours of spots can be obtained from the database table place. \"opening_hours_begin\" and \"opening_hours_end\" are the opening and closing times respectively\n4. On the basis of completing the above conditions (especially the budget), spend as little time as possible.\n",
        "demands": {
            "TravelSimulator": {
                "begin_time": "2023-07-01 07:00",
                "end_time": "2023-07-20 00:00",
                "origin_city": "Wuhan",
                "origin_place": "Wuhan Railway Hotel",
                "budget": 99999,
                "check_opening_hours": true,
                "check_meal": false,
                "set_budget": true,
                "type": 3,
                "limit": "money",
                "money_min": 0,
                "money_max": 1629
            },
            "Constraints": {
                "SpotDurationConstraint": [
                    {
                        "spot": "Baotong Temple",
                        "minutes": 240
                    },
                    {
                        "spot": "Hubu Alley",
                        "minutes": 270
                    },
                    {
                        "spot": "Beijing Stone Carvings Art Museum",
                        "minutes": 120
                    },
                    {
                        "spot": "Beijing Olympic Park",
                        "minutes": 300
                    },
                    {
                        "spot": "The Temple of Heaven",
                        "minutes": 180
                    },
                    {
                        "spot": "The Great Wall",
                        "minutes": 300
                    }
                ]
            }
        },
        "type": 3
    },
    {
        "question": "Bob is going to visit some spots across cities, please make a visit plan for him, including inter-city transportation, intra-city transportation, and visit time for each spot.The demands are as follows:\n1. He now lives in Wuhan Railway Hotel in Wuhan. Every time he takes a train to a city, he lives in f\"{city} Railway Hotel\", such as \"Beijing Railway Hotel\" In Guangzhou, he needs to visit Baiyun Mountain for 300 minutes, Huacheng Square for 120 minutes.In Beijing, he needs to visit The Summer Palace for 270 minutes, Tiananmen Square for 210 minutes. And the order can be decided by you.\n2. He is free to travel from 2023.7.1 to 2023.7.20. The budget for transportation is 2600.0 CNY.\n3. The daily opening_hours of spots can be obtained from the database table place. \"opening_hours_begin\" and \"opening_hours_end\" are the opening and closing times respectively\n4. On the basis of completing the above conditions (especially the budget), spend as little time as possible.\n",
        "demands": {
            "TravelSimulator": {
                "begin_time": "2023-07-01 07:00",
                "end_time": "2023-07-20 00:00",
                "origin_city": "Wuhan",
                "origin_place": "Wuhan Railway Hotel",
                "budget": 99999,
                "check_opening_hours": true,
                "check_meal": false,
                "set_budget": true,
                "type": 3,
                "limit": "money",
                "money_min": 0,
                "money_max": 2937
            },
            "Constraints": {
                "SpotDurationConstraint": [
                    {
                        "spot": "Baiyun Mountain",
                        "minutes": 300
                    },
                    {
                        "spot": "Huacheng Square",
                        "minutes": 120
                    },
                    {
                        "spot": "The Summer Palace",
                        "minutes": 270
                    },
                    {
                        "spot": "Tiananmen Square",
                        "minutes": 210
                    }
                ]
            }
        },
        "type": 3
    },
    {
        "question": "Bob is going to visit some spots across cities, please make a visit plan for him, including inter-city transportation, intra-city transportation, and visit time for each spot.The demands are as follows:\n1. He now lives in Nanjing Railway Hotel in Nanjing. Every time he takes a train to a city, he lives in f\"{city} Railway Hotel\", such as \"Beijing Railway Hotel\" In Beijing, he needs to visit The Temple of Heaven for 120 minutes, Shihua Cave for 300 minutes, Tiananmen Square for 270 minutes.In Shanghai, he needs to visit Huangpu River Cruise for 210 minutes, Shanghai Disney for 240 minutes. And the order can be decided by you.\n2. He is free to travel from 2023.7.1 to 2023.7.20. The budget for transportation is 2100.0 CNY.\n3. The daily opening_hours of spots can be obtained from the database table place. \"opening_hours_begin\" and \"opening_hours_end\" are the opening and closing times respectively\n4. On the basis of completing the above conditions (especially the budget), spend as little time as possible.\n",
        "demands": {
            "TravelSimulator": {
                "begin_time": "2023-07-01 07:00",
                "end_time": "2023-07-20 00:00",
                "origin_city": "Nanjing",
                "origin_place": "Nanjing Railway Hotel",
                "budget": 99999,
                "check_opening_hours": true,
                "check_meal": false,
                "set_budget": true,
                "type": 3,
                "limit": "money",
                "money_min": 284,
                "money_max": 1501
            },
            "Constraints": {
                "SpotDurationConstraint": [
                    {
                        "spot": "The Temple of Heaven",
                        "minutes": 120
                    },
                    {
                        "spot": "Shihua Cave",
                        "minutes": 300
                    },
                    {
                        "spot": "Tiananmen Square",
                        "minutes": 270
                    },
                    {
                        "spot": "Huangpu River Cruise",
                        "minutes": 210
                    },
                    {
                        "spot": "Shanghai Disney",
                        "minutes": 240
                    }
                ]
            }
        },
        "type": 3
    },
    {
        "question": "Bob is going to visit some spots across cities, please make a visit plan for him, including inter-city transportation, intra-city transportation, and visit time for each spot.The demands are as follows:\n1. He now lives in Guangzhou Railway Hotel in Guangzhou. Every time he takes a train to a city, he lives in f\"{city} Railway Hotel\", such as \"Beijing Railway Hotel\" In Guangzhou, he needs to visit Canton Tower for 150 minutes, Baiyun Mountain for 210 minutes.In Hangzhou, he needs to visit China National Tea Museum for 120 minutes, Quaint Water Towns for 150 minutes, Lingyin Temple for 240 minutes, West Lake for 180 minutes. And the order can be decided by you.\n2. 6 days (2023-07-10 00:00 ~ 2023-07-16 00:00) for this trip.\n3. Ignore the opening hours of attractions, assuming they are open all day. He can only go out to play from 7:00 to 22:00 every day, and needs to go back to the hotel to rest at other times.\n4. On the basis of completing the above conditions (especially the time limit), spend as little money as possible.\n",
        "demands": {
            "TravelSimulator": {
                "begin_time": "2023-07-10 00:00",
                "end_time": "2023-07-16 00:00",
                "origin_city": "Guangzhou",
                "origin_place": "Guangzhou Railway Hotel",
                "budget": 99999,
                "check_opening_hours": false,
                "check_meal": false,
                "set_budget": false,
                "type": 3,
                "limit": "time",
                "time_min": 112715,
                "time_max": 265026
            },
            "Constraints": {
                "SpotDurationConstraint": [
                    {
                        "spot": "Canton Tower",
                        "minutes": 150
                    },
                    {
                        "spot": "Baiyun Mountain",
                        "minutes": 210
                    },
                    {
                        "spot": "China National Tea Museum",
                        "minutes": 120
                    },
                    {
                        "spot": "Quaint Water Towns",
                        "minutes": 150
                    },
                    {
                        "spot": "Lingyin Temple",
                        "minutes": 240
                    },
                    {
                        "spot": "West Lake",
                        "minutes": 180
                    }
                ]
            }
        },
        "type": 3
    },
    {
        "question": "Bob is going to visit some spots across cities, please make a visit plan for him, including inter-city transportation, intra-city transportation, and visit time for each spot.The demands are as follows:\n1. He now lives in Shanghai Railway Hotel in Shanghai. Every time he takes a train to a city, he lives in f\"{city} Railway Hotel\", such as \"Beijing Railway Hotel\" In Shanghai, he needs to visit Shanghai Sightseeing Tunnel for 270 minutes, Shanghai Disney for 150 minutes, Century Park for 120 minutes.In Chengdu, he needs to visit Chengdu Panda Base for 120 minutes, The Chengdu Wuhou Shrine for 300 minutes, Leshan Giant Buddha for 240 minutes, Du Fu Thatched Cottage for 270 minutes. And the order can be decided by you.\n2. 6 days (2023-07-07 00:00 ~ 2023-07-13 00:00) for this trip.\n3. Ignore the opening hours of attractions, assuming they are open all day. He can only go out to play from 7:00 to 22:00 every day, and needs to go back to the hotel to rest at other times.\n4. On the basis of completing the above conditions (especially the time limit), spend as little money as possible.\n",
        "demands": {
            "TravelSimulator": {
                "begin_time": "2023-07-07 00:00",
                "end_time": "2023-07-13 00:00",
                "origin_city": "Shanghai",
                "origin_place": "Shanghai Railway Hotel",
                "budget": 99999,
                "check_opening_hours": false,
                "check_meal": false,
                "set_budget": false,
                "type": 3,
                "limit": "time",
                "time_min": 177132,
                "time_max": 438699
            },
            "Constraints": {
                "SpotDurationConstraint": [
                    {
                        "spot": "Shanghai Sightseeing Tunnel",
                        "minutes": 270
                    },
                    {
                        "spot": "Shanghai Disney",
                        "minutes": 150
                    },
                    {
                        "spot": "Century Park",
                        "minutes": 120
                    },
                    {
                        "spot": "Chengdu Panda Base",
                        "minutes": 120
                    },
                    {
                        "spot": "The Chengdu Wuhou Shrine",
                        "minutes": 300
                    },
                    {
                        "spot": "Leshan Giant Buddha",
                        "minutes": 240
                    },
                    {
                        "spot": "Du Fu Thatched Cottage",
                        "minutes": 270
                    }
                ]
            }
        },
        "type": 3
    },
    {
        "question": "Bob is going to visit some spots across cities, please make a visit plan for him, including inter-city transportation, intra-city transportation, and visit time for each spot.The demands are as follows:\n1. He now lives in Chengdu Railway Hotel in Chengdu. Every time he takes a train to a city, he lives in f\"{city} Railway Hotel\", such as \"Beijing Railway Hotel\" In Guangzhou, he needs to visit Canton Tower for 150 minutes, Yuexiu Park for 270 minutes.In Wuhan, he needs to visit Tan Hua Lin for 270 minutes, Baotong Temple for 270 minutes. And the order can be decided by you.\n2. 6 days (2023-07-11 00:00 ~ 2023-07-17 00:00) for this trip.\n3. Ignore the opening hours of attractions, assuming they are open all day. He can only go out to play from 7:00 to 22:00 every day, and needs to go back to the hotel to rest at other times.\n4. On the basis of completing the above conditions (especially the time limit), spend as little money as possible.\n",
        "demands": {
            "TravelSimulator": {
                "begin_time": "2023-07-11 00:00",
                "end_time": "2023-07-17 00:00",
                "origin_city": "Chengdu",
                "origin_place": "Chengdu Railway Hotel",
                "budget": 99999,
                "check_opening_hours": false,
                "check_meal": false,
                "set_budget": false,
                "type": 3,
                "limit": "time",
                "time_min": 143908,
                "time_max": 199830
            },
            "Constraints": {
                "SpotDurationConstraint": [
                    {
                        "spot": "Canton Tower",
                        "minutes": 150
                    },
                    {
                        "spot": "Yuexiu Park",
                        "minutes": 270
                    },
                    {
                        "spot": "Tan Hua Lin",
                        "minutes": 270
                    },
                    {
                        "spot": "Baotong Temple",
                        "minutes": 270
                    }
                ]
            }
        },
        "type": 3
    },
    {
        "question": "Bob is going to visit some spots across cities, please make a visit plan for him, including inter-city transportation, intra-city transportation, and visit time for each spot.The demands are as follows:\n1. He now lives in Wuhan Railway Hotel in Wuhan. Every time he takes a train to a city, he lives in f\"{city} Railway Hotel\", such as \"Beijing Railway Hotel\" In Hangzhou, he needs to visit Hefang Street for 210 minutes, China National Tea Museum for 150 minutes.In Shanghai, he needs to visit Shanghai History Museum for 240 minutes, Century Park for 270 minutes. And the order can be decided by you.\n2. 6 days (2023-07-02 00:00 ~ 2023-07-08 00:00) for this trip.\n3. Ignore the opening hours of attractions, assuming they are open all day. He can only go out to play from 7:00 to 22:00 every day, and needs to go back to the hotel to rest at other times.\n4. On the basis of completing the above conditions (especially the time limit), spend as little money as possible.\n",
        "demands": {
            "TravelSimulator": {
                "begin_time": "2023-07-02 00:00",
                "end_time": "2023-07-08 00:00",
                "origin_city": "Wuhan",
                "origin_place": "Wuhan Railway Hotel",
                "budget": 99999,
                "check_opening_hours": false,
                "check_meal": false,
                "set_budget": false,
                "type": 3,
                "limit": "time",
                "time_min": 99219,
                "time_max": 238123
            },
            "Constraints": {
                "SpotDurationConstraint": [
                    {
                        "spot": "Hefang Street",
                        "minutes": 210
                    },
                    {
                        "spot": "China National Tea Museum",
                        "minutes": 150
                    },
                    {
                        "spot": "Shanghai History Museum",
                        "minutes": 240
                    },
                    {
                        "spot": "Century Park",
                        "minutes": 270
                    }
                ]
            }
        },
        "type": 3
    },
    {
        "question": "Bob is going to visit some spots across cities, please make a visit plan for him, including inter-city transportation, intra-city transportation, and visit time for each spot.The demands are as follows:\n1. He now lives in Nanjing Railway Hotel in Nanjing. Every time he takes a train to a city, he lives in f\"{city} Railway Hotel\", such as \"Beijing Railway Hotel\" In Nanjing, he needs to visit Tomb of Ming Emperor Zhu Yuanzhang for 300 minutes, Ming Palace for 180 minutes, Lake Xuanwu for 270 minutes, Bailuzhou Park for 120 minutes, Qinhuai River for 180 minutes.In Hangzhou, he needs to visit West Lake for 270 minutes, Hefang Street for 120 minutes. And the order can be decided by you.\n2. 6 days (2023-07-04 00:00 ~ 2023-07-10 00:00) for this trip.\n3. The daily opening_hours of spots can be obtained from the database table place. \"opening_hours_begin\" and \"opening_hours_end\" are the opening and closing times respectively\n4. On the basis of completing the above conditions (especially the time limit), spend as little money as possible.\n",
        "demands": {
            "TravelSimulator": {
                "begin_time": "2023-07-04 00:00",
                "end_time": "2023-07-10 00:00",
                "origin_city": "Nanjing",
                "origin_place": "Nanjing Railway Hotel",
                "budget": 99999,
                "check_opening_hours": true,
                "check_meal": false,
                "set_budget": false,
                "type": 3,
                "limit": "time",
                "time_min": 270096,
                "time_max": 315389
            },
            "Constraints": {
                "SpotDurationConstraint": [
                    {
                        "spot": "Tomb of Ming Emperor Zhu Yuanzhang",
                        "minutes": 300
                    },
                    {
                        "spot": "Ming Palace",
                        "minutes": 180
                    },
                    {
                        "spot": "Lake Xuanwu",
                        "minutes": 270
                    },
                    {
                        "spot": "Bailuzhou Park",
                        "minutes": 120
                    },
                    {
                        "spot": "Qinhuai River",
                        "minutes": 180
                    },
                    {
                        "spot": "West Lake",
                        "minutes": 270
                    },
                    {
                        "spot": "Hefang Street",
                        "minutes": 120
                    }
                ]
            }
        },
        "type": 3
    },
    {
        "question": "Bob is going to visit some spots across cities, please make a visit plan for him, including inter-city transportation, intra-city transportation, and visit time for each spot.The demands are as follows:\n1. He now lives in Wuhan Railway Hotel in Wuhan. Every time he takes a train to a city, he lives in f\"{city} Railway Hotel\", such as \"Beijing Railway Hotel\" In Wuhan, he needs to visit Han Show for 150 minutes, East Lake for 240 minutes, Tan Hua Lin for 210 minutes.In Chengdu, he needs to visit Chengdu Panda Base for 150 minutes, Du Fu Thatched Cottage for 120 minutes, Leshan Giant Buddha for 210 minutes. And the order can be decided by you.\n2. 6 days (2023-07-11 00:00 ~ 2023-07-17 00:00) for this trip.\n3. The daily opening_hours of spots can be obtained from the database table place. \"opening_hours_begin\" and \"opening_hours_end\" are the opening and closing times respectively\n4. On the basis of completing the above conditions (especially the time limit), spend as little money as possible.\n",
        "demands": {
            "TravelSimulator": {
                "begin_time": "2023-07-11 00:00",
                "end_time": "2023-07-17 00:00",
                "origin_city": "Wuhan",
                "origin_place": "Wuhan Railway Hotel",
                "budget": 99999,
                "check_opening_hours": true,
                "check_meal": false,
                "set_budget": false,
                "type": 3,
                "limit": "time",
                "time_min": 158342,
                "time_max": 285581
            },
            "Constraints": {
                "SpotDurationConstraint": [
                    {
                        "spot": "Han Show",
                        "minutes": 150
                    },
                    {
                        "spot": "East Lake",
                        "minutes": 240
                    },
                    {
                        "spot": "Tan Hua Lin",
                        "minutes": 210
                    },
                    {
                        "spot": "Chengdu Panda Base",
                        "minutes": 150
                    },
                    {
                        "spot": "Du Fu Thatched Cottage",
                        "minutes": 120
                    },
                    {
                        "spot": "Leshan Giant Buddha",
                        "minutes": 210
                    }
                ]
            }
        },
        "type": 3
    },
    {
        "question": "Bob is going to visit some spots across cities, please make a visit plan for him, including inter-city transportation, intra-city transportation, and visit time for each spot.The demands are as follows:\n1. He now lives in Beijing Railway Hotel in Beijing. Every time he takes a train to a city, he lives in f\"{city} Railway Hotel\", such as \"Beijing Railway Hotel\" In Nanjing, he needs to visit Ming Palace for 120 minutes, Tomb of Ming Emperor Zhu Yuanzhang for 150 minutes.In Shanghai, he needs to visit Qibao Ancient Town for 240 minutes, Shanghai Sightseeing Tunnel for 210 minutes, Huangpu River Cruise for 240 minutes. And the order can be decided by you.\n2. 6 days (2023-07-02 00:00 ~ 2023-07-08 00:00) for this trip.\n3. The daily opening_hours of spots can be obtained from the database table place. \"opening_hours_begin\" and \"opening_hours_end\" are the opening and closing times respectively\n4. On the basis of completing the above conditions (especially the time limit), spend as little money as possible.\n",
        "demands": {
            "TravelSimulator": {
                "begin_time": "2023-07-02 00:00",
                "end_time": "2023-07-08 00:00",
                "origin_city": "Beijing",
                "origin_place": "Beijing Railway Hotel",
                "budget": 99999,
                "check_opening_hours": true,
                "check_meal": false,
                "set_budget": false,
                "type": 3,
                "limit": "time",
                "time_min": 158232,
                "time_max": 246155
            },
            "Constraints": {
                "SpotDurationConstraint": [
                    {
                        "spot": "Ming Palace",
                        "minutes": 120
                    },
                    {
                        "spot": "Tomb of Ming Emperor Zhu Yuanzhang",
                        "minutes": 150
                    },
                    {
                        "spot": "Qibao Ancient Town",
                        "minutes": 240
                    },
                    {
                        "spot": "Shanghai Sightseeing Tunnel",
                        "minutes": 210
                    },
                    {
                        "spot": "Huangpu River Cruise",
                        "minutes": 240
                    }
                ]
            }
        },
        "type": 3
    },
    {
        "question": "Bob is going to visit some spots across cities, please make a visit plan for him, including inter-city transportation, intra-city transportation, and visit time for each spot.The demands are as follows:\n1. He now lives in Wuhan Railway Hotel in Wuhan. Every time he takes a train to a city, he lives in f\"{city} Railway Hotel\", such as \"Beijing Railway Hotel\" In Shanghai, he needs to visit Shanghai Disney for 180 minutes, Shanghai History Museum for 240 minutes. And the order can be decided by you.\n2. 6 days (2023-07-06 00:00 ~ 2023-07-12 00:00) for this trip.\n3. The daily opening_hours of spots can be obtained from the database table place. \"opening_hours_begin\" and \"opening_hours_end\" are the opening and closing times respectively\n4. On the basis of completing the above conditions (especially the time limit), spend as little money as possible.\n",
        "demands": {
            "TravelSimulator": {
                "begin_time": "2023-07-06 00:00",
                "end_time": "2023-07-12 00:00",
                "origin_city": "Wuhan",
                "origin_place": "Wuhan Railway Hotel",
                "budget": 99999,
                "check_opening_hours": true,
                "check_meal": false,
                "set_budget": false,
                "type": 3,
                "limit": "time",
                "time_min": 66195,
                "time_max": 102587
            },
            "Constraints": {
                "SpotDurationConstraint": [
                    {
                        "spot": "Shanghai Disney",
                        "minutes": 180
                    },
                    {
                        "spot": "Shanghai History Museum",
                        "minutes": 240
                    }
                ]
            }
        },
        "type": 3
    },
    {
        "question": "Bob is going to visit some spots across cities, please make a visit plan for him, including inter-city transportation, intra-city transportation, and visit time for each spot.The demands are as follows:\n1. He now lives in Wuhan Railway Hotel in Wuhan. Every time he takes a train to a city, he lives in f\"{city} Railway Hotel\", such as \"Beijing Railway Hotel\" In Beijing, he needs to visit Tiananmen Square for 180 minutes, Beijing Olympic Park for 240 minutes, The Forbidden City for 150 minutes, The Temple of Heaven for 270 minutes, Beijing Stone Carvings Art Museum for 210 minutes, The Summer Palace for 180 minutes, Shihua Cave for 150 minutes, The Great Wall for 150 minutes. And the order can be decided by you.\n2. 7 days (2023-07-05 00:00 ~ 2023-07-12 00:00) for this trip.\n3. Ignore the opening hours of attractions, assuming they are open all day. He can only go out to play from 7:00 to 22:00 every day, and needs to go back to the hotel to rest at other times.\n4. On the basis of completing the above conditions (especially the time limit), spend as little money as possible.\n",
        "demands": {
            "TravelSimulator": {
                "begin_time": "2023-07-05 00:00",
                "end_time": "2023-07-12 00:00",
                "origin_city": "Wuhan",
                "origin_place": "Wuhan Railway Hotel",
                "budget": 99999,
                "check_opening_hours": false,
                "check_meal": false,
                "set_budget": false,
                "type": 3,
                "limit": "time",
                "time_min": 238903,
                "time_max": 380637
            },
            "Constraints": {
                "SpotDurationConstraint": [
                    {
                        "spot": "Tiananmen Square",
                        "minutes": 180
                    },
                    {
                        "spot": "Beijing Olympic Park",
                        "minutes": 240
                    },
                    {
                        "spot": "The Forbidden City",
                        "minutes": 150
                    },
                    {
                        "spot": "The Temple of Heaven",
                        "minutes": 270
                    },
                    {
                        "spot": "Beijing Stone Carvings Art Museum",
                        "minutes": 210
                    },
                    {
                        "spot": "The Summer Palace",
                        "minutes": 180
                    },
                    {
                        "spot": "Shihua Cave",
                        "minutes": 150
                    },
                    {
                        "spot": "The Great Wall",
                        "minutes": 150
                    }
                ]
            }
        },
        "type": 3
    },
    {
        "question": "Bob is going to visit some spots across cities, please make a visit plan for him, including inter-city transportation, intra-city transportation, and visit time for each spot.The demands are as follows:\n1. He now lives in Beijing Railway Hotel in Beijing. Every time he takes a train to a city, he lives in f\"{city} Railway Hotel\", such as \"Beijing Railway Hotel\" In Beijing, he needs to visit Beijing Olympic Park for 150 minutes, The Great Wall for 180 minutes, The Summer Palace for 210 minutes, Shihua Cave for 240 minutes, Beijing Stone Carvings Art Museum for 180 minutes, Tiananmen Square for 210 minutes.In Wuhan, he needs to visit Yellow Crane Tower for 270 minutes, Baotong Temple for 150 minutes. And the order can be decided by you.\n2. He is free to travel from 2023.7.1 to 2023.7.20. The budget for transportation is 2200.0 CNY.\n3. Ignore the opening hours of attractions, assuming they are open all day. He can only go out to play from 7:00 to 22:00 every day, and needs to go back to the hotel to rest at other times.\n4. On the basis of completing the above conditions (especially the budget), spend as little time as possible.\n",
        "demands": {
            "TravelSimulator": {
                "begin_time": "2023-07-01 07:00",
                "end_time": "2023-07-20 00:00",
                "origin_city": "Beijing",
                "origin_place": "Beijing Railway Hotel",
                "budget": 99999,
                "check_opening_hours": false,
                "check_meal": false,
                "set_budget": true,
                "type": 3,
                "limit": "money",
                "money_min": 159,
                "money_max": 1632
            },
            "Constraints": {
                "SpotDurationConstraint": [
                    {
                        "spot": "Beijing Olympic Park",
                        "minutes": 150
                    },
                    {
                        "spot": "The Great Wall",
                        "minutes": 180
                    },
                    {
                        "spot": "The Summer Palace",
                        "minutes": 210
                    },
                    {
                        "spot": "Shihua Cave",
                        "minutes": 240
                    },
                    {
                        "spot": "Beijing Stone Carvings Art Museum",
                        "minutes": 180
                    },
                    {
                        "spot": "Tiananmen Square",
                        "minutes": 210
                    },
                    {
                        "spot": "Yellow Crane Tower",
                        "minutes": 270
                    },
                    {
                        "spot": "Baotong Temple",
                        "minutes": 150
                    }
                ]
            }
        },
        "type": 3
    },
    {
        "question": "Bob is going to visit some spots across cities, please make a visit plan for him, including inter-city transportation, intra-city transportation, and visit time for each spot.The demands are as follows:\n1. He now lives in Nanjing Railway Hotel in Nanjing. Every time he takes a train to a city, he lives in f\"{city} Railway Hotel\", such as \"Beijing Railway Hotel\" In Nanjing, he needs to visit Tomb of Ming Emperor Zhu Yuanzhang for 270 minutes, Bailuzhou Park for 180 minutes, Qinhuai River for 210 minutes, Ming Palace for 180 minutes, Lake Xuanwu for 300 minutes.In Beijing, he needs to visit The Summer Palace for 300 minutes, The Great Wall for 150 minutes, The Forbidden City for 180 minutes. And the order can be decided by you.\n2. He is free to travel from 2023.7.1 to 2023.7.20. The budget for transportation is 2200.0 CNY.\n3. Ignore the opening hours of attractions, assuming they are open all day. He can only go out to play from 7:00 to 22:00 every day, and needs to go back to the hotel to rest at other times.\n4. On the basis of completing the above conditions (especially the budget), spend as little time as possible.\n",
        "demands": {
            "TravelSimulator": {
                "begin_time": "2023-07-01 07:00",
                "end_time": "2023-07-20 00:00",
                "origin_city": "Nanjing",
                "origin_place": "Nanjing Railway Hotel",
                "budget": 99999,
                "check_opening_hours": false,
                "check_meal": false,
                "set_budget": true,
                "type": 3,
                "limit": "money",
                "money_min": 167,
                "money_max": 1213
            },
            "Constraints": {
                "SpotDurationConstraint": [
                    {
                        "spot": "Tomb of Ming Emperor Zhu Yuanzhang",
                        "minutes": 270
                    },
                    {
                        "spot": "Bailuzhou Park",
                        "minutes": 180
                    },
                    {
                        "spot": "Qinhuai River",
                        "minutes": 210
                    },
                    {
                        "spot": "Ming Palace",
                        "minutes": 180
                    },
                    {
                        "spot": "Lake Xuanwu",
                        "minutes": 300
                    },
                    {
                        "spot": "The Summer Palace",
                        "minutes": 300
                    },
                    {
                        "spot": "The Great Wall",
                        "minutes": 150
                    },
                    {
                        "spot": "The Forbidden City",
                        "minutes": 180
                    }
                ]
            }
        },
        "type": 3
    },
    {
        "question": "Bob is going to visit some spots across cities, please make a visit plan for him, including inter-city transportation, intra-city transportation, and visit time for each spot.The demands are as follows:\n1. He now lives in Wuhan Railway Hotel in Wuhan. Every time he takes a train to a city, he lives in f\"{city} Railway Hotel\", such as \"Beijing Railway Hotel\" In Beijing, he needs to visit The Summer Palace for 300 minutes, Beijing Stone Carvings Art Museum for 180 minutes, Shihua Cave for 180 minutes, The Great Wall for 300 minutes, The Forbidden City for 120 minutes.In Nanjing, he needs to visit Taiping Heavenly-Kingdom Palace for 210 minutes, Qinhuai River for 300 minutes. And the order can be decided by you.\n2. He is free to travel from 2023.7.1 to 2023.7.20. The budget for transportation is 2700.0 CNY.\n3. Ignore the opening hours of attractions, assuming they are open all day. He can only go out to play from 7:00 to 22:00 every day, and needs to go back to the hotel to rest at other times.\n4. On the basis of completing the above conditions (especially the budget), spend as little time as possible.\n",
        "demands": {
            "TravelSimulator": {
                "begin_time": "2023-07-01 07:00",
                "end_time": "2023-07-20 00:00",
                "origin_city": "Wuhan",
                "origin_place": "Wuhan Railway Hotel",
                "budget": 99999,
                "check_opening_hours": false,
                "check_meal": false,
                "set_budget": true,
                "type": 3,
                "limit": "money",
                "money_min": 590,
                "money_max": 1420
            },
            "Constraints": {
                "SpotDurationConstraint": [
                    {
                        "spot": "The Summer Palace",
                        "minutes": 300
                    },
                    {
                        "spot": "Beijing Stone Carvings Art Museum",
                        "minutes": 180
                    },
                    {
                        "spot": "Shihua Cave",
                        "minutes": 180
                    },
                    {
                        "spot": "The Great Wall",
                        "minutes": 300
                    },
                    {
                        "spot": "The Forbidden City",
                        "minutes": 120
                    },
                    {
                        "spot": "Taiping Heavenly-Kingdom Palace",
                        "minutes": 210
                    },
                    {
                        "spot": "Qinhuai River",
                        "minutes": 300
                    }
                ]
            }
        },
        "type": 3
    },
    {
        "question": "Bob is going to visit some spots across cities, please make a visit plan for him, including inter-city transportation, intra-city transportation, and visit time for each spot.The demands are as follows:\n1. He now lives in Guangzhou Railway Hotel in Guangzhou. Every time he takes a train to a city, he lives in f\"{city} Railway Hotel\", such as \"Beijing Railway Hotel\" In Hangzhou, he needs to visit Lingyin Temple for 150 minutes, China National Tea Museum for 210 minutes, Quaint Water Towns for 180 minutes, Hefang Street for 120 minutes.In Nanjing, he needs to visit Taiping Heavenly-Kingdom Palace for 270 minutes, Bailuzhou Park for 150 minutes, Tomb of Ming Emperor Zhu Yuanzhang for 210 minutes. And the order can be decided by you.\n2. He is free to travel from 2023.7.1 to 2023.7.20. The budget for transportation is 2500.0 CNY.\n3. Ignore the opening hours of attractions, assuming they are open all day. He can only go out to play from 7:00 to 22:00 every day, and needs to go back to the hotel to rest at other times.\n4. On the basis of completing the above conditions (especially the budget), spend as little time as possible.\n",
        "demands": {
            "TravelSimulator": {
                "begin_time": "2023-07-01 07:00",
                "end_time": "2023-07-20 00:00",
                "origin_city": "Guangzhou",
                "origin_place": "Guangzhou Railway Hotel",
                "budget": 99999,
                "check_opening_hours": false,
                "check_meal": false,
                "set_budget": true,
                "type": 3,
                "limit": "money",
                "money_min": 456,
                "money_max": 1952
            },
            "Constraints": {
                "SpotDurationConstraint": [
                    {
                        "spot": "Lingyin Temple",
                        "minutes": 150
                    },
                    {
                        "spot": "China National Tea Museum",
                        "minutes": 210
                    },
                    {
                        "spot": "Quaint Water Towns",
                        "minutes": 180
                    },
                    {
                        "spot": "Hefang Street",
                        "minutes": 120
                    },
                    {
                        "spot": "Taiping Heavenly-Kingdom Palace",
                        "minutes": 270
                    },
                    {
                        "spot": "Bailuzhou Park",
                        "minutes": 150
                    },
                    {
                        "spot": "Tomb of Ming Emperor Zhu Yuanzhang",
                        "minutes": 210
                    }
                ]
            }
        },
        "type": 3
    },
    {
        "question": "Bob is going to visit some spots across cities, please make a visit plan for him, including inter-city transportation, intra-city transportation, and visit time for each spot.The demands are as follows:\n1. He now lives in Beijing Railway Hotel in Beijing. Every time he takes a train to a city, he lives in f\"{city} Railway Hotel\", such as \"Beijing Railway Hotel\" In Beijing, he needs to visit Beijing Stone Carvings Art Museum for 210 minutes, Tiananmen Square for 270 minutes, The Great Wall for 300 minutes, The Temple of Heaven for 120 minutes, The Summer Palace for 210 minutes, Beijing Olympic Park for 210 minutes, Shihua Cave for 300 minutes.In Hangzhou, he needs to visit Lingyin Temple for 270 minutes, West Lake for 120 minutes, Hefang Street for 120 minutes. And the order can be decided by you.\n2. He is free to travel from 2023.7.1 to 2023.7.20. The budget for transportation is 2700.0 CNY.\n3. The daily opening_hours of spots can be obtained from the database table place. \"opening_hours_begin\" and \"opening_hours_end\" are the opening and closing times respectively\n4. On the basis of completing the above conditions (especially the budget), spend as little time as possible.\n",
        "demands": {
            "TravelSimulator": {
                "begin_time": "2023-07-01 07:00",
                "end_time": "2023-07-20 00:00",
                "origin_city": "Beijing",
                "origin_place": "Beijing Railway Hotel",
                "budget": 99999,
                "check_opening_hours": true,
                "check_meal": false,
                "set_budget": true,
                "type": 3,
                "limit": "money",
                "money_min": 378,
                "money_max": 1572
            },
            "Constraints": {
                "SpotDurationConstraint": [
                    {
                        "spot": "Beijing Stone Carvings Art Museum",
                        "minutes": 210
                    },
                    {
                        "spot": "Tiananmen Square",
                        "minutes": 270
                    },
                    {
                        "spot": "The Great Wall",
                        "minutes": 300
                    },
                    {
                        "spot": "The Temple of Heaven",
                        "minutes": 120
                    },
                    {
                        "spot": "The Summer Palace",
                        "minutes": 210
                    },
                    {
                        "spot": "Beijing Olympic Park",
                        "minutes": 210
                    },
                    {
                        "spot": "Shihua Cave",
                        "minutes": 300
                    },
                    {
                        "spot": "Lingyin Temple",
                        "minutes": 270
                    },
                    {
                        "spot": "West Lake",
                        "minutes": 120
                    },
                    {
                        "spot": "Hefang Street",
                        "minutes": 120
                    }
                ]
            }
        },
        "type": 3
    },
    {
        "question": "Bob is going to visit some spots across cities, please make a visit plan for him, including inter-city transportation, intra-city transportation, and visit time for each spot.The demands are as follows:\n1. He now lives in Nanjing Railway Hotel in Nanjing. Every time he takes a train to a city, he lives in f\"{city} Railway Hotel\", such as \"Beijing Railway Hotel\" In Nanjing, he needs to visit Bailuzhou Park for 270 minutes, Tomb of Ming Emperor Zhu Yuanzhang for 240 minutes, Ming Palace for 240 minutes, Lake Xuanwu for 300 minutes, Qinhuai River for 270 minutes.In Beijing, he needs to visit The Forbidden City for 150 minutes, Shihua Cave for 210 minutes, The Temple of Heaven for 180 minutes, Tiananmen Square for 300 minutes. And the order can be decided by you.\n2. He is free to travel from 2023.7.1 to 2023.7.20. The budget for transportation is 2400.0 CNY.\n3. The daily opening_hours of spots can be obtained from the database table place. \"opening_hours_begin\" and \"opening_hours_end\" are the opening and closing times respectively\n4. On the basis of completing the above conditions (especially the budget), spend as little time as possible.\n",
        "demands": {
            "TravelSimulator": {
                "begin_time": "2023-07-01 07:00",
                "end_time": "2023-07-20 00:00",
                "origin_city": "Nanjing",
                "origin_place": "Nanjing Railway Hotel",
                "budget": 99999,
                "check_opening_hours": true,
                "check_meal": false,
                "set_budget": true,
                "type": 3,
                "limit": "money",
                "money_min": 337,
                "money_max": 1142
            },
            "Constraints": {
                "SpotDurationConstraint": [
                    {
                        "spot": "Bailuzhou Park",
                        "minutes": 270
                    },
                    {
                        "spot": "Tomb of Ming Emperor Zhu Yuanzhang",
                        "minutes": 240
                    },
                    {
                        "spot": "Ming Palace",
                        "minutes": 240
                    },
                    {
                        "spot": "Lake Xuanwu",
                        "minutes": 300
                    },
                    {
                        "spot": "Qinhuai River",
                        "minutes": 270
                    },
                    {
                        "spot": "The Forbidden City",
                        "minutes": 150
                    },
                    {
                        "spot": "Shihua Cave",
                        "minutes": 210
                    },
                    {
                        "spot": "The Temple of Heaven",
                        "minutes": 180
                    },
                    {
                        "spot": "Tiananmen Square",
                        "minutes": 300
                    }
                ]
            }
        },
        "type": 3
    },
    {
        "question": "Bob is going to visit some spots across cities, please make a visit plan for him, including inter-city transportation, intra-city transportation, and visit time for each spot.The demands are as follows:\n1. He now lives in Hangzhou Railway Hotel in Hangzhou. Every time he takes a train to a city, he lives in f\"{city} Railway Hotel\", such as \"Beijing Railway Hotel\" In Chengdu, he needs to visit Chengdu Tea Houses for 270 minutes, Du Fu Thatched Cottage for 210 minutes, The Chengdu Wuhou Shrine for 150 minutes, Chengdu Panda Base for 240 minutes.In Wuhan, he needs to visit Han Show for 270 minutes, Tan Hua Lin for 120 minutes. And the order can be decided by you.\n2. He is free to travel from 2023.7.1 to 2023.7.20. The budget for transportation is 2600.0 CNY.\n3. The daily opening_hours of spots can be obtained from the database table place. \"opening_hours_begin\" and \"opening_hours_end\" are the opening and closing times respectively\n4. On the basis of completing the above conditions (especially the budget), spend as little time as possible.\n",
        "demands": {
            "TravelSimulator": {
                "begin_time": "2023-07-01 07:00",
                "end_time": "2023-07-20 00:00",
                "origin_city": "Hangzhou",
                "origin_place": "Hangzhou Railway Hotel",
                "budget": 99999,
                "check_opening_hours": true,
                "check_meal": false,
                "set_budget": true,
                "type": 3,
                "limit": "money",
                "money_min": 57,
                "money_max": 2128
            },
            "Constraints": {
                "SpotDurationConstraint": [
                    {
                        "spot": "Chengdu Tea Houses",
                        "minutes": 270
                    },
                    {
                        "spot": "Du Fu Thatched Cottage",
                        "minutes": 210
                    },
                    {
                        "spot": "The Chengdu Wuhou Shrine",
                        "minutes": 150
                    },
                    {
                        "spot": "Chengdu Panda Base",
                        "minutes": 240
                    },
                    {
                        "spot": "Han Show",
                        "minutes": 270
                    },
                    {
                        "spot": "Tan Hua Lin",
                        "minutes": 120
                    }
                ]
            }
        },
        "type": 3
    },
    {
        "question": "Bob is going to visit some spots across cities, please make a visit plan for him, including inter-city transportation, intra-city transportation, and visit time for each spot.The demands are as follows:\n1. He now lives in Guangzhou Railway Hotel in Guangzhou. Every time he takes a train to a city, he lives in f\"{city} Railway Hotel\", such as \"Beijing Railway Hotel\" In Chengdu, he needs to visit The Chengdu Wuhou Shrine for 210 minutes, Chengdu Tea Houses for 270 minutes, Leshan Giant Buddha for 150 minutes, Chengdu Panda Base for 180 minutes.In Shanghai, he needs to visit Qibao Ancient Town for 270 minutes, Longhua Temple for 270 minutes, Shanghai History Museum for 240 minutes. And the order can be decided by you.\n2. He is free to travel from 2023.7.1 to 2023.7.20. The budget for transportation is 4100.0 CNY.\n3. The daily opening_hours of spots can be obtained from the database table place. \"opening_hours_begin\" and \"opening_hours_end\" are the opening and closing times respectively\n4. On the basis of completing the above conditions (especially the budget), spend as little time as possible.\n",
        "demands": {
            "TravelSimulator": {
                "begin_time": "2023-07-01 07:00",
                "end_time": "2023-07-20 00:00",
                "origin_city": "Guangzhou",
                "origin_place": "Guangzhou Railway Hotel",
                "budget": 99999,
                "check_opening_hours": true,
                "check_meal": false,
                "set_budget": true,
                "type": 3,
                "limit": "money",
                "money_min": 908,
                "money_max": 1909
            },
            "Constraints": {
                "SpotDurationConstraint": [
                    {
                        "spot": "The Chengdu Wuhou Shrine",
                        "minutes": 210
                    },
                    {
                        "spot": "Chengdu Tea Houses",
                        "minutes": 270
                    },
                    {
                        "spot": "Leshan Giant Buddha",
                        "minutes": 150
                    },
                    {
                        "spot": "Chengdu Panda Base",
                        "minutes": 180
                    },
                    {
                        "spot": "Qibao Ancient Town",
                        "minutes": 270
                    },
                    {
                        "spot": "Longhua Temple",
                        "minutes": 270
                    },
                    {
                        "spot": "Shanghai History Museum",
                        "minutes": 240
                    }
                ]
            }
        },
        "type": 3
    },
    {
        "question": "Bob is going to visit some spots across cities, please make a visit plan for him, including inter-city transportation, intra-city transportation, and visit time for each spot.The demands are as follows:\n1. He now lives in Shanghai Railway Hotel in Shanghai. Every time he takes a train to a city, he lives in f\"{city} Railway Hotel\", such as \"Beijing Railway Hotel\" In Shanghai, he needs to visit Shanghai Sightseeing Tunnel for 300 minutes, Huangpu River Cruise for 180 minutes, Qibao Ancient Town for 120 minutes, Century Park for 120 minutes, Shanghai Disney for 240 minutes, Shanghai History Museum for 300 minutes.In Chengdu, he needs to visit The Chengdu Wuhou Shrine for 150 minutes, Leshan Giant Buddha for 240 minutes, Chengdu Panda Base for 240 minutes, Du Fu Thatched Cottage for 150 minutes. And the order can be decided by you.\n2. 7 days (2023-07-03 00:00 ~ 2023-07-10 00:00) for this trip.\n3. Ignore the opening hours of attractions, assuming they are open all day. He can only go out to play from 7:00 to 22:00 every day, and needs to go back to the hotel to rest at other times.\n4. On the basis of completing the above conditions (especially the time limit), spend as little money as possible.\n",
        "demands": {
            "TravelSimulator": {
                "begin_time": "2023-07-03 00:00",
                "end_time": "2023-07-10 00:00",
                "origin_city": "Shanghai",
                "origin_place": "Shanghai Railway Hotel",
                "budget": 99999,
                "check_opening_hours": false,
                "check_meal": false,
                "set_budget": false,
                "type": 3,
                "limit": "time",
                "time_min": 387728,
                "time_max": 505753
            },
            "Constraints": {
                "SpotDurationConstraint": [
                    {
                        "spot": "Shanghai Sightseeing Tunnel",
                        "minutes": 300
                    },
                    {
                        "spot": "Huangpu River Cruise",
                        "minutes": 180
                    },
                    {
                        "spot": "Qibao Ancient Town",
                        "minutes": 120
                    },
                    {
                        "spot": "Century Park",
                        "minutes": 120
                    },
                    {
                        "spot": "Shanghai Disney",
                        "minutes": 240
                    },
                    {
                        "spot": "Shanghai History Museum",
                        "minutes": 300
                    },
                    {
                        "spot": "The Chengdu Wuhou Shrine",
                        "minutes": 150
                    },
                    {
                        "spot": "Leshan Giant Buddha",
                        "minutes": 240
                    },
                    {
                        "spot": "Chengdu Panda Base",
                        "minutes": 240
                    },
                    {
                        "spot": "Du Fu Thatched Cottage",
                        "minutes": 150
                    }
                ]
            }
        },
        "type": 3
    },
    {
        "question": "Bob is going to visit some spots across cities, please make a visit plan for him, including inter-city transportation, intra-city transportation, and visit time for each spot.The demands are as follows:\n1. He now lives in Beijing Railway Hotel in Beijing. Every time he takes a train to a city, he lives in f\"{city} Railway Hotel\", such as \"Beijing Railway Hotel\" In Beijing, he needs to visit Beijing Olympic Park for 180 minutes, Tiananmen Square for 240 minutes, The Temple of Heaven for 150 minutes, Beijing Stone Carvings Art Museum for 150 minutes, Shihua Cave for 210 minutes, The Forbidden City for 210 minutes.In Hangzhou, he needs to visit Hefang Street for 180 minutes, Lingyin Temple for 210 minutes, Quaint Water Towns for 300 minutes, West Lake for 210 minutes. And the order can be decided by you.\n2. 7 days (2023-07-04 00:00 ~ 2023-07-11 00:00) for this trip.\n3. Ignore the opening hours of attractions, assuming they are open all day. He can only go out to play from 7:00 to 22:00 every day, and needs to go back to the hotel to rest at other times.\n4. On the basis of completing the above conditions (especially the time limit), spend as little money as possible.\n",
        "demands": {
            "TravelSimulator": {
                "begin_time": "2023-07-04 00:00",
                "end_time": "2023-07-11 00:00",
                "origin_city": "Beijing",
                "origin_place": "Beijing Railway Hotel",
                "budget": 99999,
                "check_opening_hours": false,
                "check_meal": false,
                "set_budget": false,
                "type": 3,
                "limit": "time",
                "time_min": 297415,
                "time_max": 470323
            },
            "Constraints": {
                "SpotDurationConstraint": [
                    {
                        "spot": "Beijing Olympic Park",
                        "minutes": 180
                    },
                    {
                        "spot": "Tiananmen Square",
                        "minutes": 240
                    },
                    {
                        "spot": "The Temple of Heaven",
                        "minutes": 150
                    },
                    {
                        "spot": "Beijing Stone Carvings Art Museum",
                        "minutes": 150
                    },
                    {
                        "spot": "Shihua Cave",
                        "minutes": 210
                    },
                    {
                        "spot": "The Forbidden City",
                        "minutes": 210
                    },
                    {
                        "spot": "Hefang Street",
                        "minutes": 180
                    },
                    {
                        "spot": "Lingyin Temple",
                        "minutes": 210
                    },
                    {
                        "spot": "Quaint Water Towns",
                        "minutes": 300
                    },
                    {
                        "spot": "West Lake",
                        "minutes": 210
                    }
                ]
            }
        },
        "type": 3
    },
    {
        "question": "Bob is going to visit some spots across cities, please make a visit plan for him, including inter-city transportation, intra-city transportation, and visit time for each spot.The demands are as follows:\n1. He now lives in Nanjing Railway Hotel in Nanjing. Every time he takes a train to a city, he lives in f\"{city} Railway Hotel\", such as \"Beijing Railway Hotel\" In Guangzhou, he needs to visit Canton Tower for 180 minutes, Huacheng Square for 150 minutes, Chimelong Tourist Resort for 180 minutes, Baiyun Mountain for 150 minutes, Yuexiu Park for 240 minutes.In Shanghai, he needs to visit Shanghai Disney for 180 minutes, Shanghai History Museum for 210 minutes. And the order can be decided by you.\n2. 7 days (2023-07-07 00:00 ~ 2023-07-14 00:00) for this trip.\n3. Ignore the opening hours of attractions, assuming they are open all day. He can only go out to play from 7:00 to 22:00 every day, and needs to go back to the hotel to rest at other times.\n4. On the basis of completing the above conditions (especially the time limit), spend as little money as possible.\n",
        "demands": {
            "TravelSimulator": {
                "begin_time": "2023-07-07 00:00",
                "end_time": "2023-07-14 00:00",
                "origin_city": "Nanjing",
                "origin_place": "Nanjing Railway Hotel",
                "budget": 99999,
                "check_opening_hours": false,
                "check_meal": false,
                "set_budget": false,
                "type": 3,
                "limit": "time",
                "time_min": 220713,
                "time_max": 279651
            },
            "Constraints": {
                "SpotDurationConstraint": [
                    {
                        "spot": "Canton Tower",
                        "minutes": 180
                    },
                    {
                        "spot": "Huacheng Square",
                        "minutes": 150
                    },
                    {
                        "spot": "Chimelong Tourist Resort",
                        "minutes": 180
                    },
                    {
                        "spot": "Baiyun Mountain",
                        "minutes": 150
                    },
                    {
                        "spot": "Yuexiu Park",
                        "minutes": 240
                    },
                    {
                        "spot": "Shanghai Disney",
                        "minutes": 180
                    },
                    {
                        "spot": "Shanghai History Museum",
                        "minutes": 210
                    }
                ]
            }
        },
        "type": 3
    },
    {
        "question": "Bob is going to visit some spots across cities, please make a visit plan for him, including inter-city transportation, intra-city transportation, and visit time for each spot.The demands are as follows:\n1. He now lives in Shanghai Railway Hotel in Shanghai. Every time he takes a train to a city, he lives in f\"{city} Railway Hotel\", such as \"Beijing Railway Hotel\" In Chengdu, he needs to visit Du Fu Thatched Cottage for 240 minutes, Chengdu Tea Houses for 270 minutes, The Chengdu Wuhou Shrine for 270 minutes. And the order can be decided by you.\n2. 7 days (2023-07-07 00:00 ~ 2023-07-14 00:00) for this trip.\n3. Ignore the opening hours of attractions, assuming they are open all day. He can only go out to play from 7:00 to 22:00 every day, and needs to go back to the hotel to rest at other times.\n4. On the basis of completing the above conditions (especially the time limit), spend as little money as possible.\n",
        "demands": {
            "TravelSimulator": {
                "begin_time": "2023-07-07 00:00",
                "end_time": "2023-07-14 00:00",
                "origin_city": "Shanghai",
                "origin_place": "Shanghai Railway Hotel",
                "budget": 99999,
                "check_opening_hours": false,
                "check_meal": false,
                "set_budget": false,
                "type": 3,
                "limit": "time",
                "time_min": 66094,
                "time_max": 198910
            },
            "Constraints": {
                "SpotDurationConstraint": [
                    {
                        "spot": "Du Fu Thatched Cottage",
                        "minutes": 240
                    },
                    {
                        "spot": "Chengdu Tea Houses",
                        "minutes": 270
                    },
                    {
                        "spot": "The Chengdu Wuhou Shrine",
                        "minutes": 270
                    }
                ]
            }
        },
        "type": 3
    },
    {
        "question": "Bob is going to visit some spots across cities, please make a visit plan for him, including inter-city transportation, intra-city transportation, and visit time for each spot.The demands are as follows:\n1. He now lives in Chengdu Railway Hotel in Chengdu. Every time he takes a train to a city, he lives in f\"{city} Railway Hotel\", such as \"Beijing Railway Hotel\" In Chengdu, he needs to visit Leshan Giant Buddha for 270 minutes, Chengdu Panda Base for 300 minutes, Chengdu Tea Houses for 300 minutes, Du Fu Thatched Cottage for 270 minutes, The Chengdu Wuhou Shrine for 240 minutes.In Nanjing, he needs to visit Bailuzhou Park for 240 minutes, Ming Palace for 120 minutes, Qinhuai River for 150 minutes. And the order can be decided by you.\n2. 7 days (2023-07-10 00:00 ~ 2023-07-17 00:00) for this trip.\n3. The daily opening_hours of spots can be obtained from the database table place. \"opening_hours_begin\" and \"opening_hours_end\" are the opening and closing times respectively\n4. On the basis of completing the above conditions (especially the time limit), spend as little money as possible.\n",
        "demands": {
            "TravelSimulator": {
                "begin_time": "2023-07-10 00:00",
                "end_time": "2023-07-17 00:00",
                "origin_city": "Chengdu",
                "origin_place": "Chengdu Railway Hotel",
                "budget": 99999,
                "check_opening_hours": true,
                "check_meal": false,
                "set_budget": false,
                "type": 3,
                "limit": "time",
                "time_min": 369376,
                "time_max": 409230
            },
            "Constraints": {
                "SpotDurationConstraint": [
                    {
                        "spot": "Leshan Giant Buddha",
                        "minutes": 270
                    },
                    {
                        "spot": "Chengdu Panda Base",
                        "minutes": 300
                    },
                    {
                        "spot": "Chengdu Tea Houses",
                        "minutes": 300
                    },
                    {
                        "spot": "Du Fu Thatched Cottage",
                        "minutes": 270
                    },
                    {
                        "spot": "The Chengdu Wuhou Shrine",
                        "minutes": 240
                    },
                    {
                        "spot": "Bailuzhou Park",
                        "minutes": 240
                    },
                    {
                        "spot": "Ming Palace",
                        "minutes": 120
                    },
                    {
                        "spot": "Qinhuai River",
                        "minutes": 150
                    }
                ]
            }
        },
        "type": 3
    },
    {
        "question": "Bob is going to visit some spots across cities, please make a visit plan for him, including inter-city transportation, intra-city transportation, and visit time for each spot.The demands are as follows:\n1. He now lives in Beijing Railway Hotel in Beijing. Every time he takes a train to a city, he lives in f\"{city} Railway Hotel\", such as \"Beijing Railway Hotel\" In Beijing, he needs to visit The Great Wall for 300 minutes, Shihua Cave for 300 minutes, Beijing Stone Carvings Art Museum for 210 minutes, The Temple of Heaven for 120 minutes, The Summer Palace for 240 minutes, Beijing Olympic Park for 270 minutes. And the order can be decided by you.\n2. 7 days (2023-07-04 00:00 ~ 2023-07-11 00:00) for this trip.\n3. The daily opening_hours of spots can be obtained from the database table place. \"opening_hours_begin\" and \"opening_hours_end\" are the opening and closing times respectively\n4. On the basis of completing the above conditions (especially the time limit), spend as little money as possible.\n",
        "demands": {
            "TravelSimulator": {
                "begin_time": "2023-07-04 00:00",
                "end_time": "2023-07-11 00:00",
                "origin_city": "Beijing",
                "origin_place": "Beijing Railway Hotel",
                "budget": 99999,
                "check_opening_hours": true,
                "check_meal": false,
                "set_budget": false,
                "type": 3,
                "limit": "time",
                "time_min": 300600,
                "time_max": 300600
            },
            "Constraints": {
                "SpotDurationConstraint": [
                    {
                        "spot": "The Great Wall",
                        "minutes": 300
                    },
                    {
                        "spot": "Shihua Cave",
                        "minutes": 300
                    },
                    {
                        "spot": "Beijing Stone Carvings Art Museum",
                        "minutes": 210
                    },
                    {
                        "spot": "The Temple of Heaven",
                        "minutes": 120
                    },
                    {
                        "spot": "The Summer Palace",
                        "minutes": 240
                    },
                    {
                        "spot": "Beijing Olympic Park",
                        "minutes": 270
                    }
                ]
            }
        },
        "type": 3
    },
    {
        "question": "Bob is going to visit some spots across cities, please make a visit plan for him, including inter-city transportation, intra-city transportation, and visit time for each spot.The demands are as follows:\n1. He now lives in Shanghai Railway Hotel in Shanghai. Every time he takes a train to a city, he lives in f\"{city} Railway Hotel\", such as \"Beijing Railway Hotel\" In Nanjing, he needs to visit Taiping Heavenly-Kingdom Palace for 300 minutes, Qinhuai River for 270 minutes, Lake Xuanwu for 150 minutes, Ming Palace for 270 minutes. And the order can be decided by you.\n2. 7 days (2023-07-08 00:00 ~ 2023-07-15 00:00) for this trip.\n3. The daily opening_hours of spots can be obtained from the database table place. \"opening_hours_begin\" and \"opening_hours_end\" are the opening and closing times respectively\n4. On the basis of completing the above conditions (especially the time limit), spend as little money as possible.\n",
        "demands": {
            "TravelSimulator": {
                "begin_time": "2023-07-08 00:00",
                "end_time": "2023-07-15 00:00",
                "origin_city": "Shanghai",
                "origin_place": "Shanghai Railway Hotel",
                "budget": 99999,
                "check_opening_hours": true,
                "check_meal": false,
                "set_budget": false,
                "type": 3,
                "limit": "time",
                "time_min": 109759,
                "time_max": 305338
            },
            "Constraints": {
                "SpotDurationConstraint": [
                    {
                        "spot": "Taiping Heavenly-Kingdom Palace",
                        "minutes": 300
                    },
                    {
                        "spot": "Qinhuai River",
                        "minutes": 270
                    },
                    {
                        "spot": "Lake Xuanwu",
                        "minutes": 150
                    },
                    {
                        "spot": "Ming Palace",
                        "minutes": 270
                    }
                ]
            }
        },
        "type": 3
    },
    {
        "question": "Bob is going to visit some spots across cities, please make a visit plan for him, including inter-city transportation, intra-city transportation, and visit time for each spot.The demands are as follows:\n1. He now lives in Wuhan Railway Hotel in Wuhan. Every time he takes a train to a city, he lives in f\"{city} Railway Hotel\", such as \"Beijing Railway Hotel\" In Guangzhou, he needs to visit Yuexiu Park for 210 minutes, Chimelong Tourist Resort for 270 minutes, Canton Tower for 270 minutes, Huacheng Square for 270 minutes.In Chengdu, he needs to visit Chengdu Panda Base for 240 minutes, Chengdu Tea Houses for 120 minutes. And the order can be decided by you.\n2. 7 days (2023-07-08 00:00 ~ 2023-07-15 00:00) for this trip.\n3. The daily opening_hours of spots can be obtained from the database table place. \"opening_hours_begin\" and \"opening_hours_end\" are the opening and closing times respectively\n4. On the basis of completing the above conditions (especially the time limit), spend as little money as possible.\n",
        "demands": {
            "TravelSimulator": {
                "begin_time": "2023-07-08 00:00",
                "end_time": "2023-07-15 00:00",
                "origin_city": "Wuhan",
                "origin_place": "Wuhan Railway Hotel",
                "budget": 99999,
                "check_opening_hours": true,
                "check_meal": false,
                "set_budget": false,
                "type": 3,
                "limit": "time",
                "time_min": 164687,
                "time_max": 396520
            },
            "Constraints": {
                "SpotDurationConstraint": [
                    {
                        "spot": "Yuexiu Park",
                        "minutes": 210
                    },
                    {
                        "spot": "Chimelong Tourist Resort",
                        "minutes": 270
                    },
                    {
                        "spot": "Canton Tower",
                        "minutes": 270
                    },
                    {
                        "spot": "Huacheng Square",
                        "minutes": 270
                    },
                    {
                        "spot": "Chengdu Panda Base",
                        "minutes": 240
                    },
                    {
                        "spot": "Chengdu Tea Houses",
                        "minutes": 120
                    }
                ]
            }
        },
        "type": 3
    }
]